{
  "type": "FeatureCollection",
  "features": [
    {
      "type": "Feature",
      "id": 18240,
      "geometry": {
        "type": "Point",
        "coordinates": [
          150.04787699982376,
          -5.334687999851269
        ]
      },
      "properties": {
        "OBJECTID": 18240,
        "CU_NAME": "BOLA (INCL. HUVALE)",
        "CU_NO": "003",
        "GEOCODE": "19021104003",
        "PROV_KEY": "19",
        "DIST_NO": "02",
        "LLG_NO": "11",
        "WARD_NO": "04",
        "WARD_NAME": "BOLA",
        "LATITUDE": -5.34184,
        "LONGITUDE": 150.044,
        "REGHH": 104,
        "TOTPOP2000": 632,
        "MALE2000": 338,
        "FEMALE2000": 294,
        "POP2008": 832,
        "G_RATE": 1.034999966621399,
        "Geocode_Num": 19021104003,
        "PROVINCE": 19
      }
    },
    {
      "type": "Feature",
      "id": 18241,
      "geometry": {
        "type": "Point",
        "coordinates": [
          150.040291999876,
          -5.35884799973536
        ]
      },
      "properties": {
        "OBJECTID": 18241,
        "CU_NAME": "NAVARAI PLANTATION",
        "CU_NO": "405",
        "GEOCODE": "19021104405",
        "PROV_KEY": "19",
        "DIST_NO": "02",
        "LLG_NO": "11",
        "WARD_NO": "04",
        "WARD_NAME": "BOLA",
        "LATITUDE": -5.3637,
        "LONGITUDE": 150.037,
        "REGHH": 69,
        "TOTPOP2000": 268,
        "MALE2000": 196,
        "FEMALE2000": 72,
        "POP2008": 353,
        "G_RATE": 1.034999966621399,
        "Geocode_Num": 19021104405,
        "PROVINCE": 19
      }
    },
    {
      "type": "Feature",
      "id": 18242,
      "geometry": {
        "type": "Point",
        "coordinates": [
          150.07697800003473,
          -5.295300000094869
        ]
      },
      "properties": {
        "OBJECTID": 18242,
        "CU_NAME": "GARUA PLANTATION",
        "CU_NO": "406",
        "GEOCODE": "19021104406",
        "PROV_KEY": "19",
        "DIST_NO": "02",
        "LLG_NO": "11",
        "WARD_NO": "04",
        "WARD_NAME": "BOLA",
        "LATITUDE": -5.29671,
        "LONGITUDE": 150.076,
        "REGHH": 29,
        "TOTPOP2000": 145,
        "MALE2000": 102,
        "FEMALE2000": 43,
        "POP2008": 190,
        "G_RATE": 1.034999966621399,
        "Geocode_Num": 19021104406,
        "PROVINCE": 19
      }
    }
  ]
}