{
  "type": "FeatureCollection",
  "features": [
    {
      "type": "Feature",
      "id": 18253,
      "geometry": {
        "type": "Point",
        "coordinates": [
          150.02385299991613,
          -5.070573999690282
        ]
      },
      "properties": {
        "OBJECTID": 18253,
        "CU_NAME": "BULUDAVA",
        "CU_NO": "004",
        "GEOCODE": "19021107004",
        "PROV_KEY": "19",
        "DIST_NO": "02",
        "LLG_NO": "11",
        "WARD_NO": "07",
        "WARD_NAME": "BULU",
        "LATITUDE": -5.07659,
        "LONGITUDE": 150.024,
        "REGHH": 51,
        "TOTPOP2000": 352,
        "MALE2000": 176,
        "FEMALE2000": 176,
        "POP2008": 464,
        "G_RATE": 1.034999966621399,
        "Geocode_Num": 19021107004,
        "PROVINCE": 19
      }
    },
    {
      "type": "Feature",
      "id": 18254,
      "geometry": {
        "type": "Point",
        "coordinates": [
          150.14167300040867,
          -5.0176950001240925
        ]
      },
      "properties": {
        "OBJECTID": 18254,
        "CU_NAME": "BULUMURI",
        "CU_NO": "005",
        "GEOCODE": "19021107005",
        "PROV_KEY": "19",
        "DIST_NO": "02",
        "LLG_NO": "11",
        "WARD_NO": "07",
        "WARD_NAME": "BULU",
        "LATITUDE": -5.01769,
        "LONGITUDE": 150.145,
        "REGHH": 43,
        "TOTPOP2000": 337,
        "MALE2000": 180,
        "FEMALE2000": 157,
        "POP2008": 445,
        "G_RATE": 1.034999966621399,
        "Geocode_Num": 19021107005,
        "PROVINCE": 19
      }
    },
    {
      "type": "Feature",
      "id": 18255,
      "geometry": {
        "type": "Point",
        "coordinates": [
          150.13097699998866,
          -5.108816999704743
        ]
      },
      "properties": {
        "OBJECTID": 18255,
        "CU_NAME": "KINTAKU",
        "CU_NO": "028",
        "GEOCODE": "19021107028",
        "PROV_KEY": "19",
        "DIST_NO": "02",
        "LLG_NO": "11",
        "WARD_NO": "07",
        "WARD_NAME": "BULU",
        "LATITUDE": -5.110225,
        "LONGITUDE": 150.13,
        "REGHH": 40,
        "TOTPOP2000": 217,
        "MALE2000": 115,
        "FEMALE2000": 102,
        "POP2008": 286,
        "G_RATE": 1.034999966621399,
        "Geocode_Num": 19021107028,
        "PROVINCE": 19
      }
    }
  ]
}