{
  "type": "FeatureCollection",
  "features": [
    {
      "type": "Feature",
      "id": 12065,
      "geometry": {
        "type": "Point",
        "coordinates": [
          147.50747699976375,
          -6.738743999735732
        ]
      },
      "properties": {
        "OBJECTID": 12065,
        "CU_NAME": "BUINGIM",
        "CU_NO": "005",
        "GEOCODE": "12082303005",
        "PROV_KEY": "12",
        "DIST_NO": "08",
        "LLG_NO": "23",
        "WARD_NO": "03",
        "WARD_NAME": "BUINGIM",
        "LATITUDE": -6.740166,
        "LONGITUDE": 147.50646,
        "REGHH": 100,
        "TOTPOP2000": 578,
        "MALE2000": 294,
        "FEMALE2000": 284,
        "POP2008": 722,
        "G_RATE": 1.027999997138977,
        "Geocode_Num": 12082303005,
        "PROVINCE": 12
      }
    }
  ]
}