{
  "type": "FeatureCollection",
  "features": [
    {
      "type": "Feature",
      "id": 12081,
      "geometry": {
        "type": "Point",
        "coordinates": [
          147.1155430002094,
          -6.682152999860989
        ]
      },
      "properties": {
        "OBJECTID": 12081,
        "CU_NAME": "MUSOM",
        "CU_NO": "001",
        "GEOCODE": "12082312001",
        "PROV_KEY": "12",
        "DIST_NO": "08",
        "LLG_NO": "23",
        "WARD_NO": "12",
        "WARD_NAME": "MUSOM/TALE",
        "LATITUDE": -6.683574,
        "LONGITUDE": 147.11452,
        "REGHH": 52,
        "TOTPOP2000": 343,
        "MALE2000": 170,
        "FEMALE2000": 173,
        "POP2008": 428,
        "G_RATE": 1.027999997138977,
        "Geocode_Num": 12082312001,
        "PROVINCE": 12
      }
    },
    {
      "type": "Feature",
      "id": 12082,
      "geometry": {
        "type": "Point",
        "coordinates": [
          147.10878299963576,
          -6.6783550000831156
        ]
      },
      "properties": {
        "OBJECTID": 12082,
        "CU_NAME": "TALE",
        "CU_NO": "002",
        "GEOCODE": "12082312002",
        "PROV_KEY": "12",
        "DIST_NO": "08",
        "LLG_NO": "23",
        "WARD_NO": "12",
        "WARD_NAME": "MUSOM/TALE",
        "LATITUDE": -6.679776,
        "LONGITUDE": 147.10776,
        "REGHH": 40,
        "TOTPOP2000": 228,
        "MALE2000": 113,
        "FEMALE2000": 115,
        "POP2008": 285,
        "G_RATE": 1.027999997138977,
        "Geocode_Num": 12082312002,
        "PROVINCE": 12
      }
    },
    {
      "type": "Feature",
      "id": 12083,
      "geometry": {
        "type": "Point",
        "coordinates": [
          147.09548000040172,
          -6.684942999919485
        ]
      },
      "properties": {
        "OBJECTID": 12083,
        "CU_NAME": "TIKELENG",
        "CU_NO": "003",
        "GEOCODE": "12082312003",
        "PROV_KEY": "12",
        "DIST_NO": "08",
        "LLG_NO": "23",
        "WARD_NO": "12",
        "WARD_NAME": "MUSOM/TALE",
        "LATITUDE": -6.686364,
        "LONGITUDE": 147.094457,
        "REGHH": 58,
        "TOTPOP2000": 350,
        "MALE2000": 186,
        "FEMALE2000": 164,
        "POP2008": 437,
        "G_RATE": 1.027999997138977,
        "Geocode_Num": 12082312003,
        "PROVINCE": 12
      }
    }
  ]
}