{
  "type": "FeatureCollection",
  "features": [
    {
      "type": "Feature",
      "id": 18374,
      "geometry": {
        "type": "Point",
        "coordinates": [
          142.04935400028694,
          -3.4636769995938153
        ]
      },
      "properties": {
        "OBJECTID": 18374,
        "CU_NAME": "ALI",
        "CU_NO": "001",
        "GEOCODE": "15010210001",
        "PROV_KEY": "15",
        "DIST_NO": "01",
        "LLG_NO": "02",
        "WARD_NO": "10",
        "WARD_NAME": "LUMI",
        "LATITUDE": -3.465631,
        "LONGITUDE": 142.043735,
        "REGHH": 27,
        "TOTPOP2000": 140,
        "MALE2000": 77,
        "FEMALE2000": 63,
        "POP2008": 170,
        "G_RATE": 1.0240000486373901,
        "Geocode_Num": 15010210001,
        "PROVINCE": 15
      }
    },
    {
      "type": "Feature",
      "id": 18375,
      "geometry": {
        "type": "Point",
        "coordinates": [
          142.04486800025802,
          -3.473599000293575
        ]
      },
      "properties": {
        "OBJECTID": 18375,
        "CU_NAME": "LUMI VILLAGE",
        "CU_NO": "010",
        "GEOCODE": "15010210010",
        "PROV_KEY": "15",
        "DIST_NO": "01",
        "LLG_NO": "02",
        "WARD_NO": "10",
        "WARD_NAME": "LUMI",
        "LATITUDE": -3.474977,
        "LONGITUDE": 142.043786,
        "REGHH": 46,
        "TOTPOP2000": 263,
        "MALE2000": 128,
        "FEMALE2000": 135,
        "POP2008": 317,
        "G_RATE": 1.0240000486373901,
        "Geocode_Num": 15010210010,
        "PROVINCE": 15
      }
    },
    {
      "type": "Feature",
      "id": 18376,
      "geometry": {
        "type": "Point",
        "coordinates": [
          142.0350750001112,
          -3.47548099984823
        ]
      },
      "properties": {
        "OBJECTID": 18376,
        "CU_NAME": "OTEMGI",
        "CU_NO": "017",
        "GEOCODE": "15010210017",
        "PROV_KEY": "15",
        "DIST_NO": "01",
        "LLG_NO": "02",
        "WARD_NO": "10",
        "WARD_NAME": "LUMI",
        "LATITUDE": -3.476859,
        "LONGITUDE": 142.033993,
        "REGHH": 26,
        "TOTPOP2000": 157,
        "MALE2000": 84,
        "FEMALE2000": 73,
        "POP2008": 189,
        "G_RATE": 1.0240000486373901,
        "Geocode_Num": 15010210017,
        "PROVINCE": 15
      }
    },
    {
      "type": "Feature",
      "id": 18377,
      "geometry": {
        "type": "Point",
        "coordinates": [
          142.0484930001519,
          -3.486185999784027
        ]
      },
      "properties": {
        "OBJECTID": 18377,
        "CU_NAME": "LUMI STATION",
        "CU_NO": "501",
        "GEOCODE": "15010210501",
        "PROV_KEY": "15",
        "DIST_NO": "01",
        "LLG_NO": "02",
        "WARD_NO": "10",
        "WARD_NAME": "LUMI",
        "LATITUDE": -3.488699,
        "LONGITUDE": 142.051951,
        "REGHH": 9,
        "TOTPOP2000": 44,
        "MALE2000": 23,
        "FEMALE2000": 21,
        "POP2008": 52,
        "G_RATE": 1.0240000486373901,
        "Geocode_Num": 15010210501,
        "PROVINCE": 15
      }
    }
  ]
}