{
  "type": "FeatureCollection",
  "features": [
    {
      "type": "Feature",
      "id": 14303,
      "geometry": {
        "type": "Point",
        "coordinates": [
          145.1148209996894,
          -6.331523000286211
        ]
      },
      "properties": {
        "OBJECTID": 14303,
        "CU_NAME": "NAM",
        "CU_NO": "002",
        "GEOCODE": "10030807002",
        "PROV_KEY": "10",
        "DIST_NO": "03",
        "LLG_NO": "08",
        "WARD_NO": "07",
        "WARD_NAME": "KORA",
        "LATITUDE": -6.332936,
        "LONGITUDE": 145.113772,
        "REGHH": 35,
        "TOTPOP2000": 181,
        "MALE2000": 99,
        "FEMALE2000": 82,
        "POP2008": 208,
        "G_RATE": 1.0180000066757202,
        "Geocode_Num": 10030807002,
        "PROVINCE": 10
      }
    },
    {
      "type": "Feature",
      "id": 14304,
      "geometry": {
        "type": "Point",
        "coordinates": [
          145.12176199961664,
          -6.328175999722589
        ]
      },
      "properties": {
        "OBJECTID": 14304,
        "CU_NAME": "GOMLA",
        "CU_NO": "003",
        "GEOCODE": "10030807003",
        "PROV_KEY": "10",
        "DIST_NO": "03",
        "LLG_NO": "08",
        "WARD_NO": "07",
        "WARD_NAME": "KORA",
        "LATITUDE": -6.329589,
        "LONGITUDE": 145.120714,
        "REGHH": 17,
        "TOTPOP2000": 69,
        "MALE2000": 34,
        "FEMALE2000": 35,
        "POP2008": 77,
        "G_RATE": 1.0180000066757202,
        "Geocode_Num": 10030807003,
        "PROVINCE": 10
      }
    },
    {
      "type": "Feature",
      "id": 14305,
      "geometry": {
        "type": "Point",
        "coordinates": [
          145.1283539996374,
          -6.3235240001324655
        ]
      },
      "properties": {
        "OBJECTID": 14305,
        "CU_NAME": "GOLA",
        "CU_NO": "004",
        "GEOCODE": "10030807004",
        "PROV_KEY": "10",
        "DIST_NO": "03",
        "LLG_NO": "08",
        "WARD_NO": "07",
        "WARD_NAME": "KORA",
        "LATITUDE": -6.324937,
        "LONGITUDE": 145.127306,
        "REGHH": 56,
        "TOTPOP2000": 268,
        "MALE2000": 144,
        "FEMALE2000": 124,
        "POP2008": 308,
        "G_RATE": 1.0180000066757202,
        "Geocode_Num": 10030807004,
        "PROVINCE": 10
      }
    },
    {
      "type": "Feature",
      "id": 14306,
      "geometry": {
        "type": "Point",
        "coordinates": [
          145.1180359995618,
          -6.33250699979817
        ]
      },
      "properties": {
        "OBJECTID": 14306,
        "CU_NAME": "YOWAI COMM. SCH",
        "CU_NO": "401",
        "GEOCODE": "10030807401",
        "PROV_KEY": "10",
        "DIST_NO": "03",
        "LLG_NO": "08",
        "WARD_NO": "07",
        "WARD_NAME": "KORA",
        "LATITUDE": -6.33392,
        "LONGITUDE": 145.116987,
        "REGHH": 3,
        "TOTPOP2000": 4,
        "MALE2000": 4,
        "FEMALE2000": 0,
        "POP2008": 4,
        "G_RATE": 1.0180000066757202,
        "Geocode_Num": 10030807401,
        "PROVINCE": 10
      }
    }
  ]
}