{
  "type": "FeatureCollection",
  "features": [
    {
      "type": "Feature",
      "id": 7154,
      "geometry": {
        "type": "Point",
        "coordinates": [
          143.05379599988555,
          -3.730399999560291
        ]
      },
      "properties": {
        "OBJECTID": 7154,
        "CU_NAME": "MIKO 2",
        "CU_NO": "027",
        "GEOCODE": "14052202027",
        "PROV_KEY": "14",
        "DIST_NO": "05",
        "LLG_NO": "22",
        "WARD_NO": "02",
        "WARD_NAME": "TIADIKIM",
        "LATITUDE": -3.731979,
        "LONGITUDE": 143.052557,
        "REGHH": 45,
        "TOTPOP2000": 239,
        "MALE2000": 110,
        "FEMALE2000": 129,
        "POP2008": 284,
        "G_RATE": 1.0219999551773071,
        "Geocode_Num": 14052202027,
        "PROVINCE": 14
      }
    },
    {
      "type": "Feature",
      "id": 7155,
      "geometry": {
        "type": "Point",
        "coordinates": [
          143.036042165014,
          -3.716385749902372
        ]
      },
      "properties": {
        "OBJECTID": 7155,
        "CU_NAME": "TIADIKIM",
        "CU_NO": "040",
        "GEOCODE": "14052202040",
        "PROV_KEY": "14",
        "DIST_NO": "05",
        "LLG_NO": "22",
        "WARD_NO": "02",
        "WARD_NAME": "TIADIKIM",
        "LATITUDE": -3.715126,
        "LONGITUDE": 143.032808,
        "REGHH": 109,
        "TOTPOP2000": 533,
        "MALE2000": 264,
        "FEMALE2000": 269,
        "POP2008": 635,
        "G_RATE": 1.0219999551773071,
        "Geocode_Num": 14052202040,
        "PROVINCE": 14
      }
    }
  ]
}