{
  "type": "FeatureCollection",
  "features": [
    {
      "type": "Feature",
      "id": 7160,
      "geometry": {
        "type": "Point",
        "coordinates": [
          143.02363392016935,
          -3.719249999787621
        ]
      },
      "properties": {
        "OBJECTID": 7160,
        "CU_NAME": "TUKOIKIM",
        "CU_NO": "042",
        "GEOCODE": "14052206042",
        "PROV_KEY": "14",
        "DIST_NO": "05",
        "LLG_NO": "22",
        "WARD_NO": "06",
        "WARD_NAME": "TUKOIKIM",
        "LATITUDE": -3.716515,
        "LONGITUDE": 143.022394,
        "REGHH": 88,
        "TOTPOP2000": 490,
        "MALE2000": 228,
        "FEMALE2000": 262,
        "POP2008": 584,
        "G_RATE": 1.0219999551773071,
        "Geocode_Num": 14052206042,
        "PROVINCE": 14
      }
    }
  ]
}