{
  "type": "FeatureCollection",
  "features": [
    {
      "type": "Feature",
      "id": 13033,
      "geometry": {
        "type": "Point",
        "coordinates": [
          148.37934300007942,
          -8.735776000062287
        ]
      },
      "properties": {
        "OBJECTID": 13033,
        "CU_NAME": "ANGO",
        "CU_NO": "001",
        "GEOCODE": "06010112001",
        "PROV_KEY": "06",
        "DIST_NO": "01",
        "LLG_NO": "01",
        "WARD_NO": "12",
        "WARD_NAME": "DOBUDURU",
        "LATITUDE": -8.737222,
        "LONGITUDE": 148.378333,
        "REGHH": 34,
        "TOTPOP2000": 196,
        "MALE2000": 112,
        "FEMALE2000": 84,
        "POP2008": 242,
        "G_RATE": 1.0269999504089355,
        "Geocode_Num": 6010112001,
        "PROVINCE": 6
      }
    },
    {
      "type": "Feature",
      "id": 13034,
      "geometry": {
        "type": "Point",
        "coordinates": [
          148.37619599974562,
          -8.767977000238318
        ]
      },
      "properties": {
        "OBJECTID": 13034,
        "CU_NAME": "DOBUDURU",
        "CU_NO": "013",
        "GEOCODE": "06010112013",
        "PROV_KEY": "06",
        "DIST_NO": "01",
        "LLG_NO": "01",
        "WARD_NO": "12",
        "WARD_NAME": "DOBUDURU",
        "LATITUDE": -8.769423,
        "LONGITUDE": 148.375186,
        "REGHH": 24,
        "TOTPOP2000": 153,
        "MALE2000": 89,
        "FEMALE2000": 64,
        "POP2008": 189,
        "G_RATE": 1.0269999504089355,
        "Geocode_Num": 6010112013,
        "PROVINCE": 6
      }
    },
    {
      "type": "Feature",
      "id": 13035,
      "geometry": {
        "type": "Point",
        "coordinates": [
          148.3804780002596,
          -8.756937000142386
        ]
      },
      "properties": {
        "OBJECTID": 13035,
        "CU_NAME": "PENUBATA",
        "CU_NO": "056",
        "GEOCODE": "06010112056",
        "PROV_KEY": "06",
        "DIST_NO": "01",
        "LLG_NO": "01",
        "WARD_NO": "12",
        "WARD_NAME": "DOBUDURU",
        "LATITUDE": -8.75338,
        "LONGITUDE": 148.381332,
        "REGHH": 10,
        "TOTPOP2000": 51,
        "MALE2000": 27,
        "FEMALE2000": 24,
        "POP2008": 62,
        "G_RATE": 1.0269999504089355,
        "Geocode_Num": 6010112056,
        "PROVINCE": 6
      }
    },
    {
      "type": "Feature",
      "id": 13036,
      "geometry": {
        "type": "Point",
        "coordinates": [
          148.37406600044562,
          -8.769664999839847
        ]
      },
      "properties": {
        "OBJECTID": 13036,
        "CU_NAME": "PARAHE OIL PALM BLOCKS",
        "CU_NO": "057",
        "GEOCODE": "06010112057",
        "PROV_KEY": "06",
        "DIST_NO": "01",
        "LLG_NO": "01",
        "WARD_NO": "12",
        "WARD_NAME": "DOBUDURU",
        "LATITUDE": -8.771111,
        "LONGITUDE": 148.373056,
        "REGHH": 53,
        "TOTPOP2000": 312,
        "MALE2000": 166,
        "FEMALE2000": 146,
        "POP2008": 386,
        "G_RATE": 1.0269999504089355,
        "Geocode_Num": 6010112057,
        "PROVINCE": 6
      }
    }
  ]
}