{
  "type": "FeatureCollection",
  "features": [
    {
      "type": "Feature",
      "id": 13047,
      "geometry": {
        "type": "Point",
        "coordinates": [
          148.40461600002845,
          -8.668113999561399
        ]
      },
      "properties": {
        "OBJECTID": 13047,
        "CU_NAME": "BUNA",
        "CU_NO": "011",
        "GEOCODE": "06010115011",
        "PROV_KEY": "06",
        "DIST_NO": "01",
        "LLG_NO": "01",
        "WARD_NO": "15",
        "WARD_NAME": "BUNA",
        "LATITUDE": -8.664529,
        "LONGITUDE": 148.39724,
        "REGHH": 83,
        "TOTPOP2000": 539,
        "MALE2000": 278,
        "FEMALE2000": 261,
        "POP2008": 668,
        "G_RATE": 1.0269999504089355,
        "Geocode_Num": 6010115011,
        "PROVINCE": 6
      }
    },
    {
      "type": "Feature",
      "id": 13048,
      "geometry": {
        "type": "Point",
        "coordinates": [
          148.36962099960954,
          -8.639111000272408
        ]
      },
      "properties": {
        "OBJECTID": 13048,
        "CU_NAME": "SANANANDA",
        "CU_NO": "037",
        "GEOCODE": "06010115037",
        "PROV_KEY": "06",
        "DIST_NO": "01",
        "LLG_NO": "01",
        "WARD_NO": "15",
        "WARD_NAME": "BUNA",
        "LATITUDE": -8.640556,
        "LONGITUDE": 148.368611,
        "REGHH": 66,
        "TOTPOP2000": 445,
        "MALE2000": 220,
        "FEMALE2000": 225,
        "POP2008": 550,
        "G_RATE": 1.0269999504089355,
        "Geocode_Num": 6010115037,
        "PROVINCE": 6
      }
    }
  ]
}