{
  "type": "FeatureCollection",
  "features": [
    {
      "type": "Feature",
      "id": 6668,
      "geometry": {
        "type": "Point",
        "coordinates": [
          143.04897199955815,
          -3.665646000062793
        ]
      },
      "properties": {
        "OBJECTID": 6668,
        "CU_NAME": "NUMAKUM",
        "CU_NO": "013",
        "GEOCODE": "14031212013",
        "PROV_KEY": "14",
        "DIST_NO": "03",
        "LLG_NO": "12",
        "WARD_NO": "12",
        "WARD_NAME": "WORA",
        "LATITUDE": -3.667224,
        "LONGITUDE": 143.047733,
        "REGHH": 55,
        "TOTPOP2000": 273,
        "MALE2000": 147,
        "FEMALE2000": 126,
        "POP2008": 325,
        "G_RATE": 1.0219999551773071,
        "Geocode_Num": 14031212013,
        "PROVINCE": 14
      }
    },
    {
      "type": "Feature",
      "id": 6669,
      "geometry": {
        "type": "Point",
        "coordinates": [
          143.02266400044334,
          -3.679162000126155
        ]
      },
      "properties": {
        "OBJECTID": 6669,
        "CU_NAME": "SERANDU",
        "CU_NO": "017",
        "GEOCODE": "14031212017",
        "PROV_KEY": "14",
        "DIST_NO": "03",
        "LLG_NO": "12",
        "WARD_NO": "12",
        "WARD_NAME": "WORA",
        "LATITUDE": -3.68074,
        "LONGITUDE": 143.021423,
        "REGHH": 41,
        "TOTPOP2000": 195,
        "MALE2000": 95,
        "FEMALE2000": 100,
        "POP2008": 232,
        "G_RATE": 1.0219999551773071,
        "Geocode_Num": 14031212017,
        "PROVINCE": 14
      }
    },
    {
      "type": "Feature",
      "id": 6670,
      "geometry": {
        "type": "Point",
        "coordinates": [
          143.05014100040694,
          -3.6802089998454335
        ]
      },
      "properties": {
        "OBJECTID": 6670,
        "CU_NAME": "WORA",
        "CU_NO": "018",
        "GEOCODE": "14031212018",
        "PROV_KEY": "14",
        "DIST_NO": "03",
        "LLG_NO": "12",
        "WARD_NO": "12",
        "WARD_NAME": "WORA",
        "LATITUDE": -3.682811,
        "LONGITUDE": 143.048397,
        "REGHH": 146,
        "TOTPOP2000": 789,
        "MALE2000": 393,
        "FEMALE2000": 396,
        "POP2008": 939,
        "G_RATE": 1.0219999551773071,
        "Geocode_Num": 14031212018,
        "PROVINCE": 14
      }
    }
  ]
}