{
  "type": "FeatureCollection",
  "features": [
    {
      "type": "Feature",
      "id": 14873,
      "geometry": {
        "type": "Point",
        "coordinates": [
          145.05992999996954,
          -6.0917840000315095
        ]
      },
      "properties": {
        "OBJECTID": 14873,
        "CU_NAME": "MASUL",
        "CU_NO": "004",
        "GEOCODE": "10061707004",
        "PROV_KEY": "10",
        "DIST_NO": "06",
        "LLG_NO": "17",
        "WARD_NO": "07",
        "WARD_NAME": "MASUL 1",
        "LATITUDE": -6.093195,
        "LONGITUDE": 145.058881,
        "REGHH": 68,
        "TOTPOP2000": 386,
        "MALE2000": 191,
        "FEMALE2000": 195,
        "POP2008": 445,
        "G_RATE": 1.0180000066757202,
        "Geocode_Num": 10061707004,
        "PROVINCE": 10
      }
    },
    {
      "type": "Feature",
      "id": 14874,
      "geometry": {
        "type": "Point",
        "coordinates": [
          145.06222399963792,
          -6.096609999551788
        ]
      },
      "properties": {
        "OBJECTID": 14874,
        "CU_NAME": "DINIMA",
        "CU_NO": "005",
        "GEOCODE": "10061707005",
        "PROV_KEY": "10",
        "DIST_NO": "06",
        "LLG_NO": "17",
        "WARD_NO": "07",
        "WARD_NAME": "MASUL 1",
        "LATITUDE": -6.0953,
        "LONGITUDE": 145.063366,
        "REGHH": 57,
        "TOTPOP2000": 239,
        "MALE2000": 118,
        "FEMALE2000": 121,
        "POP2008": 276,
        "G_RATE": 1.0180000066757202,
        "Geocode_Num": 10061707005,
        "PROVINCE": 10
      }
    },
    {
      "type": "Feature",
      "id": 14875,
      "geometry": {
        "type": "Point",
        "coordinates": [
          145.06075900042754,
          -6.092379999637217
        ]
      },
      "properties": {
        "OBJECTID": 14875,
        "CU_NAME": "MASUL POLICE STN",
        "CU_NO": "401",
        "GEOCODE": "10061707401",
        "PROV_KEY": "10",
        "DIST_NO": "06",
        "LLG_NO": "17",
        "WARD_NO": "07",
        "WARD_NAME": "MASUL 1",
        "LATITUDE": -6.093791,
        "LONGITUDE": 145.05971,
        "REGHH": 2,
        "TOTPOP2000": 14,
        "MALE2000": 9,
        "FEMALE2000": 5,
        "POP2008": 14,
        "G_RATE": 1.0180000066757202,
        "Geocode_Num": 10061707401,
        "PROVINCE": 10
      }
    },
    {
      "type": "Feature",
      "id": 14876,
      "geometry": {
        "type": "Point",
        "coordinates": [
          145.06512899960376,
          -6.095231999856878
        ]
      },
      "properties": {
        "OBJECTID": 14876,
        "CU_NAME": "DINIMA C/S",
        "CU_NO": "402",
        "GEOCODE": "10061707402",
        "PROV_KEY": "10",
        "DIST_NO": "06",
        "LLG_NO": "17",
        "WARD_NO": "07",
        "WARD_NAME": "MASUL 1",
        "LATITUDE": -6.096643,
        "LONGITUDE": 145.06408,
        "REGHH": 4,
        "TOTPOP2000": 24,
        "MALE2000": 13,
        "FEMALE2000": 11,
        "POP2008": 24,
        "G_RATE": 1.0180000066757202,
        "Geocode_Num": 10061707402,
        "PROVINCE": 10
      }
    }
  ]
}