{
  "type": "FeatureCollection",
  "features": [
    {
      "type": "Feature",
      "id": 17780,
      "geometry": {
        "type": "Point",
        "coordinates": [
          149.47561400038592,
          -6.0917490002161685
        ]
      },
      "properties": {
        "OBJECTID": 17780,
        "CU_NAME": "AMGORENG",
        "CU_NO": "005",
        "GEOCODE": "19010306005",
        "PROV_KEY": "19",
        "DIST_NO": "01",
        "LLG_NO": "03",
        "WARD_NO": "06",
        "WARD_NAME": "LOKO NAMBIS",
        "LATITUDE": -6.093201,
        "LONGITUDE": 149.467626,
        "REGHH": 34,
        "TOTPOP2000": 188,
        "MALE2000": 113,
        "FEMALE2000": 75,
        "POP2008": 248,
        "G_RATE": 1.034999966621399,
        "Geocode_Num": 19010306005,
        "PROVINCE": 19
      }
    },
    {
      "type": "Feature",
      "id": 17781,
      "geometry": {
        "type": "Point",
        "coordinates": [
          149.4583019997376,
          -6.095278000179519
        ]
      },
      "properties": {
        "OBJECTID": 17781,
        "CU_NAME": "ARESVO (BUPON)",
        "CU_NO": "010",
        "GEOCODE": "19010306010",
        "PROV_KEY": "19",
        "DIST_NO": "01",
        "LLG_NO": "03",
        "WARD_NO": "06",
        "WARD_NAME": "LOKO NAMBIS",
        "LATITUDE": -6.096697,
        "LONGITUDE": 149.457313,
        "REGHH": 28,
        "TOTPOP2000": 178,
        "MALE2000": 94,
        "FEMALE2000": 84,
        "POP2008": 234,
        "G_RATE": 1.034999966621399,
        "Geocode_Num": 19010306010,
        "PROVINCE": 19
      }
    },
    {
      "type": "Feature",
      "id": 17782,
      "geometry": {
        "type": "Point",
        "coordinates": [
          149.4323629996528,
          -6.087322000210122
        ]
      },
      "properties": {
        "OBJECTID": 17782,
        "CU_NAME": "OKUR",
        "CU_NO": "016",
        "GEOCODE": "19010306016",
        "PROV_KEY": "19",
        "DIST_NO": "01",
        "LLG_NO": "03",
        "WARD_NO": "06",
        "WARD_NAME": "LOKO NAMBIS",
        "LATITUDE": -6.088741,
        "LONGITUDE": 149.431374,
        "REGHH": 86,
        "TOTPOP2000": 426,
        "MALE2000": 215,
        "FEMALE2000": 211,
        "POP2008": 561,
        "G_RATE": 1.034999966621399,
        "Geocode_Num": 19010306016,
        "PROVINCE": 19
      }
    },
    {
      "type": "Feature",
      "id": 17783,
      "geometry": {
        "type": "Point",
        "coordinates": [
          149.4797159997936,
          -6.097832000146639
        ]
      },
      "properties": {
        "OBJECTID": 17783,
        "CU_NAME": "AULO",
        "CU_NO": "405",
        "GEOCODE": "19010306405",
        "PROV_KEY": "19",
        "DIST_NO": "01",
        "LLG_NO": "03",
        "WARD_NO": "06",
        "WARD_NAME": "LOKO NAMBIS",
        "LATITUDE": -6.10335,
        "LONGITUDE": 149.474,
        "REGHH": 25,
        "TOTPOP2000": 140,
        "MALE2000": 66,
        "FEMALE2000": 74,
        "POP2008": 184,
        "G_RATE": 1.034999966621399,
        "Geocode_Num": 19010306405,
        "PROVINCE": 19
      }
    }
  ]
}