{
  "type": "FeatureCollection",
  "features": [
    {
      "type": "Feature",
      "id": 12509,
      "geometry": {
        "type": "Point",
        "coordinates": [
          150.96010699993815,
          -2.7815149998173183
        ]
      },
      "properties": {
        "OBJECTID": 12509,
        "CU_NAME": "BAGATARE",
        "CU_NO": "002",
        "GEOCODE": "17010305002",
        "PROV_KEY": "17",
        "DIST_NO": "01",
        "LLG_NO": "03",
        "WARD_NO": "05",
        "WARD_NAME": "BAGATARE",
        "LATITUDE": -2.782893,
        "LONGITUDE": 150.959145,
        "REGHH": 13,
        "TOTPOP2000": 55,
        "MALE2000": 27,
        "FEMALE2000": 28,
        "POP2008": 71,
        "G_RATE": 1.0290000438690186,
        "Geocode_Num": 17010305002,
        "PROVINCE": 17
      }
    },
    {
      "type": "Feature",
      "id": 12510,
      "geometry": {
        "type": "Point",
        "coordinates": [
          150.8937490002163,
          -2.7691420003030203
        ]
      },
      "properties": {
        "OBJECTID": 12510,
        "CU_NAME": "KAUT",
        "CU_NO": "010",
        "GEOCODE": "17010305010",
        "PROV_KEY": "17",
        "DIST_NO": "01",
        "LLG_NO": "03",
        "WARD_NO": "05",
        "WARD_NAME": "BAGATARE",
        "LATITUDE": -2.77052,
        "LONGITUDE": 150.892786,
        "REGHH": 50,
        "TOTPOP2000": 272,
        "MALE2000": 143,
        "FEMALE2000": 129,
        "POP2008": 342,
        "G_RATE": 1.0290000438690186,
        "Geocode_Num": 17010305010,
        "PROVINCE": 17
      }
    },
    {
      "type": "Feature",
      "id": 12511,
      "geometry": {
        "type": "Point",
        "coordinates": [
          150.88172399966288,
          -2.700235999991378
        ]
      },
      "properties": {
        "OBJECTID": 12511,
        "CU_NAME": "TOME",
        "CU_NO": "024",
        "GEOCODE": "17010305024",
        "PROV_KEY": "17",
        "DIST_NO": "01",
        "LLG_NO": "03",
        "WARD_NO": "05",
        "WARD_NAME": "BAGATARE",
        "LATITUDE": -2.699489,
        "LONGITUDE": 150.881609,
        "REGHH": 29,
        "TOTPOP2000": 170,
        "MALE2000": 89,
        "FEMALE2000": 81,
        "POP2008": 214,
        "G_RATE": 1.0290000438690186,
        "Geocode_Num": 17010305024,
        "PROVINCE": 17
      }
    }
  ]
}