{
  "type": "FeatureCollection",
  "features": [
    {
      "type": "Feature",
      "id": 12567,
      "geometry": {
        "type": "Point",
        "coordinates": [
          151.08440000035978,
          -2.834127999707391
        ]
      },
      "properties": {
        "OBJECTID": 12567,
        "CU_NAME": "LAVOLAI",
        "CU_NO": "005",
        "GEOCODE": "17010316005",
        "PROV_KEY": "17",
        "DIST_NO": "01",
        "LLG_NO": "03",
        "WARD_NO": "16",
        "WARD_NAME": "LAMUSMUS",
        "LATITUDE": -2.835507,
        "LONGITUDE": 151.083439,
        "REGHH": 69,
        "TOTPOP2000": 330,
        "MALE2000": 182,
        "FEMALE2000": 148,
        "POP2008": 415,
        "G_RATE": 1.0290000438690186,
        "Geocode_Num": 17010316005,
        "PROVINCE": 17
      }
    },
    {
      "type": "Feature",
      "id": 12568,
      "geometry": {
        "type": "Point",
        "coordinates": [
          151.13966900042408,
          -2.8917389998549083
        ]
      },
      "properties": {
        "OBJECTID": 12568,
        "CU_NAME": "LAMUSMUS 1",
        "CU_NO": "007",
        "GEOCODE": "17010316007",
        "PROV_KEY": "17",
        "DIST_NO": "01",
        "LLG_NO": "03",
        "WARD_NO": "16",
        "WARD_NAME": "LAMUSMUS",
        "LATITUDE": -2.893119,
        "LONGITUDE": 151.138709,
        "REGHH": 90,
        "TOTPOP2000": 528,
        "MALE2000": 288,
        "FEMALE2000": 240,
        "POP2008": 664,
        "G_RATE": 1.0290000438690186,
        "Geocode_Num": 17010316007,
        "PROVINCE": 17
      }
    },
    {
      "type": "Feature",
      "id": 12569,
      "geometry": {
        "type": "Point",
        "coordinates": [
          151.1241279996076,
          -2.8696959995706948
        ]
      },
      "properties": {
        "OBJECTID": 12569,
        "CU_NAME": "LAMASMUS 2",
        "CU_NO": "008",
        "GEOCODE": "17010316008",
        "PROV_KEY": "17",
        "DIST_NO": "01",
        "LLG_NO": "03",
        "WARD_NO": "16",
        "WARD_NAME": "LAMUSMUS",
        "LATITUDE": -2.871076,
        "LONGITUDE": 151.123168,
        "REGHH": 54,
        "TOTPOP2000": 304,
        "MALE2000": 170,
        "FEMALE2000": 134,
        "POP2008": 382,
        "G_RATE": 1.0290000438690186,
        "Geocode_Num": 17010316008,
        "PROVINCE": 17
      }
    },
    {
      "type": "Feature",
      "id": 12570,
      "geometry": {
        "type": "Point",
        "coordinates": [
          151.051634000209,
          -2.8290450000266674
        ]
      },
      "properties": {
        "OBJECTID": 12570,
        "CU_NAME": "SICACUI PLTN",
        "CU_NO": "509",
        "GEOCODE": "17010316509",
        "PROV_KEY": "17",
        "DIST_NO": "01",
        "LLG_NO": "03",
        "WARD_NO": "16",
        "WARD_NAME": "LAMUSMUS",
        "LATITUDE": -2.830424,
        "LONGITUDE": 151.050673,
        "REGHH": 14,
        "TOTPOP2000": 93,
        "MALE2000": 58,
        "FEMALE2000": 35,
        "POP2008": 117,
        "G_RATE": 1.0290000438690186,
        "Geocode_Num": 17010316509,
        "PROVINCE": 17
      }
    }
  ]
}