{
  "type": "FeatureCollection",
  "features": [
    {
      "type": "Feature",
      "id": 18193,
      "geometry": {
        "type": "Point",
        "coordinates": [
          150.37797500044599,
          -5.626024999953756
        ]
      },
      "properties": {
        "OBJECTID": 18193,
        "CU_NAME": "BUVUSSI SETTLEMENT",
        "CU_NO": "502",
        "GEOCODE": "19021002502",
        "PROV_KEY": "19",
        "DIST_NO": "02",
        "LLG_NO": "10",
        "WARD_NO": "02",
        "WARD_NAME": "BUGAL",
        "LATITUDE": -5.62744,
        "LONGITUDE": 150.377,
        "REGHH": 520,
        "TOTPOP2000": 3543,
        "MALE2000": 1865,
        "FEMALE2000": 1678,
        "POP2008": 4664,
        "G_RATE": 1.034999966621399,
        "Geocode_Num": 19021002502,
        "PROVINCE": 19
      }
    },
    {
      "type": "Feature",
      "id": 18194,
      "geometry": {
        "type": "Point",
        "coordinates": [
          150.37477500036607,
          -5.663290999879678
        ]
      },
      "properties": {
        "OBJECTID": 18194,
        "CU_NAME": "GALAI 1 SETTLEMENT",
        "CU_NO": "504",
        "GEOCODE": "19021002504",
        "PROV_KEY": "19",
        "DIST_NO": "02",
        "LLG_NO": "10",
        "WARD_NO": "02",
        "WARD_NAME": "BUGAL",
        "LATITUDE": -5.6643,
        "LONGITUDE": 150.373,
        "REGHH": 274,
        "TOTPOP2000": 1999,
        "MALE2000": 1058,
        "FEMALE2000": 941,
        "POP2008": 2632,
        "G_RATE": 1.034999966621399,
        "Geocode_Num": 19021002504,
        "PROVINCE": 19
      }
    }
  ]
}