{
  "type": "FeatureCollection",
  "features": [
    {
      "type": "Feature",
      "id": 18195,
      "geometry": {
        "type": "Point",
        "coordinates": [
          150.30337200001782,
          -5.588027000445663
        ]
      },
      "properties": {
        "OBJECTID": 18195,
        "CU_NAME": "KAVUI SETTLEMENT",
        "CU_NO": "507",
        "GEOCODE": "19021003507",
        "PROV_KEY": "19",
        "DIST_NO": "02",
        "LLG_NO": "10",
        "WARD_NO": "03",
        "WARD_NAME": "KAVUI",
        "LATITUDE": -5.59026,
        "LONGITUDE": 150.306,
        "REGHH": 438,
        "TOTPOP2000": 3224,
        "MALE2000": 1758,
        "FEMALE2000": 1466,
        "POP2008": 4246,
        "G_RATE": 1.034999966621399,
        "Geocode_Num": 19021003507,
        "PROVINCE": 19
      }
    }
  ]
}