{
  "type": "FeatureCollection",
  "features": [
    {
      "type": "Feature",
      "id": 19348,
      "geometry": {
        "type": "Point",
        "coordinates": [
          144.10842599996,
          -6.424899000388507
        ]
      },
      "properties": {
        "OBJECTID": 19348,
        "CU_NAME": "POLOKO",
        "CU_NO": "026",
        "GEOCODE": "07010402026",
        "PROV_KEY": "07",
        "DIST_NO": "01",
        "LLG_NO": "04",
        "WARD_NO": "02",
        "WARD_NAME": "POLOKO 1",
        "LATITUDE": -6.433245,
        "LONGITUDE": 144.109646,
        "REGHH": 15,
        "TOTPOP2000": 70,
        "MALE2000": 37,
        "FEMALE2000": 33,
        "POP2008": 97,
        "G_RATE": 1.0420000553131104,
        "Geocode_Num": 7010402026,
        "PROVINCE": 7
      }
    },
    {
      "type": "Feature",
      "id": 19349,
      "geometry": {
        "type": "Point",
        "coordinates": [
          144.11207199992293,
          -6.425333999764234
        ]
      },
      "properties": {
        "OBJECTID": 19349,
        "CU_NAME": "ANDAU",
        "CU_NO": "027",
        "GEOCODE": "07010402027",
        "PROV_KEY": "07",
        "DIST_NO": "01",
        "LLG_NO": "04",
        "WARD_NO": "02",
        "WARD_NAME": "POLOKO 1",
        "LATITUDE": -6.433245,
        "LONGITUDE": 144.109646,
        "REGHH": 9,
        "TOTPOP2000": 50,
        "MALE2000": 26,
        "FEMALE2000": 24,
        "POP2008": 69,
        "G_RATE": 1.0420000553131104,
        "Geocode_Num": 7010402027,
        "PROVINCE": 7
      }
    },
    {
      "type": "Feature",
      "id": 19350,
      "geometry": {
        "type": "Point",
        "coordinates": [
          144.114371999868,
          -6.428969000119196
        ]
      },
      "properties": {
        "OBJECTID": 19350,
        "CU_NAME": "TIAWEA",
        "CU_NO": "028",
        "GEOCODE": "07010402028",
        "PROV_KEY": "07",
        "DIST_NO": "01",
        "LLG_NO": "04",
        "WARD_NO": "02",
        "WARD_NAME": "POLOKO 1",
        "LATITUDE": -6.433245,
        "LONGITUDE": 144.109646,
        "REGHH": 21,
        "TOTPOP2000": 71,
        "MALE2000": 36,
        "FEMALE2000": 35,
        "POP2008": 98,
        "G_RATE": 1.0420000553131104,
        "Geocode_Num": 7010402028,
        "PROVINCE": 7
      }
    },
    {
      "type": "Feature",
      "id": 19351,
      "geometry": {
        "type": "Point",
        "coordinates": [
          144.1134830002403,
          -6.432624999643963
        ]
      },
      "properties": {
        "OBJECTID": 19351,
        "CU_NAME": "PONDIA",
        "CU_NO": "029",
        "GEOCODE": "07010402029",
        "PROV_KEY": "07",
        "DIST_NO": "01",
        "LLG_NO": "04",
        "WARD_NO": "02",
        "WARD_NAME": "POLOKO 1",
        "LATITUDE": -6.433245,
        "LONGITUDE": 144.109646,
        "REGHH": 28,
        "TOTPOP2000": 128,
        "MALE2000": 66,
        "FEMALE2000": 62,
        "POP2008": 178,
        "G_RATE": 1.0420000553131104,
        "Geocode_Num": 7010402029,
        "PROVINCE": 7
      }
    }
  ]
}