{
  "type": "FeatureCollection",
  "features": [
    {
      "type": "Feature",
      "id": 19441,
      "geometry": {
        "type": "Point",
        "coordinates": [
          144.21168199972453,
          -6.465359000117701
        ]
      },
      "properties": {
        "OBJECTID": 19441,
        "CU_NAME": "POLUANE",
        "CU_NO": "001",
        "GEOCODE": "07010420001",
        "PROV_KEY": "07",
        "DIST_NO": "01",
        "LLG_NO": "04",
        "WARD_NO": "20",
        "WARD_NAME": "TIMBARI 2",
        "LATITUDE": -6.469927,
        "LONGITUDE": 144.210943,
        "REGHH": 7,
        "TOTPOP2000": 37,
        "MALE2000": 19,
        "FEMALE2000": 18,
        "POP2008": 53,
        "G_RATE": 1.0420000553131104,
        "Geocode_Num": 7010420001,
        "PROVINCE": 7
      }
    },
    {
      "type": "Feature",
      "id": 19442,
      "geometry": {
        "type": "Point",
        "coordinates": [
          144.2126819999744,
          -6.467685000362451
        ]
      },
      "properties": {
        "OBJECTID": 19442,
        "CU_NAME": "WILLIAM",
        "CU_NO": "002",
        "GEOCODE": "07010420002",
        "PROV_KEY": "07",
        "DIST_NO": "01",
        "LLG_NO": "04",
        "WARD_NO": "20",
        "WARD_NAME": "TIMBARI 2",
        "LATITUDE": -6.469927,
        "LONGITUDE": 144.210943,
        "REGHH": 21,
        "TOTPOP2000": 122,
        "MALE2000": 61,
        "FEMALE2000": 61,
        "POP2008": 170,
        "G_RATE": 1.0420000553131104,
        "Geocode_Num": 7010420002,
        "PROVINCE": 7
      }
    },
    {
      "type": "Feature",
      "id": 19443,
      "geometry": {
        "type": "Point",
        "coordinates": [
          144.21063500000525,
          -6.462454000151922
        ]
      },
      "properties": {
        "OBJECTID": 19443,
        "CU_NAME": "WILLIAM COMM. SCH",
        "CU_NO": "801",
        "GEOCODE": "07010420801",
        "PROV_KEY": "07",
        "DIST_NO": "01",
        "LLG_NO": "04",
        "WARD_NO": "20",
        "WARD_NAME": "TIMBARI 2",
        "LATITUDE": -6.469927,
        "LONGITUDE": 144.210943,
        "REGHH": 21,
        "TOTPOP2000": 120,
        "MALE2000": 59,
        "FEMALE2000": 61,
        "POP2008": 166,
        "G_RATE": 1.0420000553131104,
        "Geocode_Num": 7010420801,
        "PROVINCE": 7
      }
    }
  ]
}