{
  "type": "FeatureCollection",
  "features": [
    {
      "type": "Feature",
      "id": 18421,
      "geometry": {
        "type": "Point",
        "coordinates": [
          142.03824799984534,
          -3.1471200001877833
        ]
      },
      "properties": {
        "OBJECTID": 18421,
        "CU_NAME": "BARERA",
        "CU_NO": "008",
        "GEOCODE": "15010315008",
        "PROV_KEY": "15",
        "DIST_NO": "01",
        "LLG_NO": "03",
        "WARD_NO": "15",
        "WARD_NAME": "BARERA",
        "LATITUDE": -3.148495,
        "LONGITUDE": 142.037166,
        "REGHH": 58,
        "TOTPOP2000": 392,
        "MALE2000": 205,
        "FEMALE2000": 187,
        "POP2008": 474,
        "G_RATE": 1.0240000486373901,
        "Geocode_Num": 15010315008,
        "PROVINCE": 15
      }
    }
  ]
}