{
  "type": "FeatureCollection",
  "features": [
    {
      "type": "Feature",
      "id": 18422,
      "geometry": {
        "type": "Point",
        "coordinates": [
          141.9555520003246,
          -3.2167450003814224
        ]
      },
      "properties": {
        "OBJECTID": 18422,
        "CU_NAME": "KAIYE",
        "CU_NO": "011",
        "GEOCODE": "15010316011",
        "PROV_KEY": "15",
        "DIST_NO": "01",
        "LLG_NO": "03",
        "WARD_NO": "16",
        "WARD_NAME": "KAIYE",
        "LATITUDE": -3.21812,
        "LONGITUDE": 141.954469,
        "REGHH": 14,
        "TOTPOP2000": 114,
        "MALE2000": 64,
        "FEMALE2000": 50,
        "POP2008": 138,
        "G_RATE": 1.0240000486373901,
        "Geocode_Num": 15010316011,
        "PROVINCE": 15
      }
    },
    {
      "type": "Feature",
      "id": 18423,
      "geometry": {
        "type": "Point",
        "coordinates": [
          141.98096500043448,
          -3.2134660002556643
        ]
      },
      "properties": {
        "OBJECTID": 18423,
        "CU_NAME": "KARANDU",
        "CU_NO": "012",
        "GEOCODE": "15010316012",
        "PROV_KEY": "15",
        "DIST_NO": "01",
        "LLG_NO": "03",
        "WARD_NO": "16",
        "WARD_NAME": "KAIYE",
        "LATITUDE": -3.2192,
        "LONGITUDE": 141.974832,
        "REGHH": 25,
        "TOTPOP2000": 144,
        "MALE2000": 76,
        "FEMALE2000": 68,
        "POP2008": 175,
        "G_RATE": 1.0240000486373901,
        "Geocode_Num": 15010316012,
        "PROVINCE": 15
      }
    }
  ]
}