{
  "type": "FeatureCollection",
  "features": [
    {
      "type": "Feature",
      "id": 16872,
      "geometry": {
        "type": "Point",
        "coordinates": [
          144.64323899997999,
          -5.487316000233193
        ]
      },
      "properties": {
        "OBJECTID": 16872,
        "CU_NAME": "KUPENG",
        "CU_NO": "007",
        "GEOCODE": "09040606007",
        "PROV_KEY": "22",
        "DIST_NO": "2",
        "LLG_NO": "06",
        "WARD_NO": "06",
        "WARD_NAME": "KUPENG",
        "LATITUDE": -5.488249,
        "LONGITUDE": 144.643578,
        "REGHH": 117,
        "TOTPOP2000": 582,
        "MALE2000": 286,
        "FEMALE2000": 296,
        "POP2008": 709,
        "G_RATE": 1.024999976158142,
        "Geocode_Num": 9040606007,
        "PROVINCE": 22
      }
    },
    {
      "type": "Feature",
      "id": 16873,
      "geometry": {
        "type": "Point",
        "coordinates": [
          144.66440500029057,
          -5.468772000327533
        ]
      },
      "properties": {
        "OBJECTID": 16873,
        "CU_NAME": "KOMONGWAI",
        "CU_NO": "008",
        "GEOCODE": "09040606008",
        "PROV_KEY": "22",
        "DIST_NO": "2",
        "LLG_NO": "06",
        "WARD_NO": "06",
        "WARD_NAME": "KUPENG",
        "LATITUDE": -5.469705,
        "LONGITUDE": 144.664743,
        "REGHH": 60,
        "TOTPOP2000": 290,
        "MALE2000": 138,
        "FEMALE2000": 152,
        "POP2008": 353,
        "G_RATE": 1.024999976158142,
        "Geocode_Num": 9040606008,
        "PROVINCE": 22
      }
    }
  ]
}