{
  "type": "FeatureCollection",
  "features": [
    {
      "type": "Feature",
      "id": 16882,
      "geometry": {
        "type": "Point",
        "coordinates": [
          144.55313299958834,
          -5.389634000308831
        ]
      },
      "properties": {
        "OBJECTID": 16882,
        "CU_NAME": "TSEMBANT",
        "CU_NO": "013",
        "GEOCODE": "09040613013",
        "PROV_KEY": "22",
        "DIST_NO": "2",
        "LLG_NO": "06",
        "WARD_NO": "13",
        "WARD_NAME": "TSEMBANT",
        "LATITUDE": -5.390566,
        "LONGITUDE": 144.55347,
        "REGHH": 64,
        "TOTPOP2000": 330,
        "MALE2000": 145,
        "FEMALE2000": 185,
        "POP2008": 402,
        "G_RATE": 1.024999976158142,
        "Geocode_Num": 9040613013,
        "PROVINCE": 22
      }
    }
  ]
}