{
  "type": "FeatureCollection",
  "features": [
    {
      "type": "Feature",
      "id": 16904,
      "geometry": {
        "type": "Point",
        "coordinates": [
          144.69003399956944,
          -5.654302999983429
        ]
      },
      "properties": {
        "OBJECTID": 16904,
        "CU_NAME": "KARAP",
        "CU_NO": "001",
        "GEOCODE": "09040628001",
        "PROV_KEY": "22",
        "DIST_NO": "2",
        "LLG_NO": "06",
        "WARD_NO": "28",
        "WARD_NAME": "KARAP",
        "LATITUDE": -5.656322,
        "LONGITUDE": 144.692248,
        "REGHH": 50,
        "TOTPOP2000": 241,
        "MALE2000": 122,
        "FEMALE2000": 119,
        "POP2008": 293,
        "G_RATE": 1.024999976158142,
        "Geocode_Num": 9040628001,
        "PROVINCE": 22
      }
    },
    {
      "type": "Feature",
      "id": 16905,
      "geometry": {
        "type": "Point",
        "coordinates": [
          144.67359100032445,
          -5.672373999660294
        ]
      },
      "properties": {
        "OBJECTID": 16905,
        "CU_NAME": "KONZA",
        "CU_NO": "002",
        "GEOCODE": "09040628002",
        "PROV_KEY": "22",
        "DIST_NO": "2",
        "LLG_NO": "06",
        "WARD_NO": "28",
        "WARD_NAME": "KARAP",
        "LATITUDE": -5.673309,
        "LONGITUDE": 144.67393,
        "REGHH": 82,
        "TOTPOP2000": 372,
        "MALE2000": 174,
        "FEMALE2000": 198,
        "POP2008": 454,
        "G_RATE": 1.024999976158142,
        "Geocode_Num": 9040628002,
        "PROVINCE": 22
      }
    },
    {
      "type": "Feature",
      "id": 16906,
      "geometry": {
        "type": "Point",
        "coordinates": [
          144.70666400024345,
          -5.637852000369492
        ]
      },
      "properties": {
        "OBJECTID": 16906,
        "CU_NAME": "NAMBA",
        "CU_NO": "003",
        "GEOCODE": "09040628003",
        "PROV_KEY": "22",
        "DIST_NO": "2",
        "LLG_NO": "06",
        "WARD_NO": "28",
        "WARD_NAME": "KARAP",
        "LATITUDE": -5.638787,
        "LONGITUDE": 144.707002,
        "REGHH": 54,
        "TOTPOP2000": 233,
        "MALE2000": 119,
        "FEMALE2000": 114,
        "POP2008": 284,
        "G_RATE": 1.024999976158142,
        "Geocode_Num": 9040628003,
        "PROVINCE": 22
      }
    },
    {
      "type": "Feature",
      "id": 16907,
      "geometry": {
        "type": "Point",
        "coordinates": [
          144.69325899990304,
          -5.65805000010738
        ]
      },
      "properties": {
        "OBJECTID": 16907,
        "CU_NAME": "TUP",
        "CU_NO": "004",
        "GEOCODE": "09040628004",
        "PROV_KEY": "22",
        "DIST_NO": "2",
        "LLG_NO": "06",
        "WARD_NO": "28",
        "WARD_NAME": "KARAP",
        "LATITUDE": -5.658985,
        "LONGITUDE": 144.693598,
        "REGHH": 92,
        "TOTPOP2000": 392,
        "MALE2000": 196,
        "FEMALE2000": 196,
        "POP2008": 478,
        "G_RATE": 1.024999976158142,
        "Geocode_Num": 9040628004,
        "PROVINCE": 22
      }
    }
  ]
}