{
  "type": "FeatureCollection",
  "features": [
    {
      "type": "Feature",
      "id": 12280,
      "geometry": {
        "type": "Point",
        "coordinates": [
          147.77431799977592,
          -5.470824999673937
        ]
      },
      "properties": {
        "OBJECTID": 12280,
        "CU_NAME": "MASELE",
        "CU_NO": "021",
        "GEOCODE": "12092702021",
        "PROV_KEY": "12",
        "DIST_NO": "09",
        "LLG_NO": "27",
        "WARD_NO": "02",
        "WARD_NAME": "MASELE",
        "LATITUDE": -5.475806,
        "LONGITUDE": 147.768568,
        "REGHH": 58,
        "TOTPOP2000": 323,
        "MALE2000": 165,
        "FEMALE2000": 158,
        "POP2008": 403,
        "G_RATE": 1.027999997138977,
        "Geocode_Num": 12092702021,
        "PROVINCE": 12
      }
    }
  ]
}