{
  "type": "FeatureCollection",
  "features": [
    {
      "type": "Feature",
      "id": 12299,
      "geometry": {
        "type": "Point",
        "coordinates": [
          147.92697499969654,
          -5.7535469999940005
        ]
      },
      "properties": {
        "OBJECTID": 12299,
        "CU_NAME": "MANGINGI",
        "CU_NO": "002",
        "GEOCODE": "12092711002",
        "PROV_KEY": "12",
        "DIST_NO": "09",
        "LLG_NO": "27",
        "WARD_NO": "11",
        "WARD_NAME": "ARONAE",
        "LATITUDE": -5.754959,
        "LONGITUDE": 147.925965,
        "REGHH": 20,
        "TOTPOP2000": 81,
        "MALE2000": 40,
        "FEMALE2000": 41,
        "POP2008": 100,
        "G_RATE": 1.027999997138977,
        "Geocode_Num": 12092711002,
        "PROVINCE": 12
      }
    },
    {
      "type": "Feature",
      "id": 12300,
      "geometry": {
        "type": "Point",
        "coordinates": [
          147.94461400013608,
          -5.789318000225478
        ]
      },
      "properties": {
        "OBJECTID": 12300,
        "CU_NAME": "ARONAI - MUTU",
        "CU_NO": "003",
        "GEOCODE": "12092711003",
        "PROV_KEY": "12",
        "DIST_NO": "09",
        "LLG_NO": "27",
        "WARD_NO": "11",
        "WARD_NAME": "ARONAE",
        "LATITUDE": -5.789389,
        "LONGITUDE": 147.946272,
        "REGHH": 56,
        "TOTPOP2000": 267,
        "MALE2000": 138,
        "FEMALE2000": 129,
        "POP2008": 333,
        "G_RATE": 1.027999997138977,
        "Geocode_Num": 12092711003,
        "PROVINCE": 12
      }
    }
  ]
}