{
  "type": "FeatureCollection",
  "features": [
    {
      "type": "Feature",
      "id": 13575,
      "geometry": {
        "type": "Point",
        "coordinates": [
          148.11397499964653,
          -8.893571000401323
        ]
      },
      "properties": {
        "OBJECTID": 13575,
        "CU_NAME": "KENDATA",
        "CU_NO": "011",
        "GEOCODE": "06020607011",
        "PROV_KEY": "06",
        "DIST_NO": "02",
        "LLG_NO": "06",
        "WARD_NO": "07",
        "WARD_NAME": "KENDATA",
        "LATITUDE": -8.895018,
        "LONGITUDE": 148.112961,
        "REGHH": 50,
        "TOTPOP2000": 305,
        "MALE2000": 165,
        "FEMALE2000": 140,
        "POP2008": 377,
        "G_RATE": 1.0269999504089355,
        "Geocode_Num": 6020607011,
        "PROVINCE": 6
      }
    },
    {
      "type": "Feature",
      "id": 13576,
      "geometry": {
        "type": "Point",
        "coordinates": [
          148.11212199963063,
          -8.891117999695894
        ]
      },
      "properties": {
        "OBJECTID": 13576,
        "CU_NAME": "URURU",
        "CU_NO": "035",
        "GEOCODE": "06020607035",
        "PROV_KEY": "06",
        "DIST_NO": "02",
        "LLG_NO": "06",
        "WARD_NO": "07",
        "WARD_NAME": "KENDATA",
        "LATITUDE": -8.892565,
        "LONGITUDE": 148.111108,
        "REGHH": 38,
        "TOTPOP2000": 200,
        "MALE2000": 110,
        "FEMALE2000": 90,
        "POP2008": 248,
        "G_RATE": 1.0269999504089355,
        "Geocode_Num": 6020607035,
        "PROVINCE": 6
      }
    },
    {
      "type": "Feature",
      "id": 13577,
      "geometry": {
        "type": "Point",
        "coordinates": [
          148.11338000008698,
          -8.900892999911946
        ]
      },
      "properties": {
        "OBJECTID": 13577,
        "CU_NAME": "SIGORETURU",
        "CU_NO": "036",
        "GEOCODE": "06020607036",
        "PROV_KEY": "06",
        "DIST_NO": "02",
        "LLG_NO": "06",
        "WARD_NO": "07",
        "WARD_NAME": "KENDATA",
        "LATITUDE": -8.90234,
        "LONGITUDE": 148.112366,
        "REGHH": 22,
        "TOTPOP2000": 88,
        "MALE2000": 41,
        "FEMALE2000": 47,
        "POP2008": 109,
        "G_RATE": 1.0269999504089355,
        "Geocode_Num": 6020607036,
        "PROVINCE": 6
      }
    },
    {
      "type": "Feature",
      "id": 13578,
      "geometry": {
        "type": "Point",
        "coordinates": [
          148.11866500008978,
          -8.90216300002237
        ]
      },
      "properties": {
        "OBJECTID": 13578,
        "CU_NAME": "SAVARITURU",
        "CU_NO": "038",
        "GEOCODE": "06020607038",
        "PROV_KEY": "06",
        "DIST_NO": "02",
        "LLG_NO": "06",
        "WARD_NO": "07",
        "WARD_NAME": "KENDATA",
        "LATITUDE": -8.90361,
        "LONGITUDE": 148.117651,
        "REGHH": 24,
        "TOTPOP2000": 123,
        "MALE2000": 79,
        "FEMALE2000": 44,
        "POP2008": 152,
        "G_RATE": 1.0269999504089355,
        "Geocode_Num": 6020607038,
        "PROVINCE": 6
      }
    }
  ]
}