{
  "type": "FeatureCollection",
  "features": [
    {
      "type": "Feature",
      "id": 7117,
      "geometry": {
        "type": "Point",
        "coordinates": [
          142.9862999998452,
          -3.725172000387488
        ]
      },
      "properties": {
        "OBJECTID": 7117,
        "CU_NAME": "KUMUNIKUM 2",
        "CU_NO": "017",
        "GEOCODE": "14052102017",
        "PROV_KEY": "14",
        "DIST_NO": "05",
        "LLG_NO": "21",
        "WARD_NO": "02",
        "WARD_NAME": "KUMUNIKUM 2",
        "LATITUDE": -3.726751,
        "LONGITUDE": 142.98506,
        "REGHH": 44,
        "TOTPOP2000": 232,
        "MALE2000": 111,
        "FEMALE2000": 121,
        "POP2008": 276,
        "G_RATE": 1.0219999551773071,
        "Geocode_Num": 14052102017,
        "PROVINCE": 14
      }
    }
  ]
}