{
  "type": "FeatureCollection",
  "features": [
    {
      "type": "Feature",
      "id": 7132,
      "geometry": {
        "type": "Point",
        "coordinates": [
          142.966321000314,
          -3.7811459996880785
        ]
      },
      "properties": {
        "OBJECTID": 7132,
        "CU_NAME": "GOLAKUM",
        "CU_NO": "006",
        "GEOCODE": "14052113006",
        "PROV_KEY": "14",
        "DIST_NO": "05",
        "LLG_NO": "21",
        "WARD_NO": "13",
        "WARD_NAME": "GOLAKUM",
        "LATITUDE": -3.782727,
        "LONGITUDE": 142.965079,
        "REGHH": 39,
        "TOTPOP2000": 177,
        "MALE2000": 88,
        "FEMALE2000": 89,
        "POP2008": 210,
        "G_RATE": 1.0219999551773071,
        "Geocode_Num": 14052113006,
        "PROVINCE": 14
      }
    }
  ]
}