{
  "type": "FeatureCollection",
  "features": [
    {
      "type": "Feature",
      "id": 7142,
      "geometry": {
        "type": "Point",
        "coordinates": [
          142.90422400013756,
          -3.793117000449172
        ]
      },
      "properties": {
        "OBJECTID": 7142,
        "CU_NAME": "JIPAKO",
        "CU_NO": "012",
        "GEOCODE": "14052119012",
        "PROV_KEY": "14",
        "DIST_NO": "05",
        "LLG_NO": "21",
        "WARD_NO": "19",
        "WARD_NAME": "JIPAKO",
        "LATITUDE": -3.794698,
        "LONGITUDE": 142.902983,
        "REGHH": 99,
        "TOTPOP2000": 355,
        "MALE2000": 173,
        "FEMALE2000": 182,
        "POP2008": 423,
        "G_RATE": 1.0219999551773071,
        "Geocode_Num": 14052119012,
        "PROVINCE": 14
      }
    }
  ]
}