{
  "type": "FeatureCollection",
  "features": [
    {
      "type": "Feature",
      "id": 7150,
      "geometry": {
        "type": "Point",
        "coordinates": [
          142.83632999972974,
          -3.814802999558708
        ]
      },
      "properties": {
        "OBJECTID": 7150,
        "CU_NAME": "NUNGWAIA",
        "CU_NO": "031",
        "GEOCODE": "14052127031",
        "PROV_KEY": "14",
        "DIST_NO": "05",
        "LLG_NO": "21",
        "WARD_NO": "27",
        "WARD_NAME": "NUNGWAIA",
        "LATITUDE": -3.819445,
        "LONGITUDE": 142.835602,
        "REGHH": 117,
        "TOTPOP2000": 491,
        "MALE2000": 246,
        "FEMALE2000": 245,
        "POP2008": 585,
        "G_RATE": 1.0219999551773071,
        "Geocode_Num": 14052127031,
        "PROVINCE": 14
      }
    }
  ]
}