{
  "type": "FeatureCollection",
  "features": [
    {
      "type": "Feature",
      "id": 18561,
      "geometry": {
        "type": "Point",
        "coordinates": [
          142.6140380000537,
          -3.513887000184866
        ]
      },
      "properties": {
        "OBJECTID": 18561,
        "CU_NAME": "WAMBI/ WASAREN",
        "CU_NO": "010",
        "GEOCODE": "15020604010",
        "PROV_KEY": "15",
        "DIST_NO": "02",
        "LLG_NO": "06",
        "WARD_NO": "04",
        "WARD_NAME": "YADAGARO",
        "LATITUDE": -3.515266,
        "LONGITUDE": 142.612961,
        "REGHH": 16,
        "TOTPOP2000": 65,
        "MALE2000": 35,
        "FEMALE2000": 30,
        "POP2008": 81,
        "G_RATE": 1.0240000486373901,
        "Geocode_Num": 15020604010,
        "PROVINCE": 15
      }
    },
    {
      "type": "Feature",
      "id": 18562,
      "geometry": {
        "type": "Point",
        "coordinates": [
          142.6023420002831,
          -3.528232999853003
        ]
      },
      "properties": {
        "OBJECTID": 18562,
        "CU_NAME": "YADAGARO",
        "CU_NO": "014",
        "GEOCODE": "15020604014",
        "PROV_KEY": "15",
        "DIST_NO": "02",
        "LLG_NO": "06",
        "WARD_NO": "04",
        "WARD_NAME": "YADAGARO",
        "LATITUDE": -3.520084,
        "LONGITUDE": 142.598254,
        "REGHH": 51,
        "TOTPOP2000": 258,
        "MALE2000": 130,
        "FEMALE2000": 128,
        "POP2008": 311,
        "G_RATE": 1.0240000486373901,
        "Geocode_Num": 15020604014,
        "PROVINCE": 15
      }
    },
    {
      "type": "Feature",
      "id": 18563,
      "geometry": {
        "type": "Point",
        "coordinates": [
          142.59259699965185,
          -3.510028000291925
        ]
      },
      "properties": {
        "OBJECTID": 18563,
        "CU_NAME": "YAMEGIL",
        "CU_NO": "015",
        "GEOCODE": "15020604015",
        "PROV_KEY": "15",
        "DIST_NO": "02",
        "LLG_NO": "06",
        "WARD_NO": "04",
        "WARD_NAME": "YADAGARO",
        "LATITUDE": -3.51542,
        "LONGITUDE": 142.592028,
        "REGHH": 46,
        "TOTPOP2000": 178,
        "MALE2000": 98,
        "FEMALE2000": 80,
        "POP2008": 215,
        "G_RATE": 1.0240000486373901,
        "Geocode_Num": 15020604015,
        "PROVINCE": 15
      }
    }
  ]
}