{
  "type": "FeatureCollection",
  "features": [
    {
      "type": "Feature",
      "id": 18564,
      "geometry": {
        "type": "Point",
        "coordinates": [
          142.57190599966225,
          -3.487145999987888
        ]
      },
      "properties": {
        "OBJECTID": 18564,
        "CU_NAME": "SUNDUN",
        "CU_NO": "009",
        "GEOCODE": "15020605009",
        "PROV_KEY": "15",
        "DIST_NO": "02",
        "LLG_NO": "06",
        "WARD_NO": "05",
        "WARD_NAME": "SUNDUN",
        "LATITUDE": -3.488525,
        "LONGITUDE": 142.57083,
        "REGHH": 39,
        "TOTPOP2000": 215,
        "MALE2000": 113,
        "FEMALE2000": 102,
        "POP2008": 260,
        "G_RATE": 1.0240000486373901,
        "Geocode_Num": 15020605009,
        "PROVINCE": 15
      }
    },
    {
      "type": "Feature",
      "id": 18565,
      "geometry": {
        "type": "Point",
        "coordinates": [
          142.58348100014814,
          -3.5076510003933095
        ]
      },
      "properties": {
        "OBJECTID": 18565,
        "CU_NAME": "YAUAN",
        "CU_NO": "017",
        "GEOCODE": "15020605017",
        "PROV_KEY": "15",
        "DIST_NO": "02",
        "LLG_NO": "06",
        "WARD_NO": "05",
        "WARD_NAME": "SUNDUN",
        "LATITUDE": -3.50179,
        "LONGITUDE": 142.57953,
        "REGHH": 55,
        "TOTPOP2000": 245,
        "MALE2000": 129,
        "FEMALE2000": 116,
        "POP2008": 296,
        "G_RATE": 1.0240000486373901,
        "Geocode_Num": 15020605017,
        "PROVINCE": 15
      }
    }
  ]
}