{
  "type": "FeatureCollection",
  "features": [
    {
      "type": "Feature",
      "id": 30547,
      "geometry": {
        "type": "Point",
        "coordinates": [
          145.44777168041878,
          -6.543080819724025
        ]
      },
      "properties": {
        "OBJECTID": 30547,
        "CU_NAME": "HAGU",
        "CU_NO": "002",
        "GEOCODE": "11071015002",
        "PROV_KEY": "11",
        "DIST_NO": "07",
        "LLG_NO": "10",
        "WARD_NO": "15",
        "WARD_NAME": "HENAGARU",
        "LATITUDE": -6.543081,
        "LONGITUDE": 145.447772,
        "REGHH": 119,
        "TOTPOP2000": 491,
        "MALE2000": 255,
        "FEMALE2000": 236,
        "POP2008": 585,
        "G_RATE": 1.0219999551773071,
        "Geocode_Num": null,
        "PROVINCE": 11
      }
    },
    {
      "type": "Feature",
      "id": 30548,
      "geometry": {
        "type": "Point",
        "coordinates": [
          145.5992848802931,
          -6.464105999891956
        ]
      },
      "properties": {
        "OBJECTID": 30548,
        "CU_NAME": "KOSENARU NO 1",
        "CU_NO": "024",
        "GEOCODE": "11071015024",
        "PROV_KEY": "11",
        "DIST_NO": "07",
        "LLG_NO": "10",
        "WARD_NO": "15",
        "WARD_NAME": "HENAGARU",
        "LATITUDE": -6.464106,
        "LONGITUDE": 145.599285,
        "REGHH": 45,
        "TOTPOP2000": 196,
        "MALE2000": 104,
        "FEMALE2000": 92,
        "POP2008": 233,
        "G_RATE": 1.0219999551773071,
        "Geocode_Num": null,
        "PROVINCE": 11
      }
    },
    {
      "type": "Feature",
      "id": 30549,
      "geometry": {
        "type": "Point",
        "coordinates": [
          145.4237571602648,
          -6.512709599967991
        ]
      },
      "properties": {
        "OBJECTID": 30549,
        "CU_NAME": "KOSENARU NO 2",
        "CU_NO": "025",
        "GEOCODE": "11071015025",
        "PROV_KEY": "11",
        "DIST_NO": "07",
        "LLG_NO": "10",
        "WARD_NO": "15",
        "WARD_NAME": "HENAGARU",
        "LATITUDE": -6.51271,
        "LONGITUDE": 145.423757,
        "REGHH": 62,
        "TOTPOP2000": 297,
        "MALE2000": 152,
        "FEMALE2000": 145,
        "POP2008": 354,
        "G_RATE": 1.0219999551773071,
        "Geocode_Num": null,
        "PROVINCE": 11
      }
    },
    {
      "type": "Feature",
      "id": 30550,
      "geometry": {
        "type": "Point",
        "coordinates": [
          145.4377219202305,
          -6.515499959755289
        ]
      },
      "properties": {
        "OBJECTID": 30550,
        "CU_NAME": "TETURA-HENAGARU NO 1",
        "CU_NO": "029",
        "GEOCODE": "11071015029",
        "PROV_KEY": "11",
        "DIST_NO": "07",
        "LLG_NO": "10",
        "WARD_NO": "15",
        "WARD_NAME": "HENAGARU",
        "LATITUDE": -6.5155,
        "LONGITUDE": 145.437722,
        "REGHH": 70,
        "TOTPOP2000": 339,
        "MALE2000": 176,
        "FEMALE2000": 163,
        "POP2008": 403,
        "G_RATE": 1.0219999551773071,
        "Geocode_Num": null,
        "PROVINCE": 11
      }
    },
    {
      "type": "Feature",
      "id": 30551,
      "geometry": {
        "type": "Point",
        "coordinates": [
          145.45091556010505,
          -6.508282320272826
        ]
      },
      "properties": {
        "OBJECTID": 30551,
        "CU_NAME": "TETURA-HENAGARU NO 2",
        "CU_NO": "030",
        "GEOCODE": "11071015030",
        "PROV_KEY": "11",
        "DIST_NO": "07",
        "LLG_NO": "10",
        "WARD_NO": "15",
        "WARD_NAME": "HENAGARU",
        "LATITUDE": -6.508282,
        "LONGITUDE": 145.450916,
        "REGHH": 34,
        "TOTPOP2000": 146,
        "MALE2000": 78,
        "FEMALE2000": 68,
        "POP2008": 173,
        "G_RATE": 1.0219999551773071,
        "Geocode_Num": null,
        "PROVINCE": 11
      }
    }
  ]
}