{
  "type": "FeatureCollection",
  "features": [
    {
      "type": "Feature",
      "id": 31072,
      "geometry": {
        "type": "Point",
        "coordinates": [
          150.46274011426488,
          -10.308869634725795
        ]
      },
      "properties": {
        "OBJECTID": 31072,
        "CU_NAME": "Toudikwa",
        "CU_NO": "867",
        "GEOCODE": "867",
        "PROV_KEY": "05",
        "DIST_NO": "1",
        "LLG_NO": "7",
        "WARD_NO": null,
        "WARD_NAME": null,
        "LATITUDE": -10.308926,
        "LONGITUDE": 150.462462,
        "REGHH": null,
        "TOTPOP2000": null,
        "MALE2000": null,
        "FEMALE2000": null,
        "POP2008": null,
        "G_RATE": null,
        "Geocode_Num": 867,
        "PROVINCE": 5
      }
    }
  ]
}