{
  "type": "FeatureCollection",
  "features": [
    {
      "type": "Feature",
      "id": 21121,
      "geometry": {
        "type": "Point",
        "coordinates": [
          143.65712900040307,
          -6.085359999664206
        ]
      },
      "properties": {
        "OBJECTID": 21121,
        "CU_NAME": "PONGAI",
        "CU_NO": "016",
        "GEOCODE": "07062103016",
        "PROV_KEY": "07",
        "DIST_NO": "06",
        "LLG_NO": "21",
        "WARD_NO": "03",
        "WARD_NAME": "PONGAI",
        "LATITUDE": -6.089628,
        "LONGITUDE": 143.652852,
        "REGHH": 202,
        "TOTPOP2000": 1203,
        "MALE2000": 590,
        "FEMALE2000": 613,
        "POP2008": 1673,
        "G_RATE": 1.0420000553131104,
        "Geocode_Num": 7062103016,
        "PROVINCE": 7
      }
    }
  ]
}