{
  "type": "FeatureCollection",
  "features": [
    {
      "type": "Feature",
      "id": 18789,
      "geometry": {
        "type": "Point",
        "coordinates": [
          141.08122799997227,
          -4.61930399957987
        ]
      },
      "properties": {
        "OBJECTID": 18789,
        "CU_NAME": "IMNAI 1",
        "CU_NO": "001",
        "GEOCODE": "15031101001",
        "PROV_KEY": "15",
        "DIST_NO": "03",
        "LLG_NO": "11",
        "WARD_NO": "01",
        "WARD_NAME": "IMNAI 1",
        "LATITUDE": -4.620693,
        "LONGITUDE": 141.080133,
        "REGHH": 33,
        "TOTPOP2000": 271,
        "MALE2000": 141,
        "FEMALE2000": 130,
        "POP2008": 329,
        "G_RATE": 1.0240000486373901,
        "Geocode_Num": 15031101001,
        "PROVINCE": 15
      }
    },
    {
      "type": "Feature",
      "id": 18790,
      "geometry": {
        "type": "Point",
        "coordinates": [
          141.10308099958854,
          -4.637730000339218
        ]
      },
      "properties": {
        "OBJECTID": 18790,
        "CU_NAME": "IBORIO",
        "CU_NO": "002",
        "GEOCODE": "15031101002",
        "PROV_KEY": "15",
        "DIST_NO": "03",
        "LLG_NO": "11",
        "WARD_NO": "01",
        "WARD_NAME": "IMNAI 1",
        "LATITUDE": -4.633418,
        "LONGITUDE": 141.100849,
        "REGHH": 25,
        "TOTPOP2000": 110,
        "MALE2000": 61,
        "FEMALE2000": 49,
        "POP2008": 134,
        "G_RATE": 1.0240000486373901,
        "Geocode_Num": 15031101002,
        "PROVINCE": 15
      }
    },
    {
      "type": "Feature",
      "id": 18791,
      "geometry": {
        "type": "Point",
        "coordinates": [
          141.07499500031906,
          -4.622061999961261
        ]
      },
      "properties": {
        "OBJECTID": 18791,
        "CU_NAME": "HAUS KONA",
        "CU_NO": "003",
        "GEOCODE": "15031101003",
        "PROV_KEY": "15",
        "DIST_NO": "03",
        "LLG_NO": "11",
        "WARD_NO": "01",
        "WARD_NAME": "IMNAI 1",
        "LATITUDE": -4.623451,
        "LONGITUDE": 141.0739,
        "REGHH": 32,
        "TOTPOP2000": 161,
        "MALE2000": 84,
        "FEMALE2000": 77,
        "POP2008": 194,
        "G_RATE": 1.0240000486373901,
        "Geocode_Num": 15031101003,
        "PROVINCE": 15
      }
    },
    {
      "type": "Feature",
      "id": 18792,
      "geometry": {
        "type": "Point",
        "coordinates": [
          141.09912299962684,
          -4.616345999867974
        ]
      },
      "properties": {
        "OBJECTID": 18792,
        "CU_NAME": "YAPSIE SDHQ",
        "CU_NO": "401",
        "GEOCODE": "15031101401",
        "PROV_KEY": "15",
        "DIST_NO": "03",
        "LLG_NO": "11",
        "WARD_NO": "01",
        "WARD_NAME": "IMNAI 1",
        "LATITUDE": -4.627999,
        "LONGITUDE": 141.095757,
        "REGHH": 16,
        "TOTPOP2000": 77,
        "MALE2000": 44,
        "FEMALE2000": 33,
        "POP2008": 93,
        "G_RATE": 1.0240000486373901,
        "Geocode_Num": 15031101401,
        "PROVINCE": 15
      }
    }
  ]
}