{
  "type": "FeatureCollection",
  "features": [
    {
      "type": "Feature",
      "id": 18795,
      "geometry": {
        "type": "Point",
        "coordinates": [
          141.11303199982694,
          -4.63410300035315
        ]
      },
      "properties": {
        "OBJECTID": 18795,
        "CU_NAME": "BITAPENA",
        "CU_NO": "002",
        "GEOCODE": "15031103002",
        "PROV_KEY": "15",
        "DIST_NO": "03",
        "LLG_NO": "11",
        "WARD_NO": "03",
        "WARD_NAME": "BITAPENA",
        "LATITUDE": -4.630308,
        "LONGITUDE": 141.110527,
        "REGHH": 34,
        "TOTPOP2000": 165,
        "MALE2000": 92,
        "FEMALE2000": 73,
        "POP2008": 199,
        "G_RATE": 1.0240000486373901,
        "Geocode_Num": 15031103002,
        "PROVINCE": 15
      }
    }
  ]
}