{
  "type": "FeatureCollection",
  "features": [
    {
      "type": "Feature",
      "id": 1518,
      "geometry": {
        "type": "Point",
        "coordinates": [
          147.27663799984384,
          -9.369168000003128
        ]
      },
      "properties": {
        "OBJECTID": 1518,
        "CU_NAME": "GOLDIE 01",
        "CU_NO": "001",
        "GEOCODE": "03030986001",
        "PROV_KEY": "03",
        "DIST_NO": "03",
        "LLG_NO": "09",
        "WARD_NO": "86",
        "WARD_NAME": "GOLDIE URBAN 01",
        "LATITUDE": -9.370617,
        "LONGITUDE": 147.275611,
        "REGHH": 32,
        "TOTPOP2000": 263,
        "MALE2000": 162,
        "FEMALE2000": 101,
        "POP2008": 315,
        "G_RATE": 1.0230000019073486,
        "Geocode_Num": 3030986001,
        "PROVINCE": 3
      }
    },
    {
      "type": "Feature",
      "id": 1519,
      "geometry": {
        "type": "Point",
        "coordinates": [
          147.27821699981473,
          -9.367142000103172
        ]
      },
      "properties": {
        "OBJECTID": 1519,
        "CU_NAME": "GOLDIE 02",
        "CU_NO": "002",
        "GEOCODE": "03030986002",
        "PROV_KEY": "03",
        "DIST_NO": "03",
        "LLG_NO": "09",
        "WARD_NO": "86",
        "WARD_NAME": "GOLDIE URBAN 02",
        "LATITUDE": -9.368591,
        "LONGITUDE": 147.27719,
        "REGHH": 72,
        "TOTPOP2000": 536,
        "MALE2000": 265,
        "FEMALE2000": 271,
        "POP2008": 643,
        "G_RATE": 1.0230000019073486,
        "Geocode_Num": 3030986002,
        "PROVINCE": 3
      }
    }
  ]
}