{
  "type": "FeatureCollection",
  "features": [
    {
      "type": "Feature",
      "id": 6615,
      "geometry": {
        "type": "Point",
        "coordinates": [
          142.86975699978575,
          -3.6250120004034443
        ]
      },
      "properties": {
        "OBJECTID": 6615,
        "CU_NAME": "ALUWINGEI",
        "CU_NO": "004",
        "GEOCODE": "14031104004",
        "PROV_KEY": "14",
        "DIST_NO": "03",
        "LLG_NO": "11",
        "WARD_NO": "04",
        "WARD_NAME": "SALATA",
        "LATITUDE": -3.62659,
        "LONGITUDE": 142.868514,
        "REGHH": 32,
        "TOTPOP2000": 154,
        "MALE2000": 72,
        "FEMALE2000": 82,
        "POP2008": 184,
        "G_RATE": 1.0219999551773071,
        "Geocode_Num": 14031104004,
        "PROVINCE": 14
      }
    },
    {
      "type": "Feature",
      "id": 6616,
      "geometry": {
        "type": "Point",
        "coordinates": [
          142.87408799986133,
          -3.626596999751712
        ]
      },
      "properties": {
        "OBJECTID": 6616,
        "CU_NAME": "SALATA",
        "CU_NO": "025",
        "GEOCODE": "14031104025",
        "PROV_KEY": "14",
        "DIST_NO": "03",
        "LLG_NO": "11",
        "WARD_NO": "04",
        "WARD_NAME": "SALATA",
        "LATITUDE": -3.628175,
        "LONGITUDE": 142.872847,
        "REGHH": 81,
        "TOTPOP2000": 356,
        "MALE2000": 192,
        "FEMALE2000": 164,
        "POP2008": 424,
        "G_RATE": 1.0219999551773071,
        "Geocode_Num": 14031104025,
        "PROVINCE": 14
      }
    },
    {
      "type": "Feature",
      "id": 6617,
      "geometry": {
        "type": "Point",
        "coordinates": [
          142.8786709998668,
          -3.6141420000532207
        ]
      },
      "properties": {
        "OBJECTID": 6617,
        "CU_NAME": "WARAGOM",
        "CU_NO": "035",
        "GEOCODE": "14031104035",
        "PROV_KEY": "14",
        "DIST_NO": "03",
        "LLG_NO": "11",
        "WARD_NO": "04",
        "WARD_NAME": "SALATA",
        "LATITUDE": -3.61572,
        "LONGITUDE": 142.87743,
        "REGHH": 72,
        "TOTPOP2000": 309,
        "MALE2000": 155,
        "FEMALE2000": 154,
        "POP2008": 368,
        "G_RATE": 1.0219999551773071,
        "Geocode_Num": 14031104035,
        "PROVINCE": 14
      }
    }
  ]
}