{
  "type": "FeatureCollection",
  "features": [
    {
      "type": "Feature",
      "id": 6618,
      "geometry": {
        "type": "Point",
        "coordinates": [
          142.8621650004145,
          -3.611950999738781
        ]
      },
      "properties": {
        "OBJECTID": 6618,
        "CU_NAME": "BONOHOL",
        "CU_NO": "009",
        "GEOCODE": "14031105009",
        "PROV_KEY": "14",
        "DIST_NO": "03",
        "LLG_NO": "11",
        "WARD_NO": "05",
        "WARD_NAME": "BONOHOL",
        "LATITUDE": -3.61353,
        "LONGITUDE": 142.860922,
        "REGHH": 115,
        "TOTPOP2000": 474,
        "MALE2000": 228,
        "FEMALE2000": 246,
        "POP2008": 564,
        "G_RATE": 1.0219999551773071,
        "Geocode_Num": 14031105009,
        "PROVINCE": 14
      }
    },
    {
      "type": "Feature",
      "id": 6619,
      "geometry": {
        "type": "Point",
        "coordinates": [
          142.85518200034915,
          -3.6332679998183153
        ]
      },
      "properties": {
        "OBJECTID": 6619,
        "CU_NAME": "SOLOM",
        "CU_NO": "026",
        "GEOCODE": "14031105026",
        "PROV_KEY": "14",
        "DIST_NO": "03",
        "LLG_NO": "11",
        "WARD_NO": "05",
        "WARD_NAME": "BONOHOL",
        "LATITUDE": -3.634846,
        "LONGITUDE": 142.853939,
        "REGHH": 57,
        "TOTPOP2000": 265,
        "MALE2000": 136,
        "FEMALE2000": 129,
        "POP2008": 315,
        "G_RATE": 1.0219999551773071,
        "Geocode_Num": 14031105026,
        "PROVINCE": 14
      }
    },
    {
      "type": "Feature",
      "id": 6620,
      "geometry": {
        "type": "Point",
        "coordinates": [
          142.860681000328,
          -3.6220109996078804
        ]
      },
      "properties": {
        "OBJECTID": 6620,
        "CU_NAME": "DOLUWOM",
        "CU_NO": "027",
        "GEOCODE": "14031105027",
        "PROV_KEY": "14",
        "DIST_NO": "03",
        "LLG_NO": "11",
        "WARD_NO": "05",
        "WARD_NAME": "BONOHOL",
        "LATITUDE": -3.623589,
        "LONGITUDE": 142.859438,
        "REGHH": 40,
        "TOTPOP2000": 178,
        "MALE2000": 82,
        "FEMALE2000": 96,
        "POP2008": 211,
        "G_RATE": 1.0219999551773071,
        "Geocode_Num": 14031105027,
        "PROVINCE": 14
      }
    }
  ]
}