{
  "type": "FeatureCollection",
  "features": [
    {
      "type": "Feature",
      "id": 6629,
      "geometry": {
        "type": "Point",
        "coordinates": [
          142.90668700040476,
          -3.721037000357228
        ]
      },
      "properties": {
        "OBJECTID": 6629,
        "CU_NAME": "SUNUHU 1",
        "CU_NO": "028",
        "GEOCODE": "14031109028",
        "PROV_KEY": "14",
        "DIST_NO": "03",
        "LLG_NO": "11",
        "WARD_NO": "09",
        "WARD_NAME": "SUNUHU 1",
        "LATITUDE": -3.722616,
        "LONGITUDE": 142.905446,
        "REGHH": 167,
        "TOTPOP2000": 727,
        "MALE2000": 363,
        "FEMALE2000": 364,
        "POP2008": 865,
        "G_RATE": 1.0219999551773071,
        "Geocode_Num": 14031109028,
        "PROVINCE": 14
      }
    },
    {
      "type": "Feature",
      "id": 6630,
      "geometry": {
        "type": "Point",
        "coordinates": [
          142.91712299962683,
          -3.725165000064635
        ]
      },
      "properties": {
        "OBJECTID": 6630,
        "CU_NAME": "SUNUHU 2",
        "CU_NO": "029",
        "GEOCODE": "14031109029",
        "PROV_KEY": "14",
        "DIST_NO": "03",
        "LLG_NO": "11",
        "WARD_NO": "09",
        "WARD_NAME": "SUNUHU 1",
        "LATITUDE": -3.726744,
        "LONGITUDE": 142.915882,
        "REGHH": 107,
        "TOTPOP2000": 500,
        "MALE2000": 253,
        "FEMALE2000": 247,
        "POP2008": 595,
        "G_RATE": 1.0219999551773071,
        "Geocode_Num": 14031109029,
        "PROVINCE": 14
      }
    }
  ]
}