{
  "type": "FeatureCollection",
  "features": [
    {
      "type": "Feature",
      "id": 6643,
      "geometry": {
        "type": "Point",
        "coordinates": [
          142.92686099993523,
          -3.685362000056216
        ]
      },
      "properties": {
        "OBJECTID": 6643,
        "CU_NAME": "ILAHITA 5",
        "CU_NO": "005",
        "GEOCODE": "14031115005",
        "PROV_KEY": "14",
        "DIST_NO": "03",
        "LLG_NO": "11",
        "WARD_NO": "15",
        "WARD_NAME": "ILAHITA 4",
        "LATITUDE": -3.68694,
        "LONGITUDE": 142.92562,
        "REGHH": 58,
        "TOTPOP2000": 254,
        "MALE2000": 126,
        "FEMALE2000": 128,
        "POP2008": 303,
        "G_RATE": 1.0219999551773071,
        "Geocode_Num": 14031115005,
        "PROVINCE": 14
      }
    },
    {
      "type": "Feature",
      "id": 6644,
      "geometry": {
        "type": "Point",
        "coordinates": [
          142.9405190002517,
          -3.6817750001160903
        ]
      },
      "properties": {
        "OBJECTID": 6644,
        "CU_NAME": "ILAHITA 4",
        "CU_NO": "012",
        "GEOCODE": "14031115012",
        "PROV_KEY": "14",
        "DIST_NO": "03",
        "LLG_NO": "11",
        "WARD_NO": "15",
        "WARD_NAME": "ILAHITA 4",
        "LATITUDE": -3.683353,
        "LONGITUDE": 142.939277,
        "REGHH": 102,
        "TOTPOP2000": 405,
        "MALE2000": 183,
        "FEMALE2000": 222,
        "POP2008": 482,
        "G_RATE": 1.0219999551773071,
        "Geocode_Num": 14031115012,
        "PROVINCE": 14
      }
    }
  ]
}