{
  "type": "FeatureCollection",
  "features": [
    {
      "type": "Feature",
      "id": 20999,
      "geometry": {
        "type": "Point",
        "coordinates": [
          143.5582009996765,
          -6.115181999849369
        ]
      },
      "properties": {
        "OBJECTID": 20999,
        "CU_NAME": "HIYU",
        "CU_NO": "001",
        "GEOCODE": "07061905001",
        "PROV_KEY": "07",
        "DIST_NO": "06",
        "LLG_NO": "19",
        "WARD_NO": "05",
        "WARD_NAME": "KIP 2",
        "LATITUDE": -6.118773,
        "LONGITUDE": 143.557156,
        "REGHH": 48,
        "TOTPOP2000": 299,
        "MALE2000": 128,
        "FEMALE2000": 171,
        "POP2008": 416,
        "G_RATE": 1.0420000553131104,
        "Geocode_Num": 7061905001,
        "PROVINCE": 7
      }
    },
    {
      "type": "Feature",
      "id": 21000,
      "geometry": {
        "type": "Point",
        "coordinates": [
          143.5579180001157,
          -6.1165459997980065
        ]
      },
      "properties": {
        "OBJECTID": 21000,
        "CU_NAME": "MEKEYA",
        "CU_NO": "002",
        "GEOCODE": "07061905002",
        "PROV_KEY": "07",
        "DIST_NO": "06",
        "LLG_NO": "19",
        "WARD_NO": "05",
        "WARD_NAME": "KIP 2",
        "LATITUDE": -6.118774,
        "LONGITUDE": 143.557157,
        "REGHH": 46,
        "TOTPOP2000": 317,
        "MALE2000": 143,
        "FEMALE2000": 174,
        "POP2008": 440,
        "G_RATE": 1.0420000553131104,
        "Geocode_Num": 7061905002,
        "PROVINCE": 7
      }
    },
    {
      "type": "Feature",
      "id": 21001,
      "geometry": {
        "type": "Point",
        "coordinates": [
          143.5440619996616,
          -6.012452000059682
        ]
      },
      "properties": {
        "OBJECTID": 21001,
        "CU_NAME": "SOPAR",
        "CU_NO": "003",
        "GEOCODE": "07061905003",
        "PROV_KEY": "07",
        "DIST_NO": "06",
        "LLG_NO": "19",
        "WARD_NO": "05",
        "WARD_NAME": "KIP 2",
        "LATITUDE": -6.016571,
        "LONGITUDE": 143.542292,
        "REGHH": 64,
        "TOTPOP2000": 469,
        "MALE2000": 231,
        "FEMALE2000": 238,
        "POP2008": 651,
        "G_RATE": 1.0420000553131104,
        "Geocode_Num": 7061905003,
        "PROVINCE": 7
      }
    },
    {
      "type": "Feature",
      "id": 21002,
      "geometry": {
        "type": "Point",
        "coordinates": [
          143.54287599982763,
          -6.009975000046154
        ]
      },
      "properties": {
        "OBJECTID": 21002,
        "CU_NAME": "SOWARTENDA",
        "CU_NO": "004",
        "GEOCODE": "07061905004",
        "PROV_KEY": "07",
        "DIST_NO": "06",
        "LLG_NO": "19",
        "WARD_NO": "05",
        "WARD_NAME": "KIP 2",
        "LATITUDE": -6.016572,
        "LONGITUDE": 143.542293,
        "REGHH": 89,
        "TOTPOP2000": 740,
        "MALE2000": 317,
        "FEMALE2000": 423,
        "POP2008": 1028,
        "G_RATE": 1.0420000553131104,
        "Geocode_Num": 7061905004,
        "PROVINCE": 7
      }
    }
  ]
}