{
  "type": "FeatureCollection",
  "features": [
    {
      "type": "Feature",
      "id": 21074,
      "geometry": {
        "type": "Point",
        "coordinates": [
          143.5011809998034,
          -5.997021999865353
        ]
      },
      "properties": {
        "OBJECTID": 21074,
        "CU_NAME": "MARISTE",
        "CU_NO": "010",
        "GEOCODE": "07061925010",
        "PROV_KEY": "07",
        "DIST_NO": "06",
        "LLG_NO": "19",
        "WARD_NO": "25",
        "WARD_NAME": "MARISTE",
        "LATITUDE": -6.000747,
        "LONGITUDE": 143.501676,
        "REGHH": 49,
        "TOTPOP2000": 308,
        "MALE2000": 129,
        "FEMALE2000": 179,
        "POP2008": 428,
        "G_RATE": 1.0420000553131104,
        "Geocode_Num": 7061925010,
        "PROVINCE": 7
      }
    },
    {
      "type": "Feature",
      "id": 21075,
      "geometry": {
        "type": "Point",
        "coordinates": [
          143.49876800004324,
          -5.993763999808721
        ]
      },
      "properties": {
        "OBJECTID": 21075,
        "CU_NAME": "SOPONDA",
        "CU_NO": "011",
        "GEOCODE": "07061925011",
        "PROV_KEY": "07",
        "DIST_NO": "06",
        "LLG_NO": "19",
        "WARD_NO": "25",
        "WARD_NAME": "MARISTE",
        "LATITUDE": -6.000747,
        "LONGITUDE": 143.501676,
        "REGHH": 41,
        "TOTPOP2000": 231,
        "MALE2000": 120,
        "FEMALE2000": 111,
        "POP2008": 321,
        "G_RATE": 1.0420000553131104,
        "Geocode_Num": 7061925011,
        "PROVINCE": 7
      }
    }
  ]
}