{
  "type": "FeatureCollection",
  "features": [
    {
      "type": "Feature",
      "id": 16193,
      "geometry": {
        "type": "Point",
        "coordinates": [
          144.49280800018914,
          -6.121387000009975
        ]
      },
      "properties": {
        "OBJECTID": 16193,
        "CU_NAME": "WUSINGE",
        "CU_NO": "004",
        "GEOCODE": "09010241004",
        "PROV_KEY": "22",
        "DIST_NO": "01",
        "LLG_NO": "02",
        "WARD_NO": "41",
        "WARD_NAME": "WUSINGE",
        "LATITUDE": -6.116819,
        "LONGITUDE": 144.492671,
        "REGHH": 6,
        "TOTPOP2000": 22,
        "MALE2000": 9,
        "FEMALE2000": 13,
        "POP2008": 30,
        "G_RATE": 1.024999976158142,
        "Geocode_Num": 9010241004,
        "PROVINCE": 22
      }
    }
  ]
}