{
  "type": "FeatureCollection",
  "features": [
    {
      "type": "Feature",
      "id": 7573,
      "geometry": {
        "type": "Point",
        "coordinates": [
          145.9518119997241,
          -7.648522000090168
        ]
      },
      "properties": {
        "OBJECTID": 7573,
        "CU_NAME": "MOIWA",
        "CU_NO": "017",
        "GEOCODE": "02010514017",
        "PROV_KEY": "02",
        "DIST_NO": "01",
        "LLG_NO": "05",
        "WARD_NO": "14",
        "WARD_NAME": "KAMINA",
        "LATITUDE": -7.649951,
        "LONGITUDE": 145.95077,
        "REGHH": 52,
        "TOTPOP2000": 236,
        "MALE2000": 122,
        "FEMALE2000": 114,
        "POP2008": 289,
        "G_RATE": 1.0260000228881836,
        "Geocode_Num": 2010514017,
        "PROVINCE": 2
      }
    },
    {
      "type": "Feature",
      "id": 7574,
      "geometry": {
        "type": "Point",
        "coordinates": [
          145.96621400017602,
          -7.649416999994514
        ]
      },
      "properties": {
        "OBJECTID": 7574,
        "CU_NAME": "KAMINA CATHOLIC MISSION",
        "CU_NO": "401",
        "GEOCODE": "02010514401",
        "PROV_KEY": "02",
        "DIST_NO": "01",
        "LLG_NO": "05",
        "WARD_NO": "14",
        "WARD_NAME": "KAMINA",
        "LATITUDE": -7.650828,
        "LONGITUDE": 145.957896,
        "REGHH": 22,
        "TOTPOP2000": 129,
        "MALE2000": 70,
        "FEMALE2000": 59,
        "POP2008": 159,
        "G_RATE": 1.0260000228881836,
        "Geocode_Num": 2010514401,
        "PROVINCE": 2
      }
    }
  ]
}