{
  "type": "FeatureCollection",
  "features": [
    {
      "type": "Feature",
      "id": 7578,
      "geometry": {
        "type": "Point",
        "coordinates": [
          145.90287500028114,
          -7.647568000163005
        ]
      },
      "properties": {
        "OBJECTID": 7578,
        "CU_NAME": "PAINA",
        "CU_NO": "010",
        "GEOCODE": "02010516010",
        "PROV_KEY": "02",
        "DIST_NO": "01",
        "LLG_NO": "05",
        "WARD_NO": "16",
        "WARD_NAME": "PAINA",
        "LATITUDE": -7.653041,
        "LONGITUDE": 145.901824,
        "REGHH": 60,
        "TOTPOP2000": 375,
        "MALE2000": 189,
        "FEMALE2000": 186,
        "POP2008": 461,
        "G_RATE": 1.0260000228881836,
        "Geocode_Num": 2010516010,
        "PROVINCE": 2
      }
    }
  ]
}