{
  "type": "FeatureCollection",
  "features": [
    {
      "type": "Feature",
      "id": 5397,
      "geometry": {
        "type": "Point",
        "coordinates": [
          143.66712199988046,
          -5.426015999938386
        ]
      },
      "properties": {
        "OBJECTID": 5397,
        "CU_NAME": "LAKUI",
        "CU_NO": "004",
        "GEOCODE": "08020310004",
        "PROV_KEY": "08",
        "DIST_NO": "02",
        "LLG_NO": "03",
        "WARD_NO": "10",
        "WARD_NAME": "LAKUI",
        "LATITUDE": -5.430146,
        "LONGITUDE": 143.668481,
        "REGHH": 56,
        "TOTPOP2000": 245,
        "MALE2000": 137,
        "FEMALE2000": 108,
        "POP2008": 308,
        "G_RATE": 1.0290000438690186,
        "Geocode_Num": 8020310004,
        "PROVINCE": 8
      }
    },
    {
      "type": "Feature",
      "id": 5398,
      "geometry": {
        "type": "Point",
        "coordinates": [
          143.66800900031512,
          -5.422431000090512
        ]
      },
      "properties": {
        "OBJECTID": 5398,
        "CU_NAME": "YALEPOS",
        "CU_NO": "005",
        "GEOCODE": "08020310005",
        "PROV_KEY": "08",
        "DIST_NO": "02",
        "LLG_NO": "03",
        "WARD_NO": "10",
        "WARD_NAME": "LAKUI",
        "LATITUDE": -5.422725,
        "LONGITUDE": 143.666939,
        "REGHH": 17,
        "TOTPOP2000": 74,
        "MALE2000": 39,
        "FEMALE2000": 35,
        "POP2008": 91,
        "G_RATE": 1.0290000438690186,
        "Geocode_Num": 8020310005,
        "PROVINCE": 8
      }
    }
  ]
}