{
  "type": "FeatureCollection",
  "features": [
    {
      "type": "Feature",
      "id": 5404,
      "geometry": {
        "type": "Point",
        "coordinates": [
          143.6634270003558,
          -5.404341999583551
        ]
      },
      "properties": {
        "OBJECTID": 5404,
        "CU_NAME": "NAILYA",
        "CU_NO": "001",
        "GEOCODE": "08020313001",
        "PROV_KEY": "08",
        "DIST_NO": "02",
        "LLG_NO": "03",
        "WARD_NO": "13",
        "WARD_NAME": "NALYA (TSIKIRO)",
        "LATITUDE": -5.405743,
        "LONGITUDE": 143.662362,
        "REGHH": 29,
        "TOTPOP2000": 182,
        "MALE2000": 94,
        "FEMALE2000": 88,
        "POP2008": 228,
        "G_RATE": 1.0290000438690186,
        "Geocode_Num": 8020313001,
        "PROVINCE": 8
      }
    },
    {
      "type": "Feature",
      "id": 5405,
      "geometry": {
        "type": "Point",
        "coordinates": [
          143.6717959995858,
          -5.399946000107775
        ]
      },
      "properties": {
        "OBJECTID": 5405,
        "CU_NAME": "PINDAL",
        "CU_NO": "002",
        "GEOCODE": "08020313002",
        "PROV_KEY": "08",
        "DIST_NO": "02",
        "LLG_NO": "03",
        "WARD_NO": "13",
        "WARD_NAME": "NALYA (TSIKIRO)",
        "LATITUDE": -5.396881,
        "LONGITUDE": 143.668481,
        "REGHH": 74,
        "TOTPOP2000": 413,
        "MALE2000": 224,
        "FEMALE2000": 189,
        "POP2008": 519,
        "G_RATE": 1.0290000438690186,
        "Geocode_Num": 8020313002,
        "PROVINCE": 8
      }
    },
    {
      "type": "Feature",
      "id": 5406,
      "geometry": {
        "type": "Point",
        "coordinates": [
          143.68082899975855,
          -5.400852999666142
        ]
      },
      "properties": {
        "OBJECTID": 5406,
        "CU_NAME": "POREA",
        "CU_NO": "003",
        "GEOCODE": "08020313003",
        "PROV_KEY": "08",
        "DIST_NO": "02",
        "LLG_NO": "03",
        "WARD_NO": "13",
        "WARD_NAME": "NALYA (TSIKIRO)",
        "LATITUDE": -5.395581,
        "LONGITUDE": 143.670368,
        "REGHH": 33,
        "TOTPOP2000": 149,
        "MALE2000": 73,
        "FEMALE2000": 76,
        "POP2008": 187,
        "G_RATE": 1.0290000438690186,
        "Geocode_Num": 8020313003,
        "PROVINCE": 8
      }
    }
  ]
}