{
  "type": "FeatureCollection",
  "features": [
    {
      "type": "Feature",
      "id": 9483,
      "geometry": {
        "type": "Point",
        "coordinates": [
          147.18893899983505,
          -2.204038000053629
        ]
      },
      "properties": {
        "OBJECTID": 9483,
        "CU_NAME": "PERE",
        "CU_NO": "006",
        "GEOCODE": "16010814006",
        "PROV_KEY": "16",
        "DIST_NO": "01",
        "LLG_NO": "08",
        "WARD_NO": "14",
        "WARD_NAME": "PERE 1",
        "LATITUDE": -2.206163,
        "LONGITUDE": 147.187684,
        "REGHH": 111,
        "TOTPOP2000": 492,
        "MALE2000": 241,
        "FEMALE2000": 251,
        "POP2008": 604,
        "G_RATE": 1.0260000228881836,
        "Geocode_Num": 16010814006,
        "PROVINCE": 16
      }
    }
  ]
}