{
  "type": "FeatureCollection",
  "features": [
    {
      "type": "Feature",
      "id": 8343,
      "geometry": {
        "type": "Point",
        "coordinates": [
          145.36787000040022,
          -5.3226600000589315
        ]
      },
      "properties": {
        "OBJECTID": 8343,
        "CU_NAME": "YAGI",
        "CU_NO": "031",
        "GEOCODE": "13020610031",
        "PROV_KEY": "13",
        "DIST_NO": "02",
        "LLG_NO": "06",
        "WARD_NO": "10",
        "WARD_NAME": "WARD TEN",
        "LATITUDE": -5.319697,
        "LONGITUDE": 145.364664,
        "REGHH": 70,
        "TOTPOP2000": 446,
        "MALE2000": 231,
        "FEMALE2000": 215,
        "POP2008": 551,
        "G_RATE": 1.0269999504089355,
        "Geocode_Num": 13020610031,
        "PROVINCE": 13
      }
    }
  ]
}