{
  "type": "FeatureCollection",
  "features": [
    {
      "type": "Feature",
      "id": 13992,
      "geometry": {
        "type": "Point",
        "coordinates": [
          145.24093899973514,
          -6.217618999617116
        ]
      },
      "properties": {
        "OBJECTID": 13992,
        "CU_NAME": "RUNUGU",
        "CU_NO": "008",
        "GEOCODE": "10010309008",
        "PROV_KEY": "10",
        "DIST_NO": "01",
        "LLG_NO": "03",
        "WARD_NO": "09",
        "WARD_NAME": "IRAFAIUFA",
        "LATITUDE": -6.219031,
        "LONGITUDE": 145.239892,
        "REGHH": 74,
        "TOTPOP2000": 311,
        "MALE2000": 151,
        "FEMALE2000": 160,
        "POP2008": 359,
        "G_RATE": 1.0180000066757202,
        "Geocode_Num": 10010309008,
        "PROVINCE": 10
      }
    },
    {
      "type": "Feature",
      "id": 13993,
      "geometry": {
        "type": "Point",
        "coordinates": [
          145.24847199998283,
          -6.220176999768682
        ]
      },
      "properties": {
        "OBJECTID": 13993,
        "CU_NAME": "WAIKUNAI",
        "CU_NO": "009",
        "GEOCODE": "10010309009",
        "PROV_KEY": "10",
        "DIST_NO": "01",
        "LLG_NO": "03",
        "WARD_NO": "09",
        "WARD_NAME": "IRAFAIUFA",
        "LATITUDE": -6.221589,
        "LONGITUDE": 145.247425,
        "REGHH": 38,
        "TOTPOP2000": 121,
        "MALE2000": 69,
        "FEMALE2000": 52,
        "POP2008": 137,
        "G_RATE": 1.0180000066757202,
        "Geocode_Num": 10010309009,
        "PROVINCE": 10
      }
    },
    {
      "type": "Feature",
      "id": 13994,
      "geometry": {
        "type": "Point",
        "coordinates": [
          145.25388799973143,
          -6.222681000128034
        ]
      },
      "properties": {
        "OBJECTID": 13994,
        "CU_NAME": "KORIPAMA/KETO",
        "CU_NO": "010",
        "GEOCODE": "10010309010",
        "PROV_KEY": "10",
        "DIST_NO": "01",
        "LLG_NO": "03",
        "WARD_NO": "09",
        "WARD_NAME": "IRAFAIUFA",
        "LATITUDE": -6.224093,
        "LONGITUDE": 145.252841,
        "REGHH": 9,
        "TOTPOP2000": 28,
        "MALE2000": 13,
        "FEMALE2000": 15,
        "POP2008": 36,
        "G_RATE": 1.0180000066757202,
        "Geocode_Num": 10010309010,
        "PROVINCE": 10
      }
    }
  ]
}