{
  "type": "FeatureCollection",
  "features": [
    {
      "type": "Feature",
      "id": 14035,
      "geometry": {
        "type": "Point",
        "coordinates": [
          145.17279699958192,
          -6.169790000008447
        ]
      },
      "properties": {
        "OBJECTID": 14035,
        "CU_NAME": "YOMBAIRARO",
        "CU_NO": "004",
        "GEOCODE": "10010318004",
        "PROV_KEY": "10",
        "DIST_NO": "01",
        "LLG_NO": "03",
        "WARD_NO": "18",
        "WARD_NAME": "LOFAIFO",
        "LATITUDE": -6.170326,
        "LONGITUDE": 145.171702,
        "REGHH": 46,
        "TOTPOP2000": 147,
        "MALE2000": 75,
        "FEMALE2000": 72,
        "POP2008": 171,
        "G_RATE": 1.0180000066757202,
        "Geocode_Num": 10010318004,
        "PROVINCE": 10
      }
    },
    {
      "type": "Feature",
      "id": 14036,
      "geometry": {
        "type": "Point",
        "coordinates": [
          145.1708089996357,
          -6.165054000141936
        ]
      },
      "properties": {
        "OBJECTID": 14036,
        "CU_NAME": "MUNIYAU",
        "CU_NO": "005",
        "GEOCODE": "10010318005",
        "PROV_KEY": "10",
        "DIST_NO": "01",
        "LLG_NO": "03",
        "WARD_NO": "18",
        "WARD_NAME": "LOFAIFO",
        "LATITUDE": -6.166466,
        "LONGITUDE": 145.169761,
        "REGHH": 22,
        "TOTPOP2000": 64,
        "MALE2000": 35,
        "FEMALE2000": 29,
        "POP2008": 72,
        "G_RATE": 1.0180000066757202,
        "Geocode_Num": 10010318005,
        "PROVINCE": 10
      }
    },
    {
      "type": "Feature",
      "id": 14037,
      "geometry": {
        "type": "Point",
        "coordinates": [
          145.16960800000925,
          -6.167679999832103
        ]
      },
      "properties": {
        "OBJECTID": 14037,
        "CU_NAME": "NEW BLOCK",
        "CU_NO": "006",
        "GEOCODE": "10010318006",
        "PROV_KEY": "10",
        "DIST_NO": "01",
        "LLG_NO": "03",
        "WARD_NO": "18",
        "WARD_NAME": "LOFAIFO",
        "LATITUDE": -6.170226,
        "LONGITUDE": 145.16871,
        "REGHH": 14,
        "TOTPOP2000": 46,
        "MALE2000": 22,
        "FEMALE2000": 24,
        "POP2008": 54,
        "G_RATE": 1.0180000066757202,
        "Geocode_Num": 10010318006,
        "PROVINCE": 10
      }
    }
  ]
}