{
  "type": "FeatureCollection",
  "features": [
    {
      "type": "Feature",
      "id": 9696,
      "geometry": {
        "type": "Point",
        "coordinates": [
          150.8536239997478,
          -10.23570199994731
        ]
      },
      "properties": {
        "OBJECTID": 9696,
        "CU_NAME": "IBULAI",
        "CU_NO": "001",
        "GEOCODE": "05010415001",
        "PROV_KEY": "05",
        "DIST_NO": "01",
        "LLG_NO": "04",
        "WARD_NO": "15",
        "WARD_NAME": "IBULAI",
        "LATITUDE": -10.237171,
        "LONGITUDE": 150.852646,
        "REGHH": 31,
        "TOTPOP2000": 168,
        "MALE2000": 79,
        "FEMALE2000": 89,
        "POP2008": 204,
        "G_RATE": 1.024999976158142,
        "Geocode_Num": 5010415001,
        "PROVINCE": 5
      }
    }
  ]
}