{
  "type": "FeatureCollection",
  "features": [
    {
      "type": "Feature",
      "id": 8417,
      "geometry": {
        "type": "Point",
        "coordinates": [
          144.67777499991632,
          -4.864098000022636
        ]
      },
      "properties": {
        "OBJECTID": 8417,
        "CU_NAME": "PAIBU",
        "CU_NO": "034",
        "GEOCODE": "13030708034",
        "PROV_KEY": "13",
        "DIST_NO": "03",
        "LLG_NO": "07",
        "WARD_NO": "08",
        "WARD_NAME": "WARD 8",
        "LATITUDE": -4.865495,
        "LONGITUDE": 144.676723,
        "REGHH": 42,
        "TOTPOP2000": 269,
        "MALE2000": 134,
        "FEMALE2000": 135,
        "POP2008": 333,
        "G_RATE": 1.0269999504089355,
        "Geocode_Num": 13030708034,
        "PROVINCE": 13
      }
    },
    {
      "type": "Feature",
      "id": 8418,
      "geometry": {
        "type": "Point",
        "coordinates": [
          144.72306000001902,
          -4.880682000373952
        ]
      },
      "properties": {
        "OBJECTID": 8418,
        "CU_NAME": "BADOBU & BALABU S/CSH",
        "CU_NO": "044",
        "GEOCODE": "13030708044",
        "PROV_KEY": "13",
        "DIST_NO": "03",
        "LLG_NO": "07",
        "WARD_NO": "08",
        "WARD_NAME": "WARD 8",
        "LATITUDE": -4.891242,
        "LONGITUDE": 144.715568,
        "REGHH": 21,
        "TOTPOP2000": 146,
        "MALE2000": 67,
        "FEMALE2000": 79,
        "POP2008": 180,
        "G_RATE": 1.0269999504089355,
        "Geocode_Num": 13030708044,
        "PROVINCE": 13
      }
    },
    {
      "type": "Feature",
      "id": 8419,
      "geometry": {
        "type": "Point",
        "coordinates": [
          144.71485800039648,
          -4.89758400010146
        ]
      },
      "properties": {
        "OBJECTID": 8419,
        "CU_NAME": "GORIBU",
        "CU_NO": "045",
        "GEOCODE": "13030708045",
        "PROV_KEY": "13",
        "DIST_NO": "03",
        "LLG_NO": "07",
        "WARD_NO": "08",
        "WARD_NAME": "WARD 8",
        "LATITUDE": -4.896961,
        "LONGITUDE": 144.705115,
        "REGHH": 7,
        "TOTPOP2000": 45,
        "MALE2000": 23,
        "FEMALE2000": 22,
        "POP2008": 53,
        "G_RATE": 1.0269999504089355,
        "Geocode_Num": 13030708045,
        "PROVINCE": 13
      }
    }
  ]
}