{
  "type": "FeatureCollection",
  "features": [
    {
      "type": "Feature",
      "id": 8484,
      "geometry": {
        "type": "Point",
        "coordinates": [
          144.73928099981833,
          -5.127575999632654
        ]
      },
      "properties": {
        "OBJECTID": 8484,
        "CU_NAME": "IPORAITZ",
        "CU_NO": "016",
        "GEOCODE": "13030729016",
        "PROV_KEY": "13",
        "DIST_NO": "03",
        "LLG_NO": "07",
        "WARD_NO": "29",
        "WARD_NAME": "WARD 29",
        "LATITUDE": -5.128976,
        "LONGITUDE": 144.73823,
        "REGHH": 22,
        "TOTPOP2000": 129,
        "MALE2000": 64,
        "FEMALE2000": 65,
        "POP2008": 160,
        "G_RATE": 1.0269999504089355,
        "Geocode_Num": 13030729016,
        "PROVINCE": 13
      }
    },
    {
      "type": "Feature",
      "id": 8485,
      "geometry": {
        "type": "Point",
        "coordinates": [
          144.7482279996226,
          -5.122036999607815
        ]
      },
      "properties": {
        "OBJECTID": 8485,
        "CU_NAME": "KURAKEM",
        "CU_NO": "025",
        "GEOCODE": "13030729025",
        "PROV_KEY": "13",
        "DIST_NO": "03",
        "LLG_NO": "07",
        "WARD_NO": "29",
        "WARD_NAME": "WARD 29",
        "LATITUDE": -5.123437,
        "LONGITUDE": 144.747177,
        "REGHH": 17,
        "TOTPOP2000": 108,
        "MALE2000": 59,
        "FEMALE2000": 49,
        "POP2008": 132,
        "G_RATE": 1.0269999504089355,
        "Geocode_Num": 13030729025,
        "PROVINCE": 13
      }
    },
    {
      "type": "Feature",
      "id": 8486,
      "geometry": {
        "type": "Point",
        "coordinates": [
          144.74272400031248,
          -5.121464000163428
        ]
      },
      "properties": {
        "OBJECTID": 8486,
        "CU_NAME": "MAUACHICH",
        "CU_NO": "026",
        "GEOCODE": "13030729026",
        "PROV_KEY": "13",
        "DIST_NO": "03",
        "LLG_NO": "07",
        "WARD_NO": "29",
        "WARD_NAME": "WARD 29",
        "LATITUDE": -5.122864,
        "LONGITUDE": 144.741673,
        "REGHH": 20,
        "TOTPOP2000": 133,
        "MALE2000": 74,
        "FEMALE2000": 59,
        "POP2008": 165,
        "G_RATE": 1.0269999504089355,
        "Geocode_Num": 13030729026,
        "PROVINCE": 13
      }
    }
  ]
}