{
  "type": "FeatureCollection",
  "features": [
    {
      "type": "Feature",
      "id": 12905,
      "geometry": {
        "type": "Point",
        "coordinates": [
          153.6235159996637,
          -4.027003999734745
        ]
      },
      "properties": {
        "OBJECTID": 12905,
        "CU_NAME": "BASAKLA",
        "CU_NO": "004",
        "GEOCODE": "17020811004",
        "PROV_KEY": "17",
        "DIST_NO": "02",
        "LLG_NO": "08",
        "WARD_NO": "11",
        "WARD_NAME": "BASAKALA",
        "LATITUDE": -4.026157,
        "LONGITUDE": 153.622219,
        "REGHH": 14,
        "TOTPOP2000": 79,
        "MALE2000": 43,
        "FEMALE2000": 36,
        "POP2008": 99,
        "G_RATE": 1.0290000438690186,
        "Geocode_Num": 17020811004,
        "PROVINCE": 17
      }
    },
    {
      "type": "Feature",
      "id": 12906,
      "geometry": {
        "type": "Point",
        "coordinates": [
          153.63436499994486,
          -4.018491000159486
        ]
      },
      "properties": {
        "OBJECTID": 12906,
        "CU_NAME": "FARNGOT",
        "CU_NO": "006",
        "GEOCODE": "17020811006",
        "PROV_KEY": "17",
        "DIST_NO": "02",
        "LLG_NO": "08",
        "WARD_NO": "11",
        "WARD_NAME": "BASAKALA",
        "LATITUDE": -4.018768,
        "LONGITUDE": 153.631951,
        "REGHH": 29,
        "TOTPOP2000": 173,
        "MALE2000": 90,
        "FEMALE2000": 83,
        "POP2008": 217,
        "G_RATE": 1.0290000438690186,
        "Geocode_Num": 17020811006,
        "PROVINCE": 17
      }
    },
    {
      "type": "Feature",
      "id": 12907,
      "geometry": {
        "type": "Point",
        "coordinates": [
          153.6073359999565,
          -4.041190000118377
        ]
      },
      "properties": {
        "OBJECTID": 12907,
        "CU_NAME": "FATKASANG",
        "CU_NO": "015",
        "GEOCODE": "17020811015",
        "PROV_KEY": "17",
        "DIST_NO": "02",
        "LLG_NO": "08",
        "WARD_NO": "11",
        "WARD_NAME": "BASAKALA",
        "LATITUDE": -4.042588,
        "LONGITUDE": 153.606412,
        "REGHH": 13,
        "TOTPOP2000": 69,
        "MALE2000": 31,
        "FEMALE2000": 38,
        "POP2008": 85,
        "G_RATE": 1.0290000438690186,
        "Geocode_Num": 17020811015,
        "PROVINCE": 17
      }
    }
  ]
}