{
  "type": "FeatureCollection",
  "features": [
    {
      "type": "Feature",
      "id": 6804,
      "geometry": {
        "type": "Point",
        "coordinates": [
          143.9344340000291,
          -3.7382520001296484
        ]
      },
      "properties": {
        "OBJECTID": 6804,
        "CU_NAME": "SAMAP 1",
        "CU_NO": "019",
        "GEOCODE": "14041505019",
        "PROV_KEY": "14",
        "DIST_NO": "04",
        "LLG_NO": "15",
        "WARD_NO": "05",
        "WARD_NAME": "SAMAP",
        "LATITUDE": -3.737823,
        "LONGITUDE": 143.933158,
        "REGHH": 29,
        "TOTPOP2000": 210,
        "MALE2000": 103,
        "FEMALE2000": 107,
        "POP2008": 250,
        "G_RATE": 1.0219999551773071,
        "Geocode_Num": 14041505019,
        "PROVINCE": 14
      }
    },
    {
      "type": "Feature",
      "id": 6805,
      "geometry": {
        "type": "Point",
        "coordinates": [
          143.92818799977647,
          -3.725035000364926
        ]
      },
      "properties": {
        "OBJECTID": 6805,
        "CU_NAME": "SAMAP 2",
        "CU_NO": "020",
        "GEOCODE": "14041505020",
        "PROV_KEY": "14",
        "DIST_NO": "04",
        "LLG_NO": "15",
        "WARD_NO": "05",
        "WARD_NAME": "SAMAP",
        "LATITUDE": -3.725588,
        "LONGITUDE": 143.928987,
        "REGHH": 20,
        "TOTPOP2000": 117,
        "MALE2000": 65,
        "FEMALE2000": 52,
        "POP2008": 141,
        "G_RATE": 1.0219999551773071,
        "Geocode_Num": 14041505020,
        "PROVINCE": 14
      }
    }
  ]
}