{
  "type": "FeatureCollection",
  "features": [
    {
      "type": "Feature",
      "id": 982,
      "geometry": {
        "type": "Point",
        "coordinates": [
          148.7943420002831,
          -10.131179000210636
        ]
      },
      "properties": {
        "OBJECTID": 982,
        "CU_NAME": "APAEVA",
        "CU_NO": "033",
        "GEOCODE": "03010303033",
        "PROV_KEY": "03",
        "DIST_NO": "01",
        "LLG_NO": "03",
        "WARD_NO": "03",
        "WARD_NAME": "ROBINSON RIVER",
        "LATITUDE": -10.137551,
        "LONGITUDE": 148.789864,
        "REGHH": 21,
        "TOTPOP2000": 102,
        "MALE2000": 58,
        "FEMALE2000": 44,
        "POP2008": 122,
        "G_RATE": 1.0230000019073486,
        "Geocode_Num": 3010303033,
        "PROVINCE": 3
      }
    },
    {
      "type": "Feature",
      "id": 983,
      "geometry": {
        "type": "Point",
        "coordinates": [
          148.8510920002957,
          -10.14237899959113
        ]
      },
      "properties": {
        "OBJECTID": 983,
        "CU_NAME": "ROBINSON RIVER PLTN",
        "CU_NO": "525",
        "GEOCODE": "03010303525",
        "PROV_KEY": "03",
        "DIST_NO": "01",
        "LLG_NO": "03",
        "WARD_NO": "03",
        "WARD_NAME": "ROBINSON RIVER",
        "LATITUDE": -10.143841,
        "LONGITUDE": 148.850085,
        "REGHH": 10,
        "TOTPOP2000": 62,
        "MALE2000": 35,
        "FEMALE2000": 27,
        "POP2008": 74,
        "G_RATE": 1.0230000019073486,
        "Geocode_Num": 3010303525,
        "PROVINCE": 3
      }
    }
  ]
}