{
  "type": "FeatureCollection",
  "features": [
    {
      "type": "Feature",
      "id": 984,
      "geometry": {
        "type": "Point",
        "coordinates": [
          148.7115390003247,
          -10.183421000079022
        ]
      },
      "properties": {
        "OBJECTID": 984,
        "CU_NAME": "ANAVE",
        "CU_NO": "002",
        "GEOCODE": "03010304002",
        "PROV_KEY": "03",
        "DIST_NO": "01",
        "LLG_NO": "03",
        "WARD_NO": "04",
        "WARD_NAME": "SI'INI",
        "LATITUDE": -10.18298,
        "LONGITUDE": 148.711056,
        "REGHH": 15,
        "TOTPOP2000": 97,
        "MALE2000": 59,
        "FEMALE2000": 38,
        "POP2008": 115,
        "G_RATE": 1.0230000019073486,
        "Geocode_Num": 3010304002,
        "PROVINCE": 3
      }
    },
    {
      "type": "Feature",
      "id": 985,
      "geometry": {
        "type": "Point",
        "coordinates": [
          148.74333399976433,
          -10.215755000093111
        ]
      },
      "properties": {
        "OBJECTID": 985,
        "CU_NAME": "SI'INI",
        "CU_NO": "039",
        "GEOCODE": "03010304039",
        "PROV_KEY": "03",
        "DIST_NO": "01",
        "LLG_NO": "03",
        "WARD_NO": "04",
        "WARD_NAME": "SI'INI",
        "LATITUDE": -10.213034,
        "LONGITUDE": 148.740809,
        "REGHH": 30,
        "TOTPOP2000": 192,
        "MALE2000": 101,
        "FEMALE2000": 91,
        "POP2008": 231,
        "G_RATE": 1.0230000019073486,
        "Geocode_Num": 3010304039,
        "PROVINCE": 3
      }
    },
    {
      "type": "Feature",
      "id": 986,
      "geometry": {
        "type": "Point",
        "coordinates": [
          148.6848489997816,
          -10.157157000295285
        ]
      },
      "properties": {
        "OBJECTID": 986,
        "CU_NAME": "GEBEA",
        "CU_NO": "040",
        "GEOCODE": "03010304040",
        "PROV_KEY": "03",
        "DIST_NO": "01",
        "LLG_NO": "03",
        "WARD_NO": "04",
        "WARD_NAME": "SI'INI",
        "LATITUDE": -10.159514,
        "LONGITUDE": 148.686991,
        "REGHH": 7,
        "TOTPOP2000": 26,
        "MALE2000": 14,
        "FEMALE2000": 12,
        "POP2008": 34,
        "G_RATE": 1.0230000019073486,
        "Geocode_Num": 3010304040,
        "PROVINCE": 3
      }
    }
  ]
}