{
  "type": "FeatureCollection",
  "features": [
    {
      "type": "Feature",
      "id": 10296,
      "geometry": {
        "type": "Point",
        "coordinates": [
          151.2608320003966,
          -9.9160210003688
        ]
      },
      "properties": {
        "OBJECTID": 10296,
        "CU_NAME": "LOBODA",
        "CU_NO": "014",
        "GEOCODE": "05041610014",
        "PROV_KEY": "05",
        "DIST_NO": "4",
        "LLG_NO": "16",
        "WARD_NO": "10",
        "WARD_NAME": "LOBODA",
        "LATITUDE": -9.917487,
        "LONGITUDE": 151.259861,
        "REGHH": 90,
        "TOTPOP2000": 408,
        "MALE2000": 206,
        "FEMALE2000": 202,
        "POP2008": 497,
        "G_RATE": 1.024999976158142,
        "Geocode_Num": 5041610014,
        "PROVINCE": 5
      }
    }
  ]
}