{
  "type": "FeatureCollection",
  "features": [
    {
      "type": "Feature",
      "id": 5893,
      "geometry": {
        "type": "Point",
        "coordinates": [
          143.91742599991005,
          -5.613094999934276
        ]
      },
      "properties": {
        "OBJECTID": 5893,
        "CU_NAME": "TAKAEPOS",
        "CU_NO": "009",
        "GEOCODE": "08051310009",
        "PROV_KEY": "08",
        "DIST_NO": "05",
        "LLG_NO": "13",
        "WARD_NO": "10",
        "WARD_NAME": "TAKAEPOS",
        "LATITUDE": -5.616716,
        "LONGITUDE": 143.920389,
        "REGHH": 139,
        "TOTPOP2000": 820,
        "MALE2000": 427,
        "FEMALE2000": 393,
        "POP2008": 1030,
        "G_RATE": 1.0290000438690186,
        "Geocode_Num": 8051310009,
        "PROVINCE": 8
      }
    },
    {
      "type": "Feature",
      "id": 5894,
      "geometry": {
        "type": "Point",
        "coordinates": [
          143.92758099966352,
          -5.6205470000439846
        ]
      },
      "properties": {
        "OBJECTID": 5894,
        "CU_NAME": "BETA",
        "CU_NO": "010",
        "GEOCODE": "08051310010",
        "PROV_KEY": "08",
        "DIST_NO": "05",
        "LLG_NO": "13",
        "WARD_NO": "10",
        "WARD_NAME": "TAKAEPOS",
        "LATITUDE": -5.618825,
        "LONGITUDE": 143.925164,
        "REGHH": 88,
        "TOTPOP2000": 397,
        "MALE2000": 200,
        "FEMALE2000": 197,
        "POP2008": 500,
        "G_RATE": 1.0290000438690186,
        "Geocode_Num": 8051310010,
        "PROVINCE": 8
      }
    }
  ]
}