{
  "type": "FeatureCollection",
  "features": [
    {
      "type": "Feature",
      "id": 5931,
      "geometry": {
        "type": "Point",
        "coordinates": [
          143.90379900012385,
          -5.513138000318406
        ]
      },
      "properties": {
        "OBJECTID": 5931,
        "CU_NAME": "TAPENDA",
        "CU_NO": "001",
        "GEOCODE": "08051328001",
        "PROV_KEY": "08",
        "DIST_NO": "05",
        "LLG_NO": "13",
        "WARD_NO": "28",
        "WARD_NAME": "TAPENDA",
        "LATITUDE": -5.515986,
        "LONGITUDE": 143.904315,
        "REGHH": 128,
        "TOTPOP2000": 621,
        "MALE2000": 297,
        "FEMALE2000": 324,
        "POP2008": 781,
        "G_RATE": 1.0290000438690186,
        "Geocode_Num": 8051328001,
        "PROVINCE": 8
      }
    },
    {
      "type": "Feature",
      "id": 5932,
      "geometry": {
        "type": "Point",
        "coordinates": [
          143.92362199965567,
          -5.657137000272314
        ]
      },
      "properties": {
        "OBJECTID": 5932,
        "CU_NAME": "KUBAS",
        "CU_NO": "006",
        "GEOCODE": "08051328006",
        "PROV_KEY": "08",
        "DIST_NO": "05",
        "LLG_NO": "13",
        "WARD_NO": "28",
        "WARD_NAME": "YARAMANDA",
        "LATITUDE": -5.658541,
        "LONGITUDE": 143.922559,
        "REGHH": 101,
        "TOTPOP2000": 697,
        "MALE2000": 356,
        "FEMALE2000": 341,
        "POP2008": 876,
        "G_RATE": 1.0290000438690186,
        "Geocode_Num": 8051328006,
        "PROVINCE": 8
      }
    },
    {
      "type": "Feature",
      "id": 5933,
      "geometry": {
        "type": "Point",
        "coordinates": [
          143.89956399997868,
          -5.518413999906102
        ]
      },
      "properties": {
        "OBJECTID": 5933,
        "CU_NAME": "TAPENDA H/SCH",
        "CU_NO": "401",
        "GEOCODE": "08051328401",
        "PROV_KEY": "08",
        "DIST_NO": "05",
        "LLG_NO": "13",
        "WARD_NO": "28",
        "WARD_NAME": "TAPENDA",
        "LATITUDE": -5.515138,
        "LONGITUDE": 143.903709,
        "REGHH": 32,
        "TOTPOP2000": 195,
        "MALE2000": 102,
        "FEMALE2000": 93,
        "POP2008": 246,
        "G_RATE": 1.0290000438690186,
        "Geocode_Num": 8051328401,
        "PROVINCE": 8
      }
    }
  ]
}