{
  "type": "FeatureCollection",
  "features": [
    {
      "type": "Feature",
      "id": 15782,
      "geometry": {
        "type": "Point",
        "coordinates": [
          144.31000200029212,
          -5.88066999962075
        ]
      },
      "properties": {
        "OBJECTID": 15782,
        "CU_NAME": "WURUP 3",
        "CU_NO": "011",
        "GEOCODE": "09010107011",
        "PROV_KEY": "22",
        "DIST_NO": "01",
        "LLG_NO": "01",
        "WARD_NO": "07",
        "WARD_NAME": "WURUP 3",
        "LATITUDE": -5.881616,
        "LONGITUDE": 144.311714,
        "REGHH": 15,
        "TOTPOP2000": 72,
        "MALE2000": 33,
        "FEMALE2000": 39,
        "POP2008": 88,
        "G_RATE": 1.024999976158142,
        "Geocode_Num": 9010107011,
        "PROVINCE": 22
      }
    },
    {
      "type": "Feature",
      "id": 15783,
      "geometry": {
        "type": "Point",
        "coordinates": [
          144.302010999608,
          -5.874104999945757
        ]
      },
      "properties": {
        "OBJECTID": 15783,
        "CU_NAME": "PULGBULG",
        "CU_NO": "012",
        "GEOCODE": "09010107012",
        "PROV_KEY": "22",
        "DIST_NO": "01",
        "LLG_NO": "01",
        "WARD_NO": "07",
        "WARD_NAME": "WURUP 3",
        "LATITUDE": -5.873671,
        "LONGITUDE": 144.30373,
        "REGHH": 110,
        "TOTPOP2000": 459,
        "MALE2000": 235,
        "FEMALE2000": 224,
        "POP2008": 559,
        "G_RATE": 1.024999976158142,
        "Geocode_Num": 9010107012,
        "PROVINCE": 22
      }
    },
    {
      "type": "Feature",
      "id": 15784,
      "geometry": {
        "type": "Point",
        "coordinates": [
          144.31250599975215,
          -5.881720000377641
        ]
      },
      "properties": {
        "OBJECTID": 15784,
        "CU_NAME": "WURUP PENA KONA",
        "CU_NO": "013",
        "GEOCODE": "09010107013",
        "PROV_KEY": "22",
        "DIST_NO": "01",
        "LLG_NO": "01",
        "WARD_NO": "07",
        "WARD_NAME": "WURUP 3",
        "LATITUDE": -5.882659,
        "LONGITUDE": 144.312841,
        "REGHH": 43,
        "TOTPOP2000": 187,
        "MALE2000": 97,
        "FEMALE2000": 90,
        "POP2008": 228,
        "G_RATE": 1.024999976158142,
        "Geocode_Num": 9010107013,
        "PROVINCE": 22
      }
    },
    {
      "type": "Feature",
      "id": 15785,
      "geometry": {
        "type": "Point",
        "coordinates": [
          144.3263729998141,
          -5.89888899982742
        ]
      },
      "properties": {
        "OBJECTID": 15785,
        "CU_NAME": "KOKPENA KONA",
        "CU_NO": "014",
        "GEOCODE": "09010107014",
        "PROV_KEY": "22",
        "DIST_NO": "01",
        "LLG_NO": "01",
        "WARD_NO": "07",
        "WARD_NAME": "WURUP 3",
        "LATITUDE": -5.899828,
        "LONGITUDE": 144.326707,
        "REGHH": 164,
        "TOTPOP2000": 656,
        "MALE2000": 330,
        "FEMALE2000": 326,
        "POP2008": 799,
        "G_RATE": 1.024999976158142,
        "Geocode_Num": 9010107014,
        "PROVINCE": 22
      }
    }
  ]
}