{
  "type": "FeatureCollection",
  "features": [
    {
      "type": "Feature",
      "id": 15799,
      "geometry": {
        "type": "Point",
        "coordinates": [
          144.32951599996352,
          -5.850293999968073
        ]
      },
      "properties": {
        "OBJECTID": 15799,
        "CU_NAME": "PANGA",
        "CU_NO": "013",
        "GEOCODE": "09010111013",
        "PROV_KEY": "22",
        "DIST_NO": "01",
        "LLG_NO": "01",
        "WARD_NO": "11",
        "WARD_NAME": "PANGA",
        "LATITUDE": -5.851233,
        "LONGITUDE": 144.32985,
        "REGHH": 69,
        "TOTPOP2000": 368,
        "MALE2000": 183,
        "FEMALE2000": 185,
        "POP2008": 448,
        "G_RATE": 1.024999976158142,
        "Geocode_Num": 9010111013,
        "PROVINCE": 22
      }
    },
    {
      "type": "Feature",
      "id": 15800,
      "geometry": {
        "type": "Point",
        "coordinates": [
          144.32733500011022,
          -5.838229000268086
        ]
      },
      "properties": {
        "OBJECTID": 15800,
        "CU_NAME": "PANGA COFFEE FACTORY",
        "CU_NO": "401",
        "GEOCODE": "09010111401",
        "PROV_KEY": "22",
        "DIST_NO": "01",
        "LLG_NO": "01",
        "WARD_NO": "11",
        "WARD_NAME": "PANGA",
        "LATITUDE": -5.839168,
        "LONGITUDE": 144.327669,
        "REGHH": 45,
        "TOTPOP2000": 252,
        "MALE2000": 138,
        "FEMALE2000": 114,
        "POP2008": 306,
        "G_RATE": 1.024999976158142,
        "Geocode_Num": 9010111401,
        "PROVINCE": 22
      }
    },
    {
      "type": "Feature",
      "id": 15801,
      "geometry": {
        "type": "Point",
        "coordinates": [
          144.32637499990642,
          -5.84681799975084
        ]
      },
      "properties": {
        "OBJECTID": 15801,
        "CU_NAME": "CRI & DPI CAMP",
        "CU_NO": "402",
        "GEOCODE": "09010111402",
        "PROV_KEY": "22",
        "DIST_NO": "01",
        "LLG_NO": "01",
        "WARD_NO": "11",
        "WARD_NAME": "PANGA",
        "LATITUDE": -5.847757,
        "LONGITUDE": 144.326709,
        "REGHH": 73,
        "TOTPOP2000": 479,
        "MALE2000": 277,
        "FEMALE2000": 202,
        "POP2008": 584,
        "G_RATE": 1.024999976158142,
        "Geocode_Num": 9010111402,
        "PROVINCE": 22
      }
    }
  ]
}