{
  "type": "FeatureCollection",
  "features": [
    {
      "type": "Feature",
      "id": 11238,
      "geometry": {
        "type": "Point",
        "coordinates": [
          147.20010400029946,
          -6.180383000175254
        ]
      },
      "properties": {
        "OBJECTID": 11238,
        "CU_NAME": "DOLO",
        "CU_NO": "003",
        "GEOCODE": "12041315003",
        "PROV_KEY": "12",
        "DIST_NO": "04",
        "LLG_NO": "13",
        "WARD_NO": "15",
        "WARD_NAME": "DOLO",
        "LATITUDE": -6.181799,
        "LONGITUDE": 147.199084,
        "REGHH": 67,
        "TOTPOP2000": 382,
        "MALE2000": 185,
        "FEMALE2000": 197,
        "POP2008": 477,
        "G_RATE": 1.027999997138977,
        "Geocode_Num": 12041315003,
        "PROVINCE": 12
      }
    },
    {
      "type": "Feature",
      "id": 11239,
      "geometry": {
        "type": "Point",
        "coordinates": [
          147.1827579998818,
          -6.171821000139005
        ]
      },
      "properties": {
        "OBJECTID": 11239,
        "CU_NAME": "WEKE",
        "CU_NO": "015",
        "GEOCODE": "12041315015",
        "PROV_KEY": "12",
        "DIST_NO": "04",
        "LLG_NO": "13",
        "WARD_NO": "15",
        "WARD_NAME": "DOLO",
        "LATITUDE": -6.173237,
        "LONGITUDE": 147.181737,
        "REGHH": 65,
        "TOTPOP2000": 308,
        "MALE2000": 136,
        "FEMALE2000": 172,
        "POP2008": 384,
        "G_RATE": 1.027999997138977,
        "Geocode_Num": 12041315015,
        "PROVINCE": 12
      }
    }
  ]
}