{
  "type": "FeatureCollection",
  "features": [
    {
      "type": "Feature",
      "id": 19093,
      "geometry": {
        "type": "Point",
        "coordinates": [
          141.4880259997002,
          -3.194665000189559
        ]
      },
      "properties": {
        "OBJECTID": 19093,
        "CU_NAME": "FAS 2",
        "CU_NO": "002",
        "GEOCODE": "15041610002",
        "PROV_KEY": "15",
        "DIST_NO": "04",
        "LLG_NO": "16",
        "WARD_NO": "10",
        "WARD_NAME": "TAMINA 1",
        "LATITUDE": -3.198947,
        "LONGITUDE": 141.479718,
        "REGHH": 18,
        "TOTPOP2000": 129,
        "MALE2000": 67,
        "FEMALE2000": 62,
        "POP2008": 155,
        "G_RATE": 1.0240000486373901,
        "Geocode_Num": 15041610002,
        "PROVINCE": 15
      }
    },
    {
      "type": "Feature",
      "id": 19094,
      "geometry": {
        "type": "Point",
        "coordinates": [
          141.52367599974764,
          -3.192205000060653
        ]
      },
      "properties": {
        "OBJECTID": 19094,
        "CU_NAME": "NEBIKE",
        "CU_NO": "005",
        "GEOCODE": "15041610005",
        "PROV_KEY": "15",
        "DIST_NO": "04",
        "LLG_NO": "16",
        "WARD_NO": "10",
        "WARD_NAME": "TAMINA 1",
        "LATITUDE": -3.195933,
        "LONGITUDE": 141.527746,
        "REGHH": 25,
        "TOTPOP2000": 143,
        "MALE2000": 85,
        "FEMALE2000": 58,
        "POP2008": 174,
        "G_RATE": 1.0240000486373901,
        "Geocode_Num": 15041610005,
        "PROVINCE": 15
      }
    },
    {
      "type": "Feature",
      "id": 19095,
      "geometry": {
        "type": "Point",
        "coordinates": [
          141.5310620004111,
          -3.219623000001377
        ]
      },
      "properties": {
        "OBJECTID": 19095,
        "CU_NAME": "TAMINA 1",
        "CU_NO": "006",
        "GEOCODE": "15041610006",
        "PROV_KEY": "15",
        "DIST_NO": "04",
        "LLG_NO": "16",
        "WARD_NO": "10",
        "WARD_NAME": "TAMINA 1",
        "LATITUDE": -3.205924,
        "LONGITUDE": 141.519653,
        "REGHH": 18,
        "TOTPOP2000": 92,
        "MALE2000": 57,
        "FEMALE2000": 35,
        "POP2008": 109,
        "G_RATE": 1.0240000486373901,
        "Geocode_Num": 15041610006,
        "PROVINCE": 15
      }
    },
    {
      "type": "Feature",
      "id": 19096,
      "geometry": {
        "type": "Point",
        "coordinates": [
          141.59837800024457,
          -3.2445500001823007
        ]
      },
      "properties": {
        "OBJECTID": 19096,
        "CU_NAME": "TAMINA 2",
        "CU_NO": "007",
        "GEOCODE": "15041610007",
        "PROV_KEY": "15",
        "DIST_NO": "04",
        "LLG_NO": "16",
        "WARD_NO": "10",
        "WARD_NAME": "TAMINA 1",
        "LATITUDE": -3.245925,
        "LONGITUDE": 141.597291,
        "REGHH": 12,
        "TOTPOP2000": 66,
        "MALE2000": 34,
        "FEMALE2000": 32,
        "POP2008": 82,
        "G_RATE": 1.0240000486373901,
        "Geocode_Num": 15041610007,
        "PROVINCE": 15
      }
    }
  ]
}