{
  "type": "FeatureCollection",
  "features": [
    {
      "type": "Feature",
      "id": 30031,
      "geometry": {
        "type": "Point",
        "coordinates": [
          145.19921075986872,
          -6.466083479568908
        ]
      },
      "properties": {
        "OBJECTID": 30031,
        "CU_NAME": "LOVAI",
        "CU_NO": "025",
        "GEOCODE": "11050708025",
        "PROV_KEY": "11",
        "DIST_NO": "05",
        "LLG_NO": "07",
        "WARD_NO": "08",
        "WARD_NAME": "AGIBU",
        "LATITUDE": -6.466083,
        "LONGITUDE": 145.199211,
        "REGHH": 28,
        "TOTPOP2000": 113,
        "MALE2000": 64,
        "FEMALE2000": 49,
        "POP2008": 136,
        "G_RATE": 1.0219999551773071,
        "Geocode_Num": null,
        "PROVINCE": 11
      }
    },
    {
      "type": "Feature",
      "id": 30032,
      "geometry": {
        "type": "Point",
        "coordinates": [
          145.19713752038035,
          -6.455744009978048
        ]
      },
      "properties": {
        "OBJECTID": 30032,
        "CU_NAME": "KOKONA",
        "CU_NO": "026",
        "GEOCODE": "11050708026",
        "PROV_KEY": "11",
        "DIST_NO": "05",
        "LLG_NO": "07",
        "WARD_NO": "08",
        "WARD_NAME": "AGIBU",
        "LATITUDE": -6.455744,
        "LONGITUDE": 145.197138,
        "REGHH": 37,
        "TOTPOP2000": 172,
        "MALE2000": 88,
        "FEMALE2000": 84,
        "POP2008": 204,
        "G_RATE": 1.0219999551773071,
        "Geocode_Num": null,
        "PROVINCE": 11
      }
    },
    {
      "type": "Feature",
      "id": 30033,
      "geometry": {
        "type": "Point",
        "coordinates": [
          145.2098552399275,
          -6.4518601501257535
        ]
      },
      "properties": {
        "OBJECTID": 30033,
        "CU_NAME": "IZOVITAI",
        "CU_NO": "027",
        "GEOCODE": "11050708027",
        "PROV_KEY": "11",
        "DIST_NO": "05",
        "LLG_NO": "07",
        "WARD_NO": "08",
        "WARD_NAME": "AGIBU",
        "LATITUDE": -6.45186,
        "LONGITUDE": 145.209855,
        "REGHH": 29,
        "TOTPOP2000": 143,
        "MALE2000": 74,
        "FEMALE2000": 69,
        "POP2008": 169,
        "G_RATE": 1.0219999551773071,
        "Geocode_Num": null,
        "PROVINCE": 11
      }
    }
  ]
}