{
  "type": "FeatureCollection",
  "features": [
    {
      "type": "Feature",
      "id": 30051,
      "geometry": {
        "type": "Point",
        "coordinates": [
          145.25211959983972,
          -6.455503349599837
        ]
      },
      "properties": {
        "OBJECTID": 30051,
        "CU_NAME": "ETABA",
        "CU_NO": "008",
        "GEOCODE": "11050712008",
        "PROV_KEY": "11",
        "DIST_NO": "05",
        "LLG_NO": "07",
        "WARD_NO": "12",
        "WARD_NAME": "FIAMOTAVA",
        "LATITUDE": -6.455503,
        "LONGITUDE": 145.25212,
        "REGHH": 34,
        "TOTPOP2000": 152,
        "MALE2000": 69,
        "FEMALE2000": 83,
        "POP2008": 181,
        "G_RATE": 1.0219999551773071,
        "Geocode_Num": null,
        "PROVINCE": 11
      }
    },
    {
      "type": "Feature",
      "id": 30052,
      "geometry": {
        "type": "Point",
        "coordinates": [
          145.27024019982548,
          -6.3608781596992685
        ]
      },
      "properties": {
        "OBJECTID": 30052,
        "CU_NAME": "BEHA NO 2",
        "CU_NO": "019",
        "GEOCODE": "11050712019",
        "PROV_KEY": "11",
        "DIST_NO": "05",
        "LLG_NO": "07",
        "WARD_NO": "12",
        "WARD_NAME": "FIAMOTAVA",
        "LATITUDE": -6.360878,
        "LONGITUDE": 145.27024,
        "REGHH": 24,
        "TOTPOP2000": 112,
        "MALE2000": 54,
        "FEMALE2000": 58,
        "POP2008": 135,
        "G_RATE": 1.0219999551773071,
        "Geocode_Num": null,
        "PROVINCE": 11
      }
    }
  ]
}