{
  "type": "FeatureCollection",
  "features": [
    {
      "type": "Feature",
      "id": 9485,
      "geometry": {
        "type": "Point",
        "coordinates": [
          147.05216899959976,
          -2.079484000186426
        ]
      },
      "properties": {
        "OBJECTID": 9485,
        "CU_NAME": "BUYANG",
        "CU_NO": "001",
        "GEOCODE": "16010901001",
        "PROV_KEY": "16",
        "DIST_NO": "01",
        "LLG_NO": "09",
        "WARD_NO": "01",
        "WARD_NAME": "BUYANG",
        "LATITUDE": -2.08085,
        "LONGITUDE": 147.051152,
        "REGHH": 62,
        "TOTPOP2000": 348,
        "MALE2000": 176,
        "FEMALE2000": 172,
        "POP2008": 428,
        "G_RATE": 1.0260000228881836,
        "Geocode_Num": 16010901001,
        "PROVINCE": 16
      }
    }
  ]
}