{
  "type": "FeatureCollection",
  "features": [
    {
      "type": "Feature",
      "id": 9489,
      "geometry": {
        "type": "Point",
        "coordinates": [
          147.07470900032013,
          -2.194315000436859
        ]
      },
      "properties": {
        "OBJECTID": 9489,
        "CU_NAME": "LOCHA",
        "CU_NO": "002",
        "GEOCODE": "16010904002",
        "PROV_KEY": "16",
        "DIST_NO": "01",
        "LLG_NO": "09",
        "WARD_NO": "04",
        "WARD_NAME": "LONDRU",
        "LATITUDE": -2.195683,
        "LONGITUDE": 147.073692,
        "REGHH": 3,
        "TOTPOP2000": 13,
        "MALE2000": 6,
        "FEMALE2000": 7,
        "POP2008": 13,
        "G_RATE": 1.0260000228881836,
        "Geocode_Num": 16010904002,
        "PROVINCE": 16
      }
    },
    {
      "type": "Feature",
      "id": 9490,
      "geometry": {
        "type": "Point",
        "coordinates": [
          147.05562499979396,
          -2.2045219998903463
        ]
      },
      "properties": {
        "OBJECTID": 9490,
        "CU_NAME": "LOI",
        "CU_NO": "003",
        "GEOCODE": "16010904003",
        "PROV_KEY": "16",
        "DIST_NO": "01",
        "LLG_NO": "09",
        "WARD_NO": "04",
        "WARD_NAME": "LONDRU",
        "LATITUDE": -2.204513,
        "LONGITUDE": 147.05543,
        "REGHH": 27,
        "TOTPOP2000": 178,
        "MALE2000": 84,
        "FEMALE2000": 94,
        "POP2008": 219,
        "G_RATE": 1.0260000228881836,
        "Geocode_Num": 16010904003,
        "PROVINCE": 16
      }
    },
    {
      "type": "Feature",
      "id": 9491,
      "geometry": {
        "type": "Point",
        "coordinates": [
          147.08339899996395,
          -2.188417000044467
        ]
      },
      "properties": {
        "OBJECTID": 9491,
        "CU_NAME": "LONDRU",
        "CU_NO": "004",
        "GEOCODE": "16010904004",
        "PROV_KEY": "16",
        "DIST_NO": "01",
        "LLG_NO": "09",
        "WARD_NO": "04",
        "WARD_NAME": "LONDRU",
        "LATITUDE": -2.188646,
        "LONGITUDE": 147.082382,
        "REGHH": 35,
        "TOTPOP2000": 233,
        "MALE2000": 118,
        "FEMALE2000": 115,
        "POP2008": 286,
        "G_RATE": 1.0260000228881836,
        "Geocode_Num": 16010904004,
        "PROVINCE": 16
      }
    }
  ]
}