{
  "type": "FeatureCollection",
  "features": [
    {
      "type": "Feature",
      "id": 9398,
      "geometry": {
        "type": "Point",
        "coordinates": [
          147.011207000103,
          -2.034215999968353
        ]
      },
      "properties": {
        "OBJECTID": 9398,
        "CU_NAME": "BADLOK",
        "CU_NO": "002",
        "GEOCODE": "16010414002",
        "PROV_KEY": "16",
        "DIST_NO": "01",
        "LLG_NO": "04",
        "WARD_NO": "14",
        "WARD_NAME": "BADLOK",
        "LATITUDE": -2.035583,
        "LONGITUDE": 147.010189,
        "REGHH": 47,
        "TOTPOP2000": 224,
        "MALE2000": 114,
        "FEMALE2000": 110,
        "POP2008": 275,
        "G_RATE": 1.0260000228881836,
        "Geocode_Num": 16010414002,
        "PROVINCE": 16
      }
    }
  ]
}