{
  "type": "FeatureCollection",
  "features": [
    {
      "type": "Feature",
      "id": 1662,
      "geometry": {
        "type": "Point",
        "coordinates": [
          147.5792039997648,
          -9.888385000267476
        ]
      },
      "properties": {
        "OBJECTID": 1662,
        "CU_NAME": "GABONE",
        "CU_NO": "020",
        "GEOCODE": "03041205020",
        "PROV_KEY": "03",
        "DIST_NO": "04",
        "LLG_NO": "12",
        "WARD_NO": "05",
        "WARD_NAME": "GABONE",
        "LATITUDE": -9.88984,
        "LONGITUDE": 147.578179,
        "REGHH": 91,
        "TOTPOP2000": 727,
        "MALE2000": 385,
        "FEMALE2000": 342,
        "POP2008": 873,
        "G_RATE": 1.0230000019073486,
        "Geocode_Num": 3041205020,
        "PROVINCE": 3
      }
    }
  ]
}