{
  "type": "FeatureCollection",
  "features": [
    {
      "type": "Feature",
      "id": 1665,
      "geometry": {
        "type": "Point",
        "coordinates": [
          147.60180799983937,
          -9.957904000069504
        ]
      },
      "properties": {
        "OBJECTID": 1665,
        "CU_NAME": "BONANAMO",
        "CU_NO": "010",
        "GEOCODE": "03041207010",
        "PROV_KEY": "03",
        "DIST_NO": "04",
        "LLG_NO": "12",
        "WARD_NO": "07",
        "WARD_NAME": "BONANAMO",
        "LATITUDE": -9.95936,
        "LONGITUDE": 147.600784,
        "REGHH": 84,
        "TOTPOP2000": 449,
        "MALE2000": 244,
        "FEMALE2000": 205,
        "POP2008": 539,
        "G_RATE": 1.0230000019073486,
        "Geocode_Num": 3041207010,
        "PROVINCE": 3
      }
    }
  ]
}