{
  "type": "FeatureCollection",
  "features": [
    {
      "type": "Feature",
      "id": 1684,
      "geometry": {
        "type": "Point",
        "coordinates": [
          147.86572599995498,
          -10.094831000350325
        ]
      },
      "properties": {
        "OBJECTID": 1684,
        "CU_NAME": "KARAWA",
        "CU_NO": "047",
        "GEOCODE": "03041222047",
        "PROV_KEY": "03",
        "DIST_NO": "04",
        "LLG_NO": "12",
        "WARD_NO": "22",
        "WARD_NAME": "KARAWA",
        "LATITUDE": -10.096289,
        "LONGITUDE": 147.864705,
        "REGHH": 65,
        "TOTPOP2000": 376,
        "MALE2000": 185,
        "FEMALE2000": 191,
        "POP2008": 451,
        "G_RATE": 1.0230000019073486,
        "Geocode_Num": 3041222047,
        "PROVINCE": 3
      }
    }
  ]
}