{
  "type": "FeatureCollection",
  "features": [
    {
      "type": "Feature",
      "id": 18917,
      "geometry": {
        "type": "Point",
        "coordinates": [
          141.4366249999439,
          -2.7377899997086956
        ]
      },
      "properties": {
        "OBJECTID": 18917,
        "CU_NAME": "NINGRA",
        "CU_NO": "002",
        "GEOCODE": "15041307002",
        "PROV_KEY": "15",
        "DIST_NO": "04",
        "LLG_NO": "13",
        "WARD_NO": "07",
        "WARD_NAME": "NINGRA",
        "LATITUDE": -2.73916,
        "LONGITUDE": 141.435536,
        "REGHH": 12,
        "TOTPOP2000": 147,
        "MALE2000": 75,
        "FEMALE2000": 72,
        "POP2008": 179,
        "G_RATE": 1.0240000486373901,
        "Geocode_Num": 15041307002,
        "PROVINCE": 15
      }
    },
    {
      "type": "Feature",
      "id": 18918,
      "geometry": {
        "type": "Point",
        "coordinates": [
          141.39132800018717,
          -2.773199000333534
        ]
      },
      "properties": {
        "OBJECTID": 18918,
        "CU_NAME": "WARA BLACK",
        "CU_NO": "003",
        "GEOCODE": "15041307003",
        "PROV_KEY": "15",
        "DIST_NO": "04",
        "LLG_NO": "13",
        "WARD_NO": "07",
        "WARD_NAME": "NINGRA",
        "LATITUDE": -2.774569,
        "LONGITUDE": 141.390239,
        "REGHH": 49,
        "TOTPOP2000": 288,
        "MALE2000": 150,
        "FEMALE2000": 138,
        "POP2008": 348,
        "G_RATE": 1.0240000486373901,
        "Geocode_Num": 15041307003,
        "PROVINCE": 15
      }
    },
    {
      "type": "Feature",
      "id": 18919,
      "geometry": {
        "type": "Point",
        "coordinates": [
          141.36991500017723,
          -2.7599089999004036
        ]
      },
      "properties": {
        "OBJECTID": 18919,
        "CU_NAME": "WARA BRIS NO.1",
        "CU_NO": "004",
        "GEOCODE": "15041307004",
        "PROV_KEY": "15",
        "DIST_NO": "04",
        "LLG_NO": "13",
        "WARD_NO": "07",
        "WARD_NAME": "NINGRA",
        "LATITUDE": -2.761279,
        "LONGITUDE": 141.368825,
        "REGHH": 35,
        "TOTPOP2000": 320,
        "MALE2000": 148,
        "FEMALE2000": 172,
        "POP2008": 387,
        "G_RATE": 1.0240000486373901,
        "Geocode_Num": 15041307004,
        "PROVINCE": 15
      }
    },
    {
      "type": "Feature",
      "id": 18920,
      "geometry": {
        "type": "Point",
        "coordinates": [
          141.41446200042105,
          -2.7973350000102073
        ]
      },
      "properties": {
        "OBJECTID": 18920,
        "CU_NAME": "VFP PUAL BASE CAMP",
        "CU_NO": "401",
        "GEOCODE": "15041307401",
        "PROV_KEY": "15",
        "DIST_NO": "04",
        "LLG_NO": "13",
        "WARD_NO": "07",
        "WARD_NAME": "NINGRA",
        "LATITUDE": -2.795876,
        "LONGITUDE": 141.415715,
        "REGHH": 11,
        "TOTPOP2000": 52,
        "MALE2000": 40,
        "FEMALE2000": 12,
        "POP2008": 60,
        "G_RATE": 1.0240000486373901,
        "Geocode_Num": 15041307401,
        "PROVINCE": 15
      }
    }
  ]
}