{
  "type": "FeatureCollection",
  "features": [
    {
      "type": "Feature",
      "id": 18945,
      "geometry": {
        "type": "Point",
        "coordinates": [
          141.2204669998522,
          -2.918761999566584
        ]
      },
      "properties": {
        "OBJECTID": 18945,
        "CU_NAME": "ILUP",
        "CU_NO": "006",
        "GEOCODE": "15041318006",
        "PROV_KEY": "15",
        "DIST_NO": "04",
        "LLG_NO": "13",
        "WARD_NO": "18",
        "WARD_NAME": "ILUP",
        "LATITUDE": -2.920133,
        "LONGITUDE": 141.219374,
        "REGHH": 77,
        "TOTPOP2000": 395,
        "MALE2000": 195,
        "FEMALE2000": 200,
        "POP2008": 477,
        "G_RATE": 1.0240000486373901,
        "Geocode_Num": 15041318006,
        "PROVINCE": 15
      }
    },
    {
      "type": "Feature",
      "id": 18946,
      "geometry": {
        "type": "Point",
        "coordinates": [
          141.23183499978552,
          -2.9248170000045093
        ]
      },
      "properties": {
        "OBJECTID": 18946,
        "CU_NAME": "ISI 1",
        "CU_NO": "007",
        "GEOCODE": "15041318007",
        "PROV_KEY": "15",
        "DIST_NO": "04",
        "LLG_NO": "13",
        "WARD_NO": "18",
        "WARD_NAME": "ILUP",
        "LATITUDE": -2.926188,
        "LONGITUDE": 141.230744,
        "REGHH": 27,
        "TOTPOP2000": 131,
        "MALE2000": 73,
        "FEMALE2000": 58,
        "POP2008": 158,
        "G_RATE": 1.0240000486373901,
        "Geocode_Num": 15041318007,
        "PROVINCE": 15
      }
    },
    {
      "type": "Feature",
      "id": 18947,
      "geometry": {
        "type": "Point",
        "coordinates": [
          141.25650599985204,
          -2.986649999697704
        ]
      },
      "properties": {
        "OBJECTID": 18947,
        "CU_NAME": "ISI 2",
        "CU_NO": "008",
        "GEOCODE": "15041318008",
        "PROV_KEY": "15",
        "DIST_NO": "04",
        "LLG_NO": "13",
        "WARD_NO": "18",
        "WARD_NAME": "ILUP",
        "LATITUDE": -2.988022,
        "LONGITUDE": 141.255415,
        "REGHH": 54,
        "TOTPOP2000": 299,
        "MALE2000": 148,
        "FEMALE2000": 151,
        "POP2008": 361,
        "G_RATE": 1.0240000486373901,
        "Geocode_Num": 15041318008,
        "PROVINCE": 15
      }
    }
  ]
}