{
  "type": "FeatureCollection",
  "features": [
    {
      "type": "Feature",
      "id": 16959,
      "geometry": {
        "type": "Point",
        "coordinates": [
          144.87083699972777,
          -5.651138999764953
        ]
      },
      "properties": {
        "OBJECTID": 16959,
        "CU_NAME": "YEWAREMUL",
        "CU_NO": "004",
        "GEOCODE": "09040710004",
        "PROV_KEY": "22",
        "DIST_NO": "2",
        "LLG_NO": "07",
        "WARD_NO": "10",
        "WARD_NAME": "YEWAREMUL",
        "LATITUDE": -5.652075,
        "LONGITUDE": 144.871179,
        "REGHH": 144,
        "TOTPOP2000": 628,
        "MALE2000": 330,
        "FEMALE2000": 298,
        "POP2008": 765,
        "G_RATE": 1.024999976158142,
        "Geocode_Num": 9040710004,
        "PROVINCE": 22
      }
    }
  ]
}