{
  "type": "FeatureCollection",
  "features": [
    {
      "type": "Feature",
      "id": 16964,
      "geometry": {
        "type": "Point",
        "coordinates": [
          144.83090099988135,
          -5.644836999627785
        ]
      },
      "properties": {
        "OBJECTID": 16964,
        "CU_NAME": "OMUN",
        "CU_NO": "014",
        "GEOCODE": "09040713014",
        "PROV_KEY": "22",
        "DIST_NO": "2",
        "LLG_NO": "07",
        "WARD_NO": "13",
        "WARD_NAME": "OMUN",
        "LATITUDE": -5.645772,
        "LONGITUDE": 144.831242,
        "REGHH": 50,
        "TOTPOP2000": 292,
        "MALE2000": 160,
        "FEMALE2000": 132,
        "POP2008": 355,
        "G_RATE": 1.024999976158142,
        "Geocode_Num": 9040713014,
        "PROVINCE": 22
      }
    }
  ]
}