{
  "type": "FeatureCollection",
  "features": [
    {
      "type": "Feature",
      "id": 10849,
      "geometry": {
        "type": "Point",
        "coordinates": [
          147.82795199998486,
          -6.6695230001862456
        ]
      },
      "properties": {
        "OBJECTID": 10849,
        "CU_NAME": "KWALANSAM",
        "CU_NO": "011",
        "GEOCODE": "12020806011",
        "PROV_KEY": "12",
        "DIST_NO": "02",
        "LLG_NO": "08",
        "WARD_NO": "06",
        "WARD_NAME": "KWALANSAM",
        "LATITUDE": -6.670945,
        "LONGITUDE": 147.826939,
        "REGHH": 93,
        "TOTPOP2000": 434,
        "MALE2000": 215,
        "FEMALE2000": 219,
        "POP2008": 541,
        "G_RATE": 1.027999997138977,
        "Geocode_Num": 12020806011,
        "PROVINCE": 12
      }
    },
    {
      "type": "Feature",
      "id": 10850,
      "geometry": {
        "type": "Point",
        "coordinates": [
          147.80273599996644,
          -6.674921000004076
        ]
      },
      "properties": {
        "OBJECTID": 10850,
        "CU_NAME": "GAWENGLABU",
        "CU_NO": "026",
        "GEOCODE": "12020806026",
        "PROV_KEY": "12",
        "DIST_NO": "02",
        "LLG_NO": "08",
        "WARD_NO": "06",
        "WARD_NAME": "KWALANSAM",
        "LATITUDE": -6.676343,
        "LONGITUDE": 147.801723,
        "REGHH": 53,
        "TOTPOP2000": 295,
        "MALE2000": 154,
        "FEMALE2000": 141,
        "POP2008": 367,
        "G_RATE": 1.027999997138977,
        "Geocode_Num": 12020806026,
        "PROVINCE": 12
      }
    }
  ]
}