{
  "type": "FeatureCollection",
  "features": [
    {
      "type": "Feature",
      "id": 10880,
      "geometry": {
        "type": "Point",
        "coordinates": [
          147.60466000005897,
          -6.539102999603699
        ]
      },
      "properties": {
        "OBJECTID": 10880,
        "CU_NAME": "BEDDING",
        "CU_NO": "004",
        "GEOCODE": "12020815004",
        "PROV_KEY": "12",
        "DIST_NO": "02",
        "LLG_NO": "08",
        "WARD_NO": "15",
        "WARD_NAME": "EMBEWANENG",
        "LATITUDE": -6.540523,
        "LONGITUDE": 147.603644,
        "REGHH": 52,
        "TOTPOP2000": 316,
        "MALE2000": 157,
        "FEMALE2000": 159,
        "POP2008": 394,
        "G_RATE": 1.027999997138977,
        "Geocode_Num": 12020815004,
        "PROVINCE": 12
      }
    },
    {
      "type": "Feature",
      "id": 10881,
      "geometry": {
        "type": "Point",
        "coordinates": [
          147.60230600032173,
          -6.504181999899345
        ]
      },
      "properties": {
        "OBJECTID": 10881,
        "CU_NAME": "GUNUZAKING",
        "CU_NO": "011",
        "GEOCODE": "12020815011",
        "PROV_KEY": "12",
        "DIST_NO": "02",
        "LLG_NO": "08",
        "WARD_NO": "15",
        "WARD_NAME": "EMBEWANENG",
        "LATITUDE": -6.508674,
        "LONGITUDE": 147.60353,
        "REGHH": 35,
        "TOTPOP2000": 188,
        "MALE2000": 85,
        "FEMALE2000": 103,
        "POP2008": 234,
        "G_RATE": 1.027999997138977,
        "Geocode_Num": 12020815011,
        "PROVINCE": 12
      }
    },
    {
      "type": "Feature",
      "id": 10882,
      "geometry": {
        "type": "Point",
        "coordinates": [
          147.54502199996534,
          -6.489426000209676
        ]
      },
      "properties": {
        "OBJECTID": 10882,
        "CU_NAME": "SOFIFI",
        "CU_NO": "012",
        "GEOCODE": "12020815012",
        "PROV_KEY": "12",
        "DIST_NO": "02",
        "LLG_NO": "08",
        "WARD_NO": "15",
        "WARD_NAME": "EMBEWANENG",
        "LATITUDE": -6.487026,
        "LONGITUDE": 147.542438,
        "REGHH": 52,
        "TOTPOP2000": 278,
        "MALE2000": 142,
        "FEMALE2000": 136,
        "POP2008": 346,
        "G_RATE": 1.027999997138977,
        "Geocode_Num": 12020815012,
        "PROVINCE": 12
      }
    },
    {
      "type": "Feature",
      "id": 10883,
      "geometry": {
        "type": "Point",
        "coordinates": [
          147.5907380001587,
          -6.490408999675537
        ]
      },
      "properties": {
        "OBJECTID": 10883,
        "CU_NAME": "EMBEWANENG",
        "CU_NO": "013",
        "GEOCODE": "12020815013",
        "PROV_KEY": "12",
        "DIST_NO": "02",
        "LLG_NO": "08",
        "WARD_NO": "15",
        "WARD_NAME": "EMBEWANENG",
        "LATITUDE": -6.491829,
        "LONGITUDE": 147.589722,
        "REGHH": 52,
        "TOTPOP2000": 285,
        "MALE2000": 131,
        "FEMALE2000": 154,
        "POP2008": 355,
        "G_RATE": 1.027999997138977,
        "Geocode_Num": 12020815013,
        "PROVINCE": 12
      }
    }
  ]
}