{
  "type": "FeatureCollection",
  "features": [
    {
      "type": "Feature",
      "id": 18450,
      "geometry": {
        "type": "Point",
        "coordinates": [
          141.95307000008052,
          -3.474122000130137
        ]
      },
      "properties": {
        "OBJECTID": 18450,
        "CU_NAME": "TALOU",
        "CU_NO": "004",
        "GEOCODE": "15010405004",
        "PROV_KEY": "15",
        "DIST_NO": "01",
        "LLG_NO": "04",
        "WARD_NO": "05",
        "WARD_NAME": "YEBIL",
        "LATITUDE": -3.4755,
        "LONGITUDE": 141.951987,
        "REGHH": 17,
        "TOTPOP2000": 87,
        "MALE2000": 50,
        "FEMALE2000": 37,
        "POP2008": 103,
        "G_RATE": 1.0240000486373901,
        "Geocode_Num": 15010405004,
        "PROVINCE": 15
      }
    },
    {
      "type": "Feature",
      "id": 18451,
      "geometry": {
        "type": "Point",
        "coordinates": [
          141.93221699981473,
          -3.4886629997975547
        ]
      },
      "properties": {
        "OBJECTID": 18451,
        "CU_NAME": "KALINGUM",
        "CU_NO": "007",
        "GEOCODE": "15010405007",
        "PROV_KEY": "15",
        "DIST_NO": "01",
        "LLG_NO": "04",
        "WARD_NO": "05",
        "WARD_NAME": "YEBIL",
        "LATITUDE": -3.483517,
        "LONGITUDE": 141.931126,
        "REGHH": 21,
        "TOTPOP2000": 107,
        "MALE2000": 57,
        "FEMALE2000": 50,
        "POP2008": 131,
        "G_RATE": 1.0240000486373901,
        "Geocode_Num": 15010405007,
        "PROVINCE": 15
      }
    },
    {
      "type": "Feature",
      "id": 18452,
      "geometry": {
        "type": "Point",
        "coordinates": [
          141.98198599985403,
          -3.462346000267644
        ]
      },
      "properties": {
        "OBJECTID": 18452,
        "CU_NAME": "URUTEI",
        "CU_NO": "016",
        "GEOCODE": "15010405016",
        "PROV_KEY": "15",
        "DIST_NO": "01",
        "LLG_NO": "04",
        "WARD_NO": "05",
        "WARD_NAME": "YEBIL",
        "LATITUDE": -3.463724,
        "LONGITUDE": 141.980903,
        "REGHH": 13,
        "TOTPOP2000": 59,
        "MALE2000": 29,
        "FEMALE2000": 30,
        "POP2008": 71,
        "G_RATE": 1.0240000486373901,
        "Geocode_Num": 15010405016,
        "PROVINCE": 15
      }
    },
    {
      "type": "Feature",
      "id": 18453,
      "geometry": {
        "type": "Point",
        "coordinates": [
          141.96601399984627,
          -3.4593620002560783
        ]
      },
      "properties": {
        "OBJECTID": 18453,
        "CU_NAME": "YEBIL",
        "CU_NO": "017",
        "GEOCODE": "15010405017",
        "PROV_KEY": "15",
        "DIST_NO": "01",
        "LLG_NO": "04",
        "WARD_NO": "05",
        "WARD_NAME": "YEBIL",
        "LATITUDE": -3.463028,
        "LONGITUDE": 141.958125,
        "REGHH": 85,
        "TOTPOP2000": 483,
        "MALE2000": 223,
        "FEMALE2000": 260,
        "POP2008": 584,
        "G_RATE": 1.0240000486373901,
        "Geocode_Num": 15010405017,
        "PROVINCE": 15
      }
    }
  ]
}