{
  "type": "FeatureCollection",
  "features": [
    {
      "type": "Feature",
      "id": 16716,
      "geometry": {
        "type": "Point",
        "coordinates": [
          144.31881400016607,
          -5.81775999972416
        ]
      },
      "properties": {
        "OBJECTID": 16716,
        "CU_NAME": "GANGA",
        "CU_NO": "003",
        "GEOCODE": "09030429003",
        "PROV_KEY": "09",
        "DIST_NO": "03",
        "LLG_NO": "04",
        "WARD_NO": "29",
        "WARD_NAME": "KAGAMUGA",
        "LATITUDE": -5.818697,
        "LONGITUDE": 144.319148,
        "REGHH": 76,
        "TOTPOP2000": 332,
        "MALE2000": 172,
        "FEMALE2000": 160,
        "POP2008": 404,
        "G_RATE": 1.024999976158142,
        "Geocode_Num": 9030429003,
        "PROVINCE": 9
      }
    },
    {
      "type": "Feature",
      "id": 16717,
      "geometry": {
        "type": "Point",
        "coordinates": [
          144.32041500025207,
          -5.821317000079432
        ]
      },
      "properties": {
        "OBJECTID": 16717,
        "CU_NAME": "JIKAORA",
        "CU_NO": "004",
        "GEOCODE": "09030429004",
        "PROV_KEY": "09",
        "DIST_NO": "03",
        "LLG_NO": "04",
        "WARD_NO": "29",
        "WARD_NAME": "KAGAMUGA",
        "LATITUDE": -5.822254,
        "LONGITUDE": 144.320749,
        "REGHH": 81,
        "TOTPOP2000": 331,
        "MALE2000": 167,
        "FEMALE2000": 164,
        "POP2008": 403,
        "G_RATE": 1.024999976158142,
        "Geocode_Num": 9030429004,
        "PROVINCE": 9
      }
    },
    {
      "type": "Feature",
      "id": 16718,
      "geometry": {
        "type": "Point",
        "coordinates": [
          144.30831900002192,
          -5.8176199995633056
        ]
      },
      "properties": {
        "OBJECTID": 16718,
        "CU_NAME": "BAGL",
        "CU_NO": "005",
        "GEOCODE": "09030429005",
        "PROV_KEY": "09",
        "DIST_NO": "03",
        "LLG_NO": "04",
        "WARD_NO": "29",
        "WARD_NAME": "KAGAMUGA",
        "LATITUDE": -5.818557,
        "LONGITUDE": 144.308653,
        "REGHH": 98,
        "TOTPOP2000": 452,
        "MALE2000": 246,
        "FEMALE2000": 206,
        "POP2008": 550,
        "G_RATE": 1.024999976158142,
        "Geocode_Num": 9030429005,
        "PROVINCE": 9
      }
    }
  ]
}