{
  "type": "FeatureCollection",
  "features": [
    {
      "type": "Feature",
      "id": 14095,
      "geometry": {
        "type": "Point",
        "coordinates": [
          144.80990900040013,
          -6.1875250003784
        ]
      },
      "properties": {
        "OBJECTID": 14095,
        "CU_NAME": "PAUME",
        "CU_NO": "010",
        "GEOCODE": "10020412010",
        "PROV_KEY": "10",
        "DIST_NO": "02",
        "LLG_NO": "04",
        "WARD_NO": "12",
        "WARD_NAME": "NEBIKU",
        "LATITUDE": -6.188936,
        "LONGITUDE": 144.808857,
        "REGHH": 50,
        "TOTPOP2000": 220,
        "MALE2000": 122,
        "FEMALE2000": 98,
        "POP2008": 252,
        "G_RATE": 1.0180000066757202,
        "Geocode_Num": 10020412010,
        "PROVINCE": 10
      }
    },
    {
      "type": "Feature",
      "id": 14096,
      "geometry": {
        "type": "Point",
        "coordinates": [
          144.79363900013982,
          -6.218528000167055
        ]
      },
      "properties": {
        "OBJECTID": 14096,
        "CU_NAME": "TAWANUGU",
        "CU_NO": "011",
        "GEOCODE": "10020412011",
        "PROV_KEY": "10",
        "DIST_NO": "02",
        "LLG_NO": "04",
        "WARD_NO": "12",
        "WARD_NAME": "NEBIKU",
        "LATITUDE": -6.219939,
        "LONGITUDE": 144.792585,
        "REGHH": 16,
        "TOTPOP2000": 70,
        "MALE2000": 35,
        "FEMALE2000": 35,
        "POP2008": 78,
        "G_RATE": 1.0180000066757202,
        "Geocode_Num": 10020412011,
        "PROVINCE": 10
      }
    },
    {
      "type": "Feature",
      "id": 14097,
      "geometry": {
        "type": "Point",
        "coordinates": [
          144.79669699996668,
          -6.235817999800815
        ]
      },
      "properties": {
        "OBJECTID": 14097,
        "CU_NAME": "DEGE",
        "CU_NO": "012",
        "GEOCODE": "10020412012",
        "PROV_KEY": "10",
        "DIST_NO": "02",
        "LLG_NO": "04",
        "WARD_NO": "12",
        "WARD_NAME": "NEBIKU",
        "LATITUDE": -6.230166,
        "LONGITUDE": 144.802763,
        "REGHH": 22,
        "TOTPOP2000": 103,
        "MALE2000": 57,
        "FEMALE2000": 46,
        "POP2008": 119,
        "G_RATE": 1.0180000066757202,
        "Geocode_Num": 10020412012,
        "PROVINCE": 10
      }
    },
    {
      "type": "Feature",
      "id": 14098,
      "geometry": {
        "type": "Point",
        "coordinates": [
          144.76780400035443,
          -6.242288122798584
        ]
      },
      "properties": {
        "OBJECTID": 14098,
        "CU_NAME": "OLEGAIN",
        "CU_NO": "013",
        "GEOCODE": "10020412013",
        "PROV_KEY": "10",
        "DIST_NO": "02",
        "LLG_NO": "04",
        "WARD_NO": "12",
        "WARD_NAME": "NEBIKU",
        "LATITUDE": -6.239181,
        "LONGITUDE": 144.766751,
        "REGHH": 82,
        "TOTPOP2000": 355,
        "MALE2000": 170,
        "FEMALE2000": 185,
        "POP2008": 409,
        "G_RATE": 1.0180000066757202,
        "Geocode_Num": 10020412013,
        "PROVINCE": 10
      }
    }
  ]
}