{
  "type": "FeatureCollection",
  "features": [
    {
      "type": "Feature",
      "id": 6298,
      "geometry": {
        "type": "Point",
        "coordinates": [
          144.04429500041397,
          -4.091420999879176
        ]
      },
      "properties": {
        "OBJECTID": 6298,
        "CU_NAME": "MAGENDO 1",
        "CU_NO": "010",
        "GEOCODE": "14020512010",
        "PROV_KEY": "14",
        "DIST_NO": "02",
        "LLG_NO": "05",
        "WARD_NO": "12",
        "WARD_NAME": "MAGENDO 1",
        "LATITUDE": -4.093005,
        "LONGITUDE": 144.043067,
        "REGHH": 33,
        "TOTPOP2000": 241,
        "MALE2000": 115,
        "FEMALE2000": 126,
        "POP2008": 287,
        "G_RATE": 1.0219999551773071,
        "Geocode_Num": 14020512010,
        "PROVINCE": 14
      }
    },
    {
      "type": "Feature",
      "id": 6299,
      "geometry": {
        "type": "Point",
        "coordinates": [
          144.07413200039161,
          -4.096077999699901
        ]
      },
      "properties": {
        "OBJECTID": 6299,
        "CU_NAME": "MAGENDO 2",
        "CU_NO": "011",
        "GEOCODE": "14020512011",
        "PROV_KEY": "14",
        "DIST_NO": "02",
        "LLG_NO": "05",
        "WARD_NO": "12",
        "WARD_NAME": "MAGENDO 1",
        "LATITUDE": -4.097662,
        "LONGITUDE": 144.072905,
        "REGHH": 34,
        "TOTPOP2000": 204,
        "MALE2000": 96,
        "FEMALE2000": 108,
        "POP2008": 243,
        "G_RATE": 1.0219999551773071,
        "Geocode_Num": 14020512011,
        "PROVINCE": 14
      }
    }
  ]
}