{
  "type": "FeatureCollection",
  "features": [
    {
      "type": "Feature",
      "id": 6315,
      "geometry": {
        "type": "Point",
        "coordinates": [
          143.35653699978275,
          -4.206706000381587
        ]
      },
      "properties": {
        "OBJECTID": 6315,
        "CU_NAME": "KARARAU",
        "CU_NO": "008",
        "GEOCODE": "14020527008",
        "PROV_KEY": "14",
        "DIST_NO": "02",
        "LLG_NO": "05",
        "WARD_NO": "27",
        "WARD_NAME": "KARARAU",
        "LATITUDE": -4.208315,
        "LONGITUDE": 143.347168,
        "REGHH": 70,
        "TOTPOP2000": 380,
        "MALE2000": 182,
        "FEMALE2000": 198,
        "POP2008": 453,
        "G_RATE": 1.0219999551773071,
        "Geocode_Num": 14020527008,
        "PROVINCE": 14
      }
    }
  ]
}