{
  "type": "FeatureCollection",
  "features": [
    {
      "type": "Feature",
      "id": 6335,
      "geometry": {
        "type": "Point",
        "coordinates": [
          144.05532600009485,
          -4.062135000130127
        ]
      },
      "properties": {
        "OBJECTID": 6335,
        "CU_NAME": "ANGORAM",
        "CU_NO": "001",
        "GEOCODE": "14020581001",
        "PROV_KEY": "14",
        "DIST_NO": "02",
        "LLG_NO": "05",
        "WARD_NO": "81",
        "WARD_NAME": "ANGORUM URBAN",
        "LATITUDE": -4.057146,
        "LONGITUDE": 144.052058,
        "REGHH": 88,
        "TOTPOP2000": 640,
        "MALE2000": 329,
        "FEMALE2000": 311,
        "POP2008": 761,
        "G_RATE": 1.0219999551773071,
        "Geocode_Num": 14020581001,
        "PROVINCE": 14
      }
    },
    {
      "type": "Feature",
      "id": 6336,
      "geometry": {
        "type": "Point",
        "coordinates": [
          144.04824900019128,
          -4.057098999918878
        ]
      },
      "properties": {
        "OBJECTID": 6336,
        "CU_NAME": "ANGORAM",
        "CU_NO": "002",
        "GEOCODE": "14020581002",
        "PROV_KEY": "14",
        "DIST_NO": "02",
        "LLG_NO": "05",
        "WARD_NO": "81",
        "WARD_NAME": "ANGORUM URBAN",
        "LATITUDE": -4.057146,
        "LONGITUDE": 144.052058,
        "REGHH": 96,
        "TOTPOP2000": 797,
        "MALE2000": 383,
        "FEMALE2000": 414,
        "POP2008": 949,
        "G_RATE": 1.0219999551773071,
        "Geocode_Num": 14020581002,
        "PROVINCE": 14
      }
    },
    {
      "type": "Feature",
      "id": 6337,
      "geometry": {
        "type": "Point",
        "coordinates": [
          144.05024599965327,
          -4.051524000032543
        ]
      },
      "properties": {
        "OBJECTID": 6337,
        "CU_NAME": "ANGORAM",
        "CU_NO": "003",
        "GEOCODE": "14020581003",
        "PROV_KEY": "14",
        "DIST_NO": "02",
        "LLG_NO": "05",
        "WARD_NO": "81",
        "WARD_NAME": "ANGORUM URBAN",
        "LATITUDE": -4.057146,
        "LONGITUDE": 144.052058,
        "REGHH": 35,
        "TOTPOP2000": 238,
        "MALE2000": 130,
        "FEMALE2000": 108,
        "POP2008": 283,
        "G_RATE": 1.0219999551773071,
        "Geocode_Num": 14020581003,
        "PROVINCE": 14
      }
    },
    {
      "type": "Feature",
      "id": 6338,
      "geometry": {
        "type": "Point",
        "coordinates": [
          144.0512829998106,
          -4.059619000116697
        ]
      },
      "properties": {
        "OBJECTID": 6338,
        "CU_NAME": "ANGORAM",
        "CU_NO": "004",
        "GEOCODE": "14020581004",
        "PROV_KEY": "14",
        "DIST_NO": "02",
        "LLG_NO": "05",
        "WARD_NO": "81",
        "WARD_NAME": "ANGORUM URBAN",
        "LATITUDE": -4.057146,
        "LONGITUDE": 144.052058,
        "REGHH": 58,
        "TOTPOP2000": 396,
        "MALE2000": 216,
        "FEMALE2000": 180,
        "POP2008": 472,
        "G_RATE": 1.0219999551773071,
        "Geocode_Num": 14020581004,
        "PROVINCE": 14
      }
    }
  ]
}