{
  "type": "FeatureCollection",
  "features": [
    {
      "type": "Feature",
      "id": 12022,
      "geometry": {
        "type": "Point",
        "coordinates": [
          146.07124700004908,
          -7.289861999831373
        ]
      },
      "properties": {
        "OBJECTID": 12022,
        "CU_NAME": "QUIWI",
        "CU_NO": "033",
        "GEOCODE": "12072204033",
        "PROV_KEY": "12",
        "DIST_NO": "07",
        "LLG_NO": "22",
        "WARD_NO": "04",
        "WARD_NAME": "WOMEI",
        "LATITUDE": -7.291287,
        "LONGITUDE": 146.070209,
        "REGHH": 82,
        "TOTPOP2000": 408,
        "MALE2000": 214,
        "FEMALE2000": 194,
        "POP2008": 508,
        "G_RATE": 1.027999997138977,
        "Geocode_Num": 12072204033,
        "PROVINCE": 12
      }
    },
    {
      "type": "Feature",
      "id": 12023,
      "geometry": {
        "type": "Point",
        "coordinates": [
          146.07402400040735,
          -7.281278999725998
        ]
      },
      "properties": {
        "OBJECTID": 12023,
        "CU_NAME": "WOMEI",
        "CU_NO": "034",
        "GEOCODE": "12072204034",
        "PROV_KEY": "12",
        "DIST_NO": "07",
        "LLG_NO": "22",
        "WARD_NO": "04",
        "WARD_NAME": "WOMEI",
        "LATITUDE": -7.282704,
        "LONGITUDE": 146.072986,
        "REGHH": 84,
        "TOTPOP2000": 433,
        "MALE2000": 215,
        "FEMALE2000": 218,
        "POP2008": 540,
        "G_RATE": 1.027999997138977,
        "Geocode_Num": 12072204034,
        "PROVINCE": 12
      }
    },
    {
      "type": "Feature",
      "id": 12024,
      "geometry": {
        "type": "Point",
        "coordinates": [
          146.06900400003462,
          -7.300899999835053
        ]
      },
      "properties": {
        "OBJECTID": 12024,
        "CU_NAME": "YAMAPA",
        "CU_NO": "037",
        "GEOCODE": "12072204037",
        "PROV_KEY": "12",
        "DIST_NO": "07",
        "LLG_NO": "22",
        "WARD_NO": "04",
        "WARD_NAME": "WOMEI",
        "LATITUDE": -7.302325,
        "LONGITUDE": 146.067966,
        "REGHH": 39,
        "TOTPOP2000": 199,
        "MALE2000": 99,
        "FEMALE2000": 100,
        "POP2008": 249,
        "G_RATE": 1.027999997138977,
        "Geocode_Num": 12072204037,
        "PROVINCE": 12
      }
    }
  ]
}