{
  "type": "FeatureCollection",
  "features": [
    {
      "type": "Feature",
      "id": 8722,
      "geometry": {
        "type": "Point",
        "coordinates": [
          146.06197399960047,
          -5.9353900004481375
        ]
      },
      "properties": {
        "OBJECTID": 8722,
        "CU_NAME": "BUTEMU",
        "CU_NO": "005",
        "GEOCODE": "13041116005",
        "PROV_KEY": "13",
        "DIST_NO": "04",
        "LLG_NO": "11",
        "WARD_NO": "16",
        "WARD_NAME": "WARD 16",
        "LATITUDE": -5.94604,
        "LONGITUDE": 146.068184,
        "REGHH": 74,
        "TOTPOP2000": 469,
        "MALE2000": 236,
        "FEMALE2000": 233,
        "POP2008": 580,
        "G_RATE": 1.0269999504089355,
        "Geocode_Num": 13041116005,
        "PROVINCE": 13
      }
    },
    {
      "type": "Feature",
      "id": 8723,
      "geometry": {
        "type": "Point",
        "coordinates": [
          146.07679400044287,
          -5.919161000279871
        ]
      },
      "properties": {
        "OBJECTID": 8723,
        "CU_NAME": "WANURU/NASKO",
        "CU_NO": "006",
        "GEOCODE": "13041116006",
        "PROV_KEY": "13",
        "DIST_NO": "04",
        "LLG_NO": "11",
        "WARD_NO": "16",
        "WARD_NAME": "WARD 16",
        "LATITUDE": -5.929233,
        "LONGITUDE": 146.071835,
        "REGHH": 26,
        "TOTPOP2000": 188,
        "MALE2000": 110,
        "FEMALE2000": 78,
        "POP2008": 232,
        "G_RATE": 1.0269999504089355,
        "Geocode_Num": 13041116006,
        "PROVINCE": 13
      }
    }
  ]
}