{
  "type": "FeatureCollection",
  "features": [
    {
      "type": "Feature",
      "id": 12094,
      "geometry": {
        "type": "Point",
        "coordinates": [
          146.90141800034053,
          -6.343774999616471
        ]
      },
      "properties": {
        "OBJECTID": 12094,
        "CU_NAME": "KIAKUM",
        "CU_NO": "015",
        "GEOCODE": "12082401015",
        "PROV_KEY": "12",
        "DIST_NO": "08",
        "LLG_NO": "24",
        "WARD_NO": "01",
        "WARD_NAME": "SATUKIMO",
        "LATITUDE": -6.345192,
        "LONGITUDE": 146.900393,
        "REGHH": 42,
        "TOTPOP2000": 180,
        "MALE2000": 89,
        "FEMALE2000": 91,
        "POP2008": 224,
        "G_RATE": 1.027999997138977,
        "Geocode_Num": 12082401015,
        "PROVINCE": 12
      }
    },
    {
      "type": "Feature",
      "id": 12095,
      "geometry": {
        "type": "Point",
        "coordinates": [
          146.92692600033467,
          -6.322915999973361
        ]
      },
      "properties": {
        "OBJECTID": 12095,
        "CU_NAME": "MOGOM",
        "CU_NO": "021",
        "GEOCODE": "12082401021",
        "PROV_KEY": "12",
        "DIST_NO": "08",
        "LLG_NO": "24",
        "WARD_NO": "01",
        "WARD_NAME": "SATUKIMO",
        "LATITUDE": -6.324333,
        "LONGITUDE": 146.925902,
        "REGHH": 21,
        "TOTPOP2000": 117,
        "MALE2000": 48,
        "FEMALE2000": 69,
        "POP2008": 146,
        "G_RATE": 1.027999997138977,
        "Geocode_Num": 12082401021,
        "PROVINCE": 12
      }
    },
    {
      "type": "Feature",
      "id": 12096,
      "geometry": {
        "type": "Point",
        "coordinates": [
          146.9263319999219,
          -6.33883700032726
        ]
      },
      "properties": {
        "OBJECTID": 12096,
        "CU_NAME": "SAKALANG",
        "CU_NO": "024",
        "GEOCODE": "12082401024",
        "PROV_KEY": "12",
        "DIST_NO": "08",
        "LLG_NO": "24",
        "WARD_NO": "01",
        "WARD_NAME": "SATUKIMO",
        "LATITUDE": -6.340254,
        "LONGITUDE": 146.925307,
        "REGHH": 69,
        "TOTPOP2000": 395,
        "MALE2000": 189,
        "FEMALE2000": 206,
        "POP2008": 492,
        "G_RATE": 1.027999997138977,
        "Geocode_Num": 12082401024,
        "PROVINCE": 12
      }
    },
    {
      "type": "Feature",
      "id": 12097,
      "geometry": {
        "type": "Point",
        "coordinates": [
          146.92204199993841,
          -6.353811000177473
        ]
      },
      "properties": {
        "OBJECTID": 12097,
        "CU_NAME": "TUWEP",
        "CU_NO": "029",
        "GEOCODE": "12082401029",
        "PROV_KEY": "12",
        "DIST_NO": "08",
        "LLG_NO": "24",
        "WARD_NO": "01",
        "WARD_NAME": "SATUKIMO",
        "LATITUDE": -6.354169,
        "LONGITUDE": 146.921546,
        "REGHH": 29,
        "TOTPOP2000": 142,
        "MALE2000": 68,
        "FEMALE2000": 74,
        "POP2008": 177,
        "G_RATE": 1.027999997138977,
        "Geocode_Num": 12082401029,
        "PROVINCE": 12
      }
    }
  ]
}