{
  "type": "FeatureCollection",
  "features": [
    {
      "type": "Feature",
      "id": 12122,
      "geometry": {
        "type": "Point",
        "coordinates": [
          146.9997430002394,
          -6.5231929997571
        ]
      },
      "properties": {
        "OBJECTID": 12122,
        "CU_NAME": "GAWAM",
        "CU_NO": "009",
        "GEOCODE": "12082411009",
        "PROV_KEY": "12",
        "DIST_NO": "08",
        "LLG_NO": "24",
        "WARD_NO": "11",
        "WARD_NAME": "GAWAM",
        "LATITUDE": -6.524612,
        "LONGITUDE": 146.998719,
        "REGHH": 28,
        "TOTPOP2000": 150,
        "MALE2000": 71,
        "FEMALE2000": 79,
        "POP2008": 187,
        "G_RATE": 1.027999997138977,
        "Geocode_Num": 12082411009,
        "PROVINCE": 12
      }
    },
    {
      "type": "Feature",
      "id": 12123,
      "geometry": {
        "type": "Point",
        "coordinates": [
          146.99323899978003,
          -6.495983999561872
        ]
      },
      "properties": {
        "OBJECTID": 12123,
        "CU_NAME": "KOPSANEK",
        "CU_NO": "017",
        "GEOCODE": "12082411017",
        "PROV_KEY": "12",
        "DIST_NO": "08",
        "LLG_NO": "24",
        "WARD_NO": "11",
        "WARD_NAME": "GAWAM",
        "LATITUDE": -6.497403,
        "LONGITUDE": 146.992215,
        "REGHH": 31,
        "TOTPOP2000": 146,
        "MALE2000": 81,
        "FEMALE2000": 65,
        "POP2008": 182,
        "G_RATE": 1.027999997138977,
        "Geocode_Num": 12082411017,
        "PROVINCE": 12
      }
    }
  ]
}