{
  "type": "FeatureCollection",
  "features": [
    {
      "type": "Feature",
      "id": 1239,
      "geometry": {
        "type": "Point",
        "coordinates": [
          147.31985499990833,
          -9.54793799993871
        ]
      },
      "properties": {
        "OBJECTID": 1239,
        "CU_NAME": "TUBUSEREIA",
        "CU_NO": "008",
        "GEOCODE": "03030709008",
        "PROV_KEY": "03",
        "DIST_NO": "03",
        "LLG_NO": "07",
        "WARD_NO": "09",
        "WARD_NAME": "TUBUSEREIA",
        "LATITUDE": -9.549389,
        "LONGITUDE": 147.318828,
        "REGHH": 402,
        "TOTPOP2000": 3673,
        "MALE2000": 1928,
        "FEMALE2000": 1745,
        "POP2008": 4404,
        "G_RATE": 1.0230000019073486,
        "Geocode_Num": 3030709008,
        "PROVINCE": 3
      }
    }
  ]
}