{
  "type": "FeatureCollection",
  "features": [
    {
      "type": "Feature",
      "id": 1286,
      "geometry": {
        "type": "Point",
        "coordinates": [
          147.17120300031831,
          -9.070456999790679
        ]
      },
      "properties": {
        "OBJECTID": 1286,
        "CU_NAME": "BADILOHO",
        "CU_NO": "002",
        "GEOCODE": "03030717002",
        "PROV_KEY": "03",
        "DIST_NO": "03",
        "LLG_NO": "07",
        "WARD_NO": "17",
        "WARD_NAME": "KEREA",
        "LATITUDE": -9.071903,
        "LONGITUDE": 147.170175,
        "REGHH": 31,
        "TOTPOP2000": 177,
        "MALE2000": 102,
        "FEMALE2000": 75,
        "POP2008": 212,
        "G_RATE": 1.0230000019073486,
        "Geocode_Num": 3030717002,
        "PROVINCE": 3
      }
    },
    {
      "type": "Feature",
      "id": 1287,
      "geometry": {
        "type": "Point",
        "coordinates": [
          147.15199200023073,
          -9.094342999629703
        ]
      },
      "properties": {
        "OBJECTID": 1287,
        "CU_NAME": "FODU",
        "CU_NO": "008",
        "GEOCODE": "03030717008",
        "PROV_KEY": "03",
        "DIST_NO": "03",
        "LLG_NO": "07",
        "WARD_NO": "17",
        "WARD_NAME": "KEREA",
        "LATITUDE": -9.095789,
        "LONGITUDE": 147.150964,
        "REGHH": 11,
        "TOTPOP2000": 72,
        "MALE2000": 41,
        "FEMALE2000": 31,
        "POP2008": 88,
        "G_RATE": 1.0230000019073486,
        "Geocode_Num": 3030717008,
        "PROVINCE": 3
      }
    },
    {
      "type": "Feature",
      "id": 1288,
      "geometry": {
        "type": "Point",
        "coordinates": [
          147.17085999978917,
          -9.08990600006183
        ]
      },
      "properties": {
        "OBJECTID": 1288,
        "CU_NAME": "KEREA",
        "CU_NO": "013",
        "GEOCODE": "03030717013",
        "PROV_KEY": "03",
        "DIST_NO": "03",
        "LLG_NO": "07",
        "WARD_NO": "17",
        "WARD_NAME": "KEREA",
        "LATITUDE": -9.091352,
        "LONGITUDE": 147.169832,
        "REGHH": 41,
        "TOTPOP2000": 286,
        "MALE2000": 156,
        "FEMALE2000": 130,
        "POP2008": 344,
        "G_RATE": 1.0230000019073486,
        "Geocode_Num": 3030717013,
        "PROVINCE": 3
      }
    },
    {
      "type": "Feature",
      "id": 1289,
      "geometry": {
        "type": "Point",
        "coordinates": [
          147.1794429998946,
          -9.054343000429071
        ]
      },
      "properties": {
        "OBJECTID": 1289,
        "CU_NAME": "BETO",
        "CU_NO": "017",
        "GEOCODE": "03030717017",
        "PROV_KEY": "03",
        "DIST_NO": "03",
        "LLG_NO": "07",
        "WARD_NO": "17",
        "WARD_NAME": "KEREA",
        "LATITUDE": -9.055789,
        "LONGITUDE": 147.178415,
        "REGHH": 14,
        "TOTPOP2000": 100,
        "MALE2000": 60,
        "FEMALE2000": 40,
        "POP2008": 119,
        "G_RATE": 1.0230000019073486,
        "Geocode_Num": 3030717017,
        "PROVINCE": 3
      }
    }
  ]
}