{
  "type": "FeatureCollection",
  "features": [
    {
      "type": "Feature",
      "id": 11564,
      "geometry": {
        "type": "Point",
        "coordinates": [
          146.16297599974268,
          -6.422726000004843
        ]
      },
      "properties": {
        "OBJECTID": 11564,
        "CU_NAME": "MIRIR",
        "CU_NO": "009",
        "GEOCODE": "12061711009",
        "PROV_KEY": "12",
        "DIST_NO": "06",
        "LLG_NO": "17",
        "WARD_NO": "11",
        "WARD_NAME": "WAMPUL",
        "LATITUDE": -6.422483,
        "LONGITUDE": 146.156993,
        "REGHH": 16,
        "TOTPOP2000": 85,
        "MALE2000": 48,
        "FEMALE2000": 37,
        "POP2008": 106,
        "G_RATE": 1.027999997138977,
        "Geocode_Num": 12061711009,
        "PROVINCE": 12
      }
    },
    {
      "type": "Feature",
      "id": 11565,
      "geometry": {
        "type": "Point",
        "coordinates": [
          146.15618500043752,
          -6.375168000302949
        ]
      },
      "properties": {
        "OBJECTID": 11565,
        "CU_NAME": "WAMPUL",
        "CU_NO": "015",
        "GEOCODE": "12061711015",
        "PROV_KEY": "12",
        "DIST_NO": "06",
        "LLG_NO": "17",
        "WARD_NO": "11",
        "WARD_NAME": "WAMPUL",
        "LATITUDE": -6.376584,
        "LONGITUDE": 146.15515,
        "REGHH": 38,
        "TOTPOP2000": 234,
        "MALE2000": 126,
        "FEMALE2000": 108,
        "POP2008": 293,
        "G_RATE": 1.027999997138977,
        "Geocode_Num": 12061711015,
        "PROVINCE": 12
      }
    },
    {
      "type": "Feature",
      "id": 11566,
      "geometry": {
        "type": "Point",
        "coordinates": [
          146.11745400040184,
          -6.392483000190282
        ]
      },
      "properties": {
        "OBJECTID": 11566,
        "CU_NAME": "OMISUAN",
        "CU_NO": "018",
        "GEOCODE": "12061711018",
        "PROV_KEY": "12",
        "DIST_NO": "06",
        "LLG_NO": "17",
        "WARD_NO": "11",
        "WARD_NAME": "WAMPUL",
        "LATITUDE": -6.393899,
        "LONGITUDE": 146.116419,
        "REGHH": 39,
        "TOTPOP2000": 208,
        "MALE2000": 115,
        "FEMALE2000": 93,
        "POP2008": 259,
        "G_RATE": 1.027999997138977,
        "Geocode_Num": 12061711018,
        "PROVINCE": 12
      }
    }
  ]
}