{
  "type": "FeatureCollection",
  "features": [
    {
      "type": "Feature",
      "id": 9526,
      "geometry": {
        "type": "Point",
        "coordinates": [
          147.34194299956982,
          -2.401209999641708
        ]
      },
      "properties": {
        "OBJECTID": 9526,
        "CU_NAME": "BAON",
        "CU_NO": "008",
        "GEOCODE": "16011106008",
        "PROV_KEY": "16",
        "DIST_NO": "01",
        "LLG_NO": "11",
        "WARD_NO": "06",
        "WARD_NAME": "BAON",
        "LATITUDE": -2.40258,
        "LONGITUDE": 147.34093,
        "REGHH": 35,
        "TOTPOP2000": 181,
        "MALE2000": 89,
        "FEMALE2000": 92,
        "POP2008": 222,
        "G_RATE": 1.0260000228881836,
        "Geocode_Num": 16011106008,
        "PROVINCE": 16
      }
    }
  ]
}