{
  "type": "FeatureCollection",
  "features": [
    {
      "type": "Feature",
      "id": 9527,
      "geometry": {
        "type": "Point",
        "coordinates": [
          147.33060199998238,
          -2.3918040002543535
        ]
      },
      "properties": {
        "OBJECTID": 9527,
        "CU_NAME": "SOLANG",
        "CU_NO": "012",
        "GEOCODE": "16011107012",
        "PROV_KEY": "16",
        "DIST_NO": "01",
        "LLG_NO": "11",
        "WARD_NO": "07",
        "WARD_NAME": "SOLANG",
        "LATITUDE": -2.393174,
        "LONGITUDE": 147.329588,
        "REGHH": 42,
        "TOTPOP2000": 226,
        "MALE2000": 118,
        "FEMALE2000": 108,
        "POP2008": 278,
        "G_RATE": 1.0260000228881836,
        "Geocode_Num": 16011107012,
        "PROVINCE": 16
      }
    }
  ]
}