{
  "type": "FeatureCollection",
  "features": [
    {
      "type": "Feature",
      "id": 9366,
      "geometry": {
        "type": "Point",
        "coordinates": [
          144.35637500020619,
          -1.243969999915521
        ]
      },
      "properties": {
        "OBJECTID": 9366,
        "CU_NAME": "AMIK",
        "CU_NO": "001",
        "GEOCODE": "16010206001",
        "PROV_KEY": "16",
        "DIST_NO": "01",
        "LLG_NO": "02",
        "WARD_NO": "06",
        "WARD_NAME": "AMIK",
        "LATITUDE": -1.24164,
        "LONGITUDE": 144.354,
        "REGHH": 30,
        "TOTPOP2000": 181,
        "MALE2000": 94,
        "FEMALE2000": 87,
        "POP2008": 222,
        "G_RATE": 1.0260000228881836,
        "Geocode_Num": 16010206001,
        "PROVINCE": 16
      }
    }
  ]
}