{
  "type": "FeatureCollection",
  "features": [
    {
      "type": "Feature",
      "id": 9713,
      "geometry": {
        "type": "Point",
        "coordinates": [
          150.15465199998982,
          -10.470356999575813
        ]
      },
      "properties": {
        "OBJECTID": 9713,
        "CU_NAME": "SIASIADA",
        "CU_NO": "004",
        "GEOCODE": "05010506004",
        "PROV_KEY": "05",
        "DIST_NO": "1",
        "LLG_NO": "05",
        "WARD_NO": "06",
        "WARD_NAME": "SIASIADA",
        "LATITUDE": -10.4686,
        "LONGITUDE": 150.153691,
        "REGHH": 77,
        "TOTPOP2000": 397,
        "MALE2000": 213,
        "FEMALE2000": 184,
        "POP2008": 483,
        "G_RATE": 1.024999976158142,
        "Geocode_Num": 5010506004,
        "PROVINCE": 5
      }
    },
    {
      "type": "Feature",
      "id": 9714,
      "geometry": {
        "type": "Point",
        "coordinates": [
          150.19123399984926,
          -10.429725000008716
        ]
      },
      "properties": {
        "OBJECTID": 9714,
        "CU_NAME": "SAGARAI ESTATE (1)",
        "CU_NO": "401",
        "GEOCODE": "05010506401",
        "PROV_KEY": "05",
        "DIST_NO": "1",
        "LLG_NO": "05",
        "WARD_NO": "06",
        "WARD_NAME": "SIASIADA",
        "LATITUDE": -10.431194,
        "LONGITUDE": 150.190245,
        "REGHH": 111,
        "TOTPOP2000": 739,
        "MALE2000": 477,
        "FEMALE2000": 262,
        "POP2008": 899,
        "G_RATE": 1.024999976158142,
        "Geocode_Num": 5010506401,
        "PROVINCE": 5
      }
    },
    {
      "type": "Feature",
      "id": 9715,
      "geometry": {
        "type": "Point",
        "coordinates": [
          150.14917800026456,
          -10.439073000318672
        ]
      },
      "properties": {
        "OBJECTID": 9715,
        "CU_NAME": "TAMONAU ESTATE (2)",
        "CU_NO": "402",
        "GEOCODE": "05010506402",
        "PROV_KEY": "05",
        "DIST_NO": "1",
        "LLG_NO": "05",
        "WARD_NO": "06",
        "WARD_NAME": "SIASIADA",
        "LATITUDE": -10.440542,
        "LONGITUDE": 150.148188,
        "REGHH": 62,
        "TOTPOP2000": 292,
        "MALE2000": 180,
        "FEMALE2000": 112,
        "POP2008": 355,
        "G_RATE": 1.024999976158142,
        "Geocode_Num": 5010506402,
        "PROVINCE": 5
      }
    },
    {
      "type": "Feature",
      "id": 9716,
      "geometry": {
        "type": "Point",
        "coordinates": [
          150.16099300012695,
          -10.465671000216446
        ]
      },
      "properties": {
        "OBJECTID": 9716,
        "CU_NAME": "SIASIADA P/SCH",
        "CU_NO": "404",
        "GEOCODE": "05010506404",
        "PROV_KEY": "05",
        "DIST_NO": "1",
        "LLG_NO": "05",
        "WARD_NO": "06",
        "WARD_NAME": "SIASIADA",
        "LATITUDE": -10.470544,
        "LONGITUDE": 150.155417,
        "REGHH": 10,
        "TOTPOP2000": 60,
        "MALE2000": 32,
        "FEMALE2000": 28,
        "POP2008": 75,
        "G_RATE": 1.024999976158142,
        "Geocode_Num": 5010506404,
        "PROVINCE": 5
      }
    },
    {
      "type": "Feature",
      "id": 9717,
      "geometry": {
        "type": "Point",
        "coordinates": [
          150.19123399984926,
          -10.429725000008716
        ]
      },
      "properties": {
        "OBJECTID": 9717,
        "CU_NAME": "SAGARAI ESTATE (3)",
        "CU_NO": "501",
        "GEOCODE": "05010506501",
        "PROV_KEY": "05",
        "DIST_NO": "1",
        "LLG_NO": "05",
        "WARD_NO": "06",
        "WARD_NAME": "SIASIADA",
        "LATITUDE": -10.431194,
        "LONGITUDE": 150.190245,
        "REGHH": 81,
        "TOTPOP2000": 340,
        "MALE2000": 213,
        "FEMALE2000": 127,
        "POP2008": 414,
        "G_RATE": 1.024999976158142,
        "Geocode_Num": 5010506501,
        "PROVINCE": 5
      }
    }
  ]
}