{
  "type": "FeatureCollection",
  "features": [
    {
      "type": "Feature",
      "id": 9748,
      "geometry": {
        "type": "Point",
        "coordinates": [
          150.4108449999968,
          -10.410721999620534
        ]
      },
      "properties": {
        "OBJECTID": 9748,
        "CU_NAME": "WAGAWAGA",
        "CU_NO": "007",
        "GEOCODE": "05010519007",
        "PROV_KEY": "05",
        "DIST_NO": "1",
        "LLG_NO": "05",
        "WARD_NO": "19",
        "WARD_NAME": "WAGAWAGA",
        "LATITUDE": -10.409733,
        "LONGITUDE": 150.410223,
        "REGHH": 92,
        "TOTPOP2000": 605,
        "MALE2000": 331,
        "FEMALE2000": 274,
        "POP2008": 738,
        "G_RATE": 1.024999976158142,
        "Geocode_Num": 5010519007,
        "PROVINCE": 5
      }
    }
  ]
}