{
  "type": "FeatureCollection",
  "features": [
    {
      "type": "Feature",
      "id": 9765,
      "geometry": {
        "type": "Point",
        "coordinates": [
          150.36809699997661,
          -10.314502999713625
        ]
      },
      "properties": {
        "OBJECTID": 9765,
        "CU_NAME": "LAVIAM",
        "CU_NO": "001",
        "GEOCODE": "05010528001",
        "PROV_KEY": "05",
        "DIST_NO": "1",
        "LLG_NO": "05",
        "WARD_NO": "28",
        "WARD_NAME": "LAVIAM",
        "LATITUDE": -10.315971,
        "LONGITUDE": 150.367111,
        "REGHH": 106,
        "TOTPOP2000": 604,
        "MALE2000": 305,
        "FEMALE2000": 299,
        "POP2008": 735,
        "G_RATE": 1.024999976158142,
        "Geocode_Num": 5010528001,
        "PROVINCE": 5
      }
    },
    {
      "type": "Feature",
      "id": 9766,
      "geometry": {
        "type": "Point",
        "coordinates": [
          150.35524499995688,
          -10.324986000203694
        ]
      },
      "properties": {
        "OBJECTID": 9766,
        "CU_NAME": "LADAVA MISSION STN",
        "CU_NO": "401",
        "GEOCODE": "05010528401",
        "PROV_KEY": "05",
        "DIST_NO": "1",
        "LLG_NO": "05",
        "WARD_NO": "28",
        "WARD_NAME": "LAVIAM",
        "LATITUDE": -10.326454,
        "LONGITUDE": 150.354259,
        "REGHH": 10,
        "TOTPOP2000": 44,
        "MALE2000": 24,
        "FEMALE2000": 20,
        "POP2008": 52,
        "G_RATE": 1.024999976158142,
        "Geocode_Num": 5010528401,
        "PROVINCE": 5
      }
    }
  ]
}