{
  "type": "FeatureCollection",
  "features": [
    {
      "type": "Feature",
      "id": 21197,
      "geometry": {
        "type": "Point",
        "coordinates": [
          143.49607199982302,
          -6.4986059999668555
        ]
      },
      "properties": {
        "OBJECTID": 21197,
        "CU_NAME": "FIWAGA",
        "CU_NO": "006",
        "GEOCODE": "07072213006",
        "PROV_KEY": "07",
        "DIST_NO": "07",
        "LLG_NO": "22",
        "WARD_NO": "13",
        "WARD_NAME": "FIWAGA",
        "LATITUDE": -6.500628,
        "LONGITUDE": 143.497996,
        "REGHH": 104,
        "TOTPOP2000": 620,
        "MALE2000": 287,
        "FEMALE2000": 333,
        "POP2008": 861,
        "G_RATE": 1.0420000553131104,
        "Geocode_Num": 7072213006,
        "PROVINCE": 7
      }
    },
    {
      "type": "Feature",
      "id": 21198,
      "geometry": {
        "type": "Point",
        "coordinates": [
          143.49412399992275,
          -6.496673999905113
        ]
      },
      "properties": {
        "OBJECTID": 21198,
        "CU_NAME": "TANUGA",
        "CU_NO": "007",
        "GEOCODE": "07072213007",
        "PROV_KEY": "07",
        "DIST_NO": "07",
        "LLG_NO": "22",
        "WARD_NO": "13",
        "WARD_NAME": "FIWAGA",
        "LATITUDE": -6.500628,
        "LONGITUDE": 143.497996,
        "REGHH": 8,
        "TOTPOP2000": 39,
        "MALE2000": 22,
        "FEMALE2000": 17,
        "POP2008": 55,
        "G_RATE": 1.0420000553131104,
        "Geocode_Num": 7072213007,
        "PROVINCE": 7
      }
    }
  ]
}