{
  "type": "FeatureCollection",
  "features": [
    {
      "type": "Feature",
      "id": 10488,
      "geometry": {
        "type": "Point",
        "coordinates": [
          146.62303799970402,
          -7.1409520000347015
        ]
      },
      "properties": {
        "OBJECTID": 10488,
        "CU_NAME": "GOLDEN PINE",
        "CU_NO": "001",
        "GEOCODE": "12010307001",
        "PROV_KEY": "12",
        "DIST_NO": "01",
        "LLG_NO": "03",
        "WARD_NO": "07",
        "WARD_NAME": "GAWAPU",
        "LATITUDE": -7.142377,
        "LONGITUDE": 146.622008,
        "REGHH": 14,
        "TOTPOP2000": 87,
        "MALE2000": 45,
        "FEMALE2000": 42,
        "POP2008": 109,
        "G_RATE": 1.027999997138977,
        "Geocode_Num": 12010307001,
        "PROVINCE": 12
      }
    },
    {
      "type": "Feature",
      "id": 10489,
      "geometry": {
        "type": "Point",
        "coordinates": [
          146.61828299986064,
          -7.1476899995937515
        ]
      },
      "properties": {
        "OBJECTID": 10489,
        "CU_NAME": "GAWAPU",
        "CU_NO": "003",
        "GEOCODE": "12010307003",
        "PROV_KEY": "12",
        "DIST_NO": "01",
        "LLG_NO": "03",
        "WARD_NO": "07",
        "WARD_NAME": "GAWAPU",
        "LATITUDE": -7.149115,
        "LONGITUDE": 146.617253,
        "REGHH": 43,
        "TOTPOP2000": 244,
        "MALE2000": 124,
        "FEMALE2000": 120,
        "POP2008": 304,
        "G_RATE": 1.027999997138977,
        "Geocode_Num": 12010307003,
        "PROVINCE": 12
      }
    },
    {
      "type": "Feature",
      "id": 10490,
      "geometry": {
        "type": "Point",
        "coordinates": [
          146.6344679997984,
          -7.177598000147555
        ]
      },
      "properties": {
        "OBJECTID": 10490,
        "CU_NAME": "BAIUS",
        "CU_NO": "004",
        "GEOCODE": "12010307004",
        "PROV_KEY": "12",
        "DIST_NO": "01",
        "LLG_NO": "03",
        "WARD_NO": "07",
        "WARD_NAME": "GAWAPU",
        "LATITUDE": -7.179023,
        "LONGITUDE": 146.633438,
        "REGHH": 40,
        "TOTPOP2000": 261,
        "MALE2000": 163,
        "FEMALE2000": 98,
        "POP2008": 326,
        "G_RATE": 1.027999997138977,
        "Geocode_Num": 12010307004,
        "PROVINCE": 12
      }
    },
    {
      "type": "Feature",
      "id": 10491,
      "geometry": {
        "type": "Point",
        "coordinates": [
          146.5961839996919,
          -7.134658000266427
        ]
      },
      "properties": {
        "OBJECTID": 10491,
        "CU_NAME": "NO. 8-2",
        "CU_NO": "005",
        "GEOCODE": "12010307005",
        "PROV_KEY": "12",
        "DIST_NO": "01",
        "LLG_NO": "03",
        "WARD_NO": "07",
        "WARD_NAME": "GAWAPU",
        "LATITUDE": -7.136083,
        "LONGITUDE": 146.595153,
        "REGHH": 80,
        "TOTPOP2000": 459,
        "MALE2000": 251,
        "FEMALE2000": 208,
        "POP2008": 573,
        "G_RATE": 1.027999997138977,
        "Geocode_Num": 12010307005,
        "PROVINCE": 12
      }
    }
  ]
}