{
  "type": "FeatureCollection",
  "features": [
    {
      "type": "Feature",
      "id": 5690,
      "geometry": {
        "type": "Point",
        "coordinates": [
          143.0245160004132,
          -5.363453999902106
        ]
      },
      "properties": {
        "OBJECTID": 5690,
        "CU_NAME": "WAIYONGA",
        "CU_NO": "001",
        "GEOCODE": "08030814001",
        "PROV_KEY": "08",
        "DIST_NO": "03",
        "LLG_NO": "08",
        "WARD_NO": "14",
        "WARD_NAME": "WAIYONGA",
        "LATITUDE": -5.365865,
        "LONGITUDE": 143.02194,
        "REGHH": 103,
        "TOTPOP2000": 454,
        "MALE2000": 269,
        "FEMALE2000": 185,
        "POP2008": 571,
        "G_RATE": 1.0290000438690186,
        "Geocode_Num": 8030814001,
        "PROVINCE": 8
      }
    }
  ]
}