{
  "type": "FeatureCollection",
  "features": [
    {
      "type": "Feature",
      "id": 4782,
      "geometry": {
        "type": "Point",
        "coordinates": [
          151.43828299976064,
          -5.561018999627095
        ]
      },
      "properties": {
        "OBJECTID": 4782,
        "CU_NAME": "RURAI",
        "CU_NO": "004",
        "GEOCODE": "18031003004",
        "PROV_KEY": "18",
        "DIST_NO": "03",
        "LLG_NO": "10",
        "WARD_NO": "03",
        "WARD_NAME": "KERKERNENA",
        "LATITUDE": -5.562869,
        "LONGITUDE": 151.446293,
        "REGHH": 39,
        "TOTPOP2000": 177,
        "MALE2000": 88,
        "FEMALE2000": 89,
        "POP2008": 216,
        "G_RATE": 1.024999976158142,
        "Geocode_Num": 18031003004,
        "PROVINCE": 18
      }
    },
    {
      "type": "Feature",
      "id": 4783,
      "geometry": {
        "type": "Point",
        "coordinates": [
          151.44814400034545,
          -5.559542999909468
        ]
      },
      "properties": {
        "OBJECTID": 4783,
        "CU_NAME": "KERKERENA",
        "CU_NO": "008",
        "GEOCODE": "18031003008",
        "PROV_KEY": "18",
        "DIST_NO": "03",
        "LLG_NO": "10",
        "WARD_NO": "03",
        "WARD_NAME": "KERKERNENA",
        "LATITUDE": -5.55858,
        "LONGITUDE": 151.44965,
        "REGHH": 20,
        "TOTPOP2000": 112,
        "MALE2000": 53,
        "FEMALE2000": 59,
        "POP2008": 136,
        "G_RATE": 1.024999976158142,
        "Geocode_Num": 18031003008,
        "PROVINCE": 18
      }
    },
    {
      "type": "Feature",
      "id": 4784,
      "geometry": {
        "type": "Point",
        "coordinates": [
          151.4366130000899,
          -5.552175000076147
        ]
      },
      "properties": {
        "OBJECTID": 4784,
        "CU_NAME": "BEGAPUNA",
        "CU_NO": "009",
        "GEOCODE": "18031003009",
        "PROV_KEY": "18",
        "DIST_NO": "03",
        "LLG_NO": "10",
        "WARD_NO": "03",
        "WARD_NAME": "KERKERNENA",
        "LATITUDE": -5.551212,
        "LONGITUDE": 151.438119,
        "REGHH": 11,
        "TOTPOP2000": 65,
        "MALE2000": 30,
        "FEMALE2000": 35,
        "POP2008": 81,
        "G_RATE": 1.024999976158142,
        "Geocode_Num": 18031003009,
        "PROVINCE": 18
      }
    }
  ]
}