{
  "type": "FeatureCollection",
  "features": [
    {
      "type": "Feature",
      "id": 4786,
      "geometry": {
        "type": "Point",
        "coordinates": [
          151.48623200040652,
          -5.513905999762017
        ]
      },
      "properties": {
        "OBJECTID": 4786,
        "CU_NAME": "GALEWA",
        "CU_NO": "010",
        "GEOCODE": "18031005010",
        "PROV_KEY": "18",
        "DIST_NO": "03",
        "LLG_NO": "10",
        "WARD_NO": "05",
        "WARD_NAME": "GALEWA",
        "LATITUDE": -5.519037,
        "LONGITUDE": 151.480613,
        "REGHH": 97,
        "TOTPOP2000": 551,
        "MALE2000": 278,
        "FEMALE2000": 273,
        "POP2008": 671,
        "G_RATE": 1.024999976158142,
        "Geocode_Num": 18031005010,
        "PROVINCE": 18
      }
    },
    {
      "type": "Feature",
      "id": 4787,
      "geometry": {
        "type": "Point",
        "coordinates": [
          151.47729700025639,
          -5.511365000394392
        ]
      },
      "properties": {
        "OBJECTID": 4787,
        "CU_NAME": "PAGEPUNA",
        "CU_NO": "011",
        "GEOCODE": "18031005011",
        "PROV_KEY": "18",
        "DIST_NO": "03",
        "LLG_NO": "10",
        "WARD_NO": "05",
        "WARD_NAME": "GALEWA",
        "LATITUDE": -5.514652,
        "LONGITUDE": 151.479125,
        "REGHH": 8,
        "TOTPOP2000": 49,
        "MALE2000": 21,
        "FEMALE2000": 28,
        "POP2008": 57,
        "G_RATE": 1.024999976158142,
        "Geocode_Num": 18031005011,
        "PROVINCE": 18
      }
    }
  ]
}