{
  "type": "FeatureCollection",
  "features": [
    {
      "type": "Feature",
      "id": 16992,
      "geometry": {
        "type": "Point",
        "coordinates": [
          144.15139000004854,
          -5.728842000158124
        ]
      },
      "properties": {
        "OBJECTID": 16992,
        "CU_NAME": "KILEG.1",
        "CU_NO": "017",
        "GEOCODE": "09050802017",
        "PROV_KEY": "09",
        "DIST_NO": "05",
        "LLG_NO": "08",
        "WARD_NO": "02",
        "WARD_NAME": "KILEG .1",
        "LATITUDE": -5.729779,
        "LONGITUDE": 144.151722,
        "REGHH": 61,
        "TOTPOP2000": 223,
        "MALE2000": 112,
        "FEMALE2000": 111,
        "POP2008": 272,
        "G_RATE": 1.024999976158142,
        "Geocode_Num": 9050802017,
        "PROVINCE": 9
      }
    },
    {
      "type": "Feature",
      "id": 16993,
      "geometry": {
        "type": "Point",
        "coordinates": [
          144.14490499956617,
          -5.729179000410511
        ]
      },
      "properties": {
        "OBJECTID": 16993,
        "CU_NAME": "ELIMP",
        "CU_NO": "018",
        "GEOCODE": "09050802018",
        "PROV_KEY": "09",
        "DIST_NO": "05",
        "LLG_NO": "08",
        "WARD_NO": "02",
        "WARD_NAME": "KILEG .1",
        "LATITUDE": -5.730116,
        "LONGITUDE": 144.145237,
        "REGHH": 70,
        "TOTPOP2000": 279,
        "MALE2000": 141,
        "FEMALE2000": 138,
        "POP2008": 340,
        "G_RATE": 1.024999976158142,
        "Geocode_Num": 9050802018,
        "PROVINCE": 9
      }
    }
  ]
}