{
  "type": "FeatureCollection",
  "features": [
    {
      "type": "Feature",
      "id": 16997,
      "geometry": {
        "type": "Point",
        "coordinates": [
          144.15381699955492,
          -5.709151000418274
        ]
      },
      "properties": {
        "OBJECTID": 16997,
        "CU_NAME": "KALINGA 2",
        "CU_NO": "019",
        "GEOCODE": "09050806019",
        "PROV_KEY": "09",
        "DIST_NO": "05",
        "LLG_NO": "08",
        "WARD_NO": "06",
        "WARD_NAME": "KALINGA 2",
        "LATITUDE": -5.710088,
        "LONGITUDE": 144.154149,
        "REGHH": 129,
        "TOTPOP2000": 546,
        "MALE2000": 254,
        "FEMALE2000": 292,
        "POP2008": 665,
        "G_RATE": 1.024999976158142,
        "Geocode_Num": 9050806019,
        "PROVINCE": 9
      }
    }
  ]
}