{
  "type": "FeatureCollection",
  "features": [
    {
      "type": "Feature",
      "id": 17020,
      "geometry": {
        "type": "Point",
        "coordinates": [
          144.19584599969323,
          -5.7096580004163116
        ]
      },
      "properties": {
        "OBJECTID": 17020,
        "CU_NAME": "KUMDI",
        "CU_NO": "034",
        "GEOCODE": "09050822034",
        "PROV_KEY": "09",
        "DIST_NO": "05",
        "LLG_NO": "08",
        "WARD_NO": "22",
        "WARD_NAME": "KUMDI",
        "LATITUDE": -5.71028,
        "LONGITUDE": 144.195404,
        "REGHH": 70,
        "TOTPOP2000": 299,
        "MALE2000": 160,
        "FEMALE2000": 139,
        "POP2008": 364,
        "G_RATE": 1.024999976158142,
        "Geocode_Num": 9050822034,
        "PROVINCE": 9
      }
    },
    {
      "type": "Feature",
      "id": 17021,
      "geometry": {
        "type": "Point",
        "coordinates": [
          144.2029740001501,
          -5.711752999900966
        ]
      },
      "properties": {
        "OBJECTID": 17021,
        "CU_NAME": "MANDA",
        "CU_NO": "035",
        "GEOCODE": "09050822035",
        "PROV_KEY": "09",
        "DIST_NO": "05",
        "LLG_NO": "08",
        "WARD_NO": "22",
        "WARD_NAME": "KUMDI",
        "LATITUDE": -5.71269,
        "LONGITUDE": 144.203307,
        "REGHH": 126,
        "TOTPOP2000": 514,
        "MALE2000": 261,
        "FEMALE2000": 253,
        "POP2008": 627,
        "G_RATE": 1.024999976158142,
        "Geocode_Num": 9050822035,
        "PROVINCE": 9
      }
    },
    {
      "type": "Feature",
      "id": 17022,
      "geometry": {
        "type": "Point",
        "coordinates": [
          144.19413700002258,
          -5.709805000000699
        ]
      },
      "properties": {
        "OBJECTID": 17022,
        "CU_NAME": "NOTRE DAME HIGH SCHOOL",
        "CU_NO": "401",
        "GEOCODE": "09050822401",
        "PROV_KEY": "09",
        "DIST_NO": "05",
        "LLG_NO": "08",
        "WARD_NO": "22",
        "WARD_NAME": "KUMDI",
        "LATITUDE": -5.71028,
        "LONGITUDE": 144.195404,
        "REGHH": 9,
        "TOTPOP2000": 51,
        "MALE2000": 19,
        "FEMALE2000": 32,
        "POP2008": 59,
        "G_RATE": 1.024999976158142,
        "Geocode_Num": 9050822401,
        "PROVINCE": 9
      }
    }
  ]
}