{
  "type": "FeatureCollection",
  "features": [
    {
      "type": "Feature",
      "id": 5643,
      "geometry": {
        "type": "Point",
        "coordinates": [
          143.25728500030255,
          -5.301650999793765
        ]
      },
      "properties": {
        "OBJECTID": 5643,
        "CU_NAME": "YEIM",
        "CU_NO": "009",
        "GEOCODE": "08030703009",
        "PROV_KEY": "08",
        "DIST_NO": "03",
        "LLG_NO": "07",
        "WARD_NO": "03",
        "WARD_NAME": "YEIM",
        "LATITUDE": -5.30305,
        "LONGITUDE": 143.256215,
        "REGHH": 51,
        "TOTPOP2000": 345,
        "MALE2000": 175,
        "FEMALE2000": 170,
        "POP2008": 434,
        "G_RATE": 1.0290000438690186,
        "Geocode_Num": 8030703009,
        "PROVINCE": 8
      }
    },
    {
      "type": "Feature",
      "id": 5644,
      "geometry": {
        "type": "Point",
        "coordinates": [
          143.23642399966786,
          -5.200593999813179
        ]
      },
      "properties": {
        "OBJECTID": 5644,
        "CU_NAME": "TOKOM",
        "CU_NO": "010",
        "GEOCODE": "08030703010",
        "PROV_KEY": "08",
        "DIST_NO": "03",
        "LLG_NO": "07",
        "WARD_NO": "03",
        "WARD_NAME": "YEIM",
        "LATITUDE": -5.198826,
        "LONGITUDE": 143.244264,
        "REGHH": 48,
        "TOTPOP2000": 292,
        "MALE2000": 152,
        "FEMALE2000": 140,
        "POP2008": 366,
        "G_RATE": 1.0290000438690186,
        "Geocode_Num": 8030703010,
        "PROVINCE": 8
      }
    },
    {
      "type": "Feature",
      "id": 5645,
      "geometry": {
        "type": "Point",
        "coordinates": [
          143.25102100011918,
          -5.249134999880312
        ]
      },
      "properties": {
        "OBJECTID": 5645,
        "CU_NAME": "WINJAKA",
        "CU_NO": "011",
        "GEOCODE": "08030703011",
        "PROV_KEY": "08",
        "DIST_NO": "03",
        "LLG_NO": "07",
        "WARD_NO": "03",
        "WARD_NAME": "YEIM",
        "LATITUDE": -5.238954,
        "LONGITUDE": 143.232066,
        "REGHH": 28,
        "TOTPOP2000": 236,
        "MALE2000": 119,
        "FEMALE2000": 117,
        "POP2008": 296,
        "G_RATE": 1.0290000438690186,
        "Geocode_Num": 8030703011,
        "PROVINCE": 8
      }
    },
    {
      "type": "Feature",
      "id": 5646,
      "geometry": {
        "type": "Point",
        "coordinates": [
          143.26782499982392,
          -5.263595000308953
        ]
      },
      "properties": {
        "OBJECTID": 5646,
        "CU_NAME": "WAILI",
        "CU_NO": "012",
        "GEOCODE": "08030703012",
        "PROV_KEY": "08",
        "DIST_NO": "03",
        "LLG_NO": "07",
        "WARD_NO": "03",
        "WARD_NAME": "YEIM",
        "LATITUDE": -5.2559,
        "LONGITUDE": 143.27414,
        "REGHH": 52,
        "TOTPOP2000": 403,
        "MALE2000": 205,
        "FEMALE2000": 198,
        "POP2008": 506,
        "G_RATE": 1.0290000438690186,
        "Geocode_Num": 8030703012,
        "PROVINCE": 8
      }
    }
  ]
}