{
  "type": "FeatureCollection",
  "features": [
    {
      "type": "Feature",
      "id": 5667,
      "geometry": {
        "type": "Point",
        "coordinates": [
          143.0451749998265,
          -5.108734000373772
        ]
      },
      "properties": {
        "OBJECTID": 5667,
        "CU_NAME": "MALAUMANDA",
        "CU_NO": "010",
        "GEOCODE": "08030710010",
        "PROV_KEY": "08",
        "DIST_NO": "03",
        "LLG_NO": "07",
        "WARD_NO": "10",
        "WARD_NAME": "MALAUMANDA",
        "LATITUDE": -5.10851,
        "LONGITUDE": 143.043449,
        "REGHH": 11,
        "TOTPOP2000": 71,
        "MALE2000": 37,
        "FEMALE2000": 34,
        "POP2008": 87,
        "G_RATE": 1.0290000438690186,
        "Geocode_Num": 8030710010,
        "PROVINCE": 8
      }
    },
    {
      "type": "Feature",
      "id": 5668,
      "geometry": {
        "type": "Point",
        "coordinates": [
          143.06952300028627,
          -5.105783000085353
        ]
      },
      "properties": {
        "OBJECTID": 5668,
        "CU_NAME": "KASAKALI",
        "CU_NO": "011",
        "GEOCODE": "08030710011",
        "PROV_KEY": "08",
        "DIST_NO": "03",
        "LLG_NO": "07",
        "WARD_NO": "10",
        "WARD_NAME": "MALAUMANDA",
        "LATITUDE": -5.121688,
        "LONGITUDE": 143.098019,
        "REGHH": 22,
        "TOTPOP2000": 149,
        "MALE2000": 74,
        "FEMALE2000": 75,
        "POP2008": 187,
        "G_RATE": 1.0290000438690186,
        "Geocode_Num": 8030710011,
        "PROVINCE": 8
      }
    },
    {
      "type": "Feature",
      "id": 5669,
      "geometry": {
        "type": "Point",
        "coordinates": [
          143.0388129996203,
          -5.114555999959407
        ]
      },
      "properties": {
        "OBJECTID": 5669,
        "CU_NAME": "MALAUMANDA A/STRIP, A/P.",
        "CU_NO": "401",
        "GEOCODE": "08030710401",
        "PROV_KEY": "08",
        "DIST_NO": "03",
        "LLG_NO": "07",
        "WARD_NO": "10",
        "WARD_NAME": "MALAUMANDA",
        "LATITUDE": -5.108361,
        "LONGITUDE": 143.043409,
        "REGHH": 40,
        "TOTPOP2000": 254,
        "MALE2000": 154,
        "FEMALE2000": 100,
        "POP2008": 319,
        "G_RATE": 1.0290000438690186,
        "Geocode_Num": 8030710401,
        "PROVINCE": 8
      }
    }
  ]
}