{
  "type": "FeatureCollection",
  "features": [
    {
      "type": "Feature",
      "id": 1341,
      "geometry": {
        "type": "Point",
        "coordinates": [
          146.49683700032733,
          -8.679134999680457
        ]
      },
      "properties": {
        "OBJECTID": 1341,
        "CU_NAME": "ABIARA OREKE",
        "CU_NO": "001",
        "GEOCODE": "03030807001",
        "PROV_KEY": "03",
        "DIST_NO": "03",
        "LLG_NO": "08",
        "WARD_NO": "07",
        "WARD_NAME": "ABIARA",
        "LATITUDE": -8.680575,
        "LONGITUDE": 146.495801,
        "REGHH": 57,
        "TOTPOP2000": 372,
        "MALE2000": 183,
        "FEMALE2000": 189,
        "POP2008": 447,
        "G_RATE": 1.0230000019073486,
        "Geocode_Num": 3030807001,
        "PROVINCE": 3
      }
    },
    {
      "type": "Feature",
      "id": 1342,
      "geometry": {
        "type": "Point",
        "coordinates": [
          146.50786199973152,
          -8.65682899985842
        ]
      },
      "properties": {
        "OBJECTID": 1342,
        "CU_NAME": "BEREINA",
        "CU_NO": "002",
        "GEOCODE": "03030807002",
        "PROV_KEY": "03",
        "DIST_NO": "03",
        "LLG_NO": "08",
        "WARD_NO": "07",
        "WARD_NAME": "ABIARA",
        "LATITUDE": -8.658269,
        "LONGITUDE": 146.506826,
        "REGHH": 69,
        "TOTPOP2000": 418,
        "MALE2000": 219,
        "FEMALE2000": 199,
        "POP2008": 502,
        "G_RATE": 1.0230000019073486,
        "Geocode_Num": 3030807002,
        "PROVINCE": 3
      }
    },
    {
      "type": "Feature",
      "id": 1343,
      "geometry": {
        "type": "Point",
        "coordinates": [
          146.51878099964347,
          -8.657181999949273
        ]
      },
      "properties": {
        "OBJECTID": 1343,
        "CU_NAME": "MAINOHANA HIGH SCHOOL",
        "CU_NO": "501",
        "GEOCODE": "03030807501",
        "PROV_KEY": "03",
        "DIST_NO": "03",
        "LLG_NO": "08",
        "WARD_NO": "07",
        "WARD_NAME": "ABIARA",
        "LATITUDE": -8.658622,
        "LONGITUDE": 146.517744,
        "REGHH": 26,
        "TOTPOP2000": 158,
        "MALE2000": 84,
        "FEMALE2000": 74,
        "POP2008": 190,
        "G_RATE": 1.0230000019073486,
        "Geocode_Num": 3030807501,
        "PROVINCE": 3
      }
    }
  ]
}