{
  "type": "FeatureCollection",
  "features": [
    {
      "type": "Feature",
      "id": 19012,
      "geometry": {
        "type": "Point",
        "coordinates": [
          141.4494000000101,
          -3.954738000058626
        ]
      },
      "properties": {
        "OBJECTID": 19012,
        "CU_NAME": "BAIO",
        "CU_NO": "001",
        "GEOCODE": "15041425001",
        "PROV_KEY": "15",
        "DIST_NO": "04",
        "LLG_NO": "14",
        "WARD_NO": "25",
        "WARD_NAME": "BAIO",
        "LATITUDE": -3.951603,
        "LONGITUDE": 141.448308,
        "REGHH": 18,
        "TOTPOP2000": 140,
        "MALE2000": 75,
        "FEMALE2000": 65,
        "POP2008": 170,
        "G_RATE": 1.0240000486373901,
        "Geocode_Num": 15041425001,
        "PROVINCE": 15
      }
    }
  ]
}