{
  "type": "FeatureCollection",
  "features": [
    {
      "type": "Feature",
      "id": 9892,
      "geometry": {
        "type": "Point",
        "coordinates": [
          152.8534559996947,
          -10.651201999872342
        ]
      },
      "properties": {
        "OBJECTID": 9892,
        "CU_NAME": "PILUPILUWA",
        "CU_NO": "013",
        "GEOCODE": "05020905013",
        "PROV_KEY": "05",
        "DIST_NO": "2",
        "LLG_NO": "09",
        "WARD_NO": "05",
        "WARD_NAME": "KAUBWAGA",
        "LATITUDE": -10.652422,
        "LONGITUDE": 152.855265,
        "REGHH": 2,
        "TOTPOP2000": 7,
        "MALE2000": 4,
        "FEMALE2000": 3,
        "POP2008": 7,
        "G_RATE": 1.024999976158142,
        "Geocode_Num": 5020905013,
        "PROVINCE": 5
      }
    },
    {
      "type": "Feature",
      "id": 9893,
      "geometry": {
        "type": "Point",
        "coordinates": [
          152.8506050004205,
          -10.646926999681227
        ]
      },
      "properties": {
        "OBJECTID": 9893,
        "CU_NAME": "GIGIG",
        "CU_NO": "014",
        "GEOCODE": "05020905014",
        "PROV_KEY": "05",
        "DIST_NO": "2",
        "LLG_NO": "09",
        "WARD_NO": "05",
        "WARD_NAME": "KAUBWAGA",
        "LATITUDE": -10.64805,
        "LONGITUDE": 152.851101,
        "REGHH": 33,
        "TOTPOP2000": 174,
        "MALE2000": 97,
        "FEMALE2000": 77,
        "POP2008": 212,
        "G_RATE": 1.024999976158142,
        "Geocode_Num": 5020905014,
        "PROVINCE": 5
      }
    },
    {
      "type": "Feature",
      "id": 9894,
      "geometry": {
        "type": "Point",
        "coordinates": [
          152.84953499964058,
          -10.6456750004009
        ]
      },
      "properties": {
        "OBJECTID": 9894,
        "CU_NAME": "LAVA",
        "CU_NO": "015",
        "GEOCODE": "05020905015",
        "PROV_KEY": "05",
        "DIST_NO": "2",
        "LLG_NO": "09",
        "WARD_NO": "05",
        "WARD_NAME": "KAUBWAGA",
        "LATITUDE": -10.647154,
        "LONGITUDE": 152.849505,
        "REGHH": 26,
        "TOTPOP2000": 122,
        "MALE2000": 65,
        "FEMALE2000": 57,
        "POP2008": 148,
        "G_RATE": 1.024999976158142,
        "Geocode_Num": 5020905015,
        "PROVINCE": 5
      }
    },
    {
      "type": "Feature",
      "id": 9895,
      "geometry": {
        "type": "Point",
        "coordinates": [
          152.84793699969282,
          -10.644420000082903
        ]
      },
      "properties": {
        "OBJECTID": 9895,
        "CU_NAME": "TALAHUWA",
        "CU_NO": "016",
        "GEOCODE": "05020905016",
        "PROV_KEY": "05",
        "DIST_NO": "2",
        "LLG_NO": "09",
        "WARD_NO": "05",
        "WARD_NAME": "KAUBWAGA",
        "LATITUDE": -10.646257,
        "LONGITUDE": 152.848137,
        "REGHH": 47,
        "TOTPOP2000": 264,
        "MALE2000": 138,
        "FEMALE2000": 126,
        "POP2008": 322,
        "G_RATE": 1.024999976158142,
        "Geocode_Num": 5020905016,
        "PROVINCE": 5
      }
    }
  ]
}