{
  "type": "FeatureCollection",
  "features": [
    {
      "type": "Feature",
      "id": 6493,
      "geometry": {
        "type": "Point",
        "coordinates": [
          144.31456500027457,
          -3.784811999673991
        ]
      },
      "properties": {
        "OBJECTID": 6493,
        "CU_NAME": "KARAU",
        "CU_NO": "004",
        "GEOCODE": "14020810004",
        "PROV_KEY": "14",
        "DIST_NO": "02",
        "LLG_NO": "08",
        "WARD_NO": "10",
        "WARD_NAME": "KARAU",
        "LATITUDE": -3.784864,
        "LONGITUDE": 144.313336,
        "REGHH": 52,
        "TOTPOP2000": 286,
        "MALE2000": 143,
        "FEMALE2000": 143,
        "POP2008": 340,
        "G_RATE": 1.0219999551773071,
        "Geocode_Num": 14020810004,
        "PROVINCE": 14
      }
    }
  ]
}