{
  "type": "FeatureCollection",
  "features": [
    {
      "type": "Feature",
      "id": 6505,
      "geometry": {
        "type": "Point",
        "coordinates": [
          144.38775700038536,
          -3.9688879996813853
        ]
      },
      "properties": {
        "OBJECTID": 6505,
        "CU_NAME": "MABUK",
        "CU_NO": "004",
        "GEOCODE": "14020818004",
        "PROV_KEY": "14",
        "DIST_NO": "02",
        "LLG_NO": "08",
        "WARD_NO": "18",
        "WARD_NAME": "MABUK",
        "LATITUDE": -3.970471,
        "LONGITUDE": 144.386534,
        "REGHH": 28,
        "TOTPOP2000": 211,
        "MALE2000": 103,
        "FEMALE2000": 108,
        "POP2008": 251,
        "G_RATE": 1.0219999551773071,
        "Geocode_Num": 14020818004,
        "PROVINCE": 14
      }
    },
    {
      "type": "Feature",
      "id": 6506,
      "geometry": {
        "type": "Point",
        "coordinates": [
          144.43703100008065,
          -3.92983500008512
        ]
      },
      "properties": {
        "OBJECTID": 6506,
        "CU_NAME": "SINGARIN",
        "CU_NO": "005",
        "GEOCODE": "14020818005",
        "PROV_KEY": "14",
        "DIST_NO": "02",
        "LLG_NO": "08",
        "WARD_NO": "18",
        "WARD_NAME": "MABUK",
        "LATITUDE": -3.939457,
        "LONGITUDE": 144.430355,
        "REGHH": 16,
        "TOTPOP2000": 147,
        "MALE2000": 72,
        "FEMALE2000": 75,
        "POP2008": 174,
        "G_RATE": 1.0219999551773071,
        "Geocode_Num": 14020818005,
        "PROVINCE": 14
      }
    }
  ]
}