{
  "type": "FeatureCollection",
  "features": [
    {
      "type": "Feature",
      "id": 5753,
      "geometry": {
        "type": "Point",
        "coordinates": [
          143.58489599955078,
          -5.410510999882717
        ]
      },
      "properties": {
        "OBJECTID": 5753,
        "CU_NAME": "AIPANDA",
        "CU_NO": "001",
        "GEOCODE": "08041102001",
        "PROV_KEY": "08",
        "DIST_NO": "04",
        "LLG_NO": "11",
        "WARD_NO": "02",
        "WARD_NAME": "AIPANDA",
        "LATITUDE": -5.412929,
        "LONGITUDE": 143.581324,
        "REGHH": 133,
        "TOTPOP2000": 704,
        "MALE2000": 366,
        "FEMALE2000": 338,
        "POP2008": 885,
        "G_RATE": 1.0290000438690186,
        "Geocode_Num": 8041102001,
        "PROVINCE": 8
      }
    },
    {
      "type": "Feature",
      "id": 5754,
      "geometry": {
        "type": "Point",
        "coordinates": [
          143.77739600042514,
          -5.491531000355337
        ]
      },
      "properties": {
        "OBJECTID": 5754,
        "CU_NAME": "TUMBILAM",
        "CU_NO": "002",
        "GEOCODE": "08041102002",
        "PROV_KEY": "08",
        "DIST_NO": "04",
        "LLG_NO": "11",
        "WARD_NO": "02",
        "WARD_NAME": "AIPANDA",
        "LATITUDE": -5.492182,
        "LONGITUDE": 143.775575,
        "REGHH": 46,
        "TOTPOP2000": 210,
        "MALE2000": 101,
        "FEMALE2000": 109,
        "POP2008": 263,
        "G_RATE": 1.0290000438690186,
        "Geocode_Num": 8041102002,
        "PROVINCE": 8
      }
    }
  ]
}