{
  "type": "FeatureCollection",
  "features": [
    {
      "type": "Feature",
      "id": 5830,
      "geometry": {
        "type": "Point",
        "coordinates": [
          143.77135100044836,
          -5.5153509998486925
        ]
      },
      "properties": {
        "OBJECTID": 5830,
        "CU_NAME": "RAKAMANDA",
        "CU_NO": "010",
        "GEOCODE": "08041124010",
        "PROV_KEY": "08",
        "DIST_NO": "04",
        "LLG_NO": "11",
        "WARD_NO": "24",
        "WARD_NAME": "RAKAMANDA",
        "LATITUDE": -5.516753,
        "LONGITUDE": 143.770287,
        "REGHH": 88,
        "TOTPOP2000": 692,
        "MALE2000": 350,
        "FEMALE2000": 342,
        "POP2008": 871,
        "G_RATE": 1.0290000438690186,
        "Geocode_Num": 8041124010,
        "PROVINCE": 8
      }
    },
    {
      "type": "Feature",
      "id": 5831,
      "geometry": {
        "type": "Point",
        "coordinates": [
          143.77389900013884,
          -5.517078000349386
        ]
      },
      "properties": {
        "OBJECTID": 5831,
        "CU_NAME": "MUGUTESA",
        "CU_NO": "011",
        "GEOCODE": "08041124011",
        "PROV_KEY": "08",
        "DIST_NO": "04",
        "LLG_NO": "11",
        "WARD_NO": "24",
        "WARD_NAME": "RAKAMANDA",
        "LATITUDE": -5.51848,
        "LONGITUDE": 143.772835,
        "REGHH": 43,
        "TOTPOP2000": 288,
        "MALE2000": 149,
        "FEMALE2000": 139,
        "POP2008": 362,
        "G_RATE": 1.0290000438690186,
        "Geocode_Num": 8041124011,
        "PROVINCE": 8
      }
    }
  ]
}