{
  "type": "FeatureCollection",
  "features": [
    {
      "type": "Feature",
      "id": 19199,
      "geometry": {
        "type": "Point",
        "coordinates": [
          143.98518799962653,
          -6.266742000442946
        ]
      },
      "properties": {
        "OBJECTID": 19199,
        "CU_NAME": "RAIMANDA",
        "CU_NO": "801",
        "GEOCODE": "07010203801",
        "PROV_KEY": "07",
        "DIST_NO": "01",
        "LLG_NO": "02",
        "WARD_NO": "03",
        "WARD_NAME": "IALIBU STATION 3",
        "LATITUDE": -6.26921,
        "LONGITUDE": 143.987047,
        "REGHH": 12,
        "TOTPOP2000": 66,
        "MALE2000": 32,
        "FEMALE2000": 34,
        "POP2008": 92,
        "G_RATE": 1.0420000553131104,
        "Geocode_Num": 7010203801,
        "PROVINCE": 7
      }
    },
    {
      "type": "Feature",
      "id": 19200,
      "geometry": {
        "type": "Point",
        "coordinates": [
          143.9838229996318,
          -6.26503900014967
        ]
      },
      "properties": {
        "OBJECTID": 19200,
        "CU_NAME": "WEST KURI",
        "CU_NO": "802",
        "GEOCODE": "07010203802",
        "PROV_KEY": "07",
        "DIST_NO": "01",
        "LLG_NO": "02",
        "WARD_NO": "03",
        "WARD_NAME": "IALIBU STATION 3",
        "LATITUDE": -6.26921,
        "LONGITUDE": 143.987047,
        "REGHH": 13,
        "TOTPOP2000": 41,
        "MALE2000": 19,
        "FEMALE2000": 22,
        "POP2008": 57,
        "G_RATE": 1.0420000553131104,
        "Geocode_Num": 7010203802,
        "PROVINCE": 7
      }
    }
  ]
}