{
  "type": "FeatureCollection",
  "features": [
    {
      "type": "Feature",
      "id": 19572,
      "geometry": {
        "type": "Point",
        "coordinates": [
          144.11012700016101,
          -6.159693000231755
        ]
      },
      "properties": {
        "OBJECTID": 19572,
        "CU_NAME": "TAPOIPOI",
        "CU_NO": "001",
        "GEOCODE": "07020602001",
        "PROV_KEY": "07",
        "DIST_NO": "02",
        "LLG_NO": "06",
        "WARD_NO": "02",
        "WARD_NAME": "MOKA 1",
        "LATITUDE": -6.163936,
        "LONGITUDE": 144.110411,
        "REGHH": 104,
        "TOTPOP2000": 574,
        "MALE2000": 290,
        "FEMALE2000": 284,
        "POP2008": 797,
        "G_RATE": 1.0420000553131104,
        "Geocode_Num": 7020602001,
        "PROVINCE": 7
      }
    }
  ]
}