{
  "type": "FeatureCollection",
  "features": [
    {
      "type": "Feature",
      "id": 19605,
      "geometry": {
        "type": "Point",
        "coordinates": [
          144.06287900036568,
          -6.141071000326349
        ]
      },
      "properties": {
        "OBJECTID": 19605,
        "CU_NAME": "ILOPULU",
        "CU_NO": "001",
        "GEOCODE": "07020615001",
        "PROV_KEY": "07",
        "DIST_NO": "02",
        "LLG_NO": "06",
        "WARD_NO": "15",
        "WARD_NAME": "PAPARE",
        "LATITUDE": -6.145314,
        "LONGITUDE": 144.063161,
        "REGHH": 102,
        "TOTPOP2000": 505,
        "MALE2000": 261,
        "FEMALE2000": 244,
        "POP2008": 701,
        "G_RATE": 1.0420000553131104,
        "Geocode_Num": 7020615001,
        "PROVINCE": 7
      }
    }
  ]
}