{
  "type": "FeatureCollection",
  "features": [
    {
      "type": "Feature",
      "id": 19607,
      "geometry": {
        "type": "Point",
        "coordinates": [
          144.0988920000658,
          -6.144861999781426
        ]
      },
      "properties": {
        "OBJECTID": 19607,
        "CU_NAME": "TIRINGIPENA",
        "CU_NO": "001",
        "GEOCODE": "07020617001",
        "PROV_KEY": "07",
        "DIST_NO": "02",
        "LLG_NO": "06",
        "WARD_NO": "17",
        "WARD_NAME": "MOKA 2",
        "LATITUDE": -6.149105,
        "LONGITUDE": 144.099176,
        "REGHH": 123,
        "TOTPOP2000": 649,
        "MALE2000": 307,
        "FEMALE2000": 342,
        "POP2008": 901,
        "G_RATE": 1.0420000553131104,
        "Geocode_Num": 7020617001,
        "PROVINCE": 7
      }
    }
  ]
}