{
  "type": "FeatureCollection",
  "features": [
    {
      "type": "Feature",
      "id": 18719,
      "geometry": {
        "type": "Point",
        "coordinates": [
          141.57346699990217,
          -4.682210000191333
        ]
      },
      "properties": {
        "OBJECTID": 18719,
        "CU_NAME": "AMAROMIN",
        "CU_NO": "001",
        "GEOCODE": "15031001001",
        "PROV_KEY": "15",
        "DIST_NO": "03",
        "LLG_NO": "10",
        "WARD_NO": "01",
        "WARD_NAME": "AMAROMIN",
        "LATITUDE": -4.681837,
        "LONGITUDE": 141.565679,
        "REGHH": 14,
        "TOTPOP2000": 70,
        "MALE2000": 36,
        "FEMALE2000": 34,
        "POP2008": 86,
        "G_RATE": 1.0240000486373901,
        "Geocode_Num": 15031001001,
        "PROVINCE": 15
      }
    }
  ]
}