{
  "type": "FeatureCollection",
  "features": [
    {
      "type": "Feature",
      "id": 18770,
      "geometry": {
        "type": "Point",
        "coordinates": [
          141.67860199998233,
          -5.2022010001759895
        ]
      },
      "properties": {
        "OBJECTID": 18770,
        "CU_NAME": "KOBRENMIN",
        "CU_NO": "019",
        "GEOCODE": "15031019019",
        "PROV_KEY": "15",
        "DIST_NO": "03",
        "LLG_NO": "10",
        "WARD_NO": "19",
        "WARD_NAME": "KOBRENMIN",
        "LATITUDE": -5.203596,
        "LONGITUDE": 141.677513,
        "REGHH": 30,
        "TOTPOP2000": 220,
        "MALE2000": 123,
        "FEMALE2000": 97,
        "POP2008": 266,
        "G_RATE": 1.0240000486373901,
        "Geocode_Num": 15031019019,
        "PROVINCE": 15
      }
    },
    {
      "type": "Feature",
      "id": 18771,
      "geometry": {
        "type": "Point",
        "coordinates": [
          141.67118799982643,
          -5.19755700005544
        ]
      },
      "properties": {
        "OBJECTID": 18771,
        "CU_NAME": "OKSIMIN",
        "CU_NO": "025",
        "GEOCODE": "15031019025",
        "PROV_KEY": "15",
        "DIST_NO": "03",
        "LLG_NO": "10",
        "WARD_NO": "19",
        "WARD_NAME": "KOBRENMIN",
        "LATITUDE": -5.198952,
        "LONGITUDE": 141.670099,
        "REGHH": 25,
        "TOTPOP2000": 159,
        "MALE2000": 88,
        "FEMALE2000": 71,
        "POP2008": 191,
        "G_RATE": 1.0240000486373901,
        "Geocode_Num": 15031019025,
        "PROVINCE": 15
      }
    }
  ]
}