{
  "type": "FeatureCollection",
  "features": [
    {
      "type": "Feature",
      "id": 6782,
      "geometry": {
        "type": "Point",
        "coordinates": [
          143.17909900011887,
          -3.3674749995715274
        ]
      },
      "properties": {
        "OBJECTID": 6782,
        "CU_NAME": "BALAM",
        "CU_NO": "002",
        "GEOCODE": "14041421002",
        "PROV_KEY": "14",
        "DIST_NO": "04",
        "LLG_NO": "14",
        "WARD_NO": "21",
        "WARD_NAME": "KAUK/BALAM",
        "LATITUDE": -3.36905,
        "LONGITUDE": 143.177862,
        "REGHH": 66,
        "TOTPOP2000": 405,
        "MALE2000": 209,
        "FEMALE2000": 196,
        "POP2008": 482,
        "G_RATE": 1.0219999551773071,
        "Geocode_Num": 14041421002,
        "PROVINCE": 14
      }
    },
    {
      "type": "Feature",
      "id": 6783,
      "geometry": {
        "type": "Point",
        "coordinates": [
          143.14755000033233,
          -3.357175000325981
        ]
      },
      "properties": {
        "OBJECTID": 6783,
        "CU_NAME": "KAUK",
        "CU_NO": "012",
        "GEOCODE": "14041421012",
        "PROV_KEY": "14",
        "DIST_NO": "04",
        "LLG_NO": "14",
        "WARD_NO": "21",
        "WARD_NAME": "KAUK/BALAM",
        "LATITUDE": -3.357715,
        "LONGITUDE": 143.148701,
        "REGHH": 78,
        "TOTPOP2000": 511,
        "MALE2000": 262,
        "FEMALE2000": 249,
        "POP2008": 608,
        "G_RATE": 1.0219999551773071,
        "Geocode_Num": 14041421012,
        "PROVINCE": 14
      }
    },
    {
      "type": "Feature",
      "id": 6784,
      "geometry": {
        "type": "Point",
        "coordinates": [
          143.15896999996562,
          -3.369020999819213
        ]
      },
      "properties": {
        "OBJECTID": 6784,
        "CU_NAME": "GILIGAMOK",
        "CU_NO": "052",
        "GEOCODE": "14041421052",
        "PROV_KEY": "14",
        "DIST_NO": "04",
        "LLG_NO": "14",
        "WARD_NO": "21",
        "WARD_NAME": "KAUK/BALAM",
        "LATITUDE": -3.370596,
        "LONGITUDE": 143.157731,
        "REGHH": 6,
        "TOTPOP2000": 55,
        "MALE2000": 23,
        "FEMALE2000": 32,
        "POP2008": 63,
        "G_RATE": 1.0219999551773071,
        "Geocode_Num": 14041421052,
        "PROVINCE": 14
      }
    },
    {
      "type": "Feature",
      "id": 6785,
      "geometry": {
        "type": "Point",
        "coordinates": [
          143.16616199977648,
          -3.3653420001331256
        ]
      },
      "properties": {
        "OBJECTID": 6785,
        "CU_NAME": "BAI MISSION",
        "CU_NO": "402",
        "GEOCODE": "14041421402",
        "PROV_KEY": "14",
        "DIST_NO": "04",
        "LLG_NO": "14",
        "WARD_NO": "21",
        "WARD_NAME": "KAUK/BALAM",
        "LATITUDE": -3.366917,
        "LONGITUDE": 143.164923,
        "REGHH": 9,
        "TOTPOP2000": 52,
        "MALE2000": 27,
        "FEMALE2000": 25,
        "POP2008": 60,
        "G_RATE": 1.0219999551773071,
        "Geocode_Num": 14041421402,
        "PROVINCE": 14
      }
    }
  ]
}