{
  "type": "FeatureCollection",
  "features": [
    {
      "type": "Feature",
      "id": 6571,
      "geometry": {
        "type": "Point",
        "coordinates": [
          143.03242700010605,
          -3.622270999906675
        ]
      },
      "properties": {
        "OBJECTID": 6571,
        "CU_NAME": "JIKINUMBU",
        "CU_NO": "004",
        "GEOCODE": "14031002004",
        "PROV_KEY": "14",
        "DIST_NO": "03",
        "LLG_NO": "10",
        "WARD_NO": "02",
        "WARD_NAME": "KUKWAL",
        "LATITUDE": -3.623849,
        "LONGITUDE": 143.031186,
        "REGHH": 108,
        "TOTPOP2000": 465,
        "MALE2000": 240,
        "FEMALE2000": 225,
        "POP2008": 553,
        "G_RATE": 1.0219999551773071,
        "Geocode_Num": 14031002004,
        "PROVINCE": 14
      }
    },
    {
      "type": "Feature",
      "id": 6572,
      "geometry": {
        "type": "Point",
        "coordinates": [
          143.02790600026174,
          -3.602258999752962
        ]
      },
      "properties": {
        "OBJECTID": 6572,
        "CU_NAME": "KUKWAL",
        "CU_NO": "006",
        "GEOCODE": "14031002006",
        "PROV_KEY": "14",
        "DIST_NO": "03",
        "LLG_NO": "10",
        "WARD_NO": "02",
        "WARD_NAME": "KUKWAL",
        "LATITUDE": -3.603837,
        "LONGITUDE": 143.026665,
        "REGHH": 72,
        "TOTPOP2000": 376,
        "MALE2000": 200,
        "FEMALE2000": 176,
        "POP2008": 447,
        "G_RATE": 1.0219999551773071,
        "Geocode_Num": 14031002006,
        "PROVINCE": 14
      }
    }
  ]
}