{
  "type": "FeatureCollection",
  "features": [
    {
      "type": "Feature",
      "id": 6576,
      "geometry": {
        "type": "Point",
        "coordinates": [
          143.0387880002661,
          -3.6078929996621696
        ]
      },
      "properties": {
        "OBJECTID": 6576,
        "CU_NAME": "BONGIORA",
        "CU_NO": "003",
        "GEOCODE": "14031004003",
        "PROV_KEY": "14",
        "DIST_NO": "03",
        "LLG_NO": "10",
        "WARD_NO": "04",
        "WARD_NAME": "BONGIORA",
        "LATITUDE": -3.609471,
        "LONGITUDE": 143.037549,
        "REGHH": 79,
        "TOTPOP2000": 354,
        "MALE2000": 181,
        "FEMALE2000": 173,
        "POP2008": 421,
        "G_RATE": 1.0219999551773071,
        "Geocode_Num": 14031004003,
        "PROVINCE": 14
      }
    },
    {
      "type": "Feature",
      "id": 6577,
      "geometry": {
        "type": "Point",
        "coordinates": [
          143.03494900039607,
          -3.5950049997808833
        ]
      },
      "properties": {
        "OBJECTID": 6577,
        "CU_NAME": "WAMBAK",
        "CU_NO": "014",
        "GEOCODE": "14031004014",
        "PROV_KEY": "14",
        "DIST_NO": "03",
        "LLG_NO": "10",
        "WARD_NO": "04",
        "WARD_NAME": "BONGIORA",
        "LATITUDE": -3.596584,
        "LONGITUDE": 143.03371,
        "REGHH": 64,
        "TOTPOP2000": 291,
        "MALE2000": 153,
        "FEMALE2000": 138,
        "POP2008": 346,
        "G_RATE": 1.0219999551773071,
        "Geocode_Num": 14031004014,
        "PROVINCE": 14
      }
    }
  ]
}