{
  "type": "FeatureCollection",
  "features": [
    {
      "type": "Feature",
      "id": 10652,
      "geometry": {
        "type": "Point",
        "coordinates": [
          146.78291699991962,
          -7.380928999573598
        ]
      },
      "properties": {
        "OBJECTID": 10652,
        "CU_NAME": "BIAWEN VILLAGE",
        "CU_NO": "001",
        "GEOCODE": "12010513001",
        "PROV_KEY": "12",
        "DIST_NO": "01",
        "LLG_NO": "05",
        "WARD_NO": "13",
        "WARD_NAME": "BIAWEN",
        "LATITUDE": -7.379567,
        "LONGITUDE": 146.779445,
        "REGHH": 57,
        "TOTPOP2000": 415,
        "MALE2000": 223,
        "FEMALE2000": 192,
        "POP2008": 518,
        "G_RATE": 1.027999997138977,
        "Geocode_Num": 12010513001,
        "PROVINCE": 12
      }
    },
    {
      "type": "Feature",
      "id": 10653,
      "geometry": {
        "type": "Point",
        "coordinates": [
          146.77261299959036,
          -7.381131999941772
        ]
      },
      "properties": {
        "OBJECTID": 10653,
        "CU_NAME": "LAWING SETTLEMENT",
        "CU_NO": "401",
        "GEOCODE": "12010513401",
        "PROV_KEY": "12",
        "DIST_NO": "01",
        "LLG_NO": "05",
        "WARD_NO": "13",
        "WARD_NAME": "BIAWEN",
        "LATITUDE": -7.38256,
        "LONGITUDE": 146.771584,
        "REGHH": 4,
        "TOTPOP2000": 39,
        "MALE2000": 15,
        "FEMALE2000": 24,
        "POP2008": 47,
        "G_RATE": 1.027999997138977,
        "Geocode_Num": 12010513401,
        "PROVINCE": 12
      }
    }
  ]
}