{
  "type": "FeatureCollection",
  "features": [
    {
      "type": "Feature",
      "id": 9786,
      "geometry": {
        "type": "Point",
        "coordinates": [
          150.28896323306685,
          -10.723426182872004
        ]
      },
      "properties": {
        "OBJECTID": 9786,
        "CU_NAME": "BAIBAISIGA",
        "CU_NO": "003",
        "GEOCODE": "05010605003",
        "PROV_KEY": "05",
        "DIST_NO": "1",
        "LLG_NO": "06",
        "WARD_NO": "05",
        "WARD_NAME": "BAIBAISIGA",
        "LATITUDE": -10.723289,
        "LONGITUDE": 150.289372,
        "REGHH": 25,
        "TOTPOP2000": 147,
        "MALE2000": 81,
        "FEMALE2000": 66,
        "POP2008": 179,
        "G_RATE": 1.024999976158142,
        "Geocode_Num": 5010605003,
        "PROVINCE": 5
      }
    }
  ]
}