{
  "type": "FeatureCollection",
  "features": [
    {
      "type": "Feature",
      "id": 9794,
      "geometry": {
        "type": "Point",
        "coordinates": [
          150.16570215073375,
          -10.648298050314736
        ]
      },
      "properties": {
        "OBJECTID": 9794,
        "CU_NAME": "ISUAE",
        "CU_NO": "012",
        "GEOCODE": "05010611012",
        "PROV_KEY": "05",
        "DIST_NO": "1",
        "LLG_NO": "06",
        "WARD_NO": "11",
        "WARD_NAME": "ISUAE",
        "LATITUDE": -10.648466,
        "LONGITUDE": 150.164297,
        "REGHH": 34,
        "TOTPOP2000": 148,
        "MALE2000": 79,
        "FEMALE2000": 69,
        "POP2008": 180,
        "G_RATE": 1.024999976158142,
        "Geocode_Num": 5010611012,
        "PROVINCE": 5
      }
    }
  ]
}