{
  "type": "FeatureCollection",
  "features": [
    {
      "type": "Feature",
      "id": 9809,
      "geometry": {
        "type": "Point",
        "coordinates": [
          150.07181100007767,
          -10.519329999779643
        ]
      },
      "properties": {
        "OBJECTID": 9809,
        "CU_NAME": "LEILEIAFA",
        "CU_NO": "017",
        "GEOCODE": "05010624017",
        "PROV_KEY": "05",
        "DIST_NO": "1",
        "LLG_NO": "06",
        "WARD_NO": "24",
        "WARD_NAME": "LEILEIAFA",
        "LATITUDE": -10.525643,
        "LONGITUDE": 150.066598,
        "REGHH": 43,
        "TOTPOP2000": 256,
        "MALE2000": 144,
        "FEMALE2000": 112,
        "POP2008": 312,
        "G_RATE": 1.024999976158142,
        "Geocode_Num": 5010624017,
        "PROVINCE": 5
      }
    }
  ]
}