{
  "type": "FeatureCollection",
  "features": [
    {
      "type": "Feature",
      "id": 9811,
      "geometry": {
        "type": "Point",
        "coordinates": [
          149.7803869995604,
          -10.358936000096264
        ]
      },
      "properties": {
        "OBJECTID": 9811,
        "CU_NAME": "GADAISU",
        "CU_NO": "008",
        "GEOCODE": "05010626008",
        "PROV_KEY": "05",
        "DIST_NO": "1",
        "LLG_NO": "06",
        "WARD_NO": "26",
        "WARD_NAME": "GADAISU",
        "LATITUDE": -10.362239,
        "LONGITUDE": 149.7752,
        "REGHH": 40,
        "TOTPOP2000": 286,
        "MALE2000": 141,
        "FEMALE2000": 145,
        "POP2008": 348,
        "G_RATE": 1.024999976158142,
        "Geocode_Num": 5010626008,
        "PROVINCE": 5
      }
    },
    {
      "type": "Feature",
      "id": 9812,
      "geometry": {
        "type": "Point",
        "coordinates": [
          149.6790300001345,
          -10.339351999894859
        ]
      },
      "properties": {
        "OBJECTID": 9812,
        "CU_NAME": "GOGOSIBA",
        "CU_NO": "951",
        "GEOCODE": "05010626951",
        "PROV_KEY": "05",
        "DIST_NO": "01",
        "LLG_NO": "06",
        "WARD_NO": "26",
        "WARD_NAME": "GADAISU",
        "LATITUDE": -10.341942,
        "LONGITUDE": 149.679747,
        "REGHH": 27,
        "TOTPOP2000": 173,
        "MALE2000": 94,
        "FEMALE2000": 79,
        "POP2008": 211,
        "G_RATE": 1.024999976158142,
        "Geocode_Num": 5010626951,
        "PROVINCE": 5
      }
    }
  ]
}