{
  "type": "FeatureCollection",
  "features": [
    {
      "type": "Feature",
      "id": 9817,
      "geometry": {
        "type": "Point",
        "coordinates": [
          150.03480300035824,
          -10.323340999887193
        ]
      },
      "properties": {
        "OBJECTID": 9817,
        "CU_NAME": "TAKWATAKWAI",
        "CU_NO": "007",
        "GEOCODE": "05010629007",
        "PROV_KEY": "05",
        "DIST_NO": "1",
        "LLG_NO": "06",
        "WARD_NO": "29",
        "WARD_NAME": "TAKWATAKWAE",
        "LATITUDE": -10.322047,
        "LONGITUDE": 150.035422,
        "REGHH": 21,
        "TOTPOP2000": 125,
        "MALE2000": 62,
        "FEMALE2000": 63,
        "POP2008": 152,
        "G_RATE": 1.024999976158142,
        "Geocode_Num": 5010629007,
        "PROVINCE": 5
      }
    }
  ]
}