{
  "type": "FeatureCollection",
  "features": [
    {
      "type": "Feature",
      "id": 15114,
      "geometry": {
        "type": "Point",
        "coordinates": [
          142.74896399978877,
          -8.052219999853037
        ]
      },
      "properties": {
        "OBJECTID": 15114,
        "CU_NAME": "DADI",
        "CU_NO": "004",
        "GEOCODE": "01010309004",
        "PROV_KEY": "01",
        "DIST_NO": "01",
        "LLG_NO": "03",
        "WARD_NO": "09",
        "WARD_NAME": "DADI",
        "LATITUDE": -8.053644,
        "LONGITUDE": 142.747881,
        "REGHH": 95,
        "TOTPOP2000": 666,
        "MALE2000": 323,
        "FEMALE2000": 343,
        "POP2008": 864,
        "G_RATE": 1.0329999923706055,
        "Geocode_Num": 1010309004,
        "PROVINCE": 1
      }
    }
  ]
}