{
  "type": "FeatureCollection",
  "features": [
    {
      "type": "Feature",
      "id": 15157,
      "geometry": {
        "type": "Point",
        "coordinates": [
          143.39540799997928,
          -8.237634999555553
        ]
      },
      "properties": {
        "OBJECTID": 15157,
        "CU_NAME": "URIO",
        "CU_NO": "026",
        "GEOCODE": "01010334026",
        "PROV_KEY": "01",
        "DIST_NO": "01",
        "LLG_NO": "03",
        "WARD_NO": "34",
        "WARD_NAME": "URIO",
        "LATITUDE": -8.239063,
        "LONGITUDE": 143.394333,
        "REGHH": 51,
        "TOTPOP2000": 399,
        "MALE2000": 208,
        "FEMALE2000": 191,
        "POP2008": 519,
        "G_RATE": 1.0329999923706055,
        "Geocode_Num": 1010334026,
        "PROVINCE": 1
      }
    },
    {
      "type": "Feature",
      "id": 15158,
      "geometry": {
        "type": "Point",
        "coordinates": [
          143.38147899975615,
          -8.239238999779957
        ]
      },
      "properties": {
        "OBJECTID": 15158,
        "CU_NAME": "KENEDIBI",
        "CU_NO": "027",
        "GEOCODE": "01010334027",
        "PROV_KEY": "01",
        "DIST_NO": "01",
        "LLG_NO": "03",
        "WARD_NO": "34",
        "WARD_NAME": "URIO",
        "LATITUDE": -8.240667,
        "LONGITUDE": 143.380404,
        "REGHH": 52,
        "TOTPOP2000": 486,
        "MALE2000": 229,
        "FEMALE2000": 257,
        "POP2008": 631,
        "G_RATE": 1.0329999923706055,
        "Geocode_Num": 1010334027,
        "PROVINCE": 1
      }
    }
  ]
}