{
  "type": "FeatureCollection",
  "features": [
    {
      "type": "Feature",
      "id": 15159,
      "geometry": {
        "type": "Point",
        "coordinates": [
          143.01224700029888,
          -8.386606000366555
        ]
      },
      "properties": {
        "OBJECTID": 15159,
        "CU_NAME": "ADURU",
        "CU_NO": "001",
        "GEOCODE": "01010335001",
        "PROV_KEY": "01",
        "DIST_NO": "01",
        "LLG_NO": "03",
        "WARD_NO": "35",
        "WARD_NAME": "ADURU",
        "LATITUDE": -8.388034,
        "LONGITUDE": 143.011167,
        "REGHH": 48,
        "TOTPOP2000": 370,
        "MALE2000": 185,
        "FEMALE2000": 185,
        "POP2008": 479,
        "G_RATE": 1.0329999923706055,
        "Geocode_Num": 1010335001,
        "PROVINCE": 1
      }
    }
  ]
}