{
  "type": "FeatureCollection",
  "features": [
    {
      "type": "Feature",
      "id": 5197,
      "geometry": {
        "type": "Point",
        "coordinates": [
          143.55748299984066,
          -5.850481999644501
        ]
      },
      "properties": {
        "OBJECTID": 5197,
        "CU_NAME": "GINI",
        "CU_NO": "001",
        "GEOCODE": "08010106001",
        "PROV_KEY": "08",
        "DIST_NO": "01",
        "LLG_NO": "01",
        "WARD_NO": "06",
        "WARD_NAME": "GINI",
        "LATITUDE": -5.851887,
        "LONGITUDE": 143.556416,
        "REGHH": 94,
        "TOTPOP2000": 523,
        "MALE2000": 252,
        "FEMALE2000": 271,
        "POP2008": 659,
        "G_RATE": 1.0290000438690186,
        "Geocode_Num": 8010106001,
        "PROVINCE": 8
      }
    }
  ]
}