{
  "type": "FeatureCollection",
  "features": [
    {
      "type": "Feature",
      "id": 5223,
      "geometry": {
        "type": "Point",
        "coordinates": [
          143.46232600034466,
          -5.6392829998105185
        ]
      },
      "properties": {
        "OBJECTID": 5223,
        "CU_NAME": "WALUPIM",
        "CU_NO": "008",
        "GEOCODE": "08010119008",
        "PROV_KEY": "08",
        "DIST_NO": "01",
        "LLG_NO": "01",
        "WARD_NO": "19",
        "WARD_NAME": "WALUPIM NO.1",
        "LATITUDE": -5.6381,
        "LONGITUDE": 143.457786,
        "REGHH": 62,
        "TOTPOP2000": 324,
        "MALE2000": 168,
        "FEMALE2000": 156,
        "POP2008": 407,
        "G_RATE": 1.0290000438690186,
        "Geocode_Num": 8010119008,
        "PROVINCE": 8
      }
    },
    {
      "type": "Feature",
      "id": 5224,
      "geometry": {
        "type": "Point",
        "coordinates": [
          143.46231099965303,
          -5.635814999962236
        ]
      },
      "properties": {
        "OBJECTID": 5224,
        "CU_NAME": "ANDAKAM C/SCH & A/POST",
        "CU_NO": "401",
        "GEOCODE": "08010119401",
        "PROV_KEY": "08",
        "DIST_NO": "01",
        "LLG_NO": "01",
        "WARD_NO": "19",
        "WARD_NAME": "WALUPIM NO.1",
        "LATITUDE": -5.6381,
        "LONGITUDE": 143.457786,
        "REGHH": 1,
        "TOTPOP2000": 8,
        "MALE2000": 7,
        "FEMALE2000": 1,
        "POP2008": 8,
        "G_RATE": 1.0290000438690186,
        "Geocode_Num": 8010119401,
        "PROVINCE": 8
      }
    }
  ]
}