{
  "type": "FeatureCollection",
  "features": [
    {
      "type": "Feature",
      "id": 9542,
      "geometry": {
        "type": "Point",
        "coordinates": [
          147.7890429998347,
          -2.2977989999238844
        ]
      },
      "properties": {
        "OBJECTID": 9542,
        "CU_NAME": "KULOU",
        "CU_NO": "002",
        "GEOCODE": "16011206002",
        "PROV_KEY": "16",
        "DIST_NO": "01",
        "LLG_NO": "12",
        "WARD_NO": "06",
        "WARD_NAME": "KULUO",
        "LATITUDE": -2.299168,
        "LONGITUDE": 147.788036,
        "REGHH": 35,
        "TOTPOP2000": 232,
        "MALE2000": 116,
        "FEMALE2000": 116,
        "POP2008": 285,
        "G_RATE": 1.0260000228881836,
        "Geocode_Num": 16011206002,
        "PROVINCE": 16
      }
    },
    {
      "type": "Feature",
      "id": 9543,
      "geometry": {
        "type": "Point",
        "coordinates": [
          147.77858499959814,
          -2.325400000209811
        ]
      },
      "properties": {
        "OBJECTID": 9543,
        "CU_NAME": "PANISELU",
        "CU_NO": "010",
        "GEOCODE": "16011206010",
        "PROV_KEY": "16",
        "DIST_NO": "01",
        "LLG_NO": "12",
        "WARD_NO": "06",
        "WARD_NAME": "KULUO",
        "LATITUDE": -2.325794,
        "LONGITUDE": 147.77596,
        "REGHH": 45,
        "TOTPOP2000": 299,
        "MALE2000": 149,
        "FEMALE2000": 150,
        "POP2008": 367,
        "G_RATE": 1.0260000228881836,
        "Geocode_Num": 16011206010,
        "PROVINCE": 16
      }
    },
    {
      "type": "Feature",
      "id": 9544,
      "geometry": {
        "type": "Point",
        "coordinates": [
          147.77895200033458,
          -2.3193530001407794
        ]
      },
      "properties": {
        "OBJECTID": 9544,
        "CU_NAME": "KUP LOCAL LEVEL GOVT. STN",
        "CU_NO": "501",
        "GEOCODE": "16011206501",
        "PROV_KEY": "16",
        "DIST_NO": "01",
        "LLG_NO": "12",
        "WARD_NO": "06",
        "WARD_NAME": "KULUO",
        "LATITUDE": -2.325606,
        "LONGITUDE": 147.777624,
        "REGHH": 4,
        "TOTPOP2000": 21,
        "MALE2000": 10,
        "FEMALE2000": 11,
        "POP2008": 29,
        "G_RATE": 1.0260000228881836,
        "Geocode_Num": 16011206501,
        "PROVINCE": 16
      }
    }
  ]
}