{
  "type": "FeatureCollection",
  "features": [
    {
      "type": "Feature",
      "id": 19728,
      "geometry": {
        "type": "Point",
        "coordinates": [
          143.6610230001114,
          -6.206769000189183
        ]
      },
      "properties": {
        "OBJECTID": 19728,
        "CU_NAME": "YAKEN 1",
        "CU_NO": "003",
        "GEOCODE": "07020722003",
        "PROV_KEY": "07",
        "DIST_NO": "02",
        "LLG_NO": "07",
        "WARD_NO": "22",
        "WARD_NAME": "YAKEN 1",
        "LATITUDE": -6.210666,
        "LONGITUDE": 143.666394,
        "REGHH": 21,
        "TOTPOP2000": 124,
        "MALE2000": 62,
        "FEMALE2000": 62,
        "POP2008": 172,
        "G_RATE": 1.0420000553131104,
        "Geocode_Num": 7020722003,
        "PROVINCE": 7
      }
    },
    {
      "type": "Feature",
      "id": 19729,
      "geometry": {
        "type": "Point",
        "coordinates": [
          143.6643260004446,
          -6.208475999767529
        ]
      },
      "properties": {
        "OBJECTID": 19729,
        "CU_NAME": "EMARU",
        "CU_NO": "004",
        "GEOCODE": "07020722004",
        "PROV_KEY": "07",
        "DIST_NO": "02",
        "LLG_NO": "07",
        "WARD_NO": "22",
        "WARD_NAME": "YAKEN 1",
        "LATITUDE": -6.210666,
        "LONGITUDE": 143.666394,
        "REGHH": 16,
        "TOTPOP2000": 97,
        "MALE2000": 48,
        "FEMALE2000": 49,
        "POP2008": 134,
        "G_RATE": 1.0420000553131104,
        "Geocode_Num": 7020722004,
        "PROVINCE": 7
      }
    },
    {
      "type": "Feature",
      "id": 19730,
      "geometry": {
        "type": "Point",
        "coordinates": [
          143.6682479996456,
          -6.206905000165591
        ]
      },
      "properties": {
        "OBJECTID": 19730,
        "CU_NAME": "YAKEN COMM. SCH",
        "CU_NO": "005",
        "GEOCODE": "07020722005",
        "PROV_KEY": "07",
        "DIST_NO": "02",
        "LLG_NO": "07",
        "WARD_NO": "22",
        "WARD_NAME": "YAKEN 1",
        "LATITUDE": -6.210666,
        "LONGITUDE": 143.666394,
        "REGHH": 3,
        "TOTPOP2000": 15,
        "MALE2000": 10,
        "FEMALE2000": 5,
        "POP2008": 23,
        "G_RATE": 1.0420000553131104,
        "Geocode_Num": 7020722005,
        "PROVINCE": 7
      }
    },
    {
      "type": "Feature",
      "id": 19731,
      "geometry": {
        "type": "Point",
        "coordinates": [
          143.66476299991257,
          -6.205445000286488
        ]
      },
      "properties": {
        "OBJECTID": 19731,
        "CU_NAME": "REKISEMBA",
        "CU_NO": "006",
        "GEOCODE": "07020722006",
        "PROV_KEY": "07",
        "DIST_NO": "02",
        "LLG_NO": "07",
        "WARD_NO": "22",
        "WARD_NAME": "YAKEN 1",
        "LATITUDE": -6.210666,
        "LONGITUDE": 143.666394,
        "REGHH": 11,
        "TOTPOP2000": 54,
        "MALE2000": 26,
        "FEMALE2000": 28,
        "POP2008": 75,
        "G_RATE": 1.0420000553131104,
        "Geocode_Num": 7020722006,
        "PROVINCE": 7
      }
    }
  ]
}