{
  "type": "FeatureCollection",
  "features": [
    {
      "type": "Feature",
      "id": 14570,
      "geometry": {
        "type": "Point",
        "coordinates": [
          144.80746600015584,
          -5.996593999913102
        ]
      },
      "properties": {
        "OBJECTID": 14570,
        "CU_NAME": "MURU 1",
        "CU_NO": "004",
        "GEOCODE": "10041204004",
        "PROV_KEY": "10",
        "DIST_NO": "04",
        "LLG_NO": "12",
        "WARD_NO": "04",
        "WARD_NAME": "KUMA DEINGEKU",
        "LATITUDE": -5.998003,
        "LONGITUDE": 144.806414,
        "REGHH": 86,
        "TOTPOP2000": 400,
        "MALE2000": 221,
        "FEMALE2000": 179,
        "POP2008": 461,
        "G_RATE": 1.0180000066757202,
        "Geocode_Num": 10041204004,
        "PROVINCE": 10
      }
    },
    {
      "type": "Feature",
      "id": 14571,
      "geometry": {
        "type": "Point",
        "coordinates": [
          144.8076820002242,
          -5.998669000274106
        ]
      },
      "properties": {
        "OBJECTID": 14571,
        "CU_NAME": "MURU C/SCH",
        "CU_NO": "401",
        "GEOCODE": "10041204401",
        "PROV_KEY": "10",
        "DIST_NO": "04",
        "LLG_NO": "12",
        "WARD_NO": "04",
        "WARD_NAME": "KUMA DEINGEKU",
        "LATITUDE": -6.000078,
        "LONGITUDE": 144.80663,
        "REGHH": 33,
        "TOTPOP2000": 180,
        "MALE2000": 95,
        "FEMALE2000": 85,
        "POP2008": 207,
        "G_RATE": 1.0180000066757202,
        "Geocode_Num": 10041204401,
        "PROVINCE": 10
      }
    }
  ]
}