{
  "type": "FeatureCollection",
  "features": [
    {
      "type": "Feature",
      "id": 6413,
      "geometry": {
        "type": "Point",
        "coordinates": [
          144.09111800039545,
          -4.5477240000624874
        ]
      },
      "properties": {
        "OBJECTID": 6413,
        "CU_NAME": "BUTEN",
        "CU_NO": "003",
        "GEOCODE": "14020709003",
        "PROV_KEY": "14",
        "DIST_NO": "02",
        "LLG_NO": "07",
        "WARD_NO": "09",
        "WARD_NAME": "BUTEN",
        "LATITUDE": -4.56159,
        "LONGITUDE": 144.08181,
        "REGHH": 54,
        "TOTPOP2000": 311,
        "MALE2000": 158,
        "FEMALE2000": 153,
        "POP2008": 370,
        "G_RATE": 1.0219999551773071,
        "Geocode_Num": 14020709003,
        "PROVINCE": 14
      }
    },
    {
      "type": "Feature",
      "id": 6414,
      "geometry": {
        "type": "Point",
        "coordinates": [
          144.07518500038748,
          -4.581467000301757
        ]
      },
      "properties": {
        "OBJECTID": 6414,
        "CU_NAME": "MUNYITEN",
        "CU_NO": "014",
        "GEOCODE": "14020709014",
        "PROV_KEY": "14",
        "DIST_NO": "02",
        "LLG_NO": "07",
        "WARD_NO": "09",
        "WARD_NAME": "BUTEN",
        "LATITUDE": -4.57846,
        "LONGITUDE": 144.075696,
        "REGHH": 24,
        "TOTPOP2000": 196,
        "MALE2000": 114,
        "FEMALE2000": 82,
        "POP2008": 233,
        "G_RATE": 1.0219999551773071,
        "Geocode_Num": 14020709014,
        "PROVINCE": 14
      }
    },
    {
      "type": "Feature",
      "id": 6415,
      "geometry": {
        "type": "Point",
        "coordinates": [
          144.00994500006175,
          -4.597286999595326
        ]
      },
      "properties": {
        "OBJECTID": 6415,
        "CU_NAME": "WORE",
        "CU_NO": "022",
        "GEOCODE": "14020709022",
        "PROV_KEY": "14",
        "DIST_NO": "02",
        "LLG_NO": "07",
        "WARD_NO": "09",
        "WARD_NAME": "BUTEN",
        "LATITUDE": -4.598342,
        "LONGITUDE": 144.012001,
        "REGHH": 17,
        "TOTPOP2000": 82,
        "MALE2000": 46,
        "FEMALE2000": 36,
        "POP2008": 98,
        "G_RATE": 1.0219999551773071,
        "Geocode_Num": 14020709022,
        "PROVINCE": 14
      }
    }
  ]
}