{
  "type": "FeatureCollection",
  "features": [
    {
      "type": "Feature",
      "id": 6463,
      "geometry": {
        "type": "Point",
        "coordinates": [
          144.0761370002225,
          -4.349264000433209
        ]
      },
      "properties": {
        "OBJECTID": 6463,
        "CU_NAME": "PANITEN",
        "CU_NO": "017",
        "GEOCODE": "14020736017",
        "PROV_KEY": "14",
        "DIST_NO": "02",
        "LLG_NO": "07",
        "WARD_NO": "36",
        "WARD_NAME": "PANITEN",
        "LATITUDE": -4.350851,
        "LONGITUDE": 144.074911,
        "REGHH": 65,
        "TOTPOP2000": 401,
        "MALE2000": 215,
        "FEMALE2000": 186,
        "POP2008": 477,
        "G_RATE": 1.0219999551773071,
        "Geocode_Num": 14020736017,
        "PROVINCE": 14
      }
    }
  ]
}