{
  "type": "FeatureCollection",
  "features": [
    {
      "type": "Feature",
      "id": 21778,
      "geometry": {
        "type": "Point",
        "coordinates": [
          142.92014699968433,
          -5.893154999803357
        ]
      },
      "properties": {
        "OBJECTID": 21778,
        "CU_NAME": "PERI",
        "CU_NO": "001",
        "GEOCODE": "07082708001",
        "PROV_KEY": "21",
        "DIST_NO": "3",
        "LLG_NO": "27",
        "WARD_NO": "08",
        "WARD_NAME": "PERI",
        "LATITUDE": -5.897388,
        "LONGITUDE": 142.923451,
        "REGHH": 140,
        "TOTPOP2000": 677,
        "MALE2000": 381,
        "FEMALE2000": 296,
        "POP2008": 941,
        "G_RATE": 1.0420000553131104,
        "Geocode_Num": 7082708001,
        "PROVINCE": 21
      }
    }
  ]
}