{
  "type": "FeatureCollection",
  "features": [
    {
      "type": "Feature",
      "id": 4549,
      "geometry": {
        "type": "Point",
        "coordinates": [
          151.75145400040185,
          -4.243467000401722
        ]
      },
      "properties": {
        "OBJECTID": 4549,
        "CU_NAME": "LAUN",
        "CU_NO": "009",
        "GEOCODE": "18010313009",
        "PROV_KEY": "18",
        "DIST_NO": "01",
        "LLG_NO": "03",
        "WARD_NO": "13",
        "WARD_NAME": "LAUN",
        "LATITUDE": -4.244866,
        "LONGITUDE": 151.750502,
        "REGHH": 52,
        "TOTPOP2000": 285,
        "MALE2000": 142,
        "FEMALE2000": 143,
        "POP2008": 346,
        "G_RATE": 1.024999976158142,
        "Geocode_Num": 18010313009,
        "PROVINCE": 18
      }
    }
  ]
}