{
  "type": "FeatureCollection",
  "features": [
    {
      "type": "Feature",
      "id": 4563,
      "geometry": {
        "type": "Point",
        "coordinates": [
          151.791580000017,
          -4.246558999997831
        ]
      },
      "properties": {
        "OBJECTID": 4563,
        "CU_NAME": "MOBISBERG PLANTATION",
        "CU_NO": "546",
        "GEOCODE": "18010322546",
        "PROV_KEY": "18",
        "DIST_NO": "01",
        "LLG_NO": "03",
        "WARD_NO": "22",
        "WARD_NAME": "MOBISBERG PLANTATION",
        "LATITUDE": -4.247958,
        "LONGITUDE": 151.790628,
        "REGHH": 10,
        "TOTPOP2000": 39,
        "MALE2000": 23,
        "FEMALE2000": 16,
        "POP2008": 47,
        "G_RATE": 1.024999976158142,
        "Geocode_Num": 18010322546,
        "PROVINCE": 18
      }
    },
    {
      "type": "Feature",
      "id": 4564,
      "geometry": {
        "type": "Point",
        "coordinates": [
          151.77367900008585,
          -4.244603999774711
        ]
      },
      "properties": {
        "OBJECTID": 4564,
        "CU_NAME": "KIPKA",
        "CU_NO": "547",
        "GEOCODE": "18010322547",
        "PROV_KEY": "18",
        "DIST_NO": "01",
        "LLG_NO": "03",
        "WARD_NO": "22",
        "WARD_NAME": "MOBISBERG PLANTATION",
        "LATITUDE": -4.246003,
        "LONGITUDE": 151.772727,
        "REGHH": 41,
        "TOTPOP2000": 267,
        "MALE2000": 142,
        "FEMALE2000": 125,
        "POP2008": 326,
        "G_RATE": 1.024999976158142,
        "Geocode_Num": 18010322547,
        "PROVINCE": 18
      }
    }
  ]
}