{
  "type": "FeatureCollection",
  "features": [
    {
      "type": "Feature",
      "id": 7270,
      "geometry": {
        "type": "Point",
        "coordinates": [
          143.3803390002447,
          -3.693450999863728
        ]
      },
      "properties": {
        "OBJECTID": 7270,
        "CU_NAME": "NYAGANDOGUM 1",
        "CU_NO": "013",
        "GEOCODE": "14062405013",
        "PROV_KEY": "14",
        "DIST_NO": "06",
        "LLG_NO": "24",
        "WARD_NO": "05",
        "WARD_NAME": "NYAGANDOGUM",
        "LATITUDE": -3.69503,
        "LONGITUDE": 143.379104,
        "REGHH": 20,
        "TOTPOP2000": 94,
        "MALE2000": 45,
        "FEMALE2000": 49,
        "POP2008": 110,
        "G_RATE": 1.0219999551773071,
        "Geocode_Num": 14062405013,
        "PROVINCE": 14
      }
    },
    {
      "type": "Feature",
      "id": 7271,
      "geometry": {
        "type": "Point",
        "coordinates": [
          143.38373799960902,
          -3.691365999940899
        ]
      },
      "properties": {
        "OBJECTID": 7271,
        "CU_NAME": "NYAGANDOGUM 2",
        "CU_NO": "014",
        "GEOCODE": "14062405014",
        "PROV_KEY": "14",
        "DIST_NO": "06",
        "LLG_NO": "24",
        "WARD_NO": "05",
        "WARD_NAME": "NYAGANDOGUM",
        "LATITUDE": -3.692945,
        "LONGITUDE": 143.382503,
        "REGHH": 67,
        "TOTPOP2000": 343,
        "MALE2000": 164,
        "FEMALE2000": 179,
        "POP2008": 409,
        "G_RATE": 1.0219999551773071,
        "Geocode_Num": 14062405014,
        "PROVINCE": 14
      }
    },
    {
      "type": "Feature",
      "id": 7272,
      "geometry": {
        "type": "Point",
        "coordinates": [
          143.37515799964206,
          -3.6934210002788745
        ]
      },
      "properties": {
        "OBJECTID": 7272,
        "CU_NAME": "NYAGANDOGUM 3",
        "CU_NO": "015",
        "GEOCODE": "14062405015",
        "PROV_KEY": "14",
        "DIST_NO": "06",
        "LLG_NO": "24",
        "WARD_NO": "05",
        "WARD_NAME": "NYAGANDOGUM",
        "LATITUDE": -3.695,
        "LONGITUDE": 143.373923,
        "REGHH": 26,
        "TOTPOP2000": 146,
        "MALE2000": 78,
        "FEMALE2000": 68,
        "POP2008": 173,
        "G_RATE": 1.0219999551773071,
        "Geocode_Num": 14062405015,
        "PROVINCE": 14
      }
    }
  ]
}