{
  "type": "FeatureCollection",
  "features": [
    {
      "type": "Feature",
      "id": 7274,
      "geometry": {
        "type": "Point",
        "coordinates": [
          143.41707500001132,
          -3.692442000098197
        ]
      },
      "properties": {
        "OBJECTID": 7274,
        "CU_NAME": "NIAHOMBI",
        "CU_NO": "011",
        "GEOCODE": "14062407011",
        "PROV_KEY": "14",
        "DIST_NO": "06",
        "LLG_NO": "24",
        "WARD_NO": "07",
        "WARD_NAME": "NIAHOMBI",
        "LATITUDE": -3.694021,
        "LONGITUDE": 143.41584,
        "REGHH": 62,
        "TOTPOP2000": 305,
        "MALE2000": 167,
        "FEMALE2000": 138,
        "POP2008": 363,
        "G_RATE": 1.0219999551773071,
        "Geocode_Num": 14062407011,
        "PROVINCE": 14
      }
    }
  ]
}