{
  "type": "FeatureCollection",
  "features": [
    {
      "type": "Feature",
      "id": 7288,
      "geometry": {
        "type": "Point",
        "coordinates": [
          143.498250999584,
          -3.721291000379324
        ]
      },
      "properties": {
        "OBJECTID": 7288,
        "CU_NAME": "NANGUMARUM",
        "CU_NO": "020",
        "GEOCODE": "14062415020",
        "PROV_KEY": "14",
        "DIST_NO": "06",
        "LLG_NO": "24",
        "WARD_NO": "15",
        "WARD_NAME": "NANGUMARUM",
        "LATITUDE": -3.722872,
        "LONGITUDE": 143.497017,
        "REGHH": 110,
        "TOTPOP2000": 567,
        "MALE2000": 276,
        "FEMALE2000": 291,
        "POP2008": 675,
        "G_RATE": 1.0219999551773071,
        "Geocode_Num": 14062415020,
        "PROVINCE": 14
      }
    }
  ]
}