{
  "type": "FeatureCollection",
  "features": [
    {
      "type": "Feature",
      "id": 7298,
      "geometry": {
        "type": "Point",
        "coordinates": [
          143.4773139999412,
          -3.665255000018192
        ]
      },
      "properties": {
        "OBJECTID": 7298,
        "CU_NAME": "HUARIPOGUM",
        "CU_NO": "009",
        "GEOCODE": "14062420009",
        "PROV_KEY": "14",
        "DIST_NO": "06",
        "LLG_NO": "24",
        "WARD_NO": "20",
        "WARD_NAME": "HUARIPOGUM",
        "LATITUDE": -3.66332,
        "LONGITUDE": 143.477568,
        "REGHH": 46,
        "TOTPOP2000": 248,
        "MALE2000": 115,
        "FEMALE2000": 133,
        "POP2008": 295,
        "G_RATE": 1.0219999551773071,
        "Geocode_Num": 14062420009,
        "PROVINCE": 14
      }
    },
    {
      "type": "Feature",
      "id": 7299,
      "geometry": {
        "type": "Point",
        "coordinates": [
          143.45586700016202,
          -3.655137000172374
        ]
      },
      "properties": {
        "OBJECTID": 7299,
        "CU_NAME": "KOIRUO",
        "CU_NO": "017",
        "GEOCODE": "14062420017",
        "PROV_KEY": "14",
        "DIST_NO": "06",
        "LLG_NO": "24",
        "WARD_NO": "20",
        "WARD_NAME": "HUARIPOGUM",
        "LATITUDE": -3.656716,
        "LONGITUDE": 143.454633,
        "REGHH": 45,
        "TOTPOP2000": 197,
        "MALE2000": 103,
        "FEMALE2000": 94,
        "POP2008": 235,
        "G_RATE": 1.0219999551773071,
        "Geocode_Num": 14062420017,
        "PROVINCE": 14
      }
    }
  ]
}