{
  "type": "FeatureCollection",
  "features": [
    {
      "type": "Feature",
      "id": 14150,
      "geometry": {
        "type": "Point",
        "coordinates": [
          144.89385299991613,
          -6.060165999761011
        ]
      },
      "properties": {
        "OBJECTID": 14150,
        "CU_NAME": "GORMA",
        "CU_NO": "001",
        "GEOCODE": "10020601001",
        "PROV_KEY": "10",
        "DIST_NO": "02",
        "LLG_NO": "06",
        "WARD_NO": "01",
        "WARD_NAME": "GORMA",
        "LATITUDE": -6.061576,
        "LONGITUDE": 144.892802,
        "REGHH": 71,
        "TOTPOP2000": 317,
        "MALE2000": 164,
        "FEMALE2000": 153,
        "POP2008": 365,
        "G_RATE": 1.0180000066757202,
        "Geocode_Num": 10020601001,
        "PROVINCE": 10
      }
    }
  ]
}