{
  "type": "FeatureCollection",
  "features": [
    {
      "type": "Feature",
      "id": 14162,
      "geometry": {
        "type": "Point",
        "coordinates": [
          144.91208399977688,
          -6.056239000329526
        ]
      },
      "properties": {
        "OBJECTID": 14162,
        "CU_NAME": "YOPAPIAU",
        "CU_NO": "009",
        "GEOCODE": "10020605009",
        "PROV_KEY": "10",
        "DIST_NO": "02",
        "LLG_NO": "06",
        "WARD_NO": "05",
        "WARD_NAME": "SIPAGUL",
        "LATITUDE": -6.057649,
        "LONGITUDE": 144.911033,
        "REGHH": 48,
        "TOTPOP2000": 230,
        "MALE2000": 115,
        "FEMALE2000": 115,
        "POP2008": 265,
        "G_RATE": 1.0180000066757202,
        "Geocode_Num": 10020605009,
        "PROVINCE": 10
      }
    },
    {
      "type": "Feature",
      "id": 14163,
      "geometry": {
        "type": "Point",
        "coordinates": [
          144.91545499964855,
          -6.045442999794545
        ]
      },
      "properties": {
        "OBJECTID": 14163,
        "CU_NAME": "SIULTOPIL YORUA",
        "CU_NO": "010",
        "GEOCODE": "10020605010",
        "PROV_KEY": "10",
        "DIST_NO": "02",
        "LLG_NO": "06",
        "WARD_NO": "05",
        "WARD_NAME": "SIPAGUL",
        "LATITUDE": -6.046853,
        "LONGITUDE": 144.914404,
        "REGHH": 63,
        "TOTPOP2000": 383,
        "MALE2000": 194,
        "FEMALE2000": 189,
        "POP2008": 442,
        "G_RATE": 1.0180000066757202,
        "Geocode_Num": 10020605010,
        "PROVINCE": 10
      }
    },
    {
      "type": "Feature",
      "id": 14164,
      "geometry": {
        "type": "Point",
        "coordinates": [
          144.911395000379,
          -6.048697999712886
        ]
      },
      "properties": {
        "OBJECTID": 14164,
        "CU_NAME": "KUMNULO",
        "CU_NO": "011",
        "GEOCODE": "10020605011",
        "PROV_KEY": "10",
        "DIST_NO": "02",
        "LLG_NO": "06",
        "WARD_NO": "05",
        "WARD_NAME": "SIPAGUL",
        "LATITUDE": -6.050108,
        "LONGITUDE": 144.910344,
        "REGHH": 102,
        "TOTPOP2000": 446,
        "MALE2000": 243,
        "FEMALE2000": 203,
        "POP2008": 514,
        "G_RATE": 1.0180000066757202,
        "Geocode_Num": 10020605011,
        "PROVINCE": 10
      }
    },
    {
      "type": "Feature",
      "id": 14165,
      "geometry": {
        "type": "Point",
        "coordinates": [
          144.92258800033596,
          -6.039532999748076
        ]
      },
      "properties": {
        "OBJECTID": 14165,
        "CU_NAME": "KOLAKUI",
        "CU_NO": "012",
        "GEOCODE": "10020605012",
        "PROV_KEY": "10",
        "DIST_NO": "02",
        "LLG_NO": "06",
        "WARD_NO": "05",
        "WARD_NAME": "SIPAGUL",
        "LATITUDE": -6.040943,
        "LONGITUDE": 144.921538,
        "REGHH": 48,
        "TOTPOP2000": 224,
        "MALE2000": 108,
        "FEMALE2000": 116,
        "POP2008": 257,
        "G_RATE": 1.0180000066757202,
        "Geocode_Num": 10020605012,
        "PROVINCE": 10
      }
    }
  ]
}