{
  "type": "FeatureCollection",
  "features": [
    {
      "type": "Feature",
      "id": 9367,
      "geometry": {
        "type": "Point",
        "coordinates": [
          146.5108520000199,
          -2.1639670002767843
        ]
      },
      "properties": {
        "OBJECTID": 9367,
        "CU_NAME": "SALIEN",
        "CU_NO": "006",
        "GEOCODE": "16010301006",
        "PROV_KEY": "16",
        "DIST_NO": "01",
        "LLG_NO": "03",
        "WARD_NO": "01",
        "WARD_NAME": "SALIEN",
        "LATITUDE": -2.164126,
        "LONGITUDE": 146.507442,
        "REGHH": 84,
        "TOTPOP2000": 427,
        "MALE2000": 219,
        "FEMALE2000": 208,
        "POP2008": 524,
        "G_RATE": 1.0260000228881836,
        "Geocode_Num": 16010301006,
        "PROVINCE": 16
      }
    },
    {
      "type": "Feature",
      "id": 9368,
      "geometry": {
        "type": "Point",
        "coordinates": [
          146.5428600002889,
          -2.1287179998357715
        ]
      },
      "properties": {
        "OBJECTID": 9368,
        "CU_NAME": "SALI-IN GOVENRMENT STN",
        "CU_NO": "501",
        "GEOCODE": "16010301501",
        "PROV_KEY": "16",
        "DIST_NO": "01",
        "LLG_NO": "03",
        "WARD_NO": "01",
        "WARD_NAME": "SALIEN",
        "LATITUDE": -2.130084,
        "LONGITUDE": 146.544437,
        "REGHH": 4,
        "TOTPOP2000": 24,
        "MALE2000": 10,
        "FEMALE2000": 14,
        "POP2008": 32,
        "G_RATE": 1.0260000228881836,
        "Geocode_Num": 16010301501,
        "PROVINCE": 16
      }
    }
  ]
}