{
  "type": "FeatureCollection",
  "features": [
    {
      "type": "Feature",
      "id": 9376,
      "geometry": {
        "type": "Point",
        "coordinates": [
          146.5850630003572,
          -1.9566759998974135
        ]
      },
      "properties": {
        "OBJECTID": 9376,
        "CU_NAME": "HARENGAN",
        "CU_NO": "001",
        "GEOCODE": "16010308001",
        "PROV_KEY": "16",
        "DIST_NO": "01",
        "LLG_NO": "03",
        "WARD_NO": "08",
        "WARD_NAME": "HARENGAN",
        "LATITUDE": -1.960157,
        "LONGITUDE": 146.58404,
        "REGHH": 51,
        "TOTPOP2000": 229,
        "MALE2000": 106,
        "FEMALE2000": 123,
        "POP2008": 281,
        "G_RATE": 1.0260000228881836,
        "Geocode_Num": 16010308001,
        "PROVINCE": 16
      }
    }
  ]
}