{
  "type": "FeatureCollection",
  "features": [
    {
      "type": "Feature",
      "id": 9381,
      "geometry": {
        "type": "Point",
        "coordinates": [
          146.68254700014404,
          -1.9827449996819269
        ]
      },
      "properties": {
        "OBJECTID": 9381,
        "CU_NAME": "SORI 2",
        "CU_NO": "009",
        "GEOCODE": "16010313009",
        "PROV_KEY": "16",
        "DIST_NO": "01",
        "LLG_NO": "03",
        "WARD_NO": "13",
        "WARD_NAME": "SORI 2",
        "LATITUDE": -1.983566,
        "LONGITUDE": 146.681525,
        "REGHH": 29,
        "TOTPOP2000": 142,
        "MALE2000": 75,
        "FEMALE2000": 67,
        "POP2008": 174,
        "G_RATE": 1.0260000228881836,
        "Geocode_Num": 16010313009,
        "PROVINCE": 16
      }
    }
  ]
}