{
  "type": "FeatureCollection",
  "features": [
    {
      "type": "Feature",
      "id": 19817,
      "geometry": {
        "type": "Point",
        "coordinates": [
          144.29657599988252,
          -6.721694000377795
        ]
      },
      "properties": {
        "OBJECTID": 19817,
        "CU_NAME": "BOLO",
        "CU_NO": "002",
        "GEOCODE": "07030815002",
        "PROV_KEY": "07",
        "DIST_NO": "03",
        "LLG_NO": "08",
        "WARD_NO": "15",
        "WARD_NAME": "PUPUTAU",
        "LATITUDE": -6.725942,
        "LONGITUDE": 144.296865,
        "REGHH": 16,
        "TOTPOP2000": 84,
        "MALE2000": 44,
        "FEMALE2000": 40,
        "POP2008": 118,
        "G_RATE": 1.0420000553131104,
        "Geocode_Num": 7030815002,
        "PROVINCE": 7
      }
    },
    {
      "type": "Feature",
      "id": 19818,
      "geometry": {
        "type": "Point",
        "coordinates": [
          144.30156499972497,
          -6.7304189998369
        ]
      },
      "properties": {
        "OBJECTID": 19818,
        "CU_NAME": "PUPUTAU",
        "CU_NO": "007",
        "GEOCODE": "07030815007",
        "PROV_KEY": "07",
        "DIST_NO": "03",
        "LLG_NO": "08",
        "WARD_NO": "15",
        "WARD_NAME": "PUPUTAU",
        "LATITUDE": -6.725942,
        "LONGITUDE": 144.296865,
        "REGHH": 75,
        "TOTPOP2000": 428,
        "MALE2000": 208,
        "FEMALE2000": 220,
        "POP2008": 595,
        "G_RATE": 1.0420000553131104,
        "Geocode_Num": 7030815007,
        "PROVINCE": 7
      }
    }
  ]
}