{
  "type": "FeatureCollection",
  "features": [
    {
      "type": "Feature",
      "id": 19832,
      "geometry": {
        "type": "Point",
        "coordinates": [
          144.00651400012111,
          -6.708950999988588
        ]
      },
      "properties": {
        "OBJECTID": 19832,
        "CU_NAME": "BESAPULU",
        "CU_NO": "001",
        "GEOCODE": "07030821001",
        "PROV_KEY": "07",
        "DIST_NO": "03",
        "LLG_NO": "08",
        "WARD_NO": "21",
        "WARD_NAME": "YANGULI 1",
        "LATITUDE": -6.711785,
        "LONGITUDE": 144.007872,
        "REGHH": 41,
        "TOTPOP2000": 227,
        "MALE2000": 106,
        "FEMALE2000": 121,
        "POP2008": 316,
        "G_RATE": 1.0420000553131104,
        "Geocode_Num": 7030821001,
        "PROVINCE": 7
      }
    },
    {
      "type": "Feature",
      "id": 19833,
      "geometry": {
        "type": "Point",
        "coordinates": [
          144.01456700006702,
          -6.706417000044496
        ]
      },
      "properties": {
        "OBJECTID": 19833,
        "CU_NAME": "TOUAREKE",
        "CU_NO": "002",
        "GEOCODE": "07030821002",
        "PROV_KEY": "07",
        "DIST_NO": "03",
        "LLG_NO": "08",
        "WARD_NO": "21",
        "WARD_NAME": "YANGULI 1",
        "LATITUDE": -6.711785,
        "LONGITUDE": 144.007872,
        "REGHH": 42,
        "TOTPOP2000": 199,
        "MALE2000": 95,
        "FEMALE2000": 104,
        "POP2008": 276,
        "G_RATE": 1.0420000553131104,
        "Geocode_Num": 7030821002,
        "PROVINCE": 7
      }
    },
    {
      "type": "Feature",
      "id": 19834,
      "geometry": {
        "type": "Point",
        "coordinates": [
          144.0172990001488,
          -6.713662999647681
        ]
      },
      "properties": {
        "OBJECTID": 19834,
        "CU_NAME": "MUGUKERE",
        "CU_NO": "003",
        "GEOCODE": "07030821003",
        "PROV_KEY": "07",
        "DIST_NO": "03",
        "LLG_NO": "08",
        "WARD_NO": "21",
        "WARD_NAME": "YANGULI 1",
        "LATITUDE": -6.711785,
        "LONGITUDE": 144.007872,
        "REGHH": 17,
        "TOTPOP2000": 79,
        "MALE2000": 36,
        "FEMALE2000": 43,
        "POP2008": 109,
        "G_RATE": 1.0420000553131104,
        "Geocode_Num": 7030821003,
        "PROVINCE": 7
      }
    }
  ]
}