{
  "type": "FeatureCollection",
  "features": [
    {
      "type": "Feature",
      "id": 9353,
      "geometry": {
        "type": "Point",
        "coordinates": [
          142.83285599960482,
          -1.7255609998402406
        ]
      },
      "properties": {
        "OBJECTID": 9353,
        "CU_NAME": "ONNEI 1",
        "CU_NO": "002",
        "GEOCODE": "16010102002",
        "PROV_KEY": "16",
        "DIST_NO": "01",
        "LLG_NO": "01",
        "WARD_NO": "02",
        "WARD_NAME": "ONNEI 1",
        "LATITUDE": -1.72692,
        "LONGITUDE": 142.831785,
        "REGHH": 50,
        "TOTPOP2000": 230,
        "MALE2000": 119,
        "FEMALE2000": 111,
        "POP2008": 282,
        "G_RATE": 1.0260000228881836,
        "Geocode_Num": 16010102002,
        "PROVINCE": 16
      }
    }
  ]
}