{
  "type": "FeatureCollection",
  "features": [
    {
      "type": "Feature",
      "id": 4573,
      "geometry": {
        "type": "Point",
        "coordinates": [
          152.0459610001002,
          -4.20091899971203
        ]
      },
      "properties": {
        "OBJECTID": 4573,
        "CU_NAME": "RATONGOR VILLAGE",
        "CU_NO": "005",
        "GEOCODE": "18010409005",
        "PROV_KEY": "18",
        "DIST_NO": "01",
        "LLG_NO": "04",
        "WARD_NO": "09",
        "WARD_NAME": "RATONGOR",
        "LATITUDE": -4.199796,
        "LONGITUDE": 152.045834,
        "REGHH": 191,
        "TOTPOP2000": 1171,
        "MALE2000": 613,
        "FEMALE2000": 558,
        "POP2008": 1427,
        "G_RATE": 1.024999976158142,
        "Geocode_Num": 18010409005,
        "PROVINCE": 18
      }
    }
  ]
}