{
  "type": "FeatureCollection",
  "features": [
    {
      "type": "Feature",
      "id": 4581,
      "geometry": {
        "type": "Point",
        "coordinates": [
          152.1144370003674,
          -4.242493999598366
        ]
      },
      "properties": {
        "OBJECTID": 4581,
        "CU_NAME": "VUNAKALKALULU",
        "CU_NO": "013",
        "GEOCODE": "18010416013",
        "PROV_KEY": "18",
        "DIST_NO": "01",
        "LLG_NO": "04",
        "WARD_NO": "16",
        "WARD_NAME": "VUNAKALKALULU",
        "LATITUDE": -4.243893,
        "LONGITUDE": 152.11349,
        "REGHH": 103,
        "TOTPOP2000": 655,
        "MALE2000": 341,
        "FEMALE2000": 314,
        "POP2008": 798,
        "G_RATE": 1.024999976158142,
        "Geocode_Num": 18010416013,
        "PROVINCE": 18
      }
    }
  ]
}