{
  "type": "FeatureCollection",
  "features": [
    {
      "type": "Feature",
      "id": 4593,
      "geometry": {
        "type": "Point",
        "coordinates": [
          152.090731999882,
          -4.24774199969346
        ]
      },
      "properties": {
        "OBJECTID": 4593,
        "CU_NAME": "TOTOVEL VILLAGE",
        "CU_NO": "006",
        "GEOCODE": "18010427006",
        "PROV_KEY": "18",
        "DIST_NO": "01",
        "LLG_NO": "04",
        "WARD_NO": "27",
        "WARD_NAME": "TOTOVEL",
        "LATITUDE": -4.249141,
        "LONGITUDE": 152.089785,
        "REGHH": 179,
        "TOTPOP2000": 907,
        "MALE2000": 483,
        "FEMALE2000": 424,
        "POP2008": 1105,
        "G_RATE": 1.024999976158142,
        "Geocode_Num": 18010427006,
        "PROVINCE": 18
      }
    },
    {
      "type": "Feature",
      "id": 4594,
      "geometry": {
        "type": "Point",
        "coordinates": [
          152.03094300001953,
          -4.271256000364076
        ]
      },
      "properties": {
        "OBJECTID": 4594,
        "CU_NAME": "GEORGE BROWN H/S",
        "CU_NO": "502",
        "GEOCODE": "18010427502",
        "PROV_KEY": "18",
        "DIST_NO": "01",
        "LLG_NO": "04",
        "WARD_NO": "27",
        "WARD_NAME": "TOTOVEL",
        "LATITUDE": -4.272656,
        "LONGITUDE": 152.029995,
        "REGHH": 25,
        "TOTPOP2000": 126,
        "MALE2000": 69,
        "FEMALE2000": 57,
        "POP2008": 153,
        "G_RATE": 1.024999976158142,
        "Geocode_Num": 18010427502,
        "PROVINCE": 18
      }
    },
    {
      "type": "Feature",
      "id": 4595,
      "geometry": {
        "type": "Point",
        "coordinates": [
          152.03399300037677,
          -4.262755999589672
        ]
      },
      "properties": {
        "OBJECTID": 4595,
        "CU_NAME": "RARONGO THEO. COLLEGE",
        "CU_NO": "503",
        "GEOCODE": "18010427503",
        "PROV_KEY": "18",
        "DIST_NO": "01",
        "LLG_NO": "04",
        "WARD_NO": "27",
        "WARD_NAME": "TOTOVEL",
        "LATITUDE": -4.264156,
        "LONGITUDE": 152.033045,
        "REGHH": 93,
        "TOTPOP2000": 451,
        "MALE2000": 239,
        "FEMALE2000": 212,
        "POP2008": 549,
        "G_RATE": 1.024999976158142,
        "Geocode_Num": 18010427503,
        "PROVINCE": 18
      }
    },
    {
      "type": "Feature",
      "id": 4596,
      "geometry": {
        "type": "Point",
        "coordinates": [
          152.03143999955637,
          -4.2659169996697415
        ]
      },
      "properties": {
        "OBJECTID": 4596,
        "CU_NAME": "PASTERS COLL",
        "CU_NO": "508",
        "GEOCODE": "18010427508",
        "PROV_KEY": "18",
        "DIST_NO": "01",
        "LLG_NO": "04",
        "WARD_NO": "27",
        "WARD_NAME": "TOTOVEL",
        "LATITUDE": -4.267317,
        "LONGITUDE": 152.030492,
        "REGHH": 61,
        "TOTPOP2000": 263,
        "MALE2000": 143,
        "FEMALE2000": 120,
        "POP2008": 321,
        "G_RATE": 1.024999976158142,
        "Geocode_Num": 18010427508,
        "PROVINCE": 18
      }
    }
  ]
}