{
  "type": "FeatureCollection",
  "features": [
    {
      "type": "Feature",
      "id": 10077,
      "geometry": {
        "type": "Point",
        "coordinates": [
          152.92179199980103,
          -9.228312000198628
        ]
      },
      "properties": {
        "OBJECTID": 10077,
        "CU_NAME": "OYAVATA",
        "CU_NO": "023",
        "GEOCODE": "05021116023",
        "PROV_KEY": "05",
        "DIST_NO": "02",
        "LLG_NO": "11",
        "WARD_NO": "16",
        "WARD_NAME": "OYAVATA",
        "LATITUDE": -9.229775,
        "LONGITUDE": 152.920848,
        "REGHH": 38,
        "TOTPOP2000": 186,
        "MALE2000": 94,
        "FEMALE2000": 92,
        "POP2008": 227,
        "G_RATE": 1.024999976158142,
        "Geocode_Num": 5021116023,
        "PROVINCE": 5
      }
    }
  ]
}