{
  "type": "FeatureCollection",
  "features": [
    {
      "type": "Feature",
      "id": 8659,
      "geometry": {
        "type": "Point",
        "coordinates": [
          145.75428199981445,
          -5.471381000133022
        ]
      },
      "properties": {
        "OBJECTID": 8659,
        "CU_NAME": "LALOK 1",
        "CU_NO": "021",
        "GEOCODE": "13041007021",
        "PROV_KEY": "13",
        "DIST_NO": "04",
        "LLG_NO": "10",
        "WARD_NO": "07",
        "WARD_NAME": "WARD 7",
        "LATITUDE": -5.474086,
        "LONGITUDE": 145.755611,
        "REGHH": 119,
        "TOTPOP2000": 715,
        "MALE2000": 364,
        "FEMALE2000": 351,
        "POP2008": 884,
        "G_RATE": 1.0269999504089355,
        "Geocode_Num": 13041007021,
        "PROVINCE": 13
      }
    }
  ]
}