{
  "type": "FeatureCollection",
  "features": [
    {
      "type": "Feature",
      "id": 4899,
      "geometry": {
        "type": "Point",
        "coordinates": [
          152.11971500004734,
          -5.369723000316185
        ]
      },
      "properties": {
        "OBJECTID": 4899,
        "CU_NAME": "TEIMTOP",
        "CU_NO": "017",
        "GEOCODE": "18031109017",
        "PROV_KEY": "18",
        "DIST_NO": "03",
        "LLG_NO": "11",
        "WARD_NO": "09",
        "WARD_NAME": "WASWAS",
        "LATITUDE": -5.371137,
        "LONGITUDE": 152.118767,
        "REGHH": 16,
        "TOTPOP2000": 88,
        "MALE2000": 44,
        "FEMALE2000": 44,
        "POP2008": 105,
        "G_RATE": 1.024999976158142,
        "Geocode_Num": 18031109017,
        "PROVINCE": 18
      }
    },
    {
      "type": "Feature",
      "id": 4900,
      "geometry": {
        "type": "Point",
        "coordinates": [
          152.1112429996648,
          -5.386735999766529
        ]
      },
      "properties": {
        "OBJECTID": 4900,
        "CU_NAME": "WASWAS",
        "CU_NO": "018",
        "GEOCODE": "18031109018",
        "PROV_KEY": "18",
        "DIST_NO": "03",
        "LLG_NO": "11",
        "WARD_NO": "09",
        "WARD_NAME": "WASWAS",
        "LATITUDE": -5.388152,
        "LONGITUDE": 152.110295,
        "REGHH": 40,
        "TOTPOP2000": 188,
        "MALE2000": 85,
        "FEMALE2000": 103,
        "POP2008": 229,
        "G_RATE": 1.024999976158142,
        "Geocode_Num": 18031109018,
        "PROVINCE": 18
      }
    }
  ]
}