{
  "type": "FeatureCollection",
  "features": [
    {
      "type": "Feature",
      "id": 4463,
      "geometry": {
        "type": "Point",
        "coordinates": [
          151.79215899973815,
          -4.472080000191795
        ]
      },
      "properties": {
        "OBJECTID": 4463,
        "CU_NAME": "LAMBERAIN",
        "CU_NO": "017",
        "GEOCODE": "18010202017",
        "PROV_KEY": "18",
        "DIST_NO": "01",
        "LLG_NO": "02",
        "WARD_NO": "02",
        "WARD_NAME": "LAMBERAIN",
        "LATITUDE": -4.473482,
        "LONGITUDE": 151.791207,
        "REGHH": 69,
        "TOTPOP2000": 419,
        "MALE2000": 225,
        "FEMALE2000": 194,
        "POP2008": 510,
        "G_RATE": 1.024999976158142,
        "Geocode_Num": 18010202017,
        "PROVINCE": 18
      }
    }
  ]
}