{
  "type": "FeatureCollection",
  "features": [
    {
      "type": "Feature",
      "id": 4507,
      "geometry": {
        "type": "Point",
        "coordinates": [
          152.12243200033663,
          -4.465544000055502
        ]
      },
      "properties": {
        "OBJECTID": 4507,
        "CU_NAME": "WAIWARE SETTLEMTENT",
        "CU_NO": "545",
        "GEOCODE": "18010222545",
        "PROV_KEY": "18",
        "DIST_NO": "01",
        "LLG_NO": "02",
        "WARD_NO": "22",
        "WARD_NAME": "KADAULUNG N0.2",
        "LATITUDE": -4.466946,
        "LONGITUDE": 152.121485,
        "REGHH": 43,
        "TOTPOP2000": 261,
        "MALE2000": 163,
        "FEMALE2000": 98,
        "POP2008": 319,
        "G_RATE": 1.024999976158142,
        "Geocode_Num": 18010222545,
        "PROVINCE": 18
      }
    },
    {
      "type": "Feature",
      "id": 4508,
      "geometry": {
        "type": "Point",
        "coordinates": [
          152.1193450000718,
          -4.451200999626394
        ]
      },
      "properties": {
        "OBJECTID": 4508,
        "CU_NAME": "KADAULUNG N0.2",
        "CU_NO": "546",
        "GEOCODE": "18010222546",
        "PROV_KEY": "18",
        "DIST_NO": "01",
        "LLG_NO": "02",
        "WARD_NO": "22",
        "WARD_NAME": "KADAULUNG N0.2",
        "LATITUDE": -4.452603,
        "LONGITUDE": 152.118398,
        "REGHH": 101,
        "TOTPOP2000": 643,
        "MALE2000": 333,
        "FEMALE2000": 310,
        "POP2008": 783,
        "G_RATE": 1.024999976158142,
        "Geocode_Num": 18010222546,
        "PROVINCE": 18
      }
    }
  ]
}