{
  "type": "FeatureCollection",
  "features": [
    {
      "type": "Feature",
      "id": 16462,
      "geometry": {
        "type": "Point",
        "coordinates": [
          144.25839199989093,
          -5.6066949997743905
        ]
      },
      "properties": {
        "OBJECTID": 16462,
        "CU_NAME": "WAIYARIPA",
        "CU_NO": "039",
        "GEOCODE": "09020347039",
        "PROV_KEY": "09",
        "DIST_NO": "02",
        "LLG_NO": "03",
        "WARD_NO": "47",
        "WARD_NAME": "TIGI.1",
        "LATITUDE": -5.607631,
        "LONGITUDE": 144.258726,
        "REGHH": 56,
        "TOTPOP2000": 234,
        "MALE2000": 116,
        "FEMALE2000": 118,
        "POP2008": 285,
        "G_RATE": 1.024999976158142,
        "Geocode_Num": 9020347039,
        "PROVINCE": 9
      }
    },
    {
      "type": "Feature",
      "id": 16463,
      "geometry": {
        "type": "Point",
        "coordinates": [
          144.2873909998948,
          -5.611872000192591
        ]
      },
      "properties": {
        "OBJECTID": 16463,
        "CU_NAME": "UMUNGA",
        "CU_NO": "040",
        "GEOCODE": "09020347040",
        "PROV_KEY": "09",
        "DIST_NO": "02",
        "LLG_NO": "03",
        "WARD_NO": "47",
        "WARD_NAME": "TIGI.1",
        "LATITUDE": -5.612807,
        "LONGITUDE": 144.287725,
        "REGHH": 60,
        "TOTPOP2000": 219,
        "MALE2000": 104,
        "FEMALE2000": 115,
        "POP2008": 267,
        "G_RATE": 1.024999976158142,
        "Geocode_Num": 9020347040,
        "PROVINCE": 9
      }
    },
    {
      "type": "Feature",
      "id": 16464,
      "geometry": {
        "type": "Point",
        "coordinates": [
          144.24203199997692,
          -5.632927999927233
        ]
      },
      "properties": {
        "OBJECTID": 16464,
        "CU_NAME": "KRAIM",
        "CU_NO": "041",
        "GEOCODE": "09020347041",
        "PROV_KEY": "09",
        "DIST_NO": "02",
        "LLG_NO": "03",
        "WARD_NO": "47",
        "WARD_NAME": "TIGI.1",
        "LATITUDE": -5.633863,
        "LONGITUDE": 144.242366,
        "REGHH": 27,
        "TOTPOP2000": 95,
        "MALE2000": 43,
        "FEMALE2000": 52,
        "POP2008": 116,
        "G_RATE": 1.024999976158142,
        "Geocode_Num": 9020347041,
        "PROVINCE": 9
      }
    }
  ]
}