{
  "type": "FeatureCollection",
  "features": [
    {
      "type": "Feature",
      "id": 18609,
      "geometry": {
        "type": "Point",
        "coordinates": [
          142.2325280000672,
          -3.4684130003596465
        ]
      },
      "properties": {
        "OBJECTID": 18609,
        "CU_NAME": "MUPUN",
        "CU_NO": "008",
        "GEOCODE": "15020702008",
        "PROV_KEY": "15",
        "DIST_NO": "02",
        "LLG_NO": "07",
        "WARD_NO": "02",
        "WARD_NAME": "MAPUN/SIKEL",
        "LATITUDE": -3.472075,
        "LONGITUDE": 142.228615,
        "REGHH": 30,
        "TOTPOP2000": 161,
        "MALE2000": 76,
        "FEMALE2000": 85,
        "POP2008": 194,
        "G_RATE": 1.0240000486373901,
        "Geocode_Num": 15020702008,
        "PROVINCE": 15
      }
    },
    {
      "type": "Feature",
      "id": 18610,
      "geometry": {
        "type": "Point",
        "coordinates": [
          142.23063299991304,
          -3.4595889999323504
        ]
      },
      "properties": {
        "OBJECTID": 18610,
        "CU_NAME": "SIKEL",
        "CU_NO": "013",
        "GEOCODE": "15020702013",
        "PROV_KEY": "15",
        "DIST_NO": "02",
        "LLG_NO": "07",
        "WARD_NO": "02",
        "WARD_NAME": "MAPUN/SIKEL",
        "LATITUDE": -3.460967,
        "LONGITUDE": 142.229553,
        "REGHH": 44,
        "TOTPOP2000": 198,
        "MALE2000": 98,
        "FEMALE2000": 100,
        "POP2008": 239,
        "G_RATE": 1.0240000486373901,
        "Geocode_Num": 15020702013,
        "PROVINCE": 15
      }
    },
    {
      "type": "Feature",
      "id": 18611,
      "geometry": {
        "type": "Point",
        "coordinates": [
          142.22840899987546,
          -3.4843529997910423
        ]
      },
      "properties": {
        "OBJECTID": 18611,
        "CU_NAME": "SOLOKU 2",
        "CU_NO": "015",
        "GEOCODE": "15020702015",
        "PROV_KEY": "15",
        "DIST_NO": "02",
        "LLG_NO": "07",
        "WARD_NO": "02",
        "WARD_NAME": "MAPUN/SIKEL",
        "LATITUDE": -3.485731,
        "LONGITUDE": 142.227329,
        "REGHH": 15,
        "TOTPOP2000": 76,
        "MALE2000": 32,
        "FEMALE2000": 44,
        "POP2008": 92,
        "G_RATE": 1.0240000486373901,
        "Geocode_Num": 15020702015,
        "PROVINCE": 15
      }
    }
  ]
}