{
  "type": "FeatureCollection",
  "features": [
    {
      "type": "Feature",
      "id": 15383,
      "geometry": {
        "type": "Point",
        "coordinates": [
          141.03939199974104,
          -5.726403000098344
        ]
      },
      "properties": {
        "OBJECTID": 15383,
        "CU_NAME": "AMBAGA",
        "CU_NO": "001",
        "GEOCODE": "01020801001",
        "PROV_KEY": "01",
        "DIST_NO": "02",
        "LLG_NO": "08",
        "WARD_NO": "01",
        "WARD_NAME": "AMBAGA",
        "LATITUDE": -5.727802,
        "LONGITUDE": 141.038294,
        "REGHH": 43,
        "TOTPOP2000": 249,
        "MALE2000": 129,
        "FEMALE2000": 120,
        "POP2008": 322,
        "G_RATE": 1.0329999923706055,
        "Geocode_Num": 1020801001,
        "PROVINCE": 1
      }
    },
    {
      "type": "Feature",
      "id": 15384,
      "geometry": {
        "type": "Point",
        "coordinates": [
          141.0990049995811,
          -5.718957000265277
        ]
      },
      "properties": {
        "OBJECTID": 15384,
        "CU_NAME": "BIRIMKAMBA",
        "CU_NO": "002",
        "GEOCODE": "01020801002",
        "PROV_KEY": "01",
        "DIST_NO": "02",
        "LLG_NO": "08",
        "WARD_NO": "01",
        "WARD_NAME": "AMBAGA",
        "LATITUDE": -5.720356,
        "LONGITUDE": 141.097908,
        "REGHH": 10,
        "TOTPOP2000": 57,
        "MALE2000": 32,
        "FEMALE2000": 25,
        "POP2008": 73,
        "G_RATE": 1.0329999923706055,
        "Geocode_Num": 1020801002,
        "PROVINCE": 1
      }
    },
    {
      "type": "Feature",
      "id": 15385,
      "geometry": {
        "type": "Point",
        "coordinates": [
          141.0995519996252,
          -5.7246809998282515
        ]
      },
      "properties": {
        "OBJECTID": 15385,
        "CU_NAME": "KUNGEMBIT",
        "CU_NO": "003",
        "GEOCODE": "01020801003",
        "PROV_KEY": "01",
        "DIST_NO": "02",
        "LLG_NO": "08",
        "WARD_NO": "01",
        "WARD_NAME": "AMBAGA",
        "LATITUDE": -5.72608,
        "LONGITUDE": 141.098455,
        "REGHH": 21,
        "TOTPOP2000": 124,
        "MALE2000": 64,
        "FEMALE2000": 60,
        "POP2008": 160,
        "G_RATE": 1.0329999923706055,
        "Geocode_Num": 1020801003,
        "PROVINCE": 1
      }
    },
    {
      "type": "Feature",
      "id": 15386,
      "geometry": {
        "type": "Point",
        "coordinates": [
          141.09612499986895,
          -5.68409999991502
        ]
      },
      "properties": {
        "OBJECTID": 15386,
        "CU_NAME": "KARANDIMOK",
        "CU_NO": "004",
        "GEOCODE": "01020801004",
        "PROV_KEY": "01",
        "DIST_NO": "02",
        "LLG_NO": "08",
        "WARD_NO": "01",
        "WARD_NAME": "AMBAGA",
        "LATITUDE": -5.685499,
        "LONGITUDE": 141.095028,
        "REGHH": 9,
        "TOTPOP2000": 44,
        "MALE2000": 23,
        "FEMALE2000": 21,
        "POP2008": 58,
        "G_RATE": 1.0329999923706055,
        "Geocode_Num": 1020801004,
        "PROVINCE": 1
      }
    }
  ]
}