{
  "type": "FeatureCollection",
  "features": [
    {
      "type": "Feature",
      "id": 15421,
      "geometry": {
        "type": "Point",
        "coordinates": [
          141.30507800044938,
          -5.475068000188003
        ]
      },
      "properties": {
        "OBJECTID": 15421,
        "CU_NAME": "SISIMAKAM (APRAM)",
        "CU_NO": "001",
        "GEOCODE": "01020813001",
        "PROV_KEY": "01",
        "DIST_NO": "02",
        "LLG_NO": "08",
        "WARD_NO": "13",
        "WARD_NAME": "SISIMAKAM",
        "LATITUDE": -5.477693,
        "LONGITUDE": 141.308046,
        "REGHH": 71,
        "TOTPOP2000": 410,
        "MALE2000": 228,
        "FEMALE2000": 182,
        "POP2008": 531,
        "G_RATE": 1.0329999923706055,
        "Geocode_Num": 1020813001,
        "PROVINCE": 1
      }
    },
    {
      "type": "Feature",
      "id": 15422,
      "geometry": {
        "type": "Point",
        "coordinates": [
          141.27396900026918,
          -5.524492999652182
        ]
      },
      "properties": {
        "OBJECTID": 15422,
        "CU_NAME": "KWILOKNAI",
        "CU_NO": "011",
        "GEOCODE": "01020813011",
        "PROV_KEY": "01",
        "DIST_NO": "02",
        "LLG_NO": "08",
        "WARD_NO": "13",
        "WARD_NAME": "SISIMAKAM",
        "LATITUDE": -5.537717,
        "LONGITUDE": 141.275831,
        "REGHH": 35,
        "TOTPOP2000": 238,
        "MALE2000": 125,
        "FEMALE2000": 113,
        "POP2008": 309,
        "G_RATE": 1.0329999923706055,
        "Geocode_Num": 1020813011,
        "PROVINCE": 1
      }
    },
    {
      "type": "Feature",
      "id": 15423,
      "geometry": {
        "type": "Point",
        "coordinates": [
          141.28539200004082,
          -5.548289999883536
        ]
      },
      "properties": {
        "OBJECTID": 15423,
        "CU_NAME": "SAPIRE",
        "CU_NO": "022",
        "GEOCODE": "01020813022",
        "PROV_KEY": "01",
        "DIST_NO": "02",
        "LLG_NO": "08",
        "WARD_NO": "13",
        "WARD_NAME": "SISIMAKAM",
        "LATITUDE": -5.539341,
        "LONGITUDE": 141.27839,
        "REGHH": 27,
        "TOTPOP2000": 155,
        "MALE2000": 80,
        "FEMALE2000": 75,
        "POP2008": 200,
        "G_RATE": 1.0329999923706055,
        "Geocode_Num": 1020813022,
        "PROVINCE": 1
      }
    }
  ]
}