{
  "type": "FeatureCollection",
  "features": [
    {
      "type": "Feature",
      "id": 6899,
      "geometry": {
        "type": "Point",
        "coordinates": [
          143.59731500028715,
          -3.433483000240244
        ]
      },
      "properties": {
        "OBJECTID": 6899,
        "CU_NAME": "BAM",
        "CU_NO": "002",
        "GEOCODE": "14041618002",
        "PROV_KEY": "14",
        "DIST_NO": "04",
        "LLG_NO": "16",
        "WARD_NO": "18",
        "WARD_NAME": "MUSHU 2",
        "LATITUDE": -3.435059,
        "LONGITUDE": 143.596083,
        "REGHH": 31,
        "TOTPOP2000": 186,
        "MALE2000": 92,
        "FEMALE2000": 94,
        "POP2008": 221,
        "G_RATE": 1.0219999551773071,
        "Geocode_Num": 14041618002,
        "PROVINCE": 14
      }
    },
    {
      "type": "Feature",
      "id": 6900,
      "geometry": {
        "type": "Point",
        "coordinates": [
          143.5558520001697,
          -3.4358800001618306
        ]
      },
      "properties": {
        "OBJECTID": 6900,
        "CU_NAME": "MUSHU 2",
        "CU_NO": "018",
        "GEOCODE": "14041618018",
        "PROV_KEY": "14",
        "DIST_NO": "04",
        "LLG_NO": "16",
        "WARD_NO": "18",
        "WARD_NAME": "MUSHU 2",
        "LATITUDE": -3.437456,
        "LONGITUDE": 143.554619,
        "REGHH": 62,
        "TOTPOP2000": 357,
        "MALE2000": 188,
        "FEMALE2000": 169,
        "POP2008": 425,
        "G_RATE": 1.0219999551773071,
        "Geocode_Num": 14041618018,
        "PROVINCE": 14
      }
    },
    {
      "type": "Feature",
      "id": 6901,
      "geometry": {
        "type": "Point",
        "coordinates": [
          143.54595299963125,
          -3.393580000116856
        ]
      },
      "properties": {
        "OBJECTID": 6901,
        "CU_NAME": "MUSHULBAI",
        "CU_NO": "056",
        "GEOCODE": "14041618056",
        "PROV_KEY": "14",
        "DIST_NO": "04",
        "LLG_NO": "16",
        "WARD_NO": "18",
        "WARD_NAME": "MUSHU 2",
        "LATITUDE": -3.390284,
        "LONGITUDE": 143.543175,
        "REGHH": 21,
        "TOTPOP2000": 113,
        "MALE2000": 60,
        "FEMALE2000": 53,
        "POP2008": 136,
        "G_RATE": 1.0219999551773071,
        "Geocode_Num": 14041618056,
        "PROVINCE": 14
      }
    },
    {
      "type": "Feature",
      "id": 6902,
      "geometry": {
        "type": "Point",
        "coordinates": [
          143.58971000031636,
          -3.39368200032402
        ]
      },
      "properties": {
        "OBJECTID": 6902,
        "CU_NAME": "FAILAU",
        "CU_NO": "058",
        "GEOCODE": "14041618058",
        "PROV_KEY": "14",
        "DIST_NO": "04",
        "LLG_NO": "16",
        "WARD_NO": "18",
        "WARD_NAME": "MUSHU 2",
        "LATITUDE": -3.391663,
        "LONGITUDE": 143.58949,
        "REGHH": 18,
        "TOTPOP2000": 61,
        "MALE2000": 35,
        "FEMALE2000": 26,
        "POP2008": 69,
        "G_RATE": 1.0219999551773071,
        "Geocode_Num": 14041618058,
        "PROVINCE": 14
      }
    }
  ]
}