{
  "type": "FeatureCollection",
  "features": [
    {
      "type": "Feature",
      "id": 14338,
      "geometry": {
        "type": "Point",
        "coordinates": [
          144.99053400044386,
          -6.260817999750827
        ]
      },
      "properties": {
        "OBJECTID": 14338,
        "CU_NAME": "HAMANEDIMANE",
        "CU_NO": "002",
        "GEOCODE": "10030906002",
        "PROV_KEY": "10",
        "DIST_NO": "03",
        "LLG_NO": "09",
        "WARD_NO": "06",
        "WARD_NAME": "AINABANE",
        "LATITUDE": -6.26223,
        "LONGITUDE": 144.989484,
        "REGHH": 71,
        "TOTPOP2000": 289,
        "MALE2000": 155,
        "FEMALE2000": 134,
        "POP2008": 333,
        "G_RATE": 1.0180000066757202,
        "Geocode_Num": 10030906002,
        "PROVINCE": 10
      }
    },
    {
      "type": "Feature",
      "id": 14339,
      "geometry": {
        "type": "Point",
        "coordinates": [
          144.9984820000443,
          -6.256030000184296
        ]
      },
      "properties": {
        "OBJECTID": 14339,
        "CU_NAME": "BOGAHULALUA",
        "CU_NO": "003",
        "GEOCODE": "10030906003",
        "PROV_KEY": "10",
        "DIST_NO": "03",
        "LLG_NO": "09",
        "WARD_NO": "06",
        "WARD_NAME": "AINABANE",
        "LATITUDE": -6.257442,
        "LONGITUDE": 144.997432,
        "REGHH": 60,
        "TOTPOP2000": 238,
        "MALE2000": 123,
        "FEMALE2000": 115,
        "POP2008": 275,
        "G_RATE": 1.0180000066757202,
        "Geocode_Num": 10030906003,
        "PROVINCE": 10
      }
    }
  ]
}