{
  "type": "FeatureCollection",
  "features": [
    {
      "type": "Feature",
      "id": 14342,
      "geometry": {
        "type": "Point",
        "coordinates": [
          144.99057100035145,
          -6.2460929996921095
        ]
      },
      "properties": {
        "OBJECTID": 14342,
        "CU_NAME": "GOMIRI",
        "CU_NO": "003",
        "GEOCODE": "10030908003",
        "PROV_KEY": "10",
        "DIST_NO": "03",
        "LLG_NO": "09",
        "WARD_NO": "08",
        "WARD_NAME": "YOPAKENI",
        "LATITUDE": -6.247505,
        "LONGITUDE": 144.989521,
        "REGHH": 123,
        "TOTPOP2000": 545,
        "MALE2000": 289,
        "FEMALE2000": 256,
        "POP2008": 629,
        "G_RATE": 1.0180000066757202,
        "Geocode_Num": 10030908003,
        "PROVINCE": 10
      }
    }
  ]
}