{
  "type": "FeatureCollection",
  "features": [
    {
      "type": "Feature",
      "id": 30339,
      "geometry": {
        "type": "Point",
        "coordinates": [
          145.81050372007064,
          -7.0268885999288955
        ]
      },
      "properties": {
        "OBJECTID": 30339,
        "CU_NAME": "MALA",
        "CU_NO": "017",
        "GEOCODE": "11060910017",
        "PROV_KEY": "11",
        "DIST_NO": "06",
        "LLG_NO": "09",
        "WARD_NO": "10",
        "WARD_NAME": "MALA",
        "LATITUDE": -7.026889,
        "LONGITUDE": 145.810504,
        "REGHH": 66,
        "TOTPOP2000": 312,
        "MALE2000": 148,
        "FEMALE2000": 164,
        "POP2008": 371,
        "G_RATE": 1.0219999551773071,
        "Geocode_Num": null,
        "PROVINCE": 11
      }
    }
  ]
}