{
  "type": "FeatureCollection",
  "features": [
    {
      "type": "Feature",
      "id": 30371,
      "geometry": {
        "type": "Point",
        "coordinates": [
          145.63811051958487,
          -6.981341129989119
        ]
      },
      "properties": {
        "OBJECTID": 30371,
        "CU_NAME": "TSANGE",
        "CU_NO": "010",
        "GEOCODE": "11060916010",
        "PROV_KEY": "11",
        "DIST_NO": "06",
        "LLG_NO": "09",
        "WARD_NO": "16",
        "WARD_NAME": "YIWANE",
        "LATITUDE": -6.981341,
        "LONGITUDE": 145.638111,
        "REGHH": 44,
        "TOTPOP2000": 199,
        "MALE2000": 91,
        "FEMALE2000": 108,
        "POP2008": 237,
        "G_RATE": 1.0219999551773071,
        "Geocode_Num": null,
        "PROVINCE": 11
      }
    },
    {
      "type": "Feature",
      "id": 30372,
      "geometry": {
        "type": "Point",
        "coordinates": [
          145.67290740025635,
          -6.912432000036745
        ]
      },
      "properties": {
        "OBJECTID": 30372,
        "CU_NAME": "NOLAMBI",
        "CU_NO": "011",
        "GEOCODE": "11060916011",
        "PROV_KEY": "11",
        "DIST_NO": "06",
        "LLG_NO": "09",
        "WARD_NO": "16",
        "WARD_NAME": "YIWANE",
        "LATITUDE": -6.912432,
        "LONGITUDE": 145.672907,
        "REGHH": 36,
        "TOTPOP2000": 201,
        "MALE2000": 89,
        "FEMALE2000": 112,
        "POP2008": 240,
        "G_RATE": 1.0219999551773071,
        "Geocode_Num": null,
        "PROVINCE": 11
      }
    },
    {
      "type": "Feature",
      "id": 30373,
      "geometry": {
        "type": "Point",
        "coordinates": [
          145.66934051994906,
          -6.928282980075437
        ]
      },
      "properties": {
        "OBJECTID": 30373,
        "CU_NAME": "KURUMAJI",
        "CU_NO": "012",
        "GEOCODE": "11060916012",
        "PROV_KEY": "11",
        "DIST_NO": "06",
        "LLG_NO": "09",
        "WARD_NO": "16",
        "WARD_NAME": "YIWANE",
        "LATITUDE": -6.928283,
        "LONGITUDE": 145.669341,
        "REGHH": 23,
        "TOTPOP2000": 119,
        "MALE2000": 62,
        "FEMALE2000": 57,
        "POP2008": 143,
        "G_RATE": 1.0219999551773071,
        "Geocode_Num": null,
        "PROVINCE": 11
      }
    }
  ]
}