{
  "type": "FeatureCollection",
  "features": [
    {
      "type": "Feature",
      "id": 7074,
      "geometry": {
        "type": "Point",
        "coordinates": [
          142.99053099980586,
          -4.0939299995697525
        ]
      },
      "properties": {
        "OBJECTID": 7074,
        "CU_NAME": "SAPANDAI",
        "CU_NO": "003",
        "GEOCODE": "14052001003",
        "PROV_KEY": "14",
        "DIST_NO": "05",
        "LLG_NO": "20",
        "WARD_NO": "01",
        "WARD_NAME": "SAPANDAI",
        "LATITUDE": -4.095513,
        "LONGITUDE": 142.989289,
        "REGHH": 45,
        "TOTPOP2000": 256,
        "MALE2000": 136,
        "FEMALE2000": 120,
        "POP2008": 305,
        "G_RATE": 1.0219999551773071,
        "Geocode_Num": 14052001003,
        "PROVINCE": 14
      }
    }
  ]
}