{
  "type": "FeatureCollection",
  "features": [
    {
      "type": "Feature",
      "id": 7082,
      "geometry": {
        "type": "Point",
        "coordinates": [
          143.09423899973012,
          -4.1292719998028815
        ]
      },
      "properties": {
        "OBJECTID": 7082,
        "CU_NAME": "KANGANGAI",
        "CU_NO": "001",
        "GEOCODE": "14052007001",
        "PROV_KEY": "14",
        "DIST_NO": "05",
        "LLG_NO": "20",
        "WARD_NO": "07",
        "WARD_NAME": "KANDINGEI",
        "LATITUDE": -4.130855,
        "LONGITUDE": 143.093,
        "REGHH": 117,
        "TOTPOP2000": 742,
        "MALE2000": 364,
        "FEMALE2000": 378,
        "POP2008": 883,
        "G_RATE": 1.0219999551773071,
        "Geocode_Num": 14052007001,
        "PROVINCE": 14
      }
    }
  ]
}