{
  "type": "FeatureCollection",
  "features": [
    {
      "type": "Feature",
      "id": 31080,
      "geometry": {
        "type": "Point",
        "coordinates": [
          142.88343931147506,
          -7.631491708475494
        ]
      },
      "properties": {
        "OBJECTID": 31080,
        "CU_NAME": "Sasareme",
        "CU_NO": "876",
        "GEOCODE": "876",
        "PROV_KEY": "01",
        "DIST_NO": "01",
        "LLG_NO": null,
        "WARD_NO": null,
        "WARD_NAME": null,
        "LATITUDE": -7.631364,
        "LONGITUDE": 142.883248,
        "REGHH": null,
        "TOTPOP2000": null,
        "MALE2000": null,
        "FEMALE2000": null,
        "POP2008": null,
        "G_RATE": null,
        "Geocode_Num": 876,
        "PROVINCE": 1
      }
    },
    {
      "type": "Feature",
      "id": 31494,
      "geometry": {
        "type": "Point",
        "coordinates": [
          142.87326499968003,
          -8.067579000370529
        ]
      },
      "properties": {
        "OBJECTID": 31494,
        "CU_NAME": "Adiba",
        "CU_NO": "889",
        "GEOCODE": "889",
        "PROV_KEY": "01",
        "DIST_NO": "01",
        "LLG_NO": null,
        "WARD_NO": null,
        "WARD_NAME": null,
        "LATITUDE": null,
        "LONGITUDE": null,
        "REGHH": null,
        "TOTPOP2000": null,
        "MALE2000": null,
        "FEMALE2000": null,
        "POP2008": null,
        "G_RATE": null,
        "Geocode_Num": 889,
        "PROVINCE": 1
      }
    },
    {
      "type": "Feature",
      "id": 31495,
      "geometry": {
        "type": "Point",
        "coordinates": [
          142.23087797164112,
          -6.556271114120591
        ]
      },
      "properties": {
        "OBJECTID": 31495,
        "CU_NAME": "Tomu",
        "CU_NO": "890",
        "GEOCODE": "890",
        "PROV_KEY": "01",
        "DIST_NO": "01",
        "LLG_NO": null,
        "WARD_NO": null,
        "WARD_NAME": null,
        "LATITUDE": null,
        "LONGITUDE": null,
        "REGHH": null,
        "TOTPOP2000": null,
        "MALE2000": null,
        "FEMALE2000": null,
        "POP2008": null,
        "G_RATE": null,
        "Geocode_Num": 890,
        "PROVINCE": 1
      }
    }
  ]
}