{
  "type": "FeatureCollection",
  "features": [
    {
      "type": "Feature",
      "id": 12418,
      "geometry": {
        "type": "Point",
        "coordinates": [
          150.3304460002828,
          -2.5183369996527745
        ]
      },
      "properties": {
        "OBJECTID": 12418,
        "CU_NAME": "KITING",
        "CU_NO": "002",
        "GEOCODE": "17010206002",
        "PROV_KEY": "17",
        "DIST_NO": "01",
        "LLG_NO": "02",
        "WARD_NO": "06",
        "WARD_NAME": "TUKULISAVA",
        "LATITUDE": -2.519711,
        "LONGITUDE": 150.329475,
        "REGHH": 24,
        "TOTPOP2000": 123,
        "MALE2000": 57,
        "FEMALE2000": 66,
        "POP2008": 155,
        "G_RATE": 1.0290000438690186,
        "Geocode_Num": 17010206002,
        "PROVINCE": 17
      }
    },
    {
      "type": "Feature",
      "id": 12419,
      "geometry": {
        "type": "Point",
        "coordinates": [
          150.34523100041042,
          -2.518780000296715
        ]
      },
      "properties": {
        "OBJECTID": 12419,
        "CU_NAME": "VAISAVAMBAM",
        "CU_NO": "021",
        "GEOCODE": "17010206021",
        "PROV_KEY": "17",
        "DIST_NO": "01",
        "LLG_NO": "02",
        "WARD_NO": "06",
        "WARD_NAME": "TUKULISAVA",
        "LATITUDE": -2.522842,
        "LONGITUDE": 150.340234,
        "REGHH": 44,
        "TOTPOP2000": 248,
        "MALE2000": 132,
        "FEMALE2000": 116,
        "POP2008": 312,
        "G_RATE": 1.0290000438690186,
        "Geocode_Num": 17010206021,
        "PROVINCE": 17
      }
    },
    {
      "type": "Feature",
      "id": 12420,
      "geometry": {
        "type": "Point",
        "coordinates": [
          150.3528730002888,
          -2.4519189998619026
        ]
      },
      "properties": {
        "OBJECTID": 12420,
        "CU_NAME": "TUKULISAVA MATAMAIAP-C/SCH",
        "CU_NO": "022",
        "GEOCODE": "17010206022",
        "PROV_KEY": "17",
        "DIST_NO": "01",
        "LLG_NO": "02",
        "WARD_NO": "06",
        "WARD_NAME": "TUKULISAVA",
        "LATITUDE": -2.451708,
        "LONGITUDE": 150.354751,
        "REGHH": 64,
        "TOTPOP2000": 270,
        "MALE2000": 135,
        "FEMALE2000": 135,
        "POP2008": 340,
        "G_RATE": 1.0290000438690186,
        "Geocode_Num": 17010206022,
        "PROVINCE": 17
      }
    },
    {
      "type": "Feature",
      "id": 12421,
      "geometry": {
        "type": "Point",
        "coordinates": [
          150.31245299970624,
          -2.4679449996619383
        ]
      },
      "properties": {
        "OBJECTID": 12421,
        "CU_NAME": "ELAVA",
        "CU_NO": "023",
        "GEOCODE": "17010206023",
        "PROV_KEY": "17",
        "DIST_NO": "01",
        "LLG_NO": "02",
        "WARD_NO": "06",
        "WARD_NAME": "TUKULISAVA",
        "LATITUDE": -2.469319,
        "LONGITUDE": 150.311481,
        "REGHH": 44,
        "TOTPOP2000": 223,
        "MALE2000": 114,
        "FEMALE2000": 109,
        "POP2008": 280,
        "G_RATE": 1.0290000438690186,
        "Geocode_Num": 17010206023,
        "PROVINCE": 17
      }
    }
  ]
}