{
  "type": "FeatureCollection",
  "features": [
    {
      "type": "Feature",
      "id": 21356,
      "geometry": {
        "type": "Point",
        "coordinates": [
          143.39396299989255,
          -6.139522999986411
        ]
      },
      "properties": {
        "OBJECTID": 21356,
        "CU_NAME": "SORIP",
        "CU_NO": "001",
        "GEOCODE": "07072515001",
        "PROV_KEY": "07",
        "DIST_NO": "07",
        "LLG_NO": "25",
        "WARD_NO": "15",
        "WARD_NAME": "UNGUBI 2",
        "LATITUDE": -6.143004,
        "LONGITUDE": 143.394716,
        "REGHH": 39,
        "TOTPOP2000": 233,
        "MALE2000": 101,
        "FEMALE2000": 132,
        "POP2008": 325,
        "G_RATE": 1.0420000553131104,
        "Geocode_Num": 7072515001,
        "PROVINCE": 7
      }
    },
    {
      "type": "Feature",
      "id": 21357,
      "geometry": {
        "type": "Point",
        "coordinates": [
          143.39354500040156,
          -6.138831999597073
        ]
      },
      "properties": {
        "OBJECTID": 21357,
        "CU_NAME": "YA",
        "CU_NO": "002",
        "GEOCODE": "07072515002",
        "PROV_KEY": "07",
        "DIST_NO": "07",
        "LLG_NO": "25",
        "WARD_NO": "15",
        "WARD_NAME": "UNGUBI 2",
        "LATITUDE": -6.143004,
        "LONGITUDE": 143.394716,
        "REGHH": 46,
        "TOTPOP2000": 300,
        "MALE2000": 148,
        "FEMALE2000": 152,
        "POP2008": 417,
        "G_RATE": 1.0420000553131104,
        "Geocode_Num": 7072515002,
        "PROVINCE": 7
      }
    },
    {
      "type": "Feature",
      "id": 21358,
      "geometry": {
        "type": "Point",
        "coordinates": [
          143.39444499963713,
          -6.139036000011345
        ]
      },
      "properties": {
        "OBJECTID": 21358,
        "CU_NAME": "PEM",
        "CU_NO": "003",
        "GEOCODE": "07072515003",
        "PROV_KEY": "07",
        "DIST_NO": "07",
        "LLG_NO": "25",
        "WARD_NO": "15",
        "WARD_NAME": "UNGUBI 2",
        "LATITUDE": -6.143004,
        "LONGITUDE": 143.394716,
        "REGHH": 34,
        "TOTPOP2000": 186,
        "MALE2000": 89,
        "FEMALE2000": 97,
        "POP2008": 258,
        "G_RATE": 1.0420000553131104,
        "Geocode_Num": 7072515003,
        "PROVINCE": 7
      }
    },
    {
      "type": "Feature",
      "id": 21359,
      "geometry": {
        "type": "Point",
        "coordinates": [
          143.39402700014602,
          -6.138343999575852
        ]
      },
      "properties": {
        "OBJECTID": 21359,
        "CU_NAME": "KOYA",
        "CU_NO": "004",
        "GEOCODE": "07072515004",
        "PROV_KEY": "07",
        "DIST_NO": "07",
        "LLG_NO": "25",
        "WARD_NO": "15",
        "WARD_NAME": "UNGUBI 2",
        "LATITUDE": -6.143004,
        "LONGITUDE": 143.394716,
        "REGHH": 36,
        "TOTPOP2000": 188,
        "MALE2000": 84,
        "FEMALE2000": 104,
        "POP2008": 262,
        "G_RATE": 1.0420000553131104,
        "Geocode_Num": 7072515004,
        "PROVINCE": 7
      }
    }
  ]
}