{
  "type": "FeatureCollection",
  "features": [
    {
      "type": "Feature",
      "id": 5463,
      "geometry": {
        "type": "Point",
        "coordinates": [
          143.92478500022764,
          -5.383951999984788
        ]
      },
      "properties": {
        "OBJECTID": 5463,
        "CU_NAME": "KOMPIAM MISS/HOSP",
        "CU_NO": "401",
        "GEOCODE": "08020408401",
        "PROV_KEY": "08",
        "DIST_NO": "02",
        "LLG_NO": "04",
        "WARD_NO": "08",
        "WARD_NAME": "KOMPIAM STAT.",
        "LATITUDE": -5.385357,
        "LONGITUDE": 143.922858,
        "REGHH": 92,
        "TOTPOP2000": 526,
        "MALE2000": 260,
        "FEMALE2000": 266,
        "POP2008": 662,
        "G_RATE": 1.0290000438690186,
        "Geocode_Num": 8020408401,
        "PROVINCE": 8
      }
    }
  ]
}