{
  "type": "FeatureCollection",
  "features": [
    {
      "type": "Feature",
      "id": 17920,
      "geometry": {
        "type": "Point",
        "coordinates": [
          149.4878140000161,
          -5.5473169999795005
        ]
      },
      "properties": {
        "OBJECTID": 17920,
        "CU_NAME": "GUHI/KIKVEAI",
        "CU_NO": "001",
        "GEOCODE": "19010504001",
        "PROV_KEY": "19",
        "DIST_NO": "01",
        "LLG_NO": "05",
        "WARD_NO": "04",
        "WARD_NAME": "KALMARUHI",
        "LATITUDE": -5.54843,
        "LONGITUDE": 149.487,
        "REGHH": 68,
        "TOTPOP2000": 492,
        "MALE2000": 238,
        "FEMALE2000": 254,
        "POP2008": 647,
        "G_RATE": 1.034999966621399,
        "Geocode_Num": 19010504001,
        "PROVINCE": 19
      }
    },
    {
      "type": "Feature",
      "id": 17921,
      "geometry": {
        "type": "Point",
        "coordinates": [
          149.47998699970037,
          -5.576466999752199
        ]
      },
      "properties": {
        "OBJECTID": 17921,
        "CU_NAME": "RANGHI",
        "CU_NO": "010",
        "GEOCODE": "19010504010",
        "PROV_KEY": "19",
        "DIST_NO": "01",
        "LLG_NO": "05",
        "WARD_NO": "04",
        "WARD_NAME": "KALMARUHI",
        "LATITUDE": -5.57788,
        "LONGITUDE": 149.479,
        "REGHH": 21,
        "TOTPOP2000": 131,
        "MALE2000": 65,
        "FEMALE2000": 66,
        "POP2008": 173,
        "G_RATE": 1.034999966621399,
        "Geocode_Num": 19010504010,
        "PROVINCE": 19
      }
    },
    {
      "type": "Feature",
      "id": 17922,
      "geometry": {
        "type": "Point",
        "coordinates": [
          149.4919279999773,
          -5.526133999784236
        ]
      },
      "properties": {
        "OBJECTID": 17922,
        "CU_NAME": "SOMALANI",
        "CU_NO": "011",
        "GEOCODE": "19010504011",
        "PROV_KEY": "19",
        "DIST_NO": "01",
        "LLG_NO": "05",
        "WARD_NO": "04",
        "WARD_NAME": "KALMARUHI",
        "LATITUDE": -5.527126,
        "LONGITUDE": 149.492331,
        "REGHH": 47,
        "TOTPOP2000": 298,
        "MALE2000": 155,
        "FEMALE2000": 143,
        "POP2008": 392,
        "G_RATE": 1.034999966621399,
        "Geocode_Num": 19010504011,
        "PROVINCE": 19
      }
    },
    {
      "type": "Feature",
      "id": 17923,
      "geometry": {
        "type": "Point",
        "coordinates": [
          149.47822999961488,
          -5.540586999890081
        ]
      },
      "properties": {
        "OBJECTID": 17923,
        "CU_NAME": "VOGEVOGE",
        "CU_NO": "015",
        "GEOCODE": "19010504015",
        "PROV_KEY": "19",
        "DIST_NO": "01",
        "LLG_NO": "05",
        "WARD_NO": "04",
        "WARD_NAME": "KALMARUHI",
        "LATITUDE": -5.539372,
        "LONGITUDE": 149.465646,
        "REGHH": 23,
        "TOTPOP2000": 104,
        "MALE2000": 49,
        "FEMALE2000": 55,
        "POP2008": 137,
        "G_RATE": 1.034999966621399,
        "Geocode_Num": 19010504015,
        "PROVINCE": 19
      }
    }
  ]
}