{
  "type": "FeatureCollection",
  "features": [
    {
      "type": "Feature",
      "id": 11803,
      "geometry": {
        "type": "Point",
        "coordinates": [
          146.46023400039883,
          -6.346112000368464
        ]
      },
      "properties": {
        "OBJECTID": 11803,
        "CU_NAME": "YUWENG",
        "CU_NO": "003",
        "GEOCODE": "12061920003",
        "PROV_KEY": "12",
        "DIST_NO": "06",
        "LLG_NO": "19",
        "WARD_NO": "20",
        "WARD_NAME": "NGARIAWANG",
        "LATITUDE": -6.347528,
        "LONGITUDE": 146.459203,
        "REGHH": 15,
        "TOTPOP2000": 87,
        "MALE2000": 47,
        "FEMALE2000": 40,
        "POP2008": 109,
        "G_RATE": 1.027999997138977,
        "Geocode_Num": 12061920003,
        "PROVINCE": 12
      }
    },
    {
      "type": "Feature",
      "id": 11804,
      "geometry": {
        "type": "Point",
        "coordinates": [
          146.4517579998319,
          -6.3489150001271355
        ]
      },
      "properties": {
        "OBJECTID": 11804,
        "CU_NAME": "NGARIAWANG",
        "CU_NO": "004",
        "GEOCODE": "12061920004",
        "PROV_KEY": "12",
        "DIST_NO": "06",
        "LLG_NO": "19",
        "WARD_NO": "20",
        "WARD_NAME": "NGARIAWANG",
        "LATITUDE": -6.347264,
        "LONGITUDE": 146.452775,
        "REGHH": 54,
        "TOTPOP2000": 266,
        "MALE2000": 134,
        "FEMALE2000": 132,
        "POP2008": 332,
        "G_RATE": 1.027999997138977,
        "Geocode_Num": 12061920004,
        "PROVINCE": 12
      }
    },
    {
      "type": "Feature",
      "id": 11805,
      "geometry": {
        "type": "Point",
        "coordinates": [
          146.41954800014014,
          -6.351653999632333
        ]
      },
      "properties": {
        "OBJECTID": 11805,
        "CU_NAME": "WANGAT",
        "CU_NO": "010",
        "GEOCODE": "12061920010",
        "PROV_KEY": "12",
        "DIST_NO": "06",
        "LLG_NO": "19",
        "WARD_NO": "20",
        "WARD_NAME": "NGARIAWANG",
        "LATITUDE": -6.35307,
        "LONGITUDE": 146.418517,
        "REGHH": 65,
        "TOTPOP2000": 375,
        "MALE2000": 204,
        "FEMALE2000": 171,
        "POP2008": 468,
        "G_RATE": 1.027999997138977,
        "Geocode_Num": 12061920010,
        "PROVINCE": 12
      }
    },
    {
      "type": "Feature",
      "id": 11806,
      "geometry": {
        "type": "Point",
        "coordinates": [
          146.41796299989255,
          -6.417351000348333
        ]
      },
      "properties": {
        "OBJECTID": 11806,
        "CU_NAME": "SASIANG FARM",
        "CU_NO": "402",
        "GEOCODE": "12061920402",
        "PROV_KEY": "12",
        "DIST_NO": "06",
        "LLG_NO": "19",
        "WARD_NO": "20",
        "WARD_NAME": "NGARIAWANG",
        "LATITUDE": -6.418768,
        "LONGITUDE": 146.416931,
        "REGHH": 27,
        "TOTPOP2000": 162,
        "MALE2000": 94,
        "FEMALE2000": 68,
        "POP2008": 203,
        "G_RATE": 1.027999997138977,
        "Geocode_Num": 12061920402,
        "PROVINCE": 12
      }
    }
  ]
}