{
  "type": "FeatureCollection",
  "features": [
    {
      "type": "Feature",
      "id": 15037,
      "geometry": {
        "type": "Point",
        "coordinates": [
          142.97110799983443,
          -8.037269000164201
        ]
      },
      "properties": {
        "OBJECTID": 15037,
        "CU_NAME": "BALIMO 01",
        "CU_NO": "001",
        "GEOCODE": "01010180001",
        "PROV_KEY": "01",
        "DIST_NO": "01",
        "LLG_NO": "01",
        "WARD_NO": "80",
        "WARD_NAME": "BALIMO URBAN",
        "LATITUDE": -8.037802,
        "LONGITUDE": 142.961998,
        "REGHH": 81,
        "TOTPOP2000": 598,
        "MALE2000": 309,
        "FEMALE2000": 289,
        "POP2008": 775,
        "G_RATE": 1.0329999923706055,
        "Geocode_Num": 1010180001,
        "PROVINCE": 1
      }
    },
    {
      "type": "Feature",
      "id": 15038,
      "geometry": {
        "type": "Point",
        "coordinates": [
          142.95869899955926,
          -8.041311000402288
        ]
      },
      "properties": {
        "OBJECTID": 15038,
        "CU_NAME": "BALIMO 02",
        "CU_NO": "002",
        "GEOCODE": "01010180002",
        "PROV_KEY": "01",
        "DIST_NO": "01",
        "LLG_NO": "01",
        "WARD_NO": "80",
        "WARD_NAME": "BALIMO URBAN",
        "LATITUDE": -8.040318,
        "LONGITUDE": 142.957607,
        "REGHH": 72,
        "TOTPOP2000": 708,
        "MALE2000": 363,
        "FEMALE2000": 345,
        "POP2008": 917,
        "G_RATE": 1.0329999923706055,
        "Geocode_Num": 1010180002,
        "PROVINCE": 1
      }
    },
    {
      "type": "Feature",
      "id": 15039,
      "geometry": {
        "type": "Point",
        "coordinates": [
          142.96634499962215,
          -8.032209999791633
        ]
      },
      "properties": {
        "OBJECTID": 15039,
        "CU_NAME": "BALIMO 03",
        "CU_NO": "003",
        "GEOCODE": "01010180003",
        "PROV_KEY": "01",
        "DIST_NO": "01",
        "LLG_NO": "01",
        "WARD_NO": "80",
        "WARD_NAME": "BALIMO URBAN",
        "LATITUDE": -8.036087,
        "LONGITUDE": 142.958185,
        "REGHH": 88,
        "TOTPOP2000": 640,
        "MALE2000": 316,
        "FEMALE2000": 324,
        "POP2008": 831,
        "G_RATE": 1.0329999923706055,
        "Geocode_Num": 1010180003,
        "PROVINCE": 1
      }
    },
    {
      "type": "Feature",
      "id": 15040,
      "geometry": {
        "type": "Point",
        "coordinates": [
          142.95527299984917,
          -8.027785999923935
        ]
      },
      "properties": {
        "OBJECTID": 15040,
        "CU_NAME": "BALIMO 04",
        "CU_NO": "004",
        "GEOCODE": "01010180004",
        "PROV_KEY": "01",
        "DIST_NO": "01",
        "LLG_NO": "01",
        "WARD_NO": "80",
        "WARD_NAME": "BALIMO URBAN",
        "LATITUDE": -8.032541,
        "LONGITUDE": 142.958128,
        "REGHH": 39,
        "TOTPOP2000": 263,
        "MALE2000": 136,
        "FEMALE2000": 127,
        "POP2008": 342,
        "G_RATE": 1.0329999923706055,
        "Geocode_Num": 1010180004,
        "PROVINCE": 1
      }
    },
    {
      "type": "Feature",
      "id": 15041,
      "geometry": {
        "type": "Point",
        "coordinates": [
          142.94053800022857,
          -8.037388000255987
        ]
      },
      "properties": {
        "OBJECTID": 15041,
        "CU_NAME": "BALIMO VILLAGE",
        "CU_NO": "600",
        "GEOCODE": "01010180600",
        "PROV_KEY": "01",
        "DIST_NO": "01",
        "LLG_NO": "01",
        "WARD_NO": "80",
        "WARD_NAME": "BALIMO URBAN",
        "LATITUDE": -8.03659,
        "LONGITUDE": 142.953367,
        "REGHH": 88,
        "TOTPOP2000": 749,
        "MALE2000": 376,
        "FEMALE2000": 373,
        "POP2008": 971,
        "G_RATE": 1.0329999923706055,
        "Geocode_Num": 1010180600,
        "PROVINCE": 1
      }
    },
    {
      "type": "Feature",
      "id": 15042,
      "geometry": {
        "type": "Point",
        "coordinates": [
          142.95356900040906,
          -8.04796200044592
        ]
      },
      "properties": {
        "OBJECTID": 15042,
        "CU_NAME": "BALIMO VILLAGE",
        "CU_NO": "601",
        "GEOCODE": "01010180601",
        "PROV_KEY": "01",
        "DIST_NO": "01",
        "LLG_NO": "01",
        "WARD_NO": "80",
        "WARD_NAME": "BALIMO URBAN",
        "LATITUDE": -8.043431,
        "LONGITUDE": 142.953207,
        "REGHH": 25,
        "TOTPOP2000": 185,
        "MALE2000": 87,
        "FEMALE2000": 98,
        "POP2008": 240,
        "G_RATE": 1.0329999923706055,
        "Geocode_Num": 1010180601,
        "PROVINCE": 1
      }
    }
  ]
}