{
  "type": "FeatureCollection",
  "features": [
    {
      "type": "Feature",
      "id": 7919,
      "geometry": {
        "type": "Point",
        "coordinates": [
          145.44342299967172,
          -4.4914349997254135
        ]
      },
      "properties": {
        "OBJECTID": 7919,
        "CU_NAME": "MEWOK",
        "CU_NO": "015",
        "GEOCODE": "13010134015",
        "PROV_KEY": "13",
        "DIST_NO": "01",
        "LLG_NO": "01",
        "WARD_NO": "34",
        "WARD_NAME": "ULINGAN",
        "LATITUDE": -4.492829,
        "LONGITUDE": 145.442382,
        "REGHH": 37,
        "TOTPOP2000": 302,
        "MALE2000": 165,
        "FEMALE2000": 137,
        "POP2008": 374,
        "G_RATE": 1.0269999504089355,
        "Geocode_Num": 13010134015,
        "PROVINCE": 13
      }
    },
    {
      "type": "Feature",
      "id": 7920,
      "geometry": {
        "type": "Point",
        "coordinates": [
          145.42132899973365,
          -4.501969999915502
        ]
      },
      "properties": {
        "OBJECTID": 7920,
        "CU_NAME": "SIKOR",
        "CU_NO": "024",
        "GEOCODE": "13010134024",
        "PROV_KEY": "13",
        "DIST_NO": "01",
        "LLG_NO": "01",
        "WARD_NO": "34",
        "WARD_NAME": "ULINGAN",
        "LATITUDE": -4.503364,
        "LONGITUDE": 145.420288,
        "REGHH": 39,
        "TOTPOP2000": 242,
        "MALE2000": 142,
        "FEMALE2000": 100,
        "POP2008": 300,
        "G_RATE": 1.0269999504089355,
        "Geocode_Num": 13010134024,
        "PROVINCE": 13
      }
    },
    {
      "type": "Feature",
      "id": 7921,
      "geometry": {
        "type": "Point",
        "coordinates": [
          145.41835099999867,
          -4.495853000215732
        ]
      },
      "properties": {
        "OBJECTID": 7921,
        "CU_NAME": "ULINGAN",
        "CU_NO": "025",
        "GEOCODE": "13010134025",
        "PROV_KEY": "13",
        "DIST_NO": "01",
        "LLG_NO": "01",
        "WARD_NO": "34",
        "WARD_NAME": "ULINGAN",
        "LATITUDE": -4.497247,
        "LONGITUDE": 145.41731,
        "REGHH": 33,
        "TOTPOP2000": 203,
        "MALE2000": 111,
        "FEMALE2000": 92,
        "POP2008": 251,
        "G_RATE": 1.0269999504089355,
        "Geocode_Num": 13010134025,
        "PROVINCE": 13
      }
    }
  ]
}