{
  "type": "FeatureCollection",
  "features": [
    {
      "type": "Feature",
      "id": 8615,
      "geometry": {
        "type": "Point",
        "coordinates": [
          144.6048559998046,
          -5.332415000252013
        ]
      },
      "properties": {
        "OBJECTID": 8615,
        "CU_NAME": "BAPAIMB/KOMERAU",
        "CU_NO": "001",
        "GEOCODE": "13030919001",
        "PROV_KEY": "13",
        "DIST_NO": "03",
        "LLG_NO": "09",
        "WARD_NO": "19",
        "WARD_NAME": "BABAIMP",
        "LATITUDE": -5.333817,
        "LONGITUDE": 144.603803,
        "REGHH": 116,
        "TOTPOP2000": 762,
        "MALE2000": 388,
        "FEMALE2000": 374,
        "POP2008": 944,
        "G_RATE": 1.0269999504089355,
        "Geocode_Num": 13030919001,
        "PROVINCE": 13
      }
    }
  ]
}