{
  "type": "FeatureCollection",
  "features": [
    {
      "type": "Feature",
      "id": 14759,
      "geometry": {
        "type": "Point",
        "coordinates": [
          145.06599499996935,
          -5.9411350000801235
        ]
      },
      "properties": {
        "OBJECTID": 14759,
        "CU_NAME": "GERE",
        "CU_NO": "009",
        "GEOCODE": "10051513009",
        "PROV_KEY": "10",
        "DIST_NO": "05",
        "LLG_NO": "15",
        "WARD_NO": "13",
        "WARD_NAME": "GIRAI TAMBAGLE",
        "LATITUDE": -5.942544,
        "LONGITUDE": 145.064947,
        "REGHH": 110,
        "TOTPOP2000": 496,
        "MALE2000": 273,
        "FEMALE2000": 223,
        "POP2008": 572,
        "G_RATE": 1.0180000066757202,
        "Geocode_Num": 10051513009,
        "PROVINCE": 10
      }
    }
  ]
}