{
  "type": "FeatureCollection",
  "features": [
    {
      "type": "Feature",
      "id": 17087,
      "geometry": {
        "type": "Point",
        "coordinates": [
          144.0871039996499,
          -5.563831999846855
        ]
      },
      "properties": {
        "OBJECTID": 17087,
        "CU_NAME": "YUKU",
        "CU_NO": "021",
        "GEOCODE": "09050918021",
        "PROV_KEY": "09",
        "DIST_NO": "05",
        "LLG_NO": "09",
        "WARD_NO": "18",
        "WARD_NAME": "YARAMANDA.2",
        "LATITUDE": -5.564767,
        "LONGITUDE": 144.087436,
        "REGHH": 74,
        "TOTPOP2000": 289,
        "MALE2000": 151,
        "FEMALE2000": 138,
        "POP2008": 352,
        "G_RATE": 1.024999976158142,
        "Geocode_Num": 9050918021,
        "PROVINCE": 9
      }
    }
  ]
}