{
  "type": "FeatureCollection",
  "features": [
    {
      "type": "Feature",
      "id": 17088,
      "geometry": {
        "type": "Point",
        "coordinates": [
          144.0840099999616,
          -5.557983999961607
        ]
      },
      "properties": {
        "OBJECTID": 17088,
        "CU_NAME": "SIMBIMALI",
        "CU_NO": "021",
        "GEOCODE": "09050919021",
        "PROV_KEY": "09",
        "DIST_NO": "05",
        "LLG_NO": "09",
        "WARD_NO": "19",
        "WARD_NAME": "YARAMANDA.3",
        "LATITUDE": -5.558919,
        "LONGITUDE": 144.084342,
        "REGHH": 74,
        "TOTPOP2000": 299,
        "MALE2000": 155,
        "FEMALE2000": 144,
        "POP2008": 364,
        "G_RATE": 1.024999976158142,
        "Geocode_Num": 9050919021,
        "PROVINCE": 9
      }
    }
  ]
}