{
  "type": "FeatureCollection",
  "features": [
    {
      "type": "Feature",
      "id": 20260,
      "geometry": {
        "type": "Point",
        "coordinates": [
          142.7601169996998,
          -5.91587099964687
        ]
      },
      "properties": {
        "OBJECTID": 20260,
        "CU_NAME": "KULU",
        "CU_NO": "012",
        "GEOCODE": "07041209012",
        "PROV_KEY": "21",
        "DIST_NO": "1",
        "LLG_NO": "12",
        "WARD_NO": "09",
        "WARD_NAME": "KULU NOGOLI",
        "LATITUDE": -5.914854,
        "LONGITUDE": 142.755904,
        "REGHH": 84,
        "TOTPOP2000": 468,
        "MALE2000": 233,
        "FEMALE2000": 235,
        "POP2008": 649,
        "G_RATE": 1.0420000553131104,
        "Geocode_Num": 7041209012,
        "PROVINCE": 21
      }
    },
    {
      "type": "Feature",
      "id": 20261,
      "geometry": {
        "type": "Point",
        "coordinates": [
          142.7501369999227,
          -5.907621999655532
        ]
      },
      "properties": {
        "OBJECTID": 20261,
        "CU_NAME": "NOGOLI CAMP",
        "CU_NO": "013",
        "GEOCODE": "07041209013",
        "PROV_KEY": "21",
        "DIST_NO": "1",
        "LLG_NO": "12",
        "WARD_NO": "09",
        "WARD_NAME": "KULU NOGOLI",
        "LATITUDE": -5.914854,
        "LONGITUDE": 142.755904,
        "REGHH": 134,
        "TOTPOP2000": 686,
        "MALE2000": 372,
        "FEMALE2000": 314,
        "POP2008": 953,
        "G_RATE": 1.0420000553131104,
        "Geocode_Num": 7041209013,
        "PROVINCE": 21
      }
    },
    {
      "type": "Feature",
      "id": 20262,
      "geometry": {
        "type": "Point",
        "coordinates": [
          142.75358199960965,
          -5.899253999572352
        ]
      },
      "properties": {
        "OBJECTID": 20262,
        "CU_NAME": "YUNI",
        "CU_NO": "014",
        "GEOCODE": "07041209014",
        "PROV_KEY": "21",
        "DIST_NO": "1",
        "LLG_NO": "12",
        "WARD_NO": "09",
        "WARD_NAME": "KULU NOGOLI",
        "LATITUDE": -5.914854,
        "LONGITUDE": 142.755904,
        "REGHH": 75,
        "TOTPOP2000": 461,
        "MALE2000": 271,
        "FEMALE2000": 190,
        "POP2008": 641,
        "G_RATE": 1.0420000553131104,
        "Geocode_Num": 7041209014,
        "PROVINCE": 21
      }
    }
  ]
}