{
  "type": "FeatureCollection",
  "features": [
    {
      "type": "Feature",
      "id": 20280,
      "geometry": {
        "type": "Point",
        "coordinates": [
          142.803927000131,
          -5.9876429999244465
        ]
      },
      "properties": {
        "OBJECTID": 20280,
        "CU_NAME": "LAITE",
        "CU_NO": "013",
        "GEOCODE": "07041216013",
        "PROV_KEY": "21",
        "DIST_NO": "1",
        "LLG_NO": "12",
        "WARD_NO": "16",
        "WARD_NAME": "LAITE",
        "LATITUDE": -5.991528,
        "LONGITUDE": 142.801954,
        "REGHH": 47,
        "TOTPOP2000": 309,
        "MALE2000": 163,
        "FEMALE2000": 146,
        "POP2008": 430,
        "G_RATE": 1.0420000553131104,
        "Geocode_Num": 7041216013,
        "PROVINCE": 21
      }
    },
    {
      "type": "Feature",
      "id": 20281,
      "geometry": {
        "type": "Point",
        "coordinates": [
          142.80167999993216,
          -5.983631000170476
        ]
      },
      "properties": {
        "OBJECTID": 20281,
        "CU_NAME": "KANGU",
        "CU_NO": "015",
        "GEOCODE": "07041216015",
        "PROV_KEY": "21",
        "DIST_NO": "1",
        "LLG_NO": "12",
        "WARD_NO": "16",
        "WARD_NAME": "LAITE",
        "LATITUDE": -5.991528,
        "LONGITUDE": 142.801954,
        "REGHH": 51,
        "TOTPOP2000": 299,
        "MALE2000": 159,
        "FEMALE2000": 140,
        "POP2008": 416,
        "G_RATE": 1.0420000553131104,
        "Geocode_Num": 7041216015,
        "PROVINCE": 21
      }
    },
    {
      "type": "Feature",
      "id": 20282,
      "geometry": {
        "type": "Point",
        "coordinates": [
          142.79946000007897,
          -5.98627599983746
        ]
      },
      "properties": {
        "OBJECTID": 20282,
        "CU_NAME": "HIDES 4",
        "CU_NO": "016",
        "GEOCODE": "07041216016",
        "PROV_KEY": "21",
        "DIST_NO": "1",
        "LLG_NO": "12",
        "WARD_NO": "16",
        "WARD_NAME": "LAITE",
        "LATITUDE": -5.991528,
        "LONGITUDE": 142.801954,
        "REGHH": 31,
        "TOTPOP2000": 217,
        "MALE2000": 124,
        "FEMALE2000": 93,
        "POP2008": 301,
        "G_RATE": 1.0420000553131104,
        "Geocode_Num": 7041216016,
        "PROVINCE": 21
      }
    }
  ]
}