{
  "type": "FeatureCollection",
  "features": [
    {
      "type": "Feature",
      "id": 13923,
      "geometry": {
        "type": "Point",
        "coordinates": [
          145.0957149999474,
          -6.236864000373259
        ]
      },
      "properties": {
        "OBJECTID": 13923,
        "CU_NAME": "BANANA BLOCK",
        "CU_NO": "002",
        "GEOCODE": "10010206002",
        "PROV_KEY": "10",
        "DIST_NO": "01",
        "LLG_NO": "02",
        "WARD_NO": "06",
        "WARD_NAME": "KURERI 2",
        "LATITUDE": -6.238276,
        "LONGITUDE": 145.094666,
        "REGHH": 62,
        "TOTPOP2000": 234,
        "MALE2000": 122,
        "FEMALE2000": 112,
        "POP2008": 270,
        "G_RATE": 1.0180000066757202,
        "Geocode_Num": 10010206002,
        "PROVINCE": 10
      }
    },
    {
      "type": "Feature",
      "id": 13924,
      "geometry": {
        "type": "Point",
        "coordinates": [
          145.08936200015626,
          -6.2265450002515195
        ]
      },
      "properties": {
        "OBJECTID": 13924,
        "CU_NAME": "KURERI 2",
        "CU_NO": "003",
        "GEOCODE": "10010206003",
        "PROV_KEY": "10",
        "DIST_NO": "01",
        "LLG_NO": "02",
        "WARD_NO": "06",
        "WARD_NAME": "KURERI 2",
        "LATITUDE": -6.227957,
        "LONGITUDE": 145.088313,
        "REGHH": 34,
        "TOTPOP2000": 155,
        "MALE2000": 85,
        "FEMALE2000": 70,
        "POP2008": 179,
        "G_RATE": 1.0180000066757202,
        "Geocode_Num": 10010206003,
        "PROVINCE": 10
      }
    },
    {
      "type": "Feature",
      "id": 13925,
      "geometry": {
        "type": "Point",
        "coordinates": [
          145.0888570002504,
          -6.224196999891603
        ]
      },
      "properties": {
        "OBJECTID": 13925,
        "CU_NAME": "AURABOL",
        "CU_NO": "004",
        "GEOCODE": "10010206004",
        "PROV_KEY": "10",
        "DIST_NO": "01",
        "LLG_NO": "02",
        "WARD_NO": "06",
        "WARD_NAME": "KURERI 2",
        "LATITUDE": -6.225609,
        "LONGITUDE": 145.087808,
        "REGHH": 46,
        "TOTPOP2000": 233,
        "MALE2000": 126,
        "FEMALE2000": 107,
        "POP2008": 268,
        "G_RATE": 1.0180000066757202,
        "Geocode_Num": 10010206004,
        "PROVINCE": 10
      }
    }
  ]
}