{
  "type": "FeatureCollection",
  "features": [
    {
      "type": "Feature",
      "id": 17631,
      "geometry": {
        "type": "Point",
        "coordinates": [
          144.18333400006406,
          -5.9982430004141065
        ]
      },
      "properties": {
        "OBJECTID": 17631,
        "CU_NAME": "OLK",
        "CU_NO": "001",
        "GEOCODE": "09071324001",
        "PROV_KEY": "09",
        "DIST_NO": "07",
        "LLG_NO": "13",
        "WARD_NO": "24",
        "WARD_NAME": "AGEGA",
        "LATITUDE": -5.999183,
        "LONGITUDE": 144.183667,
        "REGHH": 216,
        "TOTPOP2000": 815,
        "MALE2000": 431,
        "FEMALE2000": 384,
        "POP2008": 992,
        "G_RATE": 1.024999976158142,
        "Geocode_Num": 9071324001,
        "PROVINCE": 9
      }
    }
  ]
}