{
  "type": "FeatureCollection",
  "features": [
    {
      "type": "Feature",
      "id": 7939,
      "geometry": {
        "type": "Point",
        "coordinates": [
          144.99850600025172,
          -4.097028000341879
        ]
      },
      "properties": {
        "OBJECTID": 7939,
        "CU_NAME": "ZOGARI",
        "CU_NO": "011",
        "GEOCODE": "13010211011",
        "PROV_KEY": "13",
        "DIST_NO": "01",
        "LLG_NO": "02",
        "WARD_NO": "11",
        "WARD_NAME": "ZOGARI",
        "LATITUDE": -4.098417,
        "LONGITUDE": 144.99746,
        "REGHH": 99,
        "TOTPOP2000": 637,
        "MALE2000": 298,
        "FEMALE2000": 339,
        "POP2008": 789,
        "G_RATE": 1.0269999504089355,
        "Geocode_Num": 13010211011,
        "PROVINCE": 13
      }
    }
  ]
}