{
  "type": "FeatureCollection",
  "features": [
    {
      "type": "Feature",
      "id": 5303,
      "geometry": {
        "type": "Point",
        "coordinates": [
          143.42793699999265,
          -5.7782269995763045
        ]
      },
      "properties": {
        "OBJECTID": 5303,
        "CU_NAME": "KUIKALE",
        "CU_NO": "001",
        "GEOCODE": "08010211001",
        "PROV_KEY": "08",
        "DIST_NO": "01",
        "LLG_NO": "02",
        "WARD_NO": "11",
        "WARD_NAME": "KUIKALE",
        "LATITUDE": -5.779631,
        "LONGITUDE": 143.426868,
        "REGHH": 67,
        "TOTPOP2000": 525,
        "MALE2000": 260,
        "FEMALE2000": 265,
        "POP2008": 661,
        "G_RATE": 1.0290000438690186,
        "Geocode_Num": 8010211001,
        "PROVINCE": 8
      }
    },
    {
      "type": "Feature",
      "id": 5304,
      "geometry": {
        "type": "Point",
        "coordinates": [
          143.42148500013275,
          -5.767757999731828
        ]
      },
      "properties": {
        "OBJECTID": 5304,
        "CU_NAME": "IPAU",
        "CU_NO": "002",
        "GEOCODE": "08010211002",
        "PROV_KEY": "08",
        "DIST_NO": "01",
        "LLG_NO": "02",
        "WARD_NO": "11",
        "WARD_NAME": "KUIKALE",
        "LATITUDE": -5.769162,
        "LONGITUDE": 143.420416,
        "REGHH": 25,
        "TOTPOP2000": 215,
        "MALE2000": 113,
        "FEMALE2000": 102,
        "POP2008": 270,
        "G_RATE": 1.0290000438690186,
        "Geocode_Num": 8010211002,
        "PROVINCE": 8
      }
    },
    {
      "type": "Feature",
      "id": 5305,
      "geometry": {
        "type": "Point",
        "coordinates": [
          143.42326400033346,
          -5.763689000047293
        ]
      },
      "properties": {
        "OBJECTID": 5305,
        "CU_NAME": "ANGOLALYA",
        "CU_NO": "003",
        "GEOCODE": "08010211003",
        "PROV_KEY": "08",
        "DIST_NO": "01",
        "LLG_NO": "02",
        "WARD_NO": "11",
        "WARD_NAME": "KUIKALE",
        "LATITUDE": -5.765093,
        "LONGITUDE": 143.422195,
        "REGHH": 56,
        "TOTPOP2000": 382,
        "MALE2000": 189,
        "FEMALE2000": 193,
        "POP2008": 480,
        "G_RATE": 1.0290000438690186,
        "Geocode_Num": 8010211003,
        "PROVINCE": 8
      }
    }
  ]
}