{
  "type": "FeatureCollection",
  "features": [
    {
      "type": "Feature",
      "id": 5347,
      "geometry": {
        "type": "Point",
        "coordinates": [
          143.43813199979206,
          -5.863066999942021
        ]
      },
      "properties": {
        "OBJECTID": 5347,
        "CU_NAME": "RUMBIPAKA",
        "CU_NO": "008",
        "GEOCODE": "08010219008",
        "PROV_KEY": "08",
        "DIST_NO": "01",
        "LLG_NO": "02",
        "WARD_NO": "19",
        "WARD_NAME": "RUMBIPAKA",
        "LATITUDE": -5.864472,
        "LONGITUDE": 143.437063,
        "REGHH": 36,
        "TOTPOP2000": 185,
        "MALE2000": 93,
        "FEMALE2000": 92,
        "POP2008": 233,
        "G_RATE": 1.0290000438690186,
        "Geocode_Num": 8010219008,
        "PROVINCE": 8
      }
    },
    {
      "type": "Feature",
      "id": 5348,
      "geometry": {
        "type": "Point",
        "coordinates": [
          143.438575000436,
          -5.859419999932982
        ]
      },
      "properties": {
        "OBJECTID": 5348,
        "CU_NAME": "MANULUM",
        "CU_NO": "009",
        "GEOCODE": "08010219009",
        "PROV_KEY": "08",
        "DIST_NO": "01",
        "LLG_NO": "02",
        "WARD_NO": "19",
        "WARD_NAME": "RUMBIPAKA",
        "LATITUDE": -5.860825,
        "LONGITUDE": 143.437506,
        "REGHH": 26,
        "TOTPOP2000": 138,
        "MALE2000": 77,
        "FEMALE2000": 61,
        "POP2008": 173,
        "G_RATE": 1.0290000438690186,
        "Geocode_Num": 8010219009,
        "PROVINCE": 8
      }
    },
    {
      "type": "Feature",
      "id": 5349,
      "geometry": {
        "type": "Point",
        "coordinates": [
          143.44505499978845,
          -5.8451690001492125
        ]
      },
      "properties": {
        "OBJECTID": 5349,
        "CU_NAME": "KAKALIAKA",
        "CU_NO": "010",
        "GEOCODE": "08010219010",
        "PROV_KEY": "08",
        "DIST_NO": "01",
        "LLG_NO": "02",
        "WARD_NO": "19",
        "WARD_NAME": "RUMBIPAKA",
        "LATITUDE": -5.84898,
        "LONGITUDE": 143.446207,
        "REGHH": 52,
        "TOTPOP2000": 298,
        "MALE2000": 153,
        "FEMALE2000": 145,
        "POP2008": 375,
        "G_RATE": 1.0290000438690186,
        "Geocode_Num": 8010219010,
        "PROVINCE": 8
      }
    },
    {
      "type": "Feature",
      "id": 5350,
      "geometry": {
        "type": "Point",
        "coordinates": [
          143.4281059996922,
          -5.850776999758693
        ]
      },
      "properties": {
        "OBJECTID": 5350,
        "CU_NAME": "ETAE",
        "CU_NO": "011",
        "GEOCODE": "08010219011",
        "PROV_KEY": "08",
        "DIST_NO": "01",
        "LLG_NO": "02",
        "WARD_NO": "19",
        "WARD_NAME": "RUMBIPAKA",
        "LATITUDE": -5.852182,
        "LONGITUDE": 143.427037,
        "REGHH": 27,
        "TOTPOP2000": 140,
        "MALE2000": 71,
        "FEMALE2000": 69,
        "POP2008": 176,
        "G_RATE": 1.0290000438690186,
        "Geocode_Num": 8010219011,
        "PROVINCE": 8
      }
    }
  ]
}