{
  "type": "FeatureCollection",
  "features": [
    {
      "type": "Feature",
      "id": 9562,
      "geometry": {
        "type": "Point",
        "coordinates": [
          150.01258800023606,
          -9.633631000070523
        ]
      },
      "properties": {
        "OBJECTID": 9562,
        "CU_NAME": "BOGABOGA",
        "CU_NO": "007",
        "GEOCODE": "05010108007",
        "PROV_KEY": "05",
        "DIST_NO": "01",
        "LLG_NO": "01",
        "WARD_NO": "08",
        "WARD_NAME": "BOGABOGA",
        "LATITUDE": -9.635095,
        "LONGITUDE": 150.012068,
        "REGHH": 49,
        "TOTPOP2000": 208,
        "MALE2000": 105,
        "FEMALE2000": 103,
        "POP2008": 253,
        "G_RATE": 1.024999976158142,
        "Geocode_Num": 5010108007,
        "PROVINCE": 5
      }
    },
    {
      "type": "Feature",
      "id": 9563,
      "geometry": {
        "type": "Point",
        "coordinates": [
          150.00013899991495,
          -9.630107000337773
        ]
      },
      "properties": {
        "OBJECTID": 9563,
        "CU_NAME": "RAUSEWA",
        "CU_NO": "008",
        "GEOCODE": "05010108008",
        "PROV_KEY": "05",
        "DIST_NO": "01",
        "LLG_NO": "01",
        "WARD_NO": "08",
        "WARD_NAME": "BOGABOGA",
        "LATITUDE": -9.62921,
        "LONGITUDE": 149.997848,
        "REGHH": 32,
        "TOTPOP2000": 151,
        "MALE2000": 83,
        "FEMALE2000": 68,
        "POP2008": 183,
        "G_RATE": 1.024999976158142,
        "Geocode_Num": 5010108008,
        "PROVINCE": 5
      }
    }
  ]
}