{
  "type": "FeatureCollection",
  "features": [
    {
      "type": "Feature",
      "id": 9565,
      "geometry": {
        "type": "Point",
        "coordinates": [
          150.0331539998573,
          -9.671578999970848
        ]
      },
      "properties": {
        "OBJECTID": 9565,
        "CU_NAME": "IRIKABA",
        "CU_NO": "001",
        "GEOCODE": "05010110001",
        "PROV_KEY": "05",
        "DIST_NO": "01",
        "LLG_NO": "01",
        "WARD_NO": "10",
        "WARD_NAME": "IRIKABA",
        "LATITUDE": -9.670073,
        "LONGITUDE": 150.033477,
        "REGHH": 15,
        "TOTPOP2000": 78,
        "MALE2000": 45,
        "FEMALE2000": 33,
        "POP2008": 94,
        "G_RATE": 1.024999976158142,
        "Geocode_Num": 5010110001,
        "PROVINCE": 5
      }
    },
    {
      "type": "Feature",
      "id": 9566,
      "geometry": {
        "type": "Point",
        "coordinates": [
          150.0335160003632,
          -9.683735000270019
        ]
      },
      "properties": {
        "OBJECTID": 9566,
        "CU_NAME": "REGIREGI",
        "CU_NO": "002",
        "GEOCODE": "05010110002",
        "PROV_KEY": "05",
        "DIST_NO": "01",
        "LLG_NO": "01",
        "WARD_NO": "10",
        "WARD_NAME": "IRIKABA",
        "LATITUDE": -9.684239,
        "LONGITUDE": 150.036679,
        "REGHH": 37,
        "TOTPOP2000": 178,
        "MALE2000": 84,
        "FEMALE2000": 94,
        "POP2008": 217,
        "G_RATE": 1.024999976158142,
        "Geocode_Num": 5010110002,
        "PROVINCE": 5
      }
    },
    {
      "type": "Feature",
      "id": 9567,
      "geometry": {
        "type": "Point",
        "coordinates": [
          150.0123789995912,
          -9.65709000000345
        ]
      },
      "properties": {
        "OBJECTID": 9567,
        "CU_NAME": "TARAKWARURU MISSION STN",
        "CU_NO": "501",
        "GEOCODE": "05010110501",
        "PROV_KEY": "05",
        "DIST_NO": "01",
        "LLG_NO": "01",
        "WARD_NO": "10",
        "WARD_NAME": "IRIKABA",
        "LATITUDE": -9.66182,
        "LONGITUDE": 150.013285,
        "REGHH": 15,
        "TOTPOP2000": 87,
        "MALE2000": 41,
        "FEMALE2000": 46,
        "POP2008": 104,
        "G_RATE": 1.024999976158142,
        "Geocode_Num": 5010110501,
        "PROVINCE": 5
      }
    }
  ]
}