{
  "type": "FeatureCollection",
  "features": [
    {
      "type": "Feature",
      "id": 9453,
      "geometry": {
        "type": "Point",
        "coordinates": [
          147.37454400020556,
          -2.0735889999323263
        ]
      },
      "properties": {
        "OBJECTID": 9453,
        "CU_NAME": "LOLAK",
        "CU_NO": "001",
        "GEOCODE": "16010702001",
        "PROV_KEY": "16",
        "DIST_NO": "01",
        "LLG_NO": "07",
        "WARD_NO": "02",
        "WARD_NAME": "LOLAK",
        "LATITUDE": -2.074955,
        "LONGITUDE": 147.373531,
        "REGHH": 22,
        "TOTPOP2000": 120,
        "MALE2000": 63,
        "FEMALE2000": 57,
        "POP2008": 147,
        "G_RATE": 1.0260000228881836,
        "Geocode_Num": 16010702001,
        "PROVINCE": 16
      }
    }
  ]
}