{
  "type": "FeatureCollection",
  "features": [
    {
      "type": "Feature",
      "id": 13245,
      "geometry": {
        "type": "Point",
        "coordinates": [
          148.36886099963544,
          -9.05112799965741
        ]
      },
      "properties": {
        "OBJECTID": 13245,
        "CU_NAME": "WUMBA/SIYURANA",
        "CU_NO": "021",
        "GEOCODE": "06010305021",
        "PROV_KEY": "06",
        "DIST_NO": "01",
        "LLG_NO": "03",
        "WARD_NO": "05",
        "WARD_NAME": "SIURANI",
        "LATITUDE": -9.052577,
        "LONGITUDE": 148.36785,
        "REGHH": 119,
        "TOTPOP2000": 756,
        "MALE2000": 392,
        "FEMALE2000": 364,
        "POP2008": 936,
        "G_RATE": 1.0269999504089355,
        "Geocode_Num": 6010305021,
        "PROVINCE": 6
      }
    }
  ]
}