{
  "type": "FeatureCollection",
  "features": [
    {
      "type": "Feature",
      "id": 7460,
      "geometry": {
        "type": "Point",
        "coordinates": [
          146.26753900042456,
          -8.343342999979427
        ]
      },
      "properties": {
        "OBJECTID": 7460,
        "CU_NAME": "MIARU",
        "CU_NO": "008",
        "GEOCODE": "02010206008",
        "PROV_KEY": "02",
        "DIST_NO": "01",
        "LLG_NO": "02",
        "WARD_NO": "06",
        "WARD_NAME": "MIARU",
        "LATITUDE": -8.343694,
        "LONGITUDE": 146.269055,
        "REGHH": 138,
        "TOTPOP2000": 845,
        "MALE2000": 452,
        "FEMALE2000": 393,
        "POP2008": 1038,
        "G_RATE": 1.0260000228881836,
        "Geocode_Num": 2010206008,
        "PROVINCE": 2
      }
    },
    {
      "type": "Feature",
      "id": 7461,
      "geometry": {
        "type": "Point",
        "coordinates": [
          146.31722100004913,
          -8.32416899979944
        ]
      },
      "properties": {
        "OBJECTID": 7461,
        "CU_NAME": "HAKE RAEPA",
        "CU_NO": "009",
        "GEOCODE": "02010206009",
        "PROV_KEY": "02",
        "DIST_NO": "01",
        "LLG_NO": "02",
        "WARD_NO": "06",
        "WARD_NAME": "MIARU",
        "LATITUDE": -8.325605,
        "LONGITUDE": 146.316184,
        "REGHH": 29,
        "TOTPOP2000": 142,
        "MALE2000": 80,
        "FEMALE2000": 62,
        "POP2008": 174,
        "G_RATE": 1.0260000228881836,
        "Geocode_Num": 2010206009,
        "PROVINCE": 2
      }
    },
    {
      "type": "Feature",
      "id": 7462,
      "geometry": {
        "type": "Point",
        "coordinates": [
          146.27794800020013,
          -8.337892000415422
        ]
      },
      "properties": {
        "OBJECTID": 7462,
        "CU_NAME": "HOUPOE/MIARU",
        "CU_NO": "010",
        "GEOCODE": "02010206010",
        "PROV_KEY": "02",
        "DIST_NO": "01",
        "LLG_NO": "02",
        "WARD_NO": "06",
        "WARD_NAME": "MIARU",
        "LATITUDE": -8.339328,
        "LONGITUDE": 146.27691,
        "REGHH": 34,
        "TOTPOP2000": 192,
        "MALE2000": 109,
        "FEMALE2000": 83,
        "POP2008": 236,
        "G_RATE": 1.0260000228881836,
        "Geocode_Num": 2010206010,
        "PROVINCE": 2
      }
    }
  ]
}