{
  "type": "FeatureCollection",
  "features": [
    {
      "type": "Feature",
      "id": 7463,
      "geometry": {
        "type": "Point",
        "coordinates": [
          146.27114500034156,
          -8.403623000001403
        ]
      },
      "properties": {
        "OBJECTID": 7463,
        "CU_NAME": "IOKEA",
        "CU_NO": "001",
        "GEOCODE": "02010207001",
        "PROV_KEY": "02",
        "DIST_NO": "01",
        "LLG_NO": "02",
        "WARD_NO": "07",
        "WARD_NAME": "IOKEA",
        "LATITUDE": -8.40506,
        "LONGITUDE": 146.270107,
        "REGHH": 255,
        "TOTPOP2000": 1684,
        "MALE2000": 880,
        "FEMALE2000": 804,
        "POP2008": 2068,
        "G_RATE": 1.0260000228881836,
        "Geocode_Num": 2010207001,
        "PROVINCE": 2
      }
    },
    {
      "type": "Feature",
      "id": 7464,
      "geometry": {
        "type": "Point",
        "coordinates": [
          146.2733599999641,
          -8.376600000289727
        ]
      },
      "properties": {
        "OBJECTID": 7464,
        "CU_NAME": "MIRAPO",
        "CU_NO": "009",
        "GEOCODE": "02010207009",
        "PROV_KEY": "02",
        "DIST_NO": "01",
        "LLG_NO": "02",
        "WARD_NO": "07",
        "WARD_NAME": "IOKEA",
        "LATITUDE": -8.378037,
        "LONGITUDE": 146.272322,
        "REGHH": 35,
        "TOTPOP2000": 234,
        "MALE2000": 118,
        "FEMALE2000": 116,
        "POP2008": 287,
        "G_RATE": 1.0260000228881836,
        "Geocode_Num": 2010207009,
        "PROVINCE": 2
      }
    }
  ]
}