{
  "type": "FeatureCollection",
  "features": [
    {
      "type": "Feature",
      "id": 12236,
      "geometry": {
        "type": "Point",
        "coordinates": [
          147.60405900022272,
          -6.145298000102571
        ]
      },
      "properties": {
        "OBJECTID": 12236,
        "CU_NAME": "KEMBURUM",
        "CU_NO": "013",
        "GEOCODE": "12092608013",
        "PROV_KEY": "12",
        "DIST_NO": "09",
        "LLG_NO": "26",
        "WARD_NO": "08",
        "WARD_NAME": "NUNZEN",
        "LATITUDE": -6.146714,
        "LONGITUDE": 147.603044,
        "REGHH": 25,
        "TOTPOP2000": 138,
        "MALE2000": 68,
        "FEMALE2000": 70,
        "POP2008": 172,
        "G_RATE": 1.027999997138977,
        "Geocode_Num": 12092608013,
        "PROVINCE": 12
      }
    },
    {
      "type": "Feature",
      "id": 12237,
      "geometry": {
        "type": "Point",
        "coordinates": [
          147.63711500025715,
          -6.148323000206233
        ]
      },
      "properties": {
        "OBJECTID": 12237,
        "CU_NAME": "NUNZEN",
        "CU_NO": "022",
        "GEOCODE": "12092608022",
        "PROV_KEY": "12",
        "DIST_NO": "09",
        "LLG_NO": "26",
        "WARD_NO": "08",
        "WARD_NAME": "NUNZEN",
        "LATITUDE": -6.148292,
        "LONGITUDE": 147.63675,
        "REGHH": 72,
        "TOTPOP2000": 397,
        "MALE2000": 192,
        "FEMALE2000": 205,
        "POP2008": 494,
        "G_RATE": 1.027999997138977,
        "Geocode_Num": 12092608022,
        "PROVINCE": 12
      }
    },
    {
      "type": "Feature",
      "id": 12238,
      "geometry": {
        "type": "Point",
        "coordinates": [
          147.60792899972364,
          -6.177424000417261
        ]
      },
      "properties": {
        "OBJECTID": 12238,
        "CU_NAME": "TUNGE",
        "CU_NO": "031",
        "GEOCODE": "12092608031",
        "PROV_KEY": "12",
        "DIST_NO": "09",
        "LLG_NO": "26",
        "WARD_NO": "08",
        "WARD_NAME": "NUNZEN",
        "LATITUDE": -6.176649,
        "LONGITUDE": 147.609409,
        "REGHH": 55,
        "TOTPOP2000": 271,
        "MALE2000": 152,
        "FEMALE2000": 119,
        "POP2008": 338,
        "G_RATE": 1.027999997138977,
        "Geocode_Num": 12092608031,
        "PROVINCE": 12
      }
    }
  ]
}