{
  "type": "FeatureCollection",
  "features": [
    {
      "type": "Feature",
      "id": 12257,
      "geometry": {
        "type": "Point",
        "coordinates": [
          147.70319599979564,
          -6.261078000049622
        ]
      },
      "properties": {
        "OBJECTID": 12257,
        "CU_NAME": "AGO",
        "CU_NO": "001",
        "GEOCODE": "12092614001",
        "PROV_KEY": "12",
        "DIST_NO": "09",
        "LLG_NO": "26",
        "WARD_NO": "14",
        "WARD_NAME": "WALINGAI",
        "LATITUDE": -6.261097,
        "LONGITUDE": 147.703577,
        "REGHH": 80,
        "TOTPOP2000": 401,
        "MALE2000": 208,
        "FEMALE2000": 193,
        "POP2008": 501,
        "G_RATE": 1.027999997138977,
        "Geocode_Num": 12092614001,
        "PROVINCE": 12
      }
    },
    {
      "type": "Feature",
      "id": 12258,
      "geometry": {
        "type": "Point",
        "coordinates": [
          147.65558700043982,
          -6.26124799979533
        ]
      },
      "properties": {
        "OBJECTID": 12258,
        "CU_NAME": "HUDEWA",
        "CU_NO": "006",
        "GEOCODE": "12092614006",
        "PROV_KEY": "12",
        "DIST_NO": "09",
        "LLG_NO": "26",
        "WARD_NO": "14",
        "WARD_NAME": "WALINGAI",
        "LATITUDE": -6.26048,
        "LONGITUDE": 147.652384,
        "REGHH": 52,
        "TOTPOP2000": 285,
        "MALE2000": 157,
        "FEMALE2000": 128,
        "POP2008": 355,
        "G_RATE": 1.027999997138977,
        "Geocode_Num": 12092614006,
        "PROVINCE": 12
      }
    },
    {
      "type": "Feature",
      "id": 12259,
      "geometry": {
        "type": "Point",
        "coordinates": [
          147.6926330001129,
          -6.2473310001254845
        ]
      },
      "properties": {
        "OBJECTID": 12259,
        "CU_NAME": "WALINGAI",
        "CU_NO": "013",
        "GEOCODE": "12092614013",
        "PROV_KEY": "12",
        "DIST_NO": "09",
        "LLG_NO": "26",
        "WARD_NO": "14",
        "WARD_NAME": "WALINGAI",
        "LATITUDE": -6.248745,
        "LONGITUDE": 147.693853,
        "REGHH": 54,
        "TOTPOP2000": 302,
        "MALE2000": 145,
        "FEMALE2000": 157,
        "POP2008": 376,
        "G_RATE": 1.027999997138977,
        "Geocode_Num": 12092614013,
        "PROVINCE": 12
      }
    }
  ]
}