{
  "type": "FeatureCollection",
  "features": [
    {
      "type": "Feature",
      "id": 17134,
      "geometry": {
        "type": "Point",
        "coordinates": [
          144.04538100013315,
          -5.548052999746119
        ]
      },
      "properties": {
        "OBJECTID": 17134,
        "CU_NAME": "KELUMANDA",
        "CU_NO": "002",
        "GEOCODE": "09051002002",
        "PROV_KEY": "09",
        "DIST_NO": "05",
        "LLG_NO": "10",
        "WARD_NO": "02",
        "WARD_NAME": "ROMBAU",
        "LATITUDE": -5.548988,
        "LONGITUDE": 144.045711,
        "REGHH": 50,
        "TOTPOP2000": 217,
        "MALE2000": 111,
        "FEMALE2000": 106,
        "POP2008": 264,
        "G_RATE": 1.024999976158142,
        "Geocode_Num": 9051002002,
        "PROVINCE": 9
      }
    },
    {
      "type": "Feature",
      "id": 17135,
      "geometry": {
        "type": "Point",
        "coordinates": [
          144.05971800028556,
          -5.550587999736365
        ]
      },
      "properties": {
        "OBJECTID": 17135,
        "CU_NAME": "LAMBAKIMBA",
        "CU_NO": "003",
        "GEOCODE": "09051002003",
        "PROV_KEY": "09",
        "DIST_NO": "05",
        "LLG_NO": "10",
        "WARD_NO": "02",
        "WARD_NAME": "ROMBAU",
        "LATITUDE": -5.551523,
        "LONGITUDE": 144.060048,
        "REGHH": 73,
        "TOTPOP2000": 296,
        "MALE2000": 156,
        "FEMALE2000": 140,
        "POP2008": 361,
        "G_RATE": 1.024999976158142,
        "Geocode_Num": 9051002003,
        "PROVINCE": 9
      }
    },
    {
      "type": "Feature",
      "id": 17136,
      "geometry": {
        "type": "Point",
        "coordinates": [
          144.0677520002547,
          -5.548843000204272
        ]
      },
      "properties": {
        "OBJECTID": 17136,
        "CU_NAME": "ROMBAU C/SCHOOL",
        "CU_NO": "401",
        "GEOCODE": "09051002401",
        "PROV_KEY": "09",
        "DIST_NO": "05",
        "LLG_NO": "10",
        "WARD_NO": "02",
        "WARD_NAME": "ROMBAU",
        "LATITUDE": -5.549778,
        "LONGITUDE": 144.068083,
        "REGHH": 3,
        "TOTPOP2000": 4,
        "MALE2000": 3,
        "FEMALE2000": 1,
        "POP2008": 4,
        "G_RATE": 1.024999976158142,
        "Geocode_Num": 9051002401,
        "PROVINCE": 9
      }
    }
  ]
}