{
  "type": "FeatureCollection",
  "features": [
    {
      "type": "Feature",
      "id": 17151,
      "geometry": {
        "type": "Point",
        "coordinates": [
          144.07039499982943,
          -5.530142000253079
        ]
      },
      "properties": {
        "OBJECTID": 17151,
        "CU_NAME": "KUMIAKAMA",
        "CU_NO": "001",
        "GEOCODE": "09051010001",
        "PROV_KEY": "09",
        "DIST_NO": "05",
        "LLG_NO": "10",
        "WARD_NO": "10",
        "WARD_NAME": "MANO",
        "LATITUDE": -5.531077,
        "LONGITUDE": 144.070727,
        "REGHH": 27,
        "TOTPOP2000": 113,
        "MALE2000": 62,
        "FEMALE2000": 51,
        "POP2008": 137,
        "G_RATE": 1.024999976158142,
        "Geocode_Num": 9051010001,
        "PROVINCE": 9
      }
    },
    {
      "type": "Feature",
      "id": 17152,
      "geometry": {
        "type": "Point",
        "coordinates": [
          144.06985800024654,
          -5.532756000289112
        ]
      },
      "properties": {
        "OBJECTID": 17152,
        "CU_NAME": "KANAPETA",
        "CU_NO": "002",
        "GEOCODE": "09051010002",
        "PROV_KEY": "09",
        "DIST_NO": "05",
        "LLG_NO": "10",
        "WARD_NO": "10",
        "WARD_NAME": "MANO",
        "LATITUDE": -5.533691,
        "LONGITUDE": 144.07019,
        "REGHH": 41,
        "TOTPOP2000": 186,
        "MALE2000": 91,
        "FEMALE2000": 95,
        "POP2008": 227,
        "G_RATE": 1.024999976158142,
        "Geocode_Num": 9051010002,
        "PROVINCE": 9
      }
    }
  ]
}