{
  "type": "FeatureCollection",
  "features": [
    {
      "type": "Feature",
      "id": 17177,
      "geometry": {
        "type": "Point",
        "coordinates": [
          144.04324999988762,
          -5.53918099980325
        ]
      },
      "properties": {
        "OBJECTID": 17177,
        "CU_NAME": "KIAKAPALE",
        "CU_NO": "001",
        "GEOCODE": "09051020001",
        "PROV_KEY": "09",
        "DIST_NO": "05",
        "LLG_NO": "10",
        "WARD_NO": "20",
        "WARD_NAME": "KAKEMALI.2",
        "LATITUDE": -5.540116,
        "LONGITUDE": 144.04358,
        "REGHH": 37,
        "TOTPOP2000": 181,
        "MALE2000": 92,
        "FEMALE2000": 89,
        "POP2008": 221,
        "G_RATE": 1.024999976158142,
        "Geocode_Num": 9051020001,
        "PROVINCE": 9
      }
    },
    {
      "type": "Feature",
      "id": 17178,
      "geometry": {
        "type": "Point",
        "coordinates": [
          144.04378500027758,
          -5.54163399960936
        ]
      },
      "properties": {
        "OBJECTID": 17178,
        "CU_NAME": "LAUKANDA",
        "CU_NO": "002",
        "GEOCODE": "09051020002",
        "PROV_KEY": "09",
        "DIST_NO": "05",
        "LLG_NO": "10",
        "WARD_NO": "20",
        "WARD_NAME": "KAKEMALI.2",
        "LATITUDE": -5.542569,
        "LONGITUDE": 144.044115,
        "REGHH": 8,
        "TOTPOP2000": 46,
        "MALE2000": 24,
        "FEMALE2000": 22,
        "POP2008": 54,
        "G_RATE": 1.024999976158142,
        "Geocode_Num": 9051020002,
        "PROVINCE": 9
      }
    }
  ]
}