{
  "type": "FeatureCollection",
  "features": [
    {
      "type": "Feature",
      "id": 17179,
      "geometry": {
        "type": "Point",
        "coordinates": [
          144.02426173848846,
          -5.538284309173491
        ]
      },
      "properties": {
        "OBJECTID": 17179,
        "CU_NAME": "RAKA",
        "CU_NO": "001",
        "GEOCODE": "09051021001",
        "PROV_KEY": "09",
        "DIST_NO": "05",
        "LLG_NO": "10",
        "WARD_NO": "21",
        "WARD_NAME": "KAKEMALI.3",
        "LATITUDE": -5.54743,
        "LONGITUDE": 144.033064,
        "REGHH": 18,
        "TOTPOP2000": 60,
        "MALE2000": 37,
        "FEMALE2000": 23,
        "POP2008": 75,
        "G_RATE": 1.024999976158142,
        "Geocode_Num": 9051021001,
        "PROVINCE": 9
      }
    },
    {
      "type": "Feature",
      "id": 17180,
      "geometry": {
        "type": "Point",
        "coordinates": [
          144.03002892349605,
          -5.5451968149809545
        ]
      },
      "properties": {
        "OBJECTID": 17180,
        "CU_NAME": "SIPSMANDA",
        "CU_NO": "002",
        "GEOCODE": "09051021002",
        "PROV_KEY": "09",
        "DIST_NO": "05",
        "LLG_NO": "10",
        "WARD_NO": "21",
        "WARD_NAME": "KAKEMALI.3",
        "LATITUDE": -5.549988,
        "LONGITUDE": 144.033578,
        "REGHH": 13,
        "TOTPOP2000": 74,
        "MALE2000": 35,
        "FEMALE2000": 39,
        "POP2008": 90,
        "G_RATE": 1.024999976158142,
        "Geocode_Num": 9051021002,
        "PROVINCE": 9
      }
    },
    {
      "type": "Feature",
      "id": 17181,
      "geometry": {
        "type": "Point",
        "coordinates": [
          144.03448400033642,
          -5.55125700001048
        ]
      },
      "properties": {
        "OBJECTID": 17181,
        "CU_NAME": "RAPUNASA",
        "CU_NO": "003",
        "GEOCODE": "09051021003",
        "PROV_KEY": "09",
        "DIST_NO": "05",
        "LLG_NO": "10",
        "WARD_NO": "21",
        "WARD_NAME": "KAKEMALI.3",
        "LATITUDE": -5.552034,
        "LONGITUDE": 144.034349,
        "REGHH": 17,
        "TOTPOP2000": 69,
        "MALE2000": 31,
        "FEMALE2000": 38,
        "POP2008": 85,
        "G_RATE": 1.024999976158142,
        "Geocode_Num": 9051021003,
        "PROVINCE": 9
      }
    }
  ]
}