{
  "type": "FeatureCollection",
  "features": [
    {
      "type": "Feature",
      "id": 18878,
      "geometry": {
        "type": "Point",
        "coordinates": [
          141.22133400026394,
          -3.61196500038443
        ]
      },
      "properties": {
        "OBJECTID": 18878,
        "CU_NAME": "AURUMP",
        "CU_NO": "003",
        "GEOCODE": "15041213003",
        "PROV_KEY": "15",
        "DIST_NO": "04",
        "LLG_NO": "12",
        "WARD_NO": "13",
        "WARD_NAME": "IVEIG",
        "LATITUDE": -3.613344,
        "LONGITUDE": 141.220242,
        "REGHH": 30,
        "TOTPOP2000": 170,
        "MALE2000": 93,
        "FEMALE2000": 77,
        "POP2008": 205,
        "G_RATE": 1.0240000486373901,
        "Geocode_Num": 15041213003,
        "PROVINCE": 15
      }
    },
    {
      "type": "Feature",
      "id": 18879,
      "geometry": {
        "type": "Point",
        "coordinates": [
          141.20784000031585,
          -3.5891979999876753
        ]
      },
      "properties": {
        "OBJECTID": 18879,
        "CU_NAME": "IFIGERI",
        "CU_NO": "011",
        "GEOCODE": "15041213011",
        "PROV_KEY": "15",
        "DIST_NO": "04",
        "LLG_NO": "12",
        "WARD_NO": "13",
        "WARD_NAME": "IVEIG",
        "LATITUDE": -3.590576,
        "LONGITUDE": 141.206748,
        "REGHH": 16,
        "TOTPOP2000": 73,
        "MALE2000": 40,
        "FEMALE2000": 33,
        "POP2008": 89,
        "G_RATE": 1.0240000486373901,
        "Geocode_Num": 15041213011,
        "PROVINCE": 15
      }
    },
    {
      "type": "Feature",
      "id": 18880,
      "geometry": {
        "type": "Point",
        "coordinates": [
          141.19627700038336,
          -3.5946319996670013
        ]
      },
      "properties": {
        "OBJECTID": 18880,
        "CU_NAME": "IFRAMINAG",
        "CU_NO": "012",
        "GEOCODE": "15041213012",
        "PROV_KEY": "15",
        "DIST_NO": "04",
        "LLG_NO": "12",
        "WARD_NO": "13",
        "WARD_NAME": "IVEIG",
        "LATITUDE": -3.592711,
        "LONGITUDE": 141.197529,
        "REGHH": 29,
        "TOTPOP2000": 161,
        "MALE2000": 90,
        "FEMALE2000": 71,
        "POP2008": 194,
        "G_RATE": 1.0240000486373901,
        "Geocode_Num": 15041213012,
        "PROVINCE": 15
      }
    },
    {
      "type": "Feature",
      "id": 18881,
      "geometry": {
        "type": "Point",
        "coordinates": [
          141.2241050003455,
          -3.6239679999231953
        ]
      },
      "properties": {
        "OBJECTID": 18881,
        "CU_NAME": "IVEIG",
        "CU_NO": "013",
        "GEOCODE": "15041213013",
        "PROV_KEY": "15",
        "DIST_NO": "04",
        "LLG_NO": "12",
        "WARD_NO": "13",
        "WARD_NAME": "IVEIG",
        "LATITUDE": -3.625347,
        "LONGITUDE": 141.223013,
        "REGHH": 39,
        "TOTPOP2000": 207,
        "MALE2000": 104,
        "FEMALE2000": 103,
        "POP2008": 250,
        "G_RATE": 1.0240000486373901,
        "Geocode_Num": 15041213013,
        "PROVINCE": 15
      }
    }
  ]
}