{
  "type": "FeatureCollection",
  "features": [
    {
      "type": "Feature",
      "id": 18893,
      "geometry": {
        "type": "Point",
        "coordinates": [
          141.61598800024603,
          -3.3724279995524853
        ]
      },
      "properties": {
        "OBJECTID": 18893,
        "CU_NAME": "AIAMINA",
        "CU_NO": "001",
        "GEOCODE": "15041216001",
        "PROV_KEY": "15",
        "DIST_NO": "04",
        "LLG_NO": "12",
        "WARD_NO": "16",
        "WARD_NAME": "UTAI",
        "LATITUDE": -3.373805,
        "LONGITUDE": 141.614901,
        "REGHH": 12,
        "TOTPOP2000": 110,
        "MALE2000": 57,
        "FEMALE2000": 53,
        "POP2008": 134,
        "G_RATE": 1.0240000486373901,
        "Geocode_Num": 15041216001,
        "PROVINCE": 15
      }
    },
    {
      "type": "Feature",
      "id": 18894,
      "geometry": {
        "type": "Point",
        "coordinates": [
          141.59795899980804,
          -3.376372999814066
        ]
      },
      "properties": {
        "OBJECTID": 18894,
        "CU_NAME": "EKAS",
        "CU_NO": "004",
        "GEOCODE": "15041216004",
        "PROV_KEY": "15",
        "DIST_NO": "04",
        "LLG_NO": "12",
        "WARD_NO": "16",
        "WARD_NAME": "UTAI",
        "LATITUDE": -3.373035,
        "LONGITUDE": 141.600619,
        "REGHH": 15,
        "TOTPOP2000": 110,
        "MALE2000": 50,
        "FEMALE2000": 60,
        "POP2008": 134,
        "G_RATE": 1.0240000486373901,
        "Geocode_Num": 15041216004,
        "PROVINCE": 15
      }
    },
    {
      "type": "Feature",
      "id": 18895,
      "geometry": {
        "type": "Point",
        "coordinates": [
          141.68783699957794,
          -3.4026120002435505
        ]
      },
      "properties": {
        "OBJECTID": 18895,
        "CU_NAME": "WURUBAI",
        "CU_NO": "014",
        "GEOCODE": "15041216014",
        "PROV_KEY": "15",
        "DIST_NO": "04",
        "LLG_NO": "12",
        "WARD_NO": "16",
        "WARD_NAME": "UTAI",
        "LATITUDE": -3.403989,
        "LONGITUDE": 141.686749,
        "REGHH": 12,
        "TOTPOP2000": 73,
        "MALE2000": 36,
        "FEMALE2000": 37,
        "POP2008": 89,
        "G_RATE": 1.0240000486373901,
        "Geocode_Num": 15041216014,
        "PROVINCE": 15
      }
    },
    {
      "type": "Feature",
      "id": 18896,
      "geometry": {
        "type": "Point",
        "coordinates": [
          141.59519700014152,
          -3.392027000445694
        ]
      },
      "properties": {
        "OBJECTID": 18896,
        "CU_NAME": "UTAI",
        "CU_NO": "015",
        "GEOCODE": "15041216015",
        "PROV_KEY": "15",
        "DIST_NO": "04",
        "LLG_NO": "12",
        "WARD_NO": "16",
        "WARD_NAME": "UTAI",
        "LATITUDE": -3.390507,
        "LONGITUDE": 141.583997,
        "REGHH": 24,
        "TOTPOP2000": 159,
        "MALE2000": 83,
        "FEMALE2000": 76,
        "POP2008": 191,
        "G_RATE": 1.0240000486373901,
        "Geocode_Num": 15041216015,
        "PROVINCE": 15
      }
    }
  ]
}