{
  "type": "FeatureCollection",
  "features": [
    {
      "type": "Feature",
      "id": 12203,
      "geometry": {
        "type": "Point",
        "coordinates": [
          146.88971999957835,
          -6.434879000165665
        ]
      },
      "properties": {
        "OBJECTID": 12203,
        "CU_NAME": "GUMBUM",
        "CU_NO": "011",
        "GEOCODE": "12082517011",
        "PROV_KEY": "12",
        "DIST_NO": "08",
        "LLG_NO": "25",
        "WARD_NO": "17",
        "WARD_NAME": "GUMBUM",
        "LATITUDE": -6.436297,
        "LONGITUDE": 146.888695,
        "REGHH": 24,
        "TOTPOP2000": 126,
        "MALE2000": 77,
        "FEMALE2000": 49,
        "POP2008": 158,
        "G_RATE": 1.027999997138977,
        "Geocode_Num": 12082517011,
        "PROVINCE": 12
      }
    },
    {
      "type": "Feature",
      "id": 12204,
      "geometry": {
        "type": "Point",
        "coordinates": [
          146.88930400017955,
          -6.424004999630995
        ]
      },
      "properties": {
        "OBJECTID": 12204,
        "CU_NAME": "GAYARAN",
        "CU_NO": "012",
        "GEOCODE": "12082517012",
        "PROV_KEY": "12",
        "DIST_NO": "08",
        "LLG_NO": "25",
        "WARD_NO": "17",
        "WARD_NAME": "GUMBUM",
        "LATITUDE": -6.425423,
        "LONGITUDE": 146.888279,
        "REGHH": 23,
        "TOTPOP2000": 78,
        "MALE2000": 40,
        "FEMALE2000": 38,
        "POP2008": 96,
        "G_RATE": 1.027999997138977,
        "Geocode_Num": 12082517012,
        "PROVINCE": 12
      }
    },
    {
      "type": "Feature",
      "id": 12205,
      "geometry": {
        "type": "Point",
        "coordinates": [
          146.87166000040872,
          -6.438166999807152
        ]
      },
      "properties": {
        "OBJECTID": 12205,
        "CU_NAME": "KARAU",
        "CU_NO": "013",
        "GEOCODE": "12082517013",
        "PROV_KEY": "12",
        "DIST_NO": "08",
        "LLG_NO": "25",
        "WARD_NO": "17",
        "WARD_NAME": "GUMBUM",
        "LATITUDE": -6.442606,
        "LONGITUDE": 146.872648,
        "REGHH": 36,
        "TOTPOP2000": 187,
        "MALE2000": 99,
        "FEMALE2000": 88,
        "POP2008": 233,
        "G_RATE": 1.027999997138977,
        "Geocode_Num": 12082517013,
        "PROVINCE": 12
      }
    }
  ]
}