{
  "type": "FeatureCollection",
  "features": [
    {
      "type": "Feature",
      "id": 9850,
      "geometry": {
        "type": "Point",
        "coordinates": [
          150.5643440000756,
          -10.619637000247337
        ]
      },
      "properties": {
        "OBJECTID": 9850,
        "CU_NAME": "GADOGADOWA",
        "CU_NO": "006",
        "GEOCODE": "05020806006",
        "PROV_KEY": "05",
        "DIST_NO": "02",
        "LLG_NO": "08",
        "WARD_NO": "06",
        "WARD_NAME": "GOTAI",
        "LATITUDE": -10.621705,
        "LONGITUDE": 150.565331,
        "REGHH": 42,
        "TOTPOP2000": 247,
        "MALE2000": 138,
        "FEMALE2000": 109,
        "POP2008": 300,
        "G_RATE": 1.024999976158142,
        "Geocode_Num": 5020806006,
        "PROVINCE": 5
      }
    },
    {
      "type": "Feature",
      "id": 9851,
      "geometry": {
        "type": "Point",
        "coordinates": [
          150.87960900015526,
          -10.649167999603435
        ]
      },
      "properties": {
        "OBJECTID": 9851,
        "CU_NAME": "GOTAI",
        "CU_NO": "007",
        "GEOCODE": "05020806007",
        "PROV_KEY": "05",
        "DIST_NO": "02",
        "LLG_NO": "08",
        "WARD_NO": "06",
        "WARD_NAME": "GOTAI",
        "LATITUDE": -10.651779,
        "LONGITUDE": 150.880142,
        "REGHH": 33,
        "TOTPOP2000": 179,
        "MALE2000": 91,
        "FEMALE2000": 88,
        "POP2008": 218,
        "G_RATE": 1.024999976158142,
        "Geocode_Num": 5020806007,
        "PROVINCE": 5
      }
    }
  ]
}