{
  "type": "FeatureCollection",
  "features": [
    {
      "type": "Feature",
      "id": 7471,
      "geometry": {
        "type": "Point",
        "coordinates": [
          146.02749000026336,
          -7.466724999958728
        ]
      },
      "properties": {
        "OBJECTID": 7471,
        "CU_NAME": "BEMA",
        "CU_NO": "001",
        "GEOCODE": "02010301001",
        "PROV_KEY": "02",
        "DIST_NO": "01",
        "LLG_NO": "03",
        "WARD_NO": "01",
        "WARD_NAME": "BEMA",
        "LATITUDE": -7.468152,
        "LONGITUDE": 146.026451,
        "REGHH": 34,
        "TOTPOP2000": 176,
        "MALE2000": 84,
        "FEMALE2000": 92,
        "POP2008": 216,
        "G_RATE": 1.0260000228881836,
        "Geocode_Num": 2010301001,
        "PROVINCE": 2
      }
    },
    {
      "type": "Feature",
      "id": 7472,
      "geometry": {
        "type": "Point",
        "coordinates": [
          146.0608839996969,
          -7.462616000228195
        ]
      },
      "properties": {
        "OBJECTID": 7472,
        "CU_NAME": "YAMBONA",
        "CU_NO": "016",
        "GEOCODE": "02010301016",
        "PROV_KEY": "02",
        "DIST_NO": "01",
        "LLG_NO": "03",
        "WARD_NO": "01",
        "WARD_NAME": "BEMA",
        "LATITUDE": -7.464043,
        "LONGITUDE": 146.059845,
        "REGHH": 71,
        "TOTPOP2000": 365,
        "MALE2000": 175,
        "FEMALE2000": 190,
        "POP2008": 448,
        "G_RATE": 1.0260000228881836,
        "Geocode_Num": 2010301016,
        "PROVINCE": 2
      }
    },
    {
      "type": "Feature",
      "id": 7473,
      "geometry": {
        "type": "Point",
        "coordinates": [
          146.0294899998637,
          -7.468339999791112
        ]
      },
      "properties": {
        "OBJECTID": 7473,
        "CU_NAME": "KEATANGA",
        "CU_NO": "017",
        "GEOCODE": "02010301017",
        "PROV_KEY": "02",
        "DIST_NO": "01",
        "LLG_NO": "03",
        "WARD_NO": "01",
        "WARD_NAME": "BEMA",
        "LATITUDE": -7.469767,
        "LONGITUDE": 146.028451,
        "REGHH": 14,
        "TOTPOP2000": 88,
        "MALE2000": 44,
        "FEMALE2000": 44,
        "POP2008": 107,
        "G_RATE": 1.0260000228881836,
        "Geocode_Num": 2010301017,
        "PROVINCE": 2
      }
    },
    {
      "type": "Feature",
      "id": 7474,
      "geometry": {
        "type": "Point",
        "coordinates": [
          146.02726399973392,
          -7.46308600031864
        ]
      },
      "properties": {
        "OBJECTID": 7474,
        "CU_NAME": "BEMA CATHOLIC MISSION",
        "CU_NO": "401",
        "GEOCODE": "02010301401",
        "PROV_KEY": "02",
        "DIST_NO": "01",
        "LLG_NO": "03",
        "WARD_NO": "01",
        "WARD_NAME": "BEMA",
        "LATITUDE": -7.464513,
        "LONGITUDE": 146.026225,
        "REGHH": 14,
        "TOTPOP2000": 71,
        "MALE2000": 32,
        "FEMALE2000": 39,
        "POP2008": 87,
        "G_RATE": 1.0260000228881836,
        "Geocode_Num": 2010301401,
        "PROVINCE": 2
      }
    }
  ]
}