{
  "type": "FeatureCollection",
  "features": [
    {
      "type": "Feature",
      "id": 7475,
      "geometry": {
        "type": "Point",
        "coordinates": [
          146.02697900008081,
          -7.4612949995645295
        ]
      },
      "properties": {
        "OBJECTID": 7475,
        "CU_NAME": "MINE",
        "CU_NO": "012",
        "GEOCODE": "02010302012",
        "PROV_KEY": "02",
        "DIST_NO": "01",
        "LLG_NO": "03",
        "WARD_NO": "02",
        "WARD_NAME": "MINE",
        "LATITUDE": -7.462722,
        "LONGITUDE": 146.02594,
        "REGHH": 46,
        "TOTPOP2000": 232,
        "MALE2000": 115,
        "FEMALE2000": 117,
        "POP2008": 285,
        "G_RATE": 1.0260000228881836,
        "Geocode_Num": 2010302012,
        "PROVINCE": 2
      }
    },
    {
      "type": "Feature",
      "id": 7476,
      "geometry": {
        "type": "Point",
        "coordinates": [
          146.02081700010456,
          -7.450548000389858
        ]
      },
      "properties": {
        "OBJECTID": 7476,
        "CU_NAME": "SANGANE",
        "CU_NO": "013",
        "GEOCODE": "02010302013",
        "PROV_KEY": "02",
        "DIST_NO": "01",
        "LLG_NO": "03",
        "WARD_NO": "02",
        "WARD_NAME": "MINE",
        "LATITUDE": -7.451975,
        "LONGITUDE": 146.019778,
        "REGHH": 50,
        "TOTPOP2000": 206,
        "MALE2000": 103,
        "FEMALE2000": 103,
        "POP2008": 252,
        "G_RATE": 1.0260000228881836,
        "Geocode_Num": 2010302013,
        "PROVINCE": 2
      }
    },
    {
      "type": "Feature",
      "id": 7477,
      "geometry": {
        "type": "Point",
        "coordinates": [
          146.00570400013953,
          -7.46522900021813
        ]
      },
      "properties": {
        "OBJECTID": 7477,
        "CU_NAME": "PULUANGA",
        "CU_NO": "014",
        "GEOCODE": "02010302014",
        "PROV_KEY": "02",
        "DIST_NO": "01",
        "LLG_NO": "03",
        "WARD_NO": "02",
        "WARD_NAME": "MINE",
        "LATITUDE": -7.459302,
        "LONGITUDE": 145.995041,
        "REGHH": 10,
        "TOTPOP2000": 49,
        "MALE2000": 24,
        "FEMALE2000": 25,
        "POP2008": 57,
        "G_RATE": 1.0260000228881836,
        "Geocode_Num": 2010302014,
        "PROVINCE": 2
      }
    }
  ]
}