{
  "type": "FeatureCollection",
  "features": [
    {
      "type": "Feature",
      "id": 20512,
      "geometry": {
        "type": "Point",
        "coordinates": [
          142.6590670000421,
          -5.53149899987892
        ]
      },
      "properties": {
        "OBJECTID": 20512,
        "CU_NAME": "KEWE 1",
        "CU_NO": "001",
        "GEOCODE": "07051415001",
        "PROV_KEY": "21",
        "DIST_NO": "2",
        "LLG_NO": "14",
        "WARD_NO": "15",
        "WARD_NAME": "KEWE 1",
        "LATITUDE": -5.535411,
        "LONGITUDE": 142.656415,
        "REGHH": 42,
        "TOTPOP2000": 159,
        "MALE2000": 68,
        "FEMALE2000": 91,
        "POP2008": 222,
        "G_RATE": 1.0420000553131104,
        "Geocode_Num": 7051415001,
        "PROVINCE": 21
      }
    },
    {
      "type": "Feature",
      "id": 20513,
      "geometry": {
        "type": "Point",
        "coordinates": [
          142.65484399955096,
          -5.532493999898122
        ]
      },
      "properties": {
        "OBJECTID": 20513,
        "CU_NAME": "TADE",
        "CU_NO": "002",
        "GEOCODE": "07051415002",
        "PROV_KEY": "21",
        "DIST_NO": "2",
        "LLG_NO": "14",
        "WARD_NO": "15",
        "WARD_NAME": "KEWE 1",
        "LATITUDE": -5.535411,
        "LONGITUDE": 142.656415,
        "REGHH": 17,
        "TOTPOP2000": 56,
        "MALE2000": 22,
        "FEMALE2000": 34,
        "POP2008": 78,
        "G_RATE": 1.0420000553131104,
        "Geocode_Num": 7051415002,
        "PROVINCE": 21
      }
    },
    {
      "type": "Feature",
      "id": 20514,
      "geometry": {
        "type": "Point",
        "coordinates": [
          142.6546480004049,
          -5.529664999839838
        ]
      },
      "properties": {
        "OBJECTID": 20514,
        "CU_NAME": "PII",
        "CU_NO": "003",
        "GEOCODE": "07051415003",
        "PROV_KEY": "21",
        "DIST_NO": "2",
        "LLG_NO": "14",
        "WARD_NO": "15",
        "WARD_NAME": "KEWE 1",
        "LATITUDE": -5.535411,
        "LONGITUDE": 142.656415,
        "REGHH": 26,
        "TOTPOP2000": 78,
        "MALE2000": 39,
        "FEMALE2000": 39,
        "POP2008": 108,
        "G_RATE": 1.0420000553131104,
        "Geocode_Num": 7051415003,
        "PROVINCE": 21
      }
    },
    {
      "type": "Feature",
      "id": 20515,
      "geometry": {
        "type": "Point",
        "coordinates": [
          142.65746700000216,
          -5.5292800000718785
        ]
      },
      "properties": {
        "OBJECTID": 20515,
        "CU_NAME": "TERUNI",
        "CU_NO": "004",
        "GEOCODE": "07051415004",
        "PROV_KEY": "21",
        "DIST_NO": "2",
        "LLG_NO": "14",
        "WARD_NO": "15",
        "WARD_NAME": "KEWE 1",
        "LATITUDE": -5.535411,
        "LONGITUDE": 142.656415,
        "REGHH": 53,
        "TOTPOP2000": 233,
        "MALE2000": 108,
        "FEMALE2000": 125,
        "POP2008": 325,
        "G_RATE": 1.0420000553131104,
        "Geocode_Num": 7051415004,
        "PROVINCE": 21
      }
    }
  ]
}