{
  "type": "FeatureCollection",
  "features": [
    {
      "type": "Feature",
      "id": 6550,
      "geometry": {
        "type": "Point",
        "coordinates": [
          143.85594300016942,
          -4.613274000294837
        ]
      },
      "properties": {
        "OBJECTID": 6550,
        "CU_NAME": "GIRIN",
        "CU_NO": "016",
        "GEOCODE": "14020912016",
        "PROV_KEY": "14",
        "DIST_NO": "02",
        "LLG_NO": "09",
        "WARD_NO": "12",
        "WARD_NAME": "GIRIN",
        "LATITUDE": -4.602663,
        "LONGITUDE": 143.844495,
        "REGHH": 35,
        "TOTPOP2000": 217,
        "MALE2000": 105,
        "FEMALE2000": 112,
        "POP2008": 258,
        "G_RATE": 1.0219999551773071,
        "Geocode_Num": 14020912016,
        "PROVINCE": 14
      }
    },
    {
      "type": "Feature",
      "id": 6551,
      "geometry": {
        "type": "Point",
        "coordinates": [
          143.8542009998763,
          -4.602479999852051
        ]
      },
      "properties": {
        "OBJECTID": 6551,
        "CU_NAME": "MUNDAMBA",
        "CU_NO": "025",
        "GEOCODE": "14020912025",
        "PROV_KEY": "14",
        "DIST_NO": "02",
        "LLG_NO": "09",
        "WARD_NO": "12",
        "WARD_NAME": "GIRIN",
        "LATITUDE": -4.608192,
        "LONGITUDE": 143.842819,
        "REGHH": 27,
        "TOTPOP2000": 182,
        "MALE2000": 73,
        "FEMALE2000": 109,
        "POP2008": 216,
        "G_RATE": 1.0219999551773071,
        "Geocode_Num": 14020912025,
        "PROVINCE": 14
      }
    }
  ]
}