{
  "type": "FeatureCollection",
  "features": [
    {
      "type": "Feature",
      "id": 6560,
      "geometry": {
        "type": "Point",
        "coordinates": [
          143.8126340003589,
          -4.410947999550501
        ]
      },
      "properties": {
        "OBJECTID": 6560,
        "CU_NAME": "ANDEFUKUAN",
        "CU_NO": "003",
        "GEOCODE": "14020918003",
        "PROV_KEY": "14",
        "DIST_NO": "02",
        "LLG_NO": "09",
        "WARD_NO": "18",
        "WARD_NAME": "ANDEFUKUAN",
        "LATITUDE": -4.410425,
        "LONGITUDE": 143.829692,
        "REGHH": 70,
        "TOTPOP2000": 432,
        "MALE2000": 215,
        "FEMALE2000": 217,
        "POP2008": 515,
        "G_RATE": 1.0219999551773071,
        "Geocode_Num": 14020918003,
        "PROVINCE": 14
      }
    },
    {
      "type": "Feature",
      "id": 6561,
      "geometry": {
        "type": "Point",
        "coordinates": [
          143.8199460003077,
          -4.38697200005771
        ]
      },
      "properties": {
        "OBJECTID": 6561,
        "CU_NAME": "DOWANING",
        "CU_NO": "014",
        "GEOCODE": "14020918014",
        "PROV_KEY": "14",
        "DIST_NO": "02",
        "LLG_NO": "09",
        "WARD_NO": "18",
        "WARD_NAME": "ANDEFUKUAN",
        "LATITUDE": -4.388559,
        "LONGITUDE": 143.818715,
        "REGHH": 42,
        "TOTPOP2000": 253,
        "MALE2000": 116,
        "FEMALE2000": 137,
        "POP2008": 301,
        "G_RATE": 1.0219999551773071,
        "Geocode_Num": 14020918014,
        "PROVINCE": 14
      }
    }
  ]
}