{
  "type": "FeatureCollection",
  "features": [
    {
      "type": "Feature",
      "id": 10722,
      "geometry": {
        "type": "Point",
        "coordinates": [
          147.41676400015854,
          -6.406934000203876
        ]
      },
      "properties": {
        "OBJECTID": 10722,
        "CU_NAME": "TOBOU",
        "CU_NO": "001",
        "GEOCODE": "12020614001",
        "PROV_KEY": "12",
        "DIST_NO": "02",
        "LLG_NO": "06",
        "WARD_NO": "14",
        "WARD_NAME": "TOBOU",
        "LATITUDE": -6.401976,
        "LONGITUDE": 147.420549,
        "REGHH": 40,
        "TOTPOP2000": 176,
        "MALE2000": 83,
        "FEMALE2000": 93,
        "POP2008": 219,
        "G_RATE": 1.027999997138977,
        "Geocode_Num": 12020614001,
        "PROVINCE": 12
      }
    },
    {
      "type": "Feature",
      "id": 10723,
      "geometry": {
        "type": "Point",
        "coordinates": [
          147.44009799972298,
          -6.367401000056077
        ]
      },
      "properties": {
        "OBJECTID": 10723,
        "CU_NAME": "LAULAU",
        "CU_NO": "002",
        "GEOCODE": "12020614002",
        "PROV_KEY": "12",
        "DIST_NO": "02",
        "LLG_NO": "06",
        "WARD_NO": "14",
        "WARD_NAME": "TOBOU",
        "LATITUDE": -6.370202,
        "LONGITUDE": 147.438044,
        "REGHH": 34,
        "TOTPOP2000": 151,
        "MALE2000": 57,
        "FEMALE2000": 94,
        "POP2008": 188,
        "G_RATE": 1.027999997138977,
        "Geocode_Num": 12020614002,
        "PROVINCE": 12
      }
    },
    {
      "type": "Feature",
      "id": 10724,
      "geometry": {
        "type": "Point",
        "coordinates": [
          147.43275700023548,
          -6.414610999897661
        ]
      },
      "properties": {
        "OBJECTID": 10724,
        "CU_NAME": "HENDENENG",
        "CU_NO": "005",
        "GEOCODE": "12020614005",
        "PROV_KEY": "12",
        "DIST_NO": "02",
        "LLG_NO": "06",
        "WARD_NO": "14",
        "WARD_NAME": "TOBOU",
        "LATITUDE": -6.41603,
        "LONGITUDE": 147.431739,
        "REGHH": 30,
        "TOTPOP2000": 132,
        "MALE2000": 60,
        "FEMALE2000": 72,
        "POP2008": 164,
        "G_RATE": 1.027999997138977,
        "Geocode_Num": 12020614005,
        "PROVINCE": 12
      }
    }
  ]
}