{
  "type": "FeatureCollection",
  "features": [
    {
      "type": "Feature",
      "id": 15476,
      "geometry": {
        "type": "Point",
        "coordinates": [
          141.43529699985675,
          -5.290402999998378
        ]
      },
      "properties": {
        "OBJECTID": 15476,
        "CU_NAME": "DUWINIM",
        "CU_NO": "009",
        "GEOCODE": "01020905009",
        "PROV_KEY": "01",
        "DIST_NO": "02",
        "LLG_NO": "09",
        "WARD_NO": "05",
        "WARD_NAME": "DUWINIM",
        "LATITUDE": -5.291799,
        "LONGITUDE": 141.434205,
        "REGHH": 18,
        "TOTPOP2000": 141,
        "MALE2000": 67,
        "FEMALE2000": 74,
        "POP2008": 183,
        "G_RATE": 1.0329999923706055,
        "Geocode_Num": 1020905009,
        "PROVINCE": 1
      }
    }
  ]
}