{
  "type": "FeatureCollection",
  "features": [
    {
      "type": "Feature",
      "id": 15477,
      "geometry": {
        "type": "Point",
        "coordinates": [
          141.53562200025522,
          -5.266752000204576
        ]
      },
      "properties": {
        "OBJECTID": 15477,
        "CU_NAME": "GOLGOBIP",
        "CU_NO": "004",
        "GEOCODE": "01020906004",
        "PROV_KEY": "01",
        "DIST_NO": "02",
        "LLG_NO": "09",
        "WARD_NO": "06",
        "WARD_NAME": "GOLGOBIP",
        "LATITUDE": -5.278491,
        "LONGITUDE": 141.540439,
        "REGHH": 14,
        "TOTPOP2000": 98,
        "MALE2000": 44,
        "FEMALE2000": 54,
        "POP2008": 127,
        "G_RATE": 1.0329999923706055,
        "Geocode_Num": 1020906004,
        "PROVINCE": 1
      }
    },
    {
      "type": "Feature",
      "id": 15478,
      "geometry": {
        "type": "Point",
        "coordinates": [
          141.52341800044042,
          -5.273696000270149
        ]
      },
      "properties": {
        "OBJECTID": 15478,
        "CU_NAME": "WAGAMBIP",
        "CU_NO": "008",
        "GEOCODE": "01020906008",
        "PROV_KEY": "01",
        "DIST_NO": "02",
        "LLG_NO": "09",
        "WARD_NO": "06",
        "WARD_NAME": "GOLGOBIP",
        "LATITUDE": -5.278035,
        "LONGITUDE": 141.538552,
        "REGHH": 21,
        "TOTPOP2000": 128,
        "MALE2000": 64,
        "FEMALE2000": 64,
        "POP2008": 165,
        "G_RATE": 1.0329999923706055,
        "Geocode_Num": 1020906008,
        "PROVINCE": 1
      }
    },
    {
      "type": "Feature",
      "id": 15479,
      "geometry": {
        "type": "Point",
        "coordinates": [
          141.55304699981923,
          -5.276198999684027
        ]
      },
      "properties": {
        "OBJECTID": 15479,
        "CU_NAME": "TUNGET",
        "CU_NO": "009",
        "GEOCODE": "01020906009",
        "PROV_KEY": "01",
        "DIST_NO": "02",
        "LLG_NO": "09",
        "WARD_NO": "06",
        "WARD_NAME": "GOLGOBIP",
        "LATITUDE": -5.283512,
        "LONGITUDE": 141.547537,
        "REGHH": 11,
        "TOTPOP2000": 87,
        "MALE2000": 36,
        "FEMALE2000": 51,
        "POP2008": 112,
        "G_RATE": 1.0329999923706055,
        "Geocode_Num": 1020906009,
        "PROVINCE": 1
      }
    }
  ]
}