{
  "type": "FeatureCollection",
  "features": [
    {
      "type": "Feature",
      "id": 15484,
      "geometry": {
        "type": "Point",
        "coordinates": [
          141.55027999992217,
          -5.438163999868664
        ]
      },
      "properties": {
        "OBJECTID": 15484,
        "CU_NAME": "DUMONAK",
        "CU_NO": "003",
        "GEOCODE": "01020909003",
        "PROV_KEY": "01",
        "DIST_NO": "02",
        "LLG_NO": "09",
        "WARD_NO": "09",
        "WARD_NAME": "DUMINAK",
        "LATITUDE": -5.445483,
        "LONGITUDE": 141.540343,
        "REGHH": 3,
        "TOTPOP2000": 12,
        "MALE2000": 9,
        "FEMALE2000": 3,
        "POP2008": 12,
        "G_RATE": 1.0329999923706055,
        "Geocode_Num": 1020909003,
        "PROVINCE": 1
      }
    },
    {
      "type": "Feature",
      "id": 15485,
      "geometry": {
        "type": "Point",
        "coordinates": [
          141.50447300002895,
          -5.546002999638688
        ]
      },
      "properties": {
        "OBJECTID": 15485,
        "CU_NAME": "KAIANGABIP",
        "CU_NO": "004",
        "GEOCODE": "01020909004",
        "PROV_KEY": "01",
        "DIST_NO": "02",
        "LLG_NO": "09",
        "WARD_NO": "09",
        "WARD_NAME": "DUMINAK",
        "LATITUDE": -5.547401,
        "LONGITUDE": 141.503381,
        "REGHH": 14,
        "TOTPOP2000": 142,
        "MALE2000": 77,
        "FEMALE2000": 65,
        "POP2008": 185,
        "G_RATE": 1.0329999923706055,
        "Geocode_Num": 1020909004,
        "PROVINCE": 1
      }
    },
    {
      "type": "Feature",
      "id": 15486,
      "geometry": {
        "type": "Point",
        "coordinates": [
          141.56088000041177,
          -5.419800000169801
        ]
      },
      "properties": {
        "OBJECTID": 15486,
        "CU_NAME": "KAIMFURABIP",
        "CU_NO": "006",
        "GEOCODE": "01020909006",
        "PROV_KEY": "01",
        "DIST_NO": "02",
        "LLG_NO": "09",
        "WARD_NO": "09",
        "WARD_NAME": "DUMINAK",
        "LATITUDE": -5.421197,
        "LONGITUDE": 141.559789,
        "REGHH": 17,
        "TOTPOP2000": 106,
        "MALE2000": 54,
        "FEMALE2000": 52,
        "POP2008": 137,
        "G_RATE": 1.0329999923706055,
        "Geocode_Num": 1020909006,
        "PROVINCE": 1
      }
    }
  ]
}