{
  "type": "FeatureCollection",
  "features": [
    {
      "type": "Feature",
      "id": 8893,
      "geometry": {
        "type": "Point",
        "coordinates": [
          146.6115430002094,
          -5.904880000011929
        ]
      },
      "properties": {
        "OBJECTID": 8893,
        "CU_NAME": "KWEMBUM",
        "CU_NO": "010",
        "GEOCODE": "13041237010",
        "PROV_KEY": "13",
        "DIST_NO": "04",
        "LLG_NO": "12",
        "WARD_NO": "37",
        "WARD_NAME": "WARD 37",
        "LATITUDE": -5.906291,
        "LONGITUDE": 146.610515,
        "REGHH": 50,
        "TOTPOP2000": 243,
        "MALE2000": 111,
        "FEMALE2000": 132,
        "POP2008": 302,
        "G_RATE": 1.0269999504089355,
        "Geocode_Num": 13041237010,
        "PROVINCE": 13
      }
    },
    {
      "type": "Feature",
      "id": 8894,
      "geometry": {
        "type": "Point",
        "coordinates": [
          146.63918999991859,
          -5.886719999828074
        ]
      },
      "properties": {
        "OBJECTID": 8894,
        "CU_NAME": "WANDABONG",
        "CU_NO": "015",
        "GEOCODE": "13041237015",
        "PROV_KEY": "13",
        "DIST_NO": "04",
        "LLG_NO": "12",
        "WARD_NO": "37",
        "WARD_NAME": "WARD 37",
        "LATITUDE": -5.888131,
        "LONGITUDE": 146.638162,
        "REGHH": 22,
        "TOTPOP2000": 126,
        "MALE2000": 66,
        "FEMALE2000": 60,
        "POP2008": 156,
        "G_RATE": 1.0269999504089355,
        "Geocode_Num": 13041237015,
        "PROVINCE": 13
      }
    },
    {
      "type": "Feature",
      "id": 8895,
      "geometry": {
        "type": "Point",
        "coordinates": [
          146.6151449999419,
          -5.898186999830159
        ]
      },
      "properties": {
        "OBJECTID": 8895,
        "CU_NAME": "WINDILUK",
        "CU_NO": "039",
        "GEOCODE": "13041237039",
        "PROV_KEY": "13",
        "DIST_NO": "04",
        "LLG_NO": "12",
        "WARD_NO": "37",
        "WARD_NAME": "WARD 37",
        "LATITUDE": -5.899598,
        "LONGITUDE": 146.614117,
        "REGHH": 26,
        "TOTPOP2000": 124,
        "MALE2000": 63,
        "FEMALE2000": 61,
        "POP2008": 154,
        "G_RATE": 1.0269999504089355,
        "Geocode_Num": 13041237039,
        "PROVINCE": 13
      }
    }
  ]
}