{
  "type": "FeatureCollection",
  "features": [
    {
      "type": "Feature",
      "id": 15313,
      "geometry": {
        "type": "Point",
        "coordinates": [
          141.43409900036863,
          -6.043269000264104
        ]
      },
      "properties": {
        "OBJECTID": 15313,
        "CU_NAME": "GIPONAI",
        "CU_NO": "005",
        "GEOCODE": "01020612005",
        "PROV_KEY": "01",
        "DIST_NO": "02",
        "LLG_NO": "06",
        "WARD_NO": "12",
        "WARD_NAME": "TIMINGONDOK",
        "LATITUDE": -6.041575,
        "LONGITUDE": 141.435649,
        "REGHH": 21,
        "TOTPOP2000": 106,
        "MALE2000": 51,
        "FEMALE2000": 55,
        "POP2008": 137,
        "G_RATE": 1.0329999923706055,
        "Geocode_Num": 1020612005,
        "PROVINCE": 1
      }
    },
    {
      "type": "Feature",
      "id": 15314,
      "geometry": {
        "type": "Point",
        "coordinates": [
          141.46738500021763,
          -5.993164000018567
        ]
      },
      "properties": {
        "OBJECTID": 15314,
        "CU_NAME": "TIMINGONDOK",
        "CU_NO": "010",
        "GEOCODE": "01020612010",
        "PROV_KEY": "01",
        "DIST_NO": "02",
        "LLG_NO": "06",
        "WARD_NO": "12",
        "WARD_NAME": "TIMINGONDOK",
        "LATITUDE": -5.994567,
        "LONGITUDE": 141.466292,
        "REGHH": 31,
        "TOTPOP2000": 206,
        "MALE2000": 108,
        "FEMALE2000": 98,
        "POP2008": 267,
        "G_RATE": 1.0329999923706055,
        "Geocode_Num": 1020612010,
        "PROVINCE": 1
      }
    }
  ]
}