{
  "type": "FeatureCollection",
  "features": [
    {
      "type": "Feature",
      "id": 15327,
      "geometry": {
        "type": "Point",
        "coordinates": [
          141.2609420002732,
          -5.8883630000523794
        ]
      },
      "properties": {
        "OBJECTID": 15327,
        "CU_NAME": "MENEMSORE",
        "CU_NO": "005",
        "GEOCODE": "01020620005",
        "PROV_KEY": "01",
        "DIST_NO": "02",
        "LLG_NO": "06",
        "WARD_NO": "20",
        "WARD_NAME": "MENUMSORE",
        "LATITUDE": -5.889764,
        "LONGITUDE": 141.259847,
        "REGHH": 33,
        "TOTPOP2000": 183,
        "MALE2000": 92,
        "FEMALE2000": 91,
        "POP2008": 237,
        "G_RATE": 1.0329999923706055,
        "Geocode_Num": 1020620005,
        "PROVINCE": 1
      }
    },
    {
      "type": "Feature",
      "id": 15328,
      "geometry": {
        "type": "Point",
        "coordinates": [
          141.23251999989816,
          -5.895989000092243
        ]
      },
      "properties": {
        "OBJECTID": 15328,
        "CU_NAME": "TOPE",
        "CU_NO": "011",
        "GEOCODE": "01020620011",
        "PROV_KEY": "01",
        "DIST_NO": "02",
        "LLG_NO": "06",
        "WARD_NO": "20",
        "WARD_NAME": "MENUMSORE",
        "LATITUDE": -5.89739,
        "LONGITUDE": 141.231424,
        "REGHH": 7,
        "TOTPOP2000": 35,
        "MALE2000": 20,
        "FEMALE2000": 15,
        "POP2008": 43,
        "G_RATE": 1.0329999923706055,
        "Geocode_Num": 1020620011,
        "PROVINCE": 1
      }
    }
  ]
}