{
  "type": "FeatureCollection",
  "features": [
    {
      "type": "Feature",
      "id": 15334,
      "geometry": {
        "type": "Point",
        "coordinates": [
          141.90579499993942,
          -5.965392999986932
        ]
      },
      "properties": {
        "OBJECTID": 15334,
        "CU_NAME": "DIABI",
        "CU_NO": "032",
        "GEOCODE": "01020625032",
        "PROV_KEY": "01",
        "DIST_NO": "02",
        "LLG_NO": "06",
        "WARD_NO": "25",
        "WARD_NAME": "DIABI",
        "LATITUDE": -5.95938,
        "LONGITUDE": 141.919459,
        "REGHH": 19,
        "TOTPOP2000": 99,
        "MALE2000": 52,
        "FEMALE2000": 47,
        "POP2008": 128,
        "G_RATE": 1.0329999923706055,
        "Geocode_Num": 1020625032,
        "PROVINCE": 1
      }
    },
    {
      "type": "Feature",
      "id": 15335,
      "geometry": {
        "type": "Point",
        "coordinates": [
          141.85512399967286,
          -5.929355000033183
        ]
      },
      "properties": {
        "OBJECTID": 15335,
        "CU_NAME": "KOMINAI",
        "CU_NO": "033",
        "GEOCODE": "01020625033",
        "PROV_KEY": "01",
        "DIST_NO": "02",
        "LLG_NO": "06",
        "WARD_NO": "25",
        "WARD_NAME": "DIABI",
        "LATITUDE": -5.930758,
        "LONGITUDE": 141.854036,
        "REGHH": 11,
        "TOTPOP2000": 28,
        "MALE2000": 15,
        "FEMALE2000": 13,
        "POP2008": 36,
        "G_RATE": 1.0329999923706055,
        "Geocode_Num": 1020625033,
        "PROVINCE": 1
      }
    },
    {
      "type": "Feature",
      "id": 15336,
      "geometry": {
        "type": "Point",
        "coordinates": [
          141.94014000006098,
          -6.017976000292151
        ]
      },
      "properties": {
        "OBJECTID": 15336,
        "CU_NAME": "KANAI",
        "CU_NO": "034",
        "GEOCODE": "01020625034",
        "PROV_KEY": "01",
        "DIST_NO": "02",
        "LLG_NO": "06",
        "WARD_NO": "25",
        "WARD_NAME": "DIABI",
        "LATITUDE": -6.01938,
        "LONGITUDE": 141.939052,
        "REGHH": 10,
        "TOTPOP2000": 36,
        "MALE2000": 21,
        "FEMALE2000": 15,
        "POP2008": 44,
        "G_RATE": 1.0329999923706055,
        "Geocode_Num": 1020625034,
        "PROVINCE": 1
      }
    }
  ]
}