{
  "type": "FeatureCollection",
  "features": [
    {
      "type": "Feature",
      "id": 9229,
      "geometry": {
        "type": "Point",
        "coordinates": [
          145.50940399999467,
          -5.659581999709474
        ]
      },
      "properties": {
        "OBJECTID": 9229,
        "CU_NAME": "KORONA",
        "CU_NO": "010",
        "GEOCODE": "13061612010",
        "PROV_KEY": "13",
        "DIST_NO": "06",
        "LLG_NO": "16",
        "WARD_NO": "12",
        "WARD_NAME": "KORONA",
        "LATITUDE": -5.660989,
        "LONGITUDE": 145.508362,
        "REGHH": 38,
        "TOTPOP2000": 283,
        "MALE2000": 134,
        "FEMALE2000": 149,
        "POP2008": 351,
        "G_RATE": 1.0269999504089355,
        "Geocode_Num": 13061612010,
        "PROVINCE": 13
      }
    },
    {
      "type": "Feature",
      "id": 9230,
      "geometry": {
        "type": "Point",
        "coordinates": [
          145.55989099986982,
          -5.595965999631119
        ]
      },
      "properties": {
        "OBJECTID": 9230,
        "CU_NAME": "MATOLOI",
        "CU_NO": "012",
        "GEOCODE": "13061612012",
        "PROV_KEY": "13",
        "DIST_NO": "06",
        "LLG_NO": "16",
        "WARD_NO": "12",
        "WARD_NAME": "KORONA",
        "LATITUDE": -5.597525,
        "LONGITUDE": 145.560342,
        "REGHH": 29,
        "TOTPOP2000": 175,
        "MALE2000": 88,
        "FEMALE2000": 87,
        "POP2008": 217,
        "G_RATE": 1.0269999504089355,
        "Geocode_Num": 13061612012,
        "PROVINCE": 13
      }
    },
    {
      "type": "Feature",
      "id": 9231,
      "geometry": {
        "type": "Point",
        "coordinates": [
          145.51528699969538,
          -5.610363999898652
        ]
      },
      "properties": {
        "OBJECTID": 9231,
        "CU_NAME": "SANA",
        "CU_NO": "016",
        "GEOCODE": "13061612016",
        "PROV_KEY": "13",
        "DIST_NO": "06",
        "LLG_NO": "16",
        "WARD_NO": "12",
        "WARD_NAME": "KORONA",
        "LATITUDE": -5.613277,
        "LONGITUDE": 145.518866,
        "REGHH": 22,
        "TOTPOP2000": 141,
        "MALE2000": 70,
        "FEMALE2000": 71,
        "POP2008": 174,
        "G_RATE": 1.0269999504089355,
        "Geocode_Num": 13061612016,
        "PROVINCE": 13
      }
    },
    {
      "type": "Feature",
      "id": 9232,
      "geometry": {
        "type": "Point",
        "coordinates": [
          145.52838800040593,
          -5.659323000356153
        ]
      },
      "properties": {
        "OBJECTID": 9232,
        "CU_NAME": "ONGORU",
        "CU_NO": "017",
        "GEOCODE": "13061612017",
        "PROV_KEY": "13",
        "DIST_NO": "06",
        "LLG_NO": "16",
        "WARD_NO": "12",
        "WARD_NAME": "KORONA",
        "LATITUDE": -5.66073,
        "LONGITUDE": 145.527346,
        "REGHH": 26,
        "TOTPOP2000": 144,
        "MALE2000": 83,
        "FEMALE2000": 61,
        "POP2008": 178,
        "G_RATE": 1.0269999504089355,
        "Geocode_Num": 13061612017,
        "PROVINCE": 13
      }
    }
  ]
}