{
  "type": "FeatureCollection",
  "features": [
    {
      "type": "Feature",
      "id": 9288,
      "geometry": {
        "type": "Point",
        "coordinates": [
          145.39022499978398,
          -5.412707999574479
        ]
      },
      "properties": {
        "OBJECTID": 9288,
        "CU_NAME": "ARIMORI",
        "CU_NO": "001",
        "GEOCODE": "13061629001",
        "PROV_KEY": "13",
        "DIST_NO": "06",
        "LLG_NO": "16",
        "WARD_NO": "29",
        "WARD_NAME": "IGOI",
        "LATITUDE": -5.421736,
        "LONGITUDE": 145.386987,
        "REGHH": 28,
        "TOTPOP2000": 170,
        "MALE2000": 89,
        "FEMALE2000": 81,
        "POP2008": 211,
        "G_RATE": 1.0269999504089355,
        "Geocode_Num": 13061629001,
        "PROVINCE": 13
      }
    },
    {
      "type": "Feature",
      "id": 9289,
      "geometry": {
        "type": "Point",
        "coordinates": [
          145.34694699960437,
          -5.426266999822133
        ]
      },
      "properties": {
        "OBJECTID": 9289,
        "CU_NAME": "DUNUBA",
        "CU_NO": "007",
        "GEOCODE": "13061629007",
        "PROV_KEY": "13",
        "DIST_NO": "06",
        "LLG_NO": "16",
        "WARD_NO": "29",
        "WARD_NAME": "IGOI",
        "LATITUDE": -5.431668,
        "LONGITUDE": 145.345893,
        "REGHH": 12,
        "TOTPOP2000": 86,
        "MALE2000": 45,
        "FEMALE2000": 41,
        "POP2008": 106,
        "G_RATE": 1.0269999504089355,
        "Geocode_Num": 13061629007,
        "PROVINCE": 13
      }
    },
    {
      "type": "Feature",
      "id": 9290,
      "geometry": {
        "type": "Point",
        "coordinates": [
          145.3263759997526,
          -5.421580999563446
        ]
      },
      "properties": {
        "OBJECTID": 9290,
        "CU_NAME": "IGOI",
        "CU_NO": "009",
        "GEOCODE": "13061629009",
        "PROV_KEY": "13",
        "DIST_NO": "06",
        "LLG_NO": "16",
        "WARD_NO": "29",
        "WARD_NAME": "IGOI",
        "LATITUDE": -5.418405,
        "LONGITUDE": 145.328396,
        "REGHH": 27,
        "TOTPOP2000": 146,
        "MALE2000": 76,
        "FEMALE2000": 70,
        "POP2008": 180,
        "G_RATE": 1.0269999504089355,
        "Geocode_Num": 13061629009,
        "PROVINCE": 13
      }
    },
    {
      "type": "Feature",
      "id": 9291,
      "geometry": {
        "type": "Point",
        "coordinates": [
          145.36342400041735,
          -5.436146000337601
        ]
      },
      "properties": {
        "OBJECTID": 9291,
        "CU_NAME": "KEPSAU",
        "CU_NO": "011",
        "GEOCODE": "13061629011",
        "PROV_KEY": "13",
        "DIST_NO": "06",
        "LLG_NO": "16",
        "WARD_NO": "29",
        "WARD_NAME": "IGOI",
        "LATITUDE": -5.43755,
        "LONGITUDE": 145.36238,
        "REGHH": 16,
        "TOTPOP2000": 76,
        "MALE2000": 38,
        "FEMALE2000": 38,
        "POP2008": 92,
        "G_RATE": 1.0269999504089355,
        "Geocode_Num": 13061629011,
        "PROVINCE": 13
      }
    }
  ]
}