{
  "type": "FeatureCollection",
  "features": [
    {
      "type": "Feature",
      "id": 19521,
      "geometry": {
        "type": "Point",
        "coordinates": [
          144.02339799991785,
          -6.147168000003148
        ]
      },
      "properties": {
        "OBJECTID": 19521,
        "CU_NAME": "KAPOLAPOPILE",
        "CU_NO": "004",
        "GEOCODE": "07020510004",
        "PROV_KEY": "07",
        "DIST_NO": "02",
        "LLG_NO": "05",
        "WARD_NO": "10",
        "WARD_NAME": "KAPOLAPOPILE",
        "LATITUDE": -6.150385,
        "LONGITUDE": 144.023573,
        "REGHH": 84,
        "TOTPOP2000": 398,
        "MALE2000": 202,
        "FEMALE2000": 196,
        "POP2008": 553,
        "G_RATE": 1.0420000553131104,
        "Geocode_Num": 7020510004,
        "PROVINCE": 7
      }
    },
    {
      "type": "Feature",
      "id": 19522,
      "geometry": {
        "type": "Point",
        "coordinates": [
          144.0220659996462,
          -6.147073000118837
        ]
      },
      "properties": {
        "OBJECTID": 19522,
        "CU_NAME": "KUMBIAWE",
        "CU_NO": "005",
        "GEOCODE": "07020510005",
        "PROV_KEY": "07",
        "DIST_NO": "02",
        "LLG_NO": "05",
        "WARD_NO": "10",
        "WARD_NAME": "KAPOLAPOPILE",
        "LATITUDE": -6.150385,
        "LONGITUDE": 144.023573,
        "REGHH": 35,
        "TOTPOP2000": 139,
        "MALE2000": 63,
        "FEMALE2000": 76,
        "POP2008": 193,
        "G_RATE": 1.0420000553131104,
        "Geocode_Num": 7020510005,
        "PROVINCE": 7
      }
    },
    {
      "type": "Feature",
      "id": 19523,
      "geometry": {
        "type": "Point",
        "coordinates": [
          144.02134299957982,
          -6.146049999707657
        ]
      },
      "properties": {
        "OBJECTID": 19523,
        "CU_NAME": "KUMBIAWE",
        "CU_NO": "006",
        "GEOCODE": "07020510006",
        "PROV_KEY": "07",
        "DIST_NO": "02",
        "LLG_NO": "05",
        "WARD_NO": "10",
        "WARD_NAME": "KAPOLAPOPILE",
        "LATITUDE": -6.150385,
        "LONGITUDE": 144.023573,
        "REGHH": 34,
        "TOTPOP2000": 153,
        "MALE2000": 80,
        "FEMALE2000": 73,
        "POP2008": 213,
        "G_RATE": 1.0420000553131104,
        "Geocode_Num": 7020510006,
        "PROVINCE": 7
      }
    }
  ]
}