{
  "type": "FeatureCollection",
  "features": [
    {
      "type": "Feature",
      "id": 19556,
      "geometry": {
        "type": "Point",
        "coordinates": [
          143.9683710002215,
          -6.177675000300951
        ]
      },
      "properties": {
        "OBJECTID": 19556,
        "CU_NAME": "IOMBI/PENA",
        "CU_NO": "001",
        "GEOCODE": "07020520001",
        "PROV_KEY": "07",
        "DIST_NO": "02",
        "LLG_NO": "05",
        "WARD_NO": "20",
        "WARD_NAME": "IOMBI 2",
        "LATITUDE": -6.182637,
        "LONGITUDE": 143.968759,
        "REGHH": 64,
        "TOTPOP2000": 364,
        "MALE2000": 175,
        "FEMALE2000": 189,
        "POP2008": 506,
        "G_RATE": 1.0420000553131104,
        "Geocode_Num": 7020520001,
        "PROVINCE": 7
      }
    },
    {
      "type": "Feature",
      "id": 19557,
      "geometry": {
        "type": "Point",
        "coordinates": [
          143.96786300017743,
          -6.178499999675182
        ]
      },
      "properties": {
        "OBJECTID": 19557,
        "CU_NAME": "KARULU",
        "CU_NO": "002",
        "GEOCODE": "07020520002",
        "PROV_KEY": "07",
        "DIST_NO": "02",
        "LLG_NO": "05",
        "WARD_NO": "20",
        "WARD_NAME": "IOMBI 2",
        "LATITUDE": -6.182637,
        "LONGITUDE": 143.968759,
        "REGHH": 33,
        "TOTPOP2000": 188,
        "MALE2000": 99,
        "FEMALE2000": 89,
        "POP2008": 262,
        "G_RATE": 1.0420000553131104,
        "Geocode_Num": 7020520002,
        "PROVINCE": 7
      }
    },
    {
      "type": "Feature",
      "id": 19558,
      "geometry": {
        "type": "Point",
        "coordinates": [
          143.96929799980296,
          -6.178492000205608
        ]
      },
      "properties": {
        "OBJECTID": 19558,
        "CU_NAME": "WANEP",
        "CU_NO": "003",
        "GEOCODE": "07020520003",
        "PROV_KEY": "07",
        "DIST_NO": "02",
        "LLG_NO": "05",
        "WARD_NO": "20",
        "WARD_NAME": "IOMBI 2",
        "LATITUDE": -6.182637,
        "LONGITUDE": 143.968759,
        "REGHH": 30,
        "TOTPOP2000": 147,
        "MALE2000": 75,
        "FEMALE2000": 72,
        "POP2008": 204,
        "G_RATE": 1.0420000553131104,
        "Geocode_Num": 7020520003,
        "PROVINCE": 7
      }
    },
    {
      "type": "Feature",
      "id": 19559,
      "geometry": {
        "type": "Point",
        "coordinates": [
          143.9650889999574,
          -6.180770000035409
        ]
      },
      "properties": {
        "OBJECTID": 19559,
        "CU_NAME": "KULLI",
        "CU_NO": "004",
        "GEOCODE": "07020520004",
        "PROV_KEY": "07",
        "DIST_NO": "02",
        "LLG_NO": "05",
        "WARD_NO": "20",
        "WARD_NAME": "IOMBI 2",
        "LATITUDE": -6.182637,
        "LONGITUDE": 143.968759,
        "REGHH": 21,
        "TOTPOP2000": 97,
        "MALE2000": 54,
        "FEMALE2000": 43,
        "POP2008": 134,
        "G_RATE": 1.0420000553131104,
        "Geocode_Num": 7020520004,
        "PROVINCE": 7
      }
    }
  ]
}