{
  "type": "FeatureCollection",
  "features": [
    {
      "type": "Feature",
      "id": 4708,
      "geometry": {
        "type": "Point",
        "coordinates": [
          152.44359499990935,
          -4.230268999714497
        ]
      },
      "properties": {
        "OBJECTID": 4708,
        "CU_NAME": "UTUAN NO.1",
        "CU_NO": "026",
        "GEOCODE": "18020715026",
        "PROV_KEY": "18",
        "DIST_NO": "02",
        "LLG_NO": "07",
        "WARD_NO": "15",
        "WARD_NAME": "UTUAN",
        "LATITUDE": -4.231079,
        "LONGITUDE": 152.442654,
        "REGHH": 102,
        "TOTPOP2000": 491,
        "MALE2000": 256,
        "FEMALE2000": 235,
        "POP2008": 599,
        "G_RATE": 1.024999976158142,
        "Geocode_Num": 18020715026,
        "PROVINCE": 18
      }
    },
    {
      "type": "Feature",
      "id": 4709,
      "geometry": {
        "type": "Point",
        "coordinates": [
          152.4211259997652,
          -4.2168260003196
        ]
      },
      "properties": {
        "OBJECTID": 4709,
        "CU_NAME": "ULU PLANTATION",
        "CU_NO": "508",
        "GEOCODE": "18020715508",
        "PROV_KEY": "18",
        "DIST_NO": "02",
        "LLG_NO": "07",
        "WARD_NO": "15",
        "WARD_NAME": "UTUAN",
        "LATITUDE": -4.218225,
        "LONGITUDE": 152.42606,
        "REGHH": 24,
        "TOTPOP2000": 172,
        "MALE2000": 82,
        "FEMALE2000": 90,
        "POP2008": 209,
        "G_RATE": 1.024999976158142,
        "Geocode_Num": 18020715508,
        "PROVINCE": 18
      }
    }
  ]
}