{
  "type": "FeatureCollection",
  "features": [
    {
      "type": "Feature",
      "id": 12932,
      "geometry": {
        "type": "Point",
        "coordinates": [
          152.59917299963433,
          -3.198133000037899
        ]
      },
      "properties": {
        "OBJECTID": 12932,
        "CU_NAME": "PANGOH",
        "CU_NO": "018",
        "GEOCODE": "17020906018",
        "PROV_KEY": "17",
        "DIST_NO": "02",
        "LLG_NO": "09",
        "WARD_NO": "06",
        "WARD_NAME": "PANGOH",
        "LATITUDE": -3.199519,
        "LONGITUDE": 152.598235,
        "REGHH": 40,
        "TOTPOP2000": 209,
        "MALE2000": 115,
        "FEMALE2000": 94,
        "POP2008": 262,
        "G_RATE": 1.0290000438690186,
        "Geocode_Num": 17020906018,
        "PROVINCE": 17
      }
    },
    {
      "type": "Feature",
      "id": 12933,
      "geometry": {
        "type": "Point",
        "coordinates": [
          152.60615699974585,
          -3.1966510000435733
        ]
      },
      "properties": {
        "OBJECTID": 12933,
        "CU_NAME": "WOLENIONG",
        "CU_NO": "019",
        "GEOCODE": "17020906019",
        "PROV_KEY": "17",
        "DIST_NO": "02",
        "LLG_NO": "09",
        "WARD_NO": "06",
        "WARD_NAME": "PANGOH",
        "LATITUDE": -3.200515,
        "LONGITUDE": 152.604702,
        "REGHH": 31,
        "TOTPOP2000": 146,
        "MALE2000": 78,
        "FEMALE2000": 68,
        "POP2008": 183,
        "G_RATE": 1.0290000438690186,
        "Geocode_Num": 17020906019,
        "PROVINCE": 17
      }
    },
    {
      "type": "Feature",
      "id": 12934,
      "geometry": {
        "type": "Point",
        "coordinates": [
          152.60235499978353,
          -3.1918220003849456
        ]
      },
      "properties": {
        "OBJECTID": 12934,
        "CU_NAME": "PALIE CATH.  MSSN",
        "CU_NO": "503",
        "GEOCODE": "17020906503",
        "PROV_KEY": "17",
        "DIST_NO": "02",
        "LLG_NO": "09",
        "WARD_NO": "06",
        "WARD_NAME": "PANGOH",
        "LATITUDE": -3.195582,
        "LONGITUDE": 152.599939,
        "REGHH": 23,
        "TOTPOP2000": 154,
        "MALE2000": 67,
        "FEMALE2000": 87,
        "POP2008": 193,
        "G_RATE": 1.0290000438690186,
        "Geocode_Num": 17020906503,
        "PROVINCE": 17
      }
    }
  ]
}