{
  "type": "FeatureCollection",
  "features": [
    {
      "type": "Feature",
      "id": 12960,
      "geometry": {
        "type": "Point",
        "coordinates": [
          152.64838700016003,
          -2.786131999592044
        ]
      },
      "properties": {
        "OBJECTID": 12960,
        "CU_NAME": "KUELAM",
        "CU_NO": "005",
        "GEOCODE": "17020915005",
        "PROV_KEY": "17",
        "DIST_NO": "02",
        "LLG_NO": "09",
        "WARD_NO": "15",
        "WARD_NAME": "MAHUR",
        "LATITUDE": -2.787512,
        "LONGITUDE": 152.64745,
        "REGHH": 65,
        "TOTPOP2000": 352,
        "MALE2000": 165,
        "FEMALE2000": 187,
        "POP2008": 441,
        "G_RATE": 1.0290000438690186,
        "Geocode_Num": 17020915005,
        "PROVINCE": 17
      }
    },
    {
      "type": "Feature",
      "id": 12961,
      "geometry": {
        "type": "Point",
        "coordinates": [
          152.65469799981292,
          -2.7953429998794945
        ]
      },
      "properties": {
        "OBJECTID": 12961,
        "CU_NAME": "LAKAMLEO (TERITERI NO. 1)",
        "CU_NO": "028",
        "GEOCODE": "17020915028",
        "PROV_KEY": "17",
        "DIST_NO": "02",
        "LLG_NO": "09",
        "WARD_NO": "15",
        "WARD_NAME": "MAHUR",
        "LATITUDE": -2.796723,
        "LONGITUDE": 152.653761,
        "REGHH": 52,
        "TOTPOP2000": 247,
        "MALE2000": 122,
        "FEMALE2000": 125,
        "POP2008": 310,
        "G_RATE": 1.0290000438690186,
        "Geocode_Num": 17020915028,
        "PROVINCE": 17
      }
    },
    {
      "type": "Feature",
      "id": 12962,
      "geometry": {
        "type": "Point",
        "coordinates": [
          152.66533400016408,
          -2.7876799999319815
        ]
      },
      "properties": {
        "OBJECTID": 12962,
        "CU_NAME": "LI (TERITERI NO. 2)",
        "CU_NO": "035",
        "GEOCODE": "17020915035",
        "PROV_KEY": "17",
        "DIST_NO": "02",
        "LLG_NO": "09",
        "WARD_NO": "15",
        "WARD_NAME": "MAHUR",
        "LATITUDE": -2.78906,
        "LONGITUDE": 152.664397,
        "REGHH": 36,
        "TOTPOP2000": 181,
        "MALE2000": 97,
        "FEMALE2000": 84,
        "POP2008": 227,
        "G_RATE": 1.0290000438690186,
        "Geocode_Num": 17020915035,
        "PROVINCE": 17
      }
    }
  ]
}