{
  "type": "FeatureCollection",
  "features": [
    {
      "type": "Feature",
      "id": 21271,
      "geometry": {
        "type": "Point",
        "coordinates": [
          143.4760710001766,
          -6.248908000004178
        ]
      },
      "properties": {
        "OBJECTID": 21271,
        "CU_NAME": "ASKAM 1",
        "CU_NO": "001",
        "GEOCODE": "07072411001",
        "PROV_KEY": "07",
        "DIST_NO": "07",
        "LLG_NO": "24",
        "WARD_NO": "11",
        "WARD_NAME": "ASKAM 1",
        "LATITUDE": -6.254684,
        "LONGITUDE": 143.475384,
        "REGHH": 104,
        "TOTPOP2000": 515,
        "MALE2000": 260,
        "FEMALE2000": 255,
        "POP2008": 719,
        "G_RATE": 1.0420000553131104,
        "Geocode_Num": 7072411001,
        "PROVINCE": 7
      }
    }
  ]
}