{
  "type": "FeatureCollection",
  "features": [
    {
      "type": "Feature",
      "id": 21279,
      "geometry": {
        "type": "Point",
        "coordinates": [
          143.45199000033836,
          -6.195463999563856
        ]
      },
      "properties": {
        "OBJECTID": 21279,
        "CU_NAME": "PINJA 2",
        "CU_NO": "001",
        "GEOCODE": "07072419001",
        "PROV_KEY": "07",
        "DIST_NO": "07",
        "LLG_NO": "24",
        "WARD_NO": "19",
        "WARD_NAME": "PINJA 2",
        "LATITUDE": -6.200197,
        "LONGITUDE": 143.451782,
        "REGHH": 141,
        "TOTPOP2000": 930,
        "MALE2000": 472,
        "FEMALE2000": 458,
        "POP2008": 1292,
        "G_RATE": 1.0420000553131104,
        "Geocode_Num": 7072419001,
        "PROVINCE": 7
      }
    }
  ]
}