{
  "type": "FeatureCollection",
  "features": [
    {
      "type": "Feature",
      "id": 12842,
      "geometry": {
        "type": "Point",
        "coordinates": [
          153.03913599992654,
          -4.5197850003773965
        ]
      },
      "properties": {
        "OBJECTID": 12842,
        "CU_NAME": "KAMILAL",
        "CU_NO": "004",
        "GEOCODE": "17020705004",
        "PROV_KEY": "17",
        "DIST_NO": "02",
        "LLG_NO": "07",
        "WARD_NO": "05",
        "WARD_NAME": "KAMILAL",
        "LATITUDE": -4.519852,
        "LONGITUDE": 153.039682,
        "REGHH": 24,
        "TOTPOP2000": 156,
        "MALE2000": 78,
        "FEMALE2000": 78,
        "POP2008": 197,
        "G_RATE": 1.0290000438690186,
        "Geocode_Num": 17020705004,
        "PROVINCE": 17
      }
    },
    {
      "type": "Feature",
      "id": 12843,
      "geometry": {
        "type": "Point",
        "coordinates": [
          153.02356000019392,
          -4.493286999695215
        ]
      },
      "properties": {
        "OBJECTID": 12843,
        "CU_NAME": "KAMPARAN",
        "CU_NO": "015",
        "GEOCODE": "17020705015",
        "PROV_KEY": "17",
        "DIST_NO": "02",
        "LLG_NO": "07",
        "WARD_NO": "05",
        "WARD_NAME": "KAMILAL",
        "LATITUDE": -4.494691,
        "LONGITUDE": 153.022627,
        "REGHH": 21,
        "TOTPOP2000": 106,
        "MALE2000": 52,
        "FEMALE2000": 54,
        "POP2008": 133,
        "G_RATE": 1.0290000438690186,
        "Geocode_Num": 17020705015,
        "PROVINCE": 17
      }
    },
    {
      "type": "Feature",
      "id": 12844,
      "geometry": {
        "type": "Point",
        "coordinates": [
          153.02941799964105,
          -4.461975000046152
        ]
      },
      "properties": {
        "OBJECTID": 12844,
        "CU_NAME": "TAHRON",
        "CU_NO": "016",
        "GEOCODE": "17020705016",
        "PROV_KEY": "17",
        "DIST_NO": "02",
        "LLG_NO": "07",
        "WARD_NO": "05",
        "WARD_NAME": "KAMILAL",
        "LATITUDE": -4.46338,
        "LONGITUDE": 153.028485,
        "REGHH": 22,
        "TOTPOP2000": 125,
        "MALE2000": 62,
        "FEMALE2000": 63,
        "POP2008": 157,
        "G_RATE": 1.0290000438690186,
        "Geocode_Num": 17020705016,
        "PROVINCE": 17
      }
    }
  ]
}