{
  "type": "FeatureCollection",
  "features": [
    {
      "type": "Feature",
      "id": 12853,
      "geometry": {
        "type": "Point",
        "coordinates": [
          152.9723680001831,
          -4.7093229995567185
        ]
      },
      "properties": {
        "OBJECTID": 12853,
        "CU_NAME": "BERIOTAR",
        "CU_NO": "003",
        "GEOCODE": "17020709003",
        "PROV_KEY": "17",
        "DIST_NO": "02",
        "LLG_NO": "07",
        "WARD_NO": "09",
        "WARD_NAME": "BERIOTAR",
        "LATITUDE": -4.71073,
        "LONGITUDE": 152.971434,
        "REGHH": 19,
        "TOTPOP2000": 87,
        "MALE2000": 43,
        "FEMALE2000": 44,
        "POP2008": 111,
        "G_RATE": 1.0290000438690186,
        "Geocode_Num": 17020709003,
        "PROVINCE": 17
      }
    }
  ]
}