{
  "type": "FeatureCollection",
  "features": [
    {
      "type": "Feature",
      "id": 12872,
      "geometry": {
        "type": "Point",
        "coordinates": [
          152.68364900030122,
          -4.226800999866214
        ]
      },
      "properties": {
        "OBJECTID": 12872,
        "CU_NAME": "TAMPAKAR",
        "CU_NO": "011",
        "GEOCODE": "17020716011",
        "PROV_KEY": "17",
        "DIST_NO": "02",
        "LLG_NO": "07",
        "WARD_NO": "16",
        "WARD_NAME": "TAMPAKAR",
        "LATITUDE": -4.228201,
        "LONGITUDE": 152.682711,
        "REGHH": 114,
        "TOTPOP2000": 647,
        "MALE2000": 393,
        "FEMALE2000": 254,
        "POP2008": 813,
        "G_RATE": 1.0290000438690186,
        "Geocode_Num": 17020716011,
        "PROVINCE": 17
      }
    },
    {
      "type": "Feature",
      "id": 12873,
      "geometry": {
        "type": "Point",
        "coordinates": [
          152.6963610001601,
          -4.211155999649634
        ]
      },
      "properties": {
        "OBJECTID": 12873,
        "CU_NAME": "KAMDARU PLTN",
        "CU_NO": "501",
        "GEOCODE": "17020716501",
        "PROV_KEY": "17",
        "DIST_NO": "02",
        "LLG_NO": "07",
        "WARD_NO": "16",
        "WARD_NAME": "TAMPAKAR",
        "LATITUDE": -4.212556,
        "LONGITUDE": 152.695423,
        "REGHH": 8,
        "TOTPOP2000": 52,
        "MALE2000": 30,
        "FEMALE2000": 22,
        "POP2008": 68,
        "G_RATE": 1.0290000438690186,
        "Geocode_Num": 17020716501,
        "PROVINCE": 17
      }
    }
  ]
}