{
  "type": "FeatureCollection",
  "features": [
    {
      "type": "Feature",
      "id": 6363,
      "geometry": {
        "type": "Point",
        "coordinates": [
          143.44700499978103,
          -4.669713000354648
        ]
      },
      "properties": {
        "OBJECTID": 6363,
        "CU_NAME": "CHIMBUT",
        "CU_NO": "003",
        "GEOCODE": "14020614003",
        "PROV_KEY": "14",
        "DIST_NO": "02",
        "LLG_NO": "06",
        "WARD_NO": "14",
        "WARD_NAME": "CHIMBUT",
        "LATITUDE": -4.666894,
        "LONGITUDE": 143.446485,
        "REGHH": 35,
        "TOTPOP2000": 212,
        "MALE2000": 111,
        "FEMALE2000": 101,
        "POP2008": 252,
        "G_RATE": 1.0219999551773071,
        "Geocode_Num": 14020614003,
        "PROVINCE": 14
      }
    },
    {
      "type": "Feature",
      "id": 6364,
      "geometry": {
        "type": "Point",
        "coordinates": [
          143.44029499971452,
          -4.625789000062241
        ]
      },
      "properties": {
        "OBJECTID": 6364,
        "CU_NAME": "MARAMBA",
        "CU_NO": "007",
        "GEOCODE": "14020614007",
        "PROV_KEY": "14",
        "DIST_NO": "02",
        "LLG_NO": "06",
        "WARD_NO": "14",
        "WARD_NAME": "CHIMBUT",
        "LATITUDE": -4.625394,
        "LONGITUDE": 143.446372,
        "REGHH": 15,
        "TOTPOP2000": 88,
        "MALE2000": 49,
        "FEMALE2000": 39,
        "POP2008": 104,
        "G_RATE": 1.0219999551773071,
        "Geocode_Num": 14020614007,
        "PROVINCE": 14
      }
    },
    {
      "type": "Feature",
      "id": 6365,
      "geometry": {
        "type": "Point",
        "coordinates": [
          143.43238400002167,
          -4.636477000113416
        ]
      },
      "properties": {
        "OBJECTID": 6365,
        "CU_NAME": "MAROUK",
        "CU_NO": "008",
        "GEOCODE": "14020614008",
        "PROV_KEY": "14",
        "DIST_NO": "02",
        "LLG_NO": "06",
        "WARD_NO": "14",
        "WARD_NAME": "CHIMBUT",
        "LATITUDE": -4.658851,
        "LONGITUDE": 143.438295,
        "REGHH": 12,
        "TOTPOP2000": 86,
        "MALE2000": 41,
        "FEMALE2000": 45,
        "POP2008": 102,
        "G_RATE": 1.0219999551773071,
        "Geocode_Num": 14020614008,
        "PROVINCE": 14
      }
    }
  ]
}