{
  "type": "FeatureCollection",
  "features": [
    {
      "type": "Feature",
      "id": 6385,
      "geometry": {
        "type": "Point",
        "coordinates": [
          143.3220480002151,
          -4.534798000227454
        ]
      },
      "properties": {
        "OBJECTID": 6385,
        "CU_NAME": "KANINGARA",
        "CU_NO": "007",
        "GEOCODE": "14020625007",
        "PROV_KEY": "14",
        "DIST_NO": "02",
        "LLG_NO": "06",
        "WARD_NO": "25",
        "WARD_NAME": "KANINGARA",
        "LATITUDE": -4.541275,
        "LONGITUDE": 143.33889,
        "REGHH": 58,
        "TOTPOP2000": 392,
        "MALE2000": 187,
        "FEMALE2000": 205,
        "POP2008": 467,
        "G_RATE": 1.0219999551773071,
        "Geocode_Num": 14020625007,
        "PROVINCE": 14
      }
    },
    {
      "type": "Feature",
      "id": 6386,
      "geometry": {
        "type": "Point",
        "coordinates": [
          143.34933200027172,
          -4.5462789999758115
        ]
      },
      "properties": {
        "OBJECTID": 6386,
        "CU_NAME": "YAMONDANAI",
        "CU_NO": "018",
        "GEOCODE": "14020625018",
        "PROV_KEY": "14",
        "DIST_NO": "02",
        "LLG_NO": "06",
        "WARD_NO": "25",
        "WARD_NAME": "KANINGARA",
        "LATITUDE": -4.547867,
        "LONGITUDE": 143.348095,
        "REGHH": 34,
        "TOTPOP2000": 199,
        "MALE2000": 101,
        "FEMALE2000": 98,
        "POP2008": 237,
        "G_RATE": 1.0219999551773071,
        "Geocode_Num": 14020625018,
        "PROVINCE": 14
      }
    }
  ]
}