{
  "type": "FeatureCollection",
  "features": [
    {
      "type": "Feature",
      "id": 10252,
      "geometry": {
        "type": "Point",
        "coordinates": [
          150.92944305535275,
          -9.847515617451734
        ]
      },
      "properties": {
        "OBJECTID": 10252,
        "CU_NAME": "MIADEBA",
        "CU_NO": "007",
        "GEOCODE": "05041507007",
        "PROV_KEY": "05",
        "DIST_NO": "4",
        "LLG_NO": "15",
        "WARD_NO": "07",
        "WARD_NAME": "MIADEBA",
        "LATITUDE": -9.848909,
        "LONGITUDE": 150.928729,
        "REGHH": 67,
        "TOTPOP2000": 341,
        "MALE2000": 181,
        "FEMALE2000": 160,
        "POP2008": 416,
        "G_RATE": 1.024999976158142,
        "Geocode_Num": 5041507007,
        "PROVINCE": 5
      }
    }
  ]
}