{
  "type": "FeatureCollection",
  "features": [
    {
      "type": "Feature",
      "id": 10255,
      "geometry": {
        "type": "Point",
        "coordinates": [
          150.8525601997934,
          -9.742135514342465
        ]
      },
      "properties": {
        "OBJECTID": 10255,
        "CU_NAME": "BUDUWAGULA",
        "CU_NO": "001",
        "GEOCODE": "05041510001",
        "PROV_KEY": "05",
        "DIST_NO": "4",
        "LLG_NO": "15",
        "WARD_NO": "10",
        "WARD_NAME": "BUDUWAGULA",
        "LATITUDE": -9.738563,
        "LONGITUDE": 150.754239,
        "REGHH": 147,
        "TOTPOP2000": 765,
        "MALE2000": 382,
        "FEMALE2000": 383,
        "POP2008": 933,
        "G_RATE": 1.024999976158142,
        "Geocode_Num": 5041510001,
        "PROVINCE": 5
      }
    }
  ]
}