{
  "type": "FeatureCollection",
  "features": [
    {
      "type": "Feature",
      "id": 10266,
      "geometry": {
        "type": "Point",
        "coordinates": [
          150.8536537466232,
          -9.674341300910271
        ]
      },
      "properties": {
        "OBJECTID": 10266,
        "CU_NAME": "DEIDEI",
        "CU_NO": "005",
        "GEOCODE": "05041521005",
        "PROV_KEY": "05",
        "DIST_NO": "4",
        "LLG_NO": "15",
        "WARD_NO": "21",
        "WARD_NAME": "DEI DEI",
        "LATITUDE": -9.677629,
        "LONGITUDE": 150.85394,
        "REGHH": 58,
        "TOTPOP2000": 299,
        "MALE2000": 143,
        "FEMALE2000": 156,
        "POP2008": 364,
        "G_RATE": 1.024999976158142,
        "Geocode_Num": 5041521005,
        "PROVINCE": 5
      }
    }
  ]
}