{
  "type": "FeatureCollection",
  "features": [
    {
      "type": "Feature",
      "id": 10270,
      "geometry": {
        "type": "Point",
        "coordinates": [
          150.86998899989248,
          -9.68485099957394
        ]
      },
      "properties": {
        "OBJECTID": 10270,
        "CU_NAME": "WALUMA WEST",
        "CU_NO": "013",
        "GEOCODE": "05041525013",
        "PROV_KEY": "05",
        "DIST_NO": "4",
        "LLG_NO": "15",
        "WARD_NO": "25",
        "WARD_NAME": "WALUMA WEST",
        "LATITUDE": -9.689296,
        "LONGITUDE": 150.872041,
        "REGHH": 127,
        "TOTPOP2000": 757,
        "MALE2000": 380,
        "FEMALE2000": 377,
        "POP2008": 921,
        "G_RATE": 1.024999976158142,
        "Geocode_Num": 5041525013,
        "PROVINCE": 5
      }
    }
  ]
}