{
  "type": "FeatureCollection",
  "features": [
    {
      "type": "Feature",
      "id": 10279,
      "geometry": {
        "type": "Point",
        "coordinates": [
          150.87874299978967,
          -9.213717999885716
        ]
      },
      "properties": {
        "OBJECTID": 10279,
        "CU_NAME": "GUMAWANA",
        "CU_NO": "001",
        "GEOCODE": "05041534001",
        "PROV_KEY": "05",
        "DIST_NO": "04",
        "LLG_NO": "15",
        "WARD_NO": "34",
        "WARD_NAME": "GUMAWANA",
        "LATITUDE": -9.22454,
        "LONGITUDE": 150.870547,
        "REGHH": 30,
        "TOTPOP2000": 154,
        "MALE2000": 81,
        "FEMALE2000": 73,
        "POP2008": 187,
        "G_RATE": 1.024999976158142,
        "Geocode_Num": 5041534001,
        "PROVINCE": 5
      }
    },
    {
      "type": "Feature",
      "id": 10280,
      "geometry": {
        "type": "Point",
        "coordinates": [
          150.81870099995126,
          -9.208222000045225
        ]
      },
      "properties": {
        "OBJECTID": 10280,
        "CU_NAME": "NABWAGETA ISLAND",
        "CU_NO": "002",
        "GEOCODE": "05041534002",
        "PROV_KEY": "05",
        "DIST_NO": "04",
        "LLG_NO": "15",
        "WARD_NO": "34",
        "WARD_NAME": "GUMAWANA",
        "LATITUDE": -9.209678,
        "LONGITUDE": 150.817725,
        "REGHH": 31,
        "TOTPOP2000": 173,
        "MALE2000": 95,
        "FEMALE2000": 78,
        "POP2008": 211,
        "G_RATE": 1.024999976158142,
        "Geocode_Num": 5041534002,
        "PROVINCE": 5
      }
    },
    {
      "type": "Feature",
      "id": 10281,
      "geometry": {
        "type": "Point",
        "coordinates": [
          150.88790499961613,
          -9.243934000253887
        ]
      },
      "properties": {
        "OBJECTID": 10281,
        "CU_NAME": "WAMEA",
        "CU_NO": "003",
        "GEOCODE": "05041534003",
        "PROV_KEY": "05",
        "DIST_NO": "04",
        "LLG_NO": "15",
        "WARD_NO": "34",
        "WARD_NAME": "GUMAWANA",
        "LATITUDE": -9.245438,
        "LONGITUDE": 150.886701,
        "REGHH": 29,
        "TOTPOP2000": 142,
        "MALE2000": 69,
        "FEMALE2000": 73,
        "POP2008": 174,
        "G_RATE": 1.024999976158142,
        "Geocode_Num": 5041534003,
        "PROVINCE": 5
      }
    }
  ]
}