{
  "type": "FeatureCollection",
  "features": [
    {
      "type": "Feature",
      "id": 27725,
      "geometry": {
        "type": "Point",
        "coordinates": [
          150.1148570003503,
          -9.354628000381865
        ]
      },
      "properties": {
        "OBJECTID": 27725,
        "CU_NAME": "Aikawa",
        "CU_NO": "849",
        "GEOCODE": "849",
        "PROV_KEY": "5",
        "DIST_NO": "03",
        "LLG_NO": null,
        "WARD_NO": null,
        "WARD_NAME": null,
        "LATITUDE": null,
        "LONGITUDE": null,
        "REGHH": null,
        "TOTPOP2000": null,
        "MALE2000": null,
        "FEMALE2000": null,
        "POP2008": null,
        "G_RATE": null,
        "Geocode_Num": 849,
        "PROVINCE": null
      }
    }
  ]
}