{
  "type": "FeatureCollection",
  "features": [
    {
      "type": "Feature",
      "id": 21092,
      "geometry": {
        "type": "Point",
        "coordinates": [
          143.65428399960695,
          -6.114897000196379
        ]
      },
      "properties": {
        "OBJECTID": 21092,
        "CU_NAME": "TENTE 1",
        "CU_NO": "018",
        "GEOCODE": "07062013018",
        "PROV_KEY": "07",
        "DIST_NO": "06",
        "LLG_NO": "20",
        "WARD_NO": "13",
        "WARD_NAME": "TENTE 1",
        "LATITUDE": -6.119141,
        "LONGITUDE": 143.65456,
        "REGHH": 95,
        "TOTPOP2000": 547,
        "MALE2000": 285,
        "FEMALE2000": 262,
        "POP2008": 760,
        "G_RATE": 1.0420000553131104,
        "Geocode_Num": 7062013018,
        "PROVINCE": 7
      }
    }
  ]
}