{
  "type": "FeatureCollection",
  "features": [
    {
      "type": "Feature",
      "id": 10223,
      "geometry": {
        "type": "Point",
        "coordinates": [
          150.49431500013725,
          -9.627244999656966
        ]
      },
      "properties": {
        "OBJECTID": 10223,
        "CU_NAME": "IGWAGETA",
        "CU_NO": "013",
        "GEOCODE": "05041405013",
        "PROV_KEY": "05",
        "DIST_NO": "4",
        "LLG_NO": "14",
        "WARD_NO": "05",
        "WARD_NAME": "IGWAGETA",
        "LATITUDE": -9.628706,
        "LONGITUDE": 150.493333,
        "REGHH": 61,
        "TOTPOP2000": 278,
        "MALE2000": 141,
        "FEMALE2000": 137,
        "POP2008": 338,
        "G_RATE": 1.024999976158142,
        "Geocode_Num": 5041405013,
        "PROVINCE": 5
      }
    }
  ]
}