{
  "type": "FeatureCollection",
  "features": [
    {
      "type": "Feature",
      "id": 10238,
      "geometry": {
        "type": "Point",
        "coordinates": [
          150.61147499987146,
          -9.388879999812104
        ]
      },
      "properties": {
        "OBJECTID": 10238,
        "CU_NAME": "GWABEGWABE",
        "CU_NO": "009",
        "GEOCODE": "05041419009",
        "PROV_KEY": "05",
        "DIST_NO": "4",
        "LLG_NO": "14",
        "WARD_NO": "19",
        "WARD_NAME": "GWABEGWABE",
        "LATITUDE": -9.388887,
        "LONGITUDE": 150.618076,
        "REGHH": 60,
        "TOTPOP2000": 333,
        "MALE2000": 168,
        "FEMALE2000": 165,
        "POP2008": 406,
        "G_RATE": 1.024999976158142,
        "Geocode_Num": 5041419009,
        "PROVINCE": 5
      }
    }
  ]
}