{
  "type": "FeatureCollection",
  "features": [
    {
      "type": "Feature",
      "id": 14223,
      "geometry": {
        "type": "Point",
        "coordinates": [
          144.7760710002765,
          -6.490417000044488
        ]
      },
      "properties": {
        "OBJECTID": 14223,
        "CU_NAME": "SOBORO",
        "CU_NO": "003",
        "GEOCODE": "10030709003",
        "PROV_KEY": "10",
        "DIST_NO": "03",
        "LLG_NO": "07",
        "WARD_NO": "09",
        "WARD_NAME": "BOISAMARU 2",
        "LATITUDE": -6.491831,
        "LONGITUDE": 144.775018,
        "REGHH": 41,
        "TOTPOP2000": 296,
        "MALE2000": 165,
        "FEMALE2000": 131,
        "POP2008": 342,
        "G_RATE": 1.0180000066757202,
        "Geocode_Num": 10030709003,
        "PROVINCE": 10
      }
    }
  ]
}