{
  "type": "FeatureCollection",
  "features": [
    {
      "type": "Feature",
      "id": 14232,
      "geometry": {
        "type": "Point",
        "coordinates": [
          144.69838199962965,
          -6.540636000151267
        ]
      },
      "properties": {
        "OBJECTID": 14232,
        "CU_NAME": "SOGO 2",
        "CU_NO": "001",
        "GEOCODE": "10030712001",
        "PROV_KEY": "10",
        "DIST_NO": "03",
        "LLG_NO": "07",
        "WARD_NO": "12",
        "WARD_NAME": "DIBE 2",
        "LATITUDE": -6.542051,
        "LONGITUDE": 144.697328,
        "REGHH": 44,
        "TOTPOP2000": 290,
        "MALE2000": 129,
        "FEMALE2000": 161,
        "POP2008": 334,
        "G_RATE": 1.0180000066757202,
        "Geocode_Num": 10030712001,
        "PROVINCE": 10
      }
    }
  ]
}