{
  "type": "FeatureCollection",
  "features": [
    {
      "type": "Feature",
      "id": 14241,
      "geometry": {
        "type": "Point",
        "coordinates": [
          144.68945799998676,
          -6.587325000248541
        ]
      },
      "properties": {
        "OBJECTID": 14241,
        "CU_NAME": "MAINA",
        "CU_NO": "003",
        "GEOCODE": "10030716003",
        "PROV_KEY": "10",
        "DIST_NO": "03",
        "LLG_NO": "07",
        "WARD_NO": "16",
        "WARD_NAME": "MASI",
        "LATITUDE": -6.58874,
        "LONGITUDE": 144.688403,
        "REGHH": 50,
        "TOTPOP2000": 313,
        "MALE2000": 168,
        "FEMALE2000": 145,
        "POP2008": 361,
        "G_RATE": 1.0180000066757202,
        "Geocode_Num": 10030716003,
        "PROVINCE": 10
      }
    },
    {
      "type": "Feature",
      "id": 14242,
      "geometry": {
        "type": "Point",
        "coordinates": [
          144.6929970004113,
          -6.602206000306637
        ]
      },
      "properties": {
        "OBJECTID": 14242,
        "CU_NAME": "WALAISIVI",
        "CU_NO": "004",
        "GEOCODE": "10030716004",
        "PROV_KEY": "10",
        "DIST_NO": "03",
        "LLG_NO": "07",
        "WARD_NO": "16",
        "WARD_NAME": "MASI",
        "LATITUDE": -6.603621,
        "LONGITUDE": 144.691942,
        "REGHH": 20,
        "TOTPOP2000": 112,
        "MALE2000": 64,
        "FEMALE2000": 48,
        "POP2008": 128,
        "G_RATE": 1.0180000066757202,
        "Geocode_Num": 10030716004,
        "PROVINCE": 10
      }
    },
    {
      "type": "Feature",
      "id": 14243,
      "geometry": {
        "type": "Point",
        "coordinates": [
          144.69268699960537,
          -6.592162000276062
        ]
      },
      "properties": {
        "OBJECTID": 14243,
        "CU_NAME": "OKANOMA",
        "CU_NO": "005",
        "GEOCODE": "10030716005",
        "PROV_KEY": "10",
        "DIST_NO": "03",
        "LLG_NO": "07",
        "WARD_NO": "16",
        "WARD_NAME": "MASI",
        "LATITUDE": -6.592283,
        "LONGITUDE": 144.697877,
        "REGHH": 46,
        "TOTPOP2000": 278,
        "MALE2000": 154,
        "FEMALE2000": 124,
        "POP2008": 320,
        "G_RATE": 1.0180000066757202,
        "Geocode_Num": 10030716005,
        "PROVINCE": 10
      }
    }
  ]
}