{
  "type": "FeatureCollection",
  "features": [
    {
      "type": "Feature",
      "id": 14249,
      "geometry": {
        "type": "Point",
        "coordinates": [
          144.62111300036474,
          -6.592549000136216
        ]
      },
      "properties": {
        "OBJECTID": 14249,
        "CU_NAME": "TOMOBIRISIBI",
        "CU_NO": "004",
        "GEOCODE": "10030719004",
        "PROV_KEY": "10",
        "DIST_NO": "03",
        "LLG_NO": "07",
        "WARD_NO": "19",
        "WARD_NAME": "SOLARI (NORU)",
        "LATITUDE": -6.593964,
        "LONGITUDE": 144.620057,
        "REGHH": 28,
        "TOTPOP2000": 199,
        "MALE2000": 107,
        "FEMALE2000": 92,
        "POP2008": 231,
        "G_RATE": 1.0180000066757202,
        "Geocode_Num": 10030719004,
        "PROVINCE": 10
      }
    },
    {
      "type": "Feature",
      "id": 14250,
      "geometry": {
        "type": "Point",
        "coordinates": [
          144.62808599996902,
          -6.594720999574406
        ]
      },
      "properties": {
        "OBJECTID": 14250,
        "CU_NAME": "ELEINAME",
        "CU_NO": "005",
        "GEOCODE": "10030719005",
        "PROV_KEY": "10",
        "DIST_NO": "03",
        "LLG_NO": "07",
        "WARD_NO": "19",
        "WARD_NAME": "SOLARI (NORU)",
        "LATITUDE": -6.596136,
        "LONGITUDE": 144.627031,
        "REGHH": 33,
        "TOTPOP2000": 218,
        "MALE2000": 112,
        "FEMALE2000": 106,
        "POP2008": 250,
        "G_RATE": 1.0180000066757202,
        "Geocode_Num": 10030719005,
        "PROVINCE": 10
      }
    },
    {
      "type": "Feature",
      "id": 14251,
      "geometry": {
        "type": "Point",
        "coordinates": [
          144.64037500010625,
          -6.596101000260887
        ]
      },
      "properties": {
        "OBJECTID": 14251,
        "CU_NAME": "SULUSIBI",
        "CU_NO": "006",
        "GEOCODE": "10030719006",
        "PROV_KEY": "10",
        "DIST_NO": "03",
        "LLG_NO": "07",
        "WARD_NO": "19",
        "WARD_NAME": "SOLARI (NORU)",
        "LATITUDE": -6.597516,
        "LONGITUDE": 144.63932,
        "REGHH": 41,
        "TOTPOP2000": 293,
        "MALE2000": 131,
        "FEMALE2000": 162,
        "POP2008": 338,
        "G_RATE": 1.0180000066757202,
        "Geocode_Num": 10030719006,
        "PROVINCE": 10
      }
    },
    {
      "type": "Feature",
      "id": 14252,
      "geometry": {
        "type": "Point",
        "coordinates": [
          144.64313699977276,
          -6.597583000255213
        ]
      },
      "properties": {
        "OBJECTID": 14252,
        "CU_NAME": "DOGOGASIBI",
        "CU_NO": "007",
        "GEOCODE": "10030719007",
        "PROV_KEY": "10",
        "DIST_NO": "03",
        "LLG_NO": "07",
        "WARD_NO": "19",
        "WARD_NAME": "SOLARI (NORU)",
        "LATITUDE": -6.598998,
        "LONGITUDE": 144.642082,
        "REGHH": 41,
        "TOTPOP2000": 281,
        "MALE2000": 142,
        "FEMALE2000": 139,
        "POP2008": 324,
        "G_RATE": 1.0180000066757202,
        "Geocode_Num": 10030719007,
        "PROVINCE": 10
      }
    }
  ]
}