{
  "type": "FeatureCollection",
  "features": [
    {
      "type": "Feature",
      "id": 14269,
      "geometry": {
        "type": "Point",
        "coordinates": [
          144.71017400023004,
          -6.387989999838567
        ]
      },
      "properties": {
        "OBJECTID": 14269,
        "CU_NAME": "TALABAKUL",
        "CU_NO": "003",
        "GEOCODE": "10030726003",
        "PROV_KEY": "10",
        "DIST_NO": "03",
        "LLG_NO": "07",
        "WARD_NO": "26",
        "WARD_NAME": "HAIA",
        "LATITUDE": -6.389403,
        "LONGITUDE": 144.70912,
        "REGHH": 50,
        "TOTPOP2000": 322,
        "MALE2000": 168,
        "FEMALE2000": 154,
        "POP2008": 371,
        "G_RATE": 1.0180000066757202,
        "Geocode_Num": 10030726003,
        "PROVINCE": 10
      }
    },
    {
      "type": "Feature",
      "id": 14270,
      "geometry": {
        "type": "Point",
        "coordinates": [
          144.72242400036737,
          -6.387323999702801
        ]
      },
      "properties": {
        "OBJECTID": 14270,
        "CU_NAME": "DIBESIBI",
        "CU_NO": "004",
        "GEOCODE": "10030726004",
        "PROV_KEY": "10",
        "DIST_NO": "03",
        "LLG_NO": "07",
        "WARD_NO": "26",
        "WARD_NAME": "HAIA",
        "LATITUDE": -6.388737,
        "LONGITUDE": 144.72137,
        "REGHH": 42,
        "TOTPOP2000": 325,
        "MALE2000": 201,
        "FEMALE2000": 124,
        "POP2008": 374,
        "G_RATE": 1.0180000066757202,
        "Geocode_Num": 10030726004,
        "PROVINCE": 10
      }
    },
    {
      "type": "Feature",
      "id": 14271,
      "geometry": {
        "type": "Point",
        "coordinates": [
          144.7090790000958,
          -6.3950370001574015
        ]
      },
      "properties": {
        "OBJECTID": 14271,
        "CU_NAME": "HUSUKAI",
        "CU_NO": "005",
        "GEOCODE": "10030726005",
        "PROV_KEY": "10",
        "DIST_NO": "03",
        "LLG_NO": "07",
        "WARD_NO": "26",
        "WARD_NAME": "HAIA",
        "LATITUDE": -6.39645,
        "LONGITUDE": 144.708025,
        "REGHH": 17,
        "TOTPOP2000": 127,
        "MALE2000": 76,
        "FEMALE2000": 51,
        "POP2008": 145,
        "G_RATE": 1.0180000066757202,
        "Geocode_Num": 10030726005,
        "PROVINCE": 10
      }
    },
    {
      "type": "Feature",
      "id": 14272,
      "geometry": {
        "type": "Point",
        "coordinates": [
          144.71785400006206,
          -6.376971999857858
        ]
      },
      "properties": {
        "OBJECTID": 14272,
        "CU_NAME": "SANIBIRI",
        "CU_NO": "006",
        "GEOCODE": "10030726006",
        "PROV_KEY": "10",
        "DIST_NO": "03",
        "LLG_NO": "07",
        "WARD_NO": "26",
        "WARD_NAME": "HAIA",
        "LATITUDE": -6.378385,
        "LONGITUDE": 144.7168,
        "REGHH": 23,
        "TOTPOP2000": 183,
        "MALE2000": 103,
        "FEMALE2000": 80,
        "POP2008": 211,
        "G_RATE": 1.0180000066757202,
        "Geocode_Num": 10030726006,
        "PROVINCE": 10
      }
    }
  ]
}