{
  "type": "FeatureCollection",
  "features": [
    {
      "type": "Feature",
      "id": 14469,
      "geometry": {
        "type": "Point",
        "coordinates": [
          144.82066299989754,
          -5.876757999981692
        ]
      },
      "properties": {
        "OBJECTID": 14469,
        "CU_NAME": "NIGLGOGL",
        "CU_NO": "010",
        "GEOCODE": "10041103010",
        "PROV_KEY": "10",
        "DIST_NO": "04",
        "LLG_NO": "11",
        "WARD_NO": "03",
        "WARD_NAME": "DAGE MITNA 2",
        "LATITUDE": -5.878166,
        "LONGITUDE": 144.819612,
        "REGHH": 47,
        "TOTPOP2000": 218,
        "MALE2000": 120,
        "FEMALE2000": 98,
        "POP2008": 250,
        "G_RATE": 1.0180000066757202,
        "Geocode_Num": 10041103010,
        "PROVINCE": 10
      }
    },
    {
      "type": "Feature",
      "id": 14470,
      "geometry": {
        "type": "Point",
        "coordinates": [
          144.82403099963096,
          -5.872794999789335
        ]
      },
      "properties": {
        "OBJECTID": 14470,
        "CU_NAME": "KEWAMUGL",
        "CU_NO": "011",
        "GEOCODE": "10041103011",
        "PROV_KEY": "10",
        "DIST_NO": "04",
        "LLG_NO": "11",
        "WARD_NO": "03",
        "WARD_NAME": "DAGE MITNA 2",
        "LATITUDE": -5.874624,
        "LONGITUDE": 144.822978,
        "REGHH": 80,
        "TOTPOP2000": 398,
        "MALE2000": 215,
        "FEMALE2000": 183,
        "POP2008": 459,
        "G_RATE": 1.0180000066757202,
        "Geocode_Num": 10041103011,
        "PROVINCE": 10
      }
    },
    {
      "type": "Feature",
      "id": 14471,
      "geometry": {
        "type": "Point",
        "coordinates": [
          144.8320050004305,
          -5.882415000052163
        ]
      },
      "properties": {
        "OBJECTID": 14471,
        "CU_NAME": "KUGAYAM",
        "CU_NO": "012",
        "GEOCODE": "10041103012",
        "PROV_KEY": "10",
        "DIST_NO": "04",
        "LLG_NO": "11",
        "WARD_NO": "03",
        "WARD_NAME": "DAGE MITNA 2",
        "LATITUDE": -5.883823,
        "LONGITUDE": 144.830954,
        "REGHH": 51,
        "TOTPOP2000": 261,
        "MALE2000": 122,
        "FEMALE2000": 139,
        "POP2008": 301,
        "G_RATE": 1.0180000066757202,
        "Geocode_Num": 10041103012,
        "PROVINCE": 10
      }
    },
    {
      "type": "Feature",
      "id": 14472,
      "geometry": {
        "type": "Point",
        "coordinates": [
          144.83911400001114,
          -5.874249000291059
        ]
      },
      "properties": {
        "OBJECTID": 14472,
        "CU_NAME": "MONDIA",
        "CU_NO": "013",
        "GEOCODE": "10041103013",
        "PROV_KEY": "10",
        "DIST_NO": "04",
        "LLG_NO": "11",
        "WARD_NO": "03",
        "WARD_NAME": "DAGE MITNA 2",
        "LATITUDE": -5.875657,
        "LONGITUDE": 144.838063,
        "REGHH": 30,
        "TOTPOP2000": 122,
        "MALE2000": 69,
        "FEMALE2000": 53,
        "POP2008": 138,
        "G_RATE": 1.0180000066757202,
        "Geocode_Num": 10041103013,
        "PROVINCE": 10
      }
    }
  ]
}