{
  "type": "FeatureCollection",
  "features": [
    {
      "type": "Feature",
      "id": 19917,
      "geometry": {
        "type": "Point",
        "coordinates": [
          143.7585429997597,
          -6.450701999597584
        ]
      },
      "properties": {
        "OBJECTID": 19917,
        "CU_NAME": "PURI",
        "CU_NO": "001",
        "GEOCODE": "07030917001",
        "PROV_KEY": "07",
        "DIST_NO": "03",
        "LLG_NO": "09",
        "WARD_NO": "17",
        "WARD_NAME": "RONGA",
        "LATITUDE": -6.453262,
        "LONGITUDE": 143.758391,
        "REGHH": 49,
        "TOTPOP2000": 244,
        "MALE2000": 132,
        "FEMALE2000": 112,
        "POP2008": 340,
        "G_RATE": 1.0420000553131104,
        "Geocode_Num": 7030917001,
        "PROVINCE": 7
      }
    },
    {
      "type": "Feature",
      "id": 19918,
      "geometry": {
        "type": "Point",
        "coordinates": [
          143.7560079997694,
          -6.4498699999005
        ]
      },
      "properties": {
        "OBJECTID": 19918,
        "CU_NAME": "OMAI",
        "CU_NO": "002",
        "GEOCODE": "07030917002",
        "PROV_KEY": "07",
        "DIST_NO": "03",
        "LLG_NO": "09",
        "WARD_NO": "17",
        "WARD_NAME": "RONGA",
        "LATITUDE": -6.453262,
        "LONGITUDE": 143.758391,
        "REGHH": 38,
        "TOTPOP2000": 225,
        "MALE2000": 115,
        "FEMALE2000": 110,
        "POP2008": 313,
        "G_RATE": 1.0420000553131104,
        "Geocode_Num": 7030917002,
        "PROVINCE": 7
      }
    },
    {
      "type": "Feature",
      "id": 19919,
      "geometry": {
        "type": "Point",
        "coordinates": [
          143.75578500027757,
          -6.447758999678058
        ]
      },
      "properties": {
        "OBJECTID": 19919,
        "CU_NAME": "RAIPALA",
        "CU_NO": "003",
        "GEOCODE": "07030917003",
        "PROV_KEY": "07",
        "DIST_NO": "03",
        "LLG_NO": "09",
        "WARD_NO": "17",
        "WARD_NAME": "RONGA",
        "LATITUDE": -6.453262,
        "LONGITUDE": 143.758391,
        "REGHH": 21,
        "TOTPOP2000": 128,
        "MALE2000": 60,
        "FEMALE2000": 68,
        "POP2008": 178,
        "G_RATE": 1.0420000553131104,
        "Geocode_Num": 7030917003,
        "PROVINCE": 7
      }
    },
    {
      "type": "Feature",
      "id": 19920,
      "geometry": {
        "type": "Point",
        "coordinates": [
          143.75789899973915,
          -6.4485930003666
        ]
      },
      "properties": {
        "OBJECTID": 19920,
        "CU_NAME": "WATA",
        "CU_NO": "004",
        "GEOCODE": "07030917004",
        "PROV_KEY": "07",
        "DIST_NO": "03",
        "LLG_NO": "09",
        "WARD_NO": "17",
        "WARD_NAME": "RONGA",
        "LATITUDE": -6.453262,
        "LONGITUDE": 143.758391,
        "REGHH": 14,
        "TOTPOP2000": 76,
        "MALE2000": 44,
        "FEMALE2000": 32,
        "POP2008": 105,
        "G_RATE": 1.0420000553131104,
        "Geocode_Num": 7030917004,
        "PROVINCE": 7
      }
    }
  ]
}