{
  "type": "FeatureCollection",
  "features": [
    {
      "type": "Feature",
      "id": 1529,
      "geometry": {
        "type": "Point",
        "coordinates": [
          146.59130699961838,
          -8.6274429999944
        ]
      },
      "properties": {
        "OBJECTID": 1529,
        "CU_NAME": "EBOA",
        "CU_NO": "005",
        "GEOCODE": "03031005005",
        "PROV_KEY": "03",
        "DIST_NO": "03",
        "LLG_NO": "10",
        "WARD_NO": "05",
        "WARD_NAME": "EBOA",
        "LATITUDE": -8.628883,
        "LONGITUDE": 146.590273,
        "REGHH": 175,
        "TOTPOP2000": 1145,
        "MALE2000": 587,
        "FEMALE2000": 558,
        "POP2008": 1374,
        "G_RATE": 1.0230000019073486,
        "Geocode_Num": 3031005005,
        "PROVINCE": 3
      }
    }
  ]
}