{
  "type": "FeatureCollection",
  "features": [
    {
      "type": "Feature",
      "id": 12669,
      "geometry": {
        "type": "Point",
        "coordinates": [
          152.5030339998193,
          -3.6723420003829688
        ]
      },
      "properties": {
        "OBJECTID": 12669,
        "CU_NAME": "NAMAROUDU",
        "CU_NO": "012",
        "GEOCODE": "17020512012",
        "PROV_KEY": "17",
        "DIST_NO": "02",
        "LLG_NO": "05",
        "WARD_NO": "12",
        "WARD_NAME": "SALIMUN",
        "LATITUDE": -3.673289,
        "LONGITUDE": 152.502538,
        "REGHH": 65,
        "TOTPOP2000": 316,
        "MALE2000": 159,
        "FEMALE2000": 157,
        "POP2008": 397,
        "G_RATE": 1.0290000438690186,
        "Geocode_Num": 17020512012,
        "PROVINCE": 17
      }
    },
    {
      "type": "Feature",
      "id": 12670,
      "geometry": {
        "type": "Point",
        "coordinates": [
          152.4683660000909,
          -3.643355000033182
        ]
      },
      "properties": {
        "OBJECTID": 12670,
        "CU_NAME": "RASESE",
        "CU_NO": "018",
        "GEOCODE": "17020512018",
        "PROV_KEY": "17",
        "DIST_NO": "02",
        "LLG_NO": "05",
        "WARD_NO": "12",
        "WARD_NAME": "SALIMUN",
        "LATITUDE": -3.644747,
        "LONGITUDE": 152.467425,
        "REGHH": 67,
        "TOTPOP2000": 402,
        "MALE2000": 216,
        "FEMALE2000": 186,
        "POP2008": 505,
        "G_RATE": 1.0290000438690186,
        "Geocode_Num": 17020512018,
        "PROVINCE": 17
      }
    },
    {
      "type": "Feature",
      "id": 12671,
      "geometry": {
        "type": "Point",
        "coordinates": [
          152.44963799979394,
          -3.6604179999906705
        ]
      },
      "properties": {
        "OBJECTID": 12671,
        "CU_NAME": "SALIMUN",
        "CU_NO": "020",
        "GEOCODE": "17020512020",
        "PROV_KEY": "17",
        "DIST_NO": "02",
        "LLG_NO": "05",
        "WARD_NO": "12",
        "WARD_NAME": "SALIMUN",
        "LATITUDE": -3.661445,
        "LONGITUDE": 152.448407,
        "REGHH": 79,
        "TOTPOP2000": 420,
        "MALE2000": 212,
        "FEMALE2000": 208,
        "POP2008": 528,
        "G_RATE": 1.0290000438690186,
        "Geocode_Num": 17020512020,
        "PROVINCE": 17
      }
    },
    {
      "type": "Feature",
      "id": 12672,
      "geometry": {
        "type": "Point",
        "coordinates": [
          152.46059799979787,
          -3.6548220000352103
        ]
      },
      "properties": {
        "OBJECTID": 12672,
        "CU_NAME": "HALIS P/SCH",
        "CU_NO": "401",
        "GEOCODE": "17020512401",
        "PROV_KEY": "17",
        "DIST_NO": "02",
        "LLG_NO": "05",
        "WARD_NO": "12",
        "WARD_NAME": "SALIMUN",
        "LATITUDE": -3.656214,
        "LONGITUDE": 152.459657,
        "REGHH": 7,
        "TOTPOP2000": 35,
        "MALE2000": 15,
        "FEMALE2000": 20,
        "POP2008": 43,
        "G_RATE": 1.0290000438690186,
        "Geocode_Num": 17020512401,
        "PROVINCE": 17
      }
    }
  ]
}