{
  "type": "FeatureCollection",
  "features": [
    {
      "type": "Feature",
      "id": 12686,
      "geometry": {
        "type": "Point",
        "coordinates": [
          152.64568399961695,
          -3.838947999650429
        ]
      },
      "properties": {
        "OBJECTID": 12686,
        "CU_NAME": "HIBALING",
        "CU_NO": "003",
        "GEOCODE": "17020516003",
        "PROV_KEY": "17",
        "DIST_NO": "02",
        "LLG_NO": "05",
        "WARD_NO": "16",
        "WARD_NAME": "HIBALING",
        "LATITUDE": -3.840344,
        "LONGITUDE": 152.644746,
        "REGHH": 48,
        "TOTPOP2000": 246,
        "MALE2000": 141,
        "FEMALE2000": 105,
        "POP2008": 309,
        "G_RATE": 1.0290000438690186,
        "Geocode_Num": 17020516003,
        "PROVINCE": 17
      }
    },
    {
      "type": "Feature",
      "id": 12687,
      "geometry": {
        "type": "Point",
        "coordinates": [
          152.67132799958756,
          -3.853773999870157
        ]
      },
      "properties": {
        "OBJECTID": 12687,
        "CU_NAME": "HILALON",
        "CU_NO": "004",
        "GEOCODE": "17020516004",
        "PROV_KEY": "17",
        "DIST_NO": "02",
        "LLG_NO": "05",
        "WARD_NO": "16",
        "WARD_NAME": "HIBALING",
        "LATITUDE": -3.849769,
        "LONGITUDE": 152.665689,
        "REGHH": 46,
        "TOTPOP2000": 215,
        "MALE2000": 122,
        "FEMALE2000": 93,
        "POP2008": 270,
        "G_RATE": 1.0290000438690186,
        "Geocode_Num": 17020516004,
        "PROVINCE": 17
      }
    },
    {
      "type": "Feature",
      "id": 12688,
      "geometry": {
        "type": "Point",
        "coordinates": [
          152.6775820002092,
          -3.863349999902539
        ]
      },
      "properties": {
        "OBJECTID": 12688,
        "CU_NAME": "PORONBUS",
        "CU_NO": "019",
        "GEOCODE": "17020516019",
        "PROV_KEY": "17",
        "DIST_NO": "02",
        "LLG_NO": "05",
        "WARD_NO": "16",
        "WARD_NAME": "HIBALING",
        "LATITUDE": -3.864745,
        "LONGITUDE": 152.676644,
        "REGHH": 57,
        "TOTPOP2000": 272,
        "MALE2000": 149,
        "FEMALE2000": 123,
        "POP2008": 342,
        "G_RATE": 1.0290000438690186,
        "Geocode_Num": 17020516019,
        "PROVINCE": 17
      }
    },
    {
      "type": "Feature",
      "id": 12689,
      "geometry": {
        "type": "Point",
        "coordinates": [
          152.700188000376,
          -3.872679000235621
        ]
      },
      "properties": {
        "OBJECTID": 12689,
        "CU_NAME": "HILALON PLANTATION",
        "CU_NO": "501",
        "GEOCODE": "17020516501",
        "PROV_KEY": "17",
        "DIST_NO": "02",
        "LLG_NO": "05",
        "WARD_NO": "16",
        "WARD_NAME": "HIBALING",
        "LATITUDE": -3.874074,
        "LONGITUDE": 152.699251,
        "REGHH": 12,
        "TOTPOP2000": 37,
        "MALE2000": 21,
        "FEMALE2000": 16,
        "POP2008": 45,
        "G_RATE": 1.0290000438690186,
        "Geocode_Num": 17020516501,
        "PROVINCE": 17
      }
    }
  ]
}