{
  "type": "FeatureCollection",
  "features": [
    {
      "type": "Feature",
      "id": 5736,
      "geometry": {
        "type": "Point",
        "coordinates": [
          143.15409399993825,
          -5.47076100031984
        ]
      },
      "properties": {
        "OBJECTID": 5736,
        "CU_NAME": "SHOPPING CENTER",
        "CU_NO": "001",
        "GEOCODE": "08030984001",
        "PROV_KEY": "08",
        "DIST_NO": "03",
        "LLG_NO": "09",
        "WARD_NO": "84",
        "WARD_NAME": "PAIAM TOWN",
        "LATITUDE": -5.469658,
        "LONGITUDE": 143.149497,
        "REGHH": 34,
        "TOTPOP2000": 267,
        "MALE2000": 165,
        "FEMALE2000": 102,
        "POP2008": 335,
        "G_RATE": 1.0290000438690186,
        "Geocode_Num": 8030984001,
        "PROVINCE": 8
      }
    },
    {
      "type": "Feature",
      "id": 5737,
      "geometry": {
        "type": "Point",
        "coordinates": [
          143.15415199991492,
          -5.468473000028894
        ]
      },
      "properties": {
        "OBJECTID": 5737,
        "CU_NAME": "HOSPITAL/HIGH SCHOOL",
        "CU_NO": "002",
        "GEOCODE": "08030984002",
        "PROV_KEY": "08",
        "DIST_NO": "03",
        "LLG_NO": "09",
        "WARD_NO": "84",
        "WARD_NAME": "PAIAM TOWN",
        "LATITUDE": -5.469658,
        "LONGITUDE": 143.149497,
        "REGHH": 36,
        "TOTPOP2000": 249,
        "MALE2000": 136,
        "FEMALE2000": 113,
        "POP2008": 313,
        "G_RATE": 1.0290000438690186,
        "Geocode_Num": 8030984002,
        "PROVINCE": 8
      }
    }
  ]
}