{
  "type": "FeatureCollection",
  "features": [
    {
      "type": "Feature",
      "id": 20762,
      "geometry": {
        "type": "Point",
        "coordinates": [
          142.59278900041215,
          -5.56004000034568
        ]
      },
      "properties": {
        "OBJECTID": 20762,
        "CU_NAME": "OKALI",
        "CU_NO": "001",
        "GEOCODE": "07051604001",
        "PROV_KEY": "21",
        "DIST_NO": "2",
        "LLG_NO": "16",
        "WARD_NO": "04",
        "WARD_NAME": "HAWIANDA",
        "LATITUDE": -5.564304,
        "LONGITUDE": 142.584853,
        "REGHH": 36,
        "TOTPOP2000": 88,
        "MALE2000": 51,
        "FEMALE2000": 37,
        "POP2008": 123,
        "G_RATE": 1.0420000553131104,
        "Geocode_Num": 7051604001,
        "PROVINCE": 21
      }
    },
    {
      "type": "Feature",
      "id": 20763,
      "geometry": {
        "type": "Point",
        "coordinates": [
          142.59280999958185,
          -5.567347000063933
        ]
      },
      "properties": {
        "OBJECTID": 20763,
        "CU_NAME": "HINIYA",
        "CU_NO": "002",
        "GEOCODE": "07051604002",
        "PROV_KEY": "21",
        "DIST_NO": "2",
        "LLG_NO": "16",
        "WARD_NO": "04",
        "WARD_NAME": "HAWIANDA",
        "LATITUDE": -5.564305,
        "LONGITUDE": 142.584854,
        "REGHH": 60,
        "TOTPOP2000": 210,
        "MALE2000": 100,
        "FEMALE2000": 110,
        "POP2008": 292,
        "G_RATE": 1.0420000553131104,
        "Geocode_Num": 7051604002,
        "PROVINCE": 21
      }
    }
  ]
}