{
  "type": "FeatureCollection",
  "features": [
    {
      "type": "Feature",
      "id": 20771,
      "geometry": {
        "type": "Point",
        "coordinates": [
          142.67396099980033,
          -5.633398000017621
        ]
      },
      "properties": {
        "OBJECTID": 20771,
        "CU_NAME": "TALIWA",
        "CU_NO": "001",
        "GEOCODE": "07051608001",
        "PROV_KEY": "21",
        "DIST_NO": "2",
        "LLG_NO": "16",
        "WARD_NO": "08",
        "WARD_NAME": "KENAMU",
        "LATITUDE": -5.63764,
        "LONGITUDE": 142.67422,
        "REGHH": 55,
        "TOTPOP2000": 250,
        "MALE2000": 124,
        "FEMALE2000": 126,
        "POP2008": 347,
        "G_RATE": 1.0420000553131104,
        "Geocode_Num": 7051608001,
        "PROVINCE": 21
      }
    },
    {
      "type": "Feature",
      "id": 20772,
      "geometry": {
        "type": "Point",
        "coordinates": [
          142.669782000439,
          -5.6325359998364775
        ]
      },
      "properties": {
        "OBJECTID": 20772,
        "CU_NAME": "TALEWA",
        "CU_NO": "002",
        "GEOCODE": "07051608002",
        "PROV_KEY": "21",
        "DIST_NO": "2",
        "LLG_NO": "16",
        "WARD_NO": "08",
        "WARD_NAME": "KENAMU",
        "LATITUDE": -5.63765,
        "LONGITUDE": 142.67423,
        "REGHH": 35,
        "TOTPOP2000": 176,
        "MALE2000": 80,
        "FEMALE2000": 96,
        "POP2008": 244,
        "G_RATE": 1.0420000553131104,
        "Geocode_Num": 7051608002,
        "PROVINCE": 21
      }
    }
  ]
}