{
  "type": "FeatureCollection",
  "features": [
    {
      "type": "Feature",
      "id": 10801,
      "geometry": {
        "type": "Point",
        "coordinates": [
          147.63455900019778,
          -6.3922809998682055
        ]
      },
      "properties": {
        "OBJECTID": 10801,
        "CU_NAME": "YUNZAING",
        "CU_NO": "044",
        "GEOCODE": "12020704044",
        "PROV_KEY": "12",
        "DIST_NO": "02",
        "LLG_NO": "07",
        "WARD_NO": "04",
        "WARD_NAME": "YUNZAING",
        "LATITUDE": -6.3937,
        "LONGITUDE": 147.633544,
        "REGHH": 45,
        "TOTPOP2000": 188,
        "MALE2000": 93,
        "FEMALE2000": 95,
        "POP2008": 234,
        "G_RATE": 1.027999997138977,
        "Geocode_Num": 12020704044,
        "PROVINCE": 12
      }
    },
    {
      "type": "Feature",
      "id": 10802,
      "geometry": {
        "type": "Point",
        "coordinates": [
          147.62039900011382,
          -6.39668299962068
        ]
      },
      "properties": {
        "OBJECTID": 10802,
        "CU_NAME": "HANONG",
        "CU_NO": "045",
        "GEOCODE": "12020704045",
        "PROV_KEY": "12",
        "DIST_NO": "02",
        "LLG_NO": "07",
        "WARD_NO": "04",
        "WARD_NAME": "YUNZAING",
        "LATITUDE": -6.398102,
        "LONGITUDE": 147.619384,
        "REGHH": 47,
        "TOTPOP2000": 247,
        "MALE2000": 124,
        "FEMALE2000": 123,
        "POP2008": 308,
        "G_RATE": 1.027999997138977,
        "Geocode_Num": 12020704045,
        "PROVINCE": 12
      }
    },
    {
      "type": "Feature",
      "id": 10803,
      "geometry": {
        "type": "Point",
        "coordinates": [
          147.61343500002533,
          -6.411244000210388
        ]
      },
      "properties": {
        "OBJECTID": 10803,
        "CU_NAME": "YUNZAING AID POST",
        "CU_NO": "046",
        "GEOCODE": "12020704046",
        "PROV_KEY": "12",
        "DIST_NO": "02",
        "LLG_NO": "07",
        "WARD_NO": "04",
        "WARD_NAME": "YUNZAING",
        "LATITUDE": -6.412663,
        "LONGITUDE": 147.61242,
        "REGHH": 12,
        "TOTPOP2000": 58,
        "MALE2000": 33,
        "FEMALE2000": 25,
        "POP2008": 74,
        "G_RATE": 1.027999997138977,
        "Geocode_Num": 12020704046,
        "PROVINCE": 12
      }
    }
  ]
}