{
  "type": "FeatureCollection",
  "features": [
    {
      "type": "Feature",
      "id": 20174,
      "geometry": {
        "type": "Point",
        "coordinates": [
          143.0238939996085,
          -5.900064000053533
        ]
      },
      "properties": {
        "OBJECTID": 20174,
        "CU_NAME": "ALUAKAMBE",
        "CU_NO": "001",
        "GEOCODE": "07041101001",
        "PROV_KEY": "21",
        "DIST_NO": "1",
        "LLG_NO": "11",
        "WARD_NO": "01",
        "WARD_NAME": "ALUAKAMBE",
        "LATITUDE": -5.899723,
        "LONGITUDE": 143.029607,
        "REGHH": 117,
        "TOTPOP2000": 516,
        "MALE2000": 236,
        "FEMALE2000": 280,
        "POP2008": 720,
        "G_RATE": 1.0420000553131104,
        "Geocode_Num": 7041101001,
        "PROVINCE": 21
      }
    }
  ]
}