{
  "type": "FeatureCollection",
  "features": [
    {
      "type": "Feature",
      "id": 20209,
      "geometry": {
        "type": "Point",
        "coordinates": [
          143.14298100007318,
          -6.181656999570805
        ]
      },
      "properties": {
        "OBJECTID": 20209,
        "CU_NAME": "HOMA",
        "CU_NO": "006",
        "GEOCODE": "07041111006",
        "PROV_KEY": "21",
        "DIST_NO": "1",
        "LLG_NO": "11",
        "WARD_NO": "11",
        "WARD_NAME": "HOMA",
        "LATITUDE": -6.190409,
        "LONGITUDE": 143.149697,
        "REGHH": 13,
        "TOTPOP2000": 91,
        "MALE2000": 41,
        "FEMALE2000": 50,
        "POP2008": 126,
        "G_RATE": 1.0420000553131104,
        "Geocode_Num": 7041111006,
        "PROVINCE": 21
      }
    },
    {
      "type": "Feature",
      "id": 20210,
      "geometry": {
        "type": "Point",
        "coordinates": [
          143.14763799989385,
          -6.195406999633292
        ]
      },
      "properties": {
        "OBJECTID": 20210,
        "CU_NAME": "TABIYA",
        "CU_NO": "007",
        "GEOCODE": "07041111007",
        "PROV_KEY": "21",
        "DIST_NO": "1",
        "LLG_NO": "11",
        "WARD_NO": "11",
        "WARD_NAME": "HOMA",
        "LATITUDE": -6.195318,
        "LONGITUDE": 143.149697,
        "REGHH": 15,
        "TOTPOP2000": 115,
        "MALE2000": 62,
        "FEMALE2000": 53,
        "POP2008": 159,
        "G_RATE": 1.0420000553131104,
        "Geocode_Num": 7041111007,
        "PROVINCE": 21
      }
    }
  ]
}