{
  "type": "FeatureCollection",
  "features": [
    {
      "type": "Feature",
      "id": 20211,
      "geometry": {
        "type": "Point",
        "coordinates": [
          143.0992640003334,
          -6.028180999653387
        ]
      },
      "properties": {
        "OBJECTID": 20211,
        "CU_NAME": "DIMU",
        "CU_NO": "003",
        "GEOCODE": "07041112003",
        "PROV_KEY": "21",
        "DIST_NO": "1",
        "LLG_NO": "11",
        "WARD_NO": "12",
        "WARD_NAME": "DIMU",
        "LATITUDE": -6.032426,
        "LONGITUDE": 143.09953,
        "REGHH": 31,
        "TOTPOP2000": 182,
        "MALE2000": 97,
        "FEMALE2000": 85,
        "POP2008": 253,
        "G_RATE": 1.0420000553131104,
        "Geocode_Num": 7041112003,
        "PROVINCE": 21
      }
    }
  ]
}