{
  "type": "FeatureCollection",
  "features": [
    {
      "type": "Feature",
      "id": 18702,
      "geometry": {
        "type": "Point",
        "coordinates": [
          142.28521000044123,
          -5.197946000007846
        ]
      },
      "properties": {
        "OBJECTID": 18702,
        "CU_NAME": "TERANAP",
        "CU_NO": "008",
        "GEOCODE": "15030908008",
        "PROV_KEY": "15",
        "DIST_NO": "03",
        "LLG_NO": "09",
        "WARD_NO": "08",
        "WARD_NAME": "TERANAP",
        "LATITUDE": -5.199342,
        "LONGITUDE": 142.284128,
        "REGHH": 156,
        "TOTPOP2000": 896,
        "MALE2000": 455,
        "FEMALE2000": 441,
        "POP2008": 1084,
        "G_RATE": 1.0240000486373901,
        "Geocode_Num": 15030908008,
        "PROVINCE": 15
      }
    }
  ]
}