{
  "type": "FeatureCollection",
  "features": [
    {
      "type": "Feature",
      "id": 18710,
      "geometry": {
        "type": "Point",
        "coordinates": [
          142.07882799971253,
          -5.258219999753123
        ]
      },
      "properties": {
        "OBJECTID": 18710,
        "CU_NAME": "KWEPTANAP",
        "CU_NO": "005",
        "GEOCODE": "15030915005",
        "PROV_KEY": "15",
        "DIST_NO": "03",
        "LLG_NO": "09",
        "WARD_NO": "15",
        "WARD_NAME": "KWEPTANAP",
        "LATITUDE": -5.259617,
        "LONGITUDE": 142.077743,
        "REGHH": 154,
        "TOTPOP2000": 865,
        "MALE2000": 398,
        "FEMALE2000": 467,
        "POP2008": 1046,
        "G_RATE": 1.0240000486373901,
        "Geocode_Num": 15030915005,
        "PROVINCE": 15
      }
    }
  ]
}