{
  "type": "FeatureCollection",
  "features": [
    {
      "type": "Feature",
      "id": 11169,
      "geometry": {
        "type": "Point",
        "coordinates": [
          147.093711999809,
          -6.204128999853424
        ]
      },
      "properties": {
        "OBJECTID": 11169,
        "CU_NAME": "HONZEUKNGON",
        "CU_NO": "015",
        "GEOCODE": "12041210015",
        "PROV_KEY": "12",
        "DIST_NO": "04",
        "LLG_NO": "12",
        "WARD_NO": "10",
        "WARD_NAME": "MUMUNGGAM",
        "LATITUDE": -6.205545,
        "LONGITUDE": 147.09269,
        "REGHH": 44,
        "TOTPOP2000": 258,
        "MALE2000": 116,
        "FEMALE2000": 142,
        "POP2008": 322,
        "G_RATE": 1.027999997138977,
        "Geocode_Num": 12041210015,
        "PROVINCE": 12
      }
    },
    {
      "type": "Feature",
      "id": 11170,
      "geometry": {
        "type": "Point",
        "coordinates": [
          147.08738799955665,
          -6.200650000397161
        ]
      },
      "properties": {
        "OBJECTID": 11170,
        "CU_NAME": "MUMUNGGAM",
        "CU_NO": "023",
        "GEOCODE": "12041210023",
        "PROV_KEY": "12",
        "DIST_NO": "04",
        "LLG_NO": "12",
        "WARD_NO": "10",
        "WARD_NAME": "MUMUNGGAM",
        "LATITUDE": -6.202066,
        "LONGITUDE": 147.086366,
        "REGHH": 60,
        "TOTPOP2000": 303,
        "MALE2000": 140,
        "FEMALE2000": 163,
        "POP2008": 377,
        "G_RATE": 1.027999997138977,
        "Geocode_Num": 12041210023,
        "PROVINCE": 12
      }
    },
    {
      "type": "Feature",
      "id": 11171,
      "geometry": {
        "type": "Point",
        "coordinates": [
          147.09483000010448,
          -6.194148000030111
        ]
      },
      "properties": {
        "OBJECTID": 11171,
        "CU_NAME": "PINON",
        "CU_NO": "026",
        "GEOCODE": "12041210026",
        "PROV_KEY": "12",
        "DIST_NO": "04",
        "LLG_NO": "12",
        "WARD_NO": "10",
        "WARD_NAME": "MUMUNGGAM",
        "LATITUDE": -6.195564,
        "LONGITUDE": 147.093808,
        "REGHH": 29,
        "TOTPOP2000": 145,
        "MALE2000": 67,
        "FEMALE2000": 78,
        "POP2008": 181,
        "G_RATE": 1.027999997138977,
        "Geocode_Num": 12041210026,
        "PROVINCE": 12
      }
    }
  ]
}