{
  "type": "FeatureCollection",
  "features": [
    {
      "type": "Feature",
      "id": 5861,
      "geometry": {
        "type": "Point",
        "coordinates": [
          143.48675900022772,
          -5.129669999970474
        ]
      },
      "properties": {
        "OBJECTID": 5861,
        "CU_NAME": "PASALAGUS",
        "CU_NO": "005",
        "GEOCODE": "08041203005",
        "PROV_KEY": "08",
        "DIST_NO": "04",
        "LLG_NO": "12",
        "WARD_NO": "03",
        "WARD_NAME": "PASALAGUS",
        "LATITUDE": -5.131078,
        "LONGITUDE": 143.483099,
        "REGHH": 142,
        "TOTPOP2000": 793,
        "MALE2000": 391,
        "FEMALE2000": 402,
        "POP2008": 997,
        "G_RATE": 1.0290000438690186,
        "Geocode_Num": 8041203005,
        "PROVINCE": 8
      }
    },
    {
      "type": "Feature",
      "id": 5862,
      "geometry": {
        "type": "Point",
        "coordinates": [
          143.4878514795622,
          -5.125437876756564
        ]
      },
      "properties": {
        "OBJECTID": 5862,
        "CU_NAME": "MARAMUNI STN",
        "CU_NO": "401",
        "GEOCODE": "08041203401",
        "PROV_KEY": "08",
        "DIST_NO": "04",
        "LLG_NO": "12",
        "WARD_NO": "03",
        "WARD_NAME": "PASALAGUS",
        "LATITUDE": -5.13674,
        "LONGITUDE": 143.488535,
        "REGHH": 41,
        "TOTPOP2000": 267,
        "MALE2000": 130,
        "FEMALE2000": 137,
        "POP2008": 335,
        "G_RATE": 1.0290000438690186,
        "Geocode_Num": 8041203401,
        "PROVINCE": 8
      }
    }
  ]
}