{
  "type": "FeatureCollection",
  "features": [
    {
      "type": "Feature",
      "id": 8196,
      "geometry": {
        "type": "Point",
        "coordinates": [
          145.55831600008344,
          -5.162889000327084
        ]
      },
      "properties": {
        "OBJECTID": 8196,
        "CU_NAME": "ASIKAN",
        "CU_NO": "001",
        "GEOCODE": "13020423001",
        "PROV_KEY": "13",
        "DIST_NO": "02",
        "LLG_NO": "04",
        "WARD_NO": "23",
        "WARD_NAME": "WARD 23",
        "LATITUDE": -5.16429,
        "LONGITUDE": 145.557275,
        "REGHH": 31,
        "TOTPOP2000": 167,
        "MALE2000": 86,
        "FEMALE2000": 81,
        "POP2008": 207,
        "G_RATE": 1.0269999504089355,
        "Geocode_Num": 13020423001,
        "PROVINCE": 13
      }
    },
    {
      "type": "Feature",
      "id": 8197,
      "geometry": {
        "type": "Point",
        "coordinates": [
          145.56329200022572,
          -5.143607999709388
        ]
      },
      "properties": {
        "OBJECTID": 8197,
        "CU_NAME": "GUTEB",
        "CU_NO": "010",
        "GEOCODE": "13020423010",
        "PROV_KEY": "13",
        "DIST_NO": "02",
        "LLG_NO": "04",
        "WARD_NO": "23",
        "WARD_NAME": "WARD 23",
        "LATITUDE": -5.125209,
        "LONGITUDE": 145.564059,
        "REGHH": 12,
        "TOTPOP2000": 65,
        "MALE2000": 32,
        "FEMALE2000": 33,
        "POP2008": 81,
        "G_RATE": 1.0269999504089355,
        "Geocode_Num": 13020423010,
        "PROVINCE": 13
      }
    },
    {
      "type": "Feature",
      "id": 8198,
      "geometry": {
        "type": "Point",
        "coordinates": [
          145.58119400020303,
          -5.131085999619131
        ]
      },
      "properties": {
        "OBJECTID": 8198,
        "CU_NAME": "SILOPI",
        "CU_NO": "019",
        "GEOCODE": "13020423019",
        "PROV_KEY": "13",
        "DIST_NO": "02",
        "LLG_NO": "04",
        "WARD_NO": "23",
        "WARD_NAME": "WARD 23",
        "LATITUDE": -5.134959,
        "LONGITUDE": 145.578385,
        "REGHH": 36,
        "TOTPOP2000": 185,
        "MALE2000": 102,
        "FEMALE2000": 83,
        "POP2008": 229,
        "G_RATE": 1.0269999504089355,
        "Geocode_Num": 13020423019,
        "PROVINCE": 13
      }
    },
    {
      "type": "Feature",
      "id": 8199,
      "geometry": {
        "type": "Point",
        "coordinates": [
          145.5420730001689,
          -5.145431000140491
        ]
      },
      "properties": {
        "OBJECTID": 8199,
        "CU_NAME": "UTU",
        "CU_NO": "020",
        "GEOCODE": "13020423020",
        "PROV_KEY": "13",
        "DIST_NO": "02",
        "LLG_NO": "04",
        "WARD_NO": "23",
        "WARD_NAME": "WARD 23",
        "LATITUDE": -5.130568,
        "LONGITUDE": 145.541975,
        "REGHH": 77,
        "TOTPOP2000": 501,
        "MALE2000": 272,
        "FEMALE2000": 229,
        "POP2008": 620,
        "G_RATE": 1.0269999504089355,
        "Geocode_Num": 13020423020,
        "PROVINCE": 13
      }
    }
  ]
}