{
  "type": "FeatureCollection",
  "features": [
    {
      "type": "Feature",
      "id": 7632,
      "geometry": {
        "type": "Point",
        "coordinates": [
          144.8823399995914,
          -7.429920999754302
        ]
      },
      "properties": {
        "OBJECTID": 7632,
        "CU_NAME": "IPIKO",
        "CU_NO": "001",
        "GEOCODE": "02020701001",
        "PROV_KEY": "02",
        "DIST_NO": "02",
        "LLG_NO": "07",
        "WARD_NO": "01",
        "WARD_NAME": "IPIKO",
        "LATITUDE": -7.435678,
        "LONGITUDE": 144.876902,
        "REGHH": 32,
        "TOTPOP2000": 241,
        "MALE2000": 130,
        "FEMALE2000": 111,
        "POP2008": 295,
        "G_RATE": 1.0260000228881836,
        "Geocode_Num": 2020701001,
        "PROVINCE": 2
      }
    },
    {
      "type": "Feature",
      "id": 7633,
      "geometry": {
        "type": "Point",
        "coordinates": [
          144.84700999991162,
          -7.445875999877444
        ]
      },
      "properties": {
        "OBJECTID": 7633,
        "CU_NAME": "PAKEMBA",
        "CU_NO": "002",
        "GEOCODE": "02020701002",
        "PROV_KEY": "02",
        "DIST_NO": "02",
        "LLG_NO": "07",
        "WARD_NO": "01",
        "WARD_NAME": "IPIKO",
        "LATITUDE": -7.445341,
        "LONGITUDE": 144.848146,
        "REGHH": 10,
        "TOTPOP2000": 104,
        "MALE2000": 68,
        "FEMALE2000": 36,
        "POP2008": 128,
        "G_RATE": 1.0260000228881836,
        "Geocode_Num": 2020701002,
        "PROVINCE": 2
      }
    }
  ]
}