{
  "type": "FeatureCollection",
  "features": [
    {
      "type": "Feature",
      "id": 9427,
      "geometry": {
        "type": "Point",
        "coordinates": [
          147.28531399974133,
          -1.96007300006886
        ]
      },
      "properties": {
        "OBJECTID": 9427,
        "CU_NAME": "HAWEI",
        "CU_NO": "003",
        "GEOCODE": "16010517003",
        "PROV_KEY": "16",
        "DIST_NO": "01",
        "LLG_NO": "05",
        "WARD_NO": "17",
        "WARD_NAME": "NDILOU",
        "LATITUDE": -1.959735,
        "LONGITUDE": 147.283708,
        "REGHH": 32,
        "TOTPOP2000": 175,
        "MALE2000": 89,
        "FEMALE2000": 86,
        "POP2008": 215,
        "G_RATE": 1.0260000228881836,
        "Geocode_Num": 16010517003,
        "PROVINCE": 16
      }
    },
    {
      "type": "Feature",
      "id": 9428,
      "geometry": {
        "type": "Point",
        "coordinates": [
          147.3495050002556,
          -1.9762650003294766
        ]
      },
      "properties": {
        "OBJECTID": 9428,
        "CU_NAME": "KORONAT",
        "CU_NO": "004",
        "GEOCODE": "16010517004",
        "PROV_KEY": "16",
        "DIST_NO": "01",
        "LLG_NO": "05",
        "WARD_NO": "17",
        "WARD_NAME": "NDILOU",
        "LATITUDE": -1.976621,
        "LONGITUDE": 147.349624,
        "REGHH": 12,
        "TOTPOP2000": 86,
        "MALE2000": 42,
        "FEMALE2000": 44,
        "POP2008": 104,
        "G_RATE": 1.0260000228881836,
        "Geocode_Num": 16010517004,
        "PROVINCE": 16
      }
    },
    {
      "type": "Feature",
      "id": 9429,
      "geometry": {
        "type": "Point",
        "coordinates": [
          147.33203999974626,
          -1.9664439997907266
        ]
      },
      "properties": {
        "OBJECTID": 9429,
        "CU_NAME": "N'DRILOU",
        "CU_NO": "007",
        "GEOCODE": "16010517007",
        "PROV_KEY": "16",
        "DIST_NO": "01",
        "LLG_NO": "05",
        "WARD_NO": "17",
        "WARD_NAME": "NDILOU",
        "LATITUDE": -1.967264,
        "LONGITUDE": 147.329185,
        "REGHH": 41,
        "TOTPOP2000": 293,
        "MALE2000": 153,
        "FEMALE2000": 140,
        "POP2008": 360,
        "G_RATE": 1.0260000228881836,
        "Geocode_Num": 16010517007,
        "PROVINCE": 16
      }
    },
    {
      "type": "Feature",
      "id": 9430,
      "geometry": {
        "type": "Point",
        "coordinates": [
          147.33624200016823,
          -2.027304999625983
        ]
      },
      "properties": {
        "OBJECTID": 9430,
        "CU_NAME": "WENAI POINT",
        "CU_NO": "503",
        "GEOCODE": "16010517503",
        "PROV_KEY": "16",
        "DIST_NO": "01",
        "LLG_NO": "05",
        "WARD_NO": "17",
        "WARD_NAME": "NDILOU",
        "LATITUDE": -2.029434,
        "LONGITUDE": 147.335771,
        "REGHH": 17,
        "TOTPOP2000": 110,
        "MALE2000": 59,
        "FEMALE2000": 51,
        "POP2008": 134,
        "G_RATE": 1.0260000228881836,
        "Geocode_Num": 16010517503,
        "PROVINCE": 16
      }
    }
  ]
}