{
  "type": "FeatureCollection",
  "features": [
    {
      "type": "Feature",
      "id": 14946,
      "geometry": {
        "type": "Point",
        "coordinates": [
          144.95265900031268,
          -6.106427999952189
        ]
      },
      "properties": {
        "OBJECTID": 14946,
        "CU_NAME": "KAGUL",
        "CU_NO": "001",
        "GEOCODE": "10061814001",
        "PROV_KEY": "10",
        "DIST_NO": "06",
        "LLG_NO": "18",
        "WARD_NO": "14",
        "WARD_NAME": "KUMANEKANE",
        "LATITUDE": -6.107839,
        "LONGITUDE": 144.951609,
        "REGHH": 19,
        "TOTPOP2000": 196,
        "MALE2000": 106,
        "FEMALE2000": 90,
        "POP2008": 228,
        "G_RATE": 1.0180000066757202,
        "Geocode_Num": 10061814001,
        "PROVINCE": 10
      }
    },
    {
      "type": "Feature",
      "id": 14947,
      "geometry": {
        "type": "Point",
        "coordinates": [
          144.94588399994666,
          -6.129992000230573
        ]
      },
      "properties": {
        "OBJECTID": 14947,
        "CU_NAME": "KINYURE",
        "CU_NO": "002",
        "GEOCODE": "10061814002",
        "PROV_KEY": "10",
        "DIST_NO": "06",
        "LLG_NO": "18",
        "WARD_NO": "14",
        "WARD_NAME": "KUMANEKANE",
        "LATITUDE": -6.131403,
        "LONGITUDE": 144.944834,
        "REGHH": 35,
        "TOTPOP2000": 327,
        "MALE2000": 173,
        "FEMALE2000": 154,
        "POP2008": 377,
        "G_RATE": 1.0180000066757202,
        "Geocode_Num": 10061814002,
        "PROVINCE": 10
      }
    },
    {
      "type": "Feature",
      "id": 14948,
      "geometry": {
        "type": "Point",
        "coordinates": [
          144.95143499962558,
          -6.119791000154464
        ]
      },
      "properties": {
        "OBJECTID": 14948,
        "CU_NAME": "GUMEPEBAI",
        "CU_NO": "003",
        "GEOCODE": "10061814003",
        "PROV_KEY": "10",
        "DIST_NO": "06",
        "LLG_NO": "18",
        "WARD_NO": "14",
        "WARD_NAME": "KUMANEKANE",
        "LATITUDE": -6.121202,
        "LONGITUDE": 144.950385,
        "REGHH": 77,
        "TOTPOP2000": 570,
        "MALE2000": 303,
        "FEMALE2000": 267,
        "POP2008": 657,
        "G_RATE": 1.0180000066757202,
        "Geocode_Num": 10061814003,
        "PROVINCE": 10
      }
    }
  ]
}