{
  "type": "FeatureCollection",
  "features": [
    {
      "type": "Feature",
      "id": 14968,
      "geometry": {
        "type": "Point",
        "coordinates": [
          144.99922900031822,
          -6.1846900000434175
        ]
      },
      "properties": {
        "OBJECTID": 14968,
        "CU_NAME": "KEBIL",
        "CU_NO": "006",
        "GEOCODE": "10061821006",
        "PROV_KEY": "10",
        "DIST_NO": "06",
        "LLG_NO": "18",
        "WARD_NO": "21",
        "WARD_NAME": "KEBIL 1",
        "LATITUDE": -6.186101,
        "LONGITUDE": 144.998179,
        "REGHH": 15,
        "TOTPOP2000": 60,
        "MALE2000": 29,
        "FEMALE2000": 31,
        "POP2008": 68,
        "G_RATE": 1.0180000066757202,
        "Geocode_Num": 10061821006,
        "PROVINCE": 10
      }
    },
    {
      "type": "Feature",
      "id": 14969,
      "geometry": {
        "type": "Point",
        "coordinates": [
          144.99255800025162,
          -6.189163000372105
        ]
      },
      "properties": {
        "OBJECTID": 14969,
        "CU_NAME": "MOGOMA",
        "CU_NO": "007",
        "GEOCODE": "10061821007",
        "PROV_KEY": "10",
        "DIST_NO": "06",
        "LLG_NO": "18",
        "WARD_NO": "21",
        "WARD_NAME": "KEBIL 1",
        "LATITUDE": -6.190574,
        "LONGITUDE": 144.991508,
        "REGHH": 33,
        "TOTPOP2000": 137,
        "MALE2000": 69,
        "FEMALE2000": 68,
        "POP2008": 160,
        "G_RATE": 1.0180000066757202,
        "Geocode_Num": 10061821007,
        "PROVINCE": 10
      }
    }
  ]
}