{
  "type": "FeatureCollection",
  "features": [
    {
      "type": "Feature",
      "id": 10210,
      "geometry": {
        "type": "Point",
        "coordinates": [
          150.25396065226232,
          -9.46718938248398
        ]
      },
      "properties": {
        "OBJECTID": 10210,
        "CU_NAME": "LAUWELA",
        "CU_NO": "013",
        "GEOCODE": "05031321013",
        "PROV_KEY": "05",
        "DIST_NO": "03",
        "LLG_NO": "13",
        "WARD_NO": "21",
        "WARD_NAME": "LAUWELA",
        "LATITUDE": -9.453383,
        "LONGITUDE": 150.244697,
        "REGHH": 226,
        "TOTPOP2000": 1087,
        "MALE2000": 554,
        "FEMALE2000": 533,
        "POP2008": 1325,
        "G_RATE": 1.024999976158142,
        "Geocode_Num": 5031321013,
        "PROVINCE": 5
      }
    }
  ]
}