{
  "type": "FeatureCollection",
  "features": [
    {
      "type": "Feature",
      "id": 10218,
      "geometry": {
        "type": "Point",
        "coordinates": [
          150.31851000023642,
          -9.28277499996625
        ]
      },
      "properties": {
        "OBJECTID": 10218,
        "CU_NAME": "KALIMUTABOTABO",
        "CU_NO": "011",
        "GEOCODE": "05031328011",
        "PROV_KEY": "05",
        "DIST_NO": "03",
        "LLG_NO": "13",
        "WARD_NO": "28",
        "WARD_NAME": "KALIMTABOTABO",
        "LATITUDE": -9.284232,
        "LONGITUDE": 150.317526,
        "REGHH": 118,
        "TOTPOP2000": 580,
        "MALE2000": 299,
        "FEMALE2000": 281,
        "POP2008": 707,
        "G_RATE": 1.024999976158142,
        "Geocode_Num": 5031328011,
        "PROVINCE": 5
      }
    }
  ]
}