{
  "type": "FeatureCollection",
  "features": [
    {
      "type": "Feature",
      "id": 13480,
      "geometry": {
        "type": "Point",
        "coordinates": [
          147.99503252652994,
          -8.934465935654373
        ]
      },
      "properties": {
        "OBJECTID": 13480,
        "CU_NAME": "BORU",
        "CU_NO": "006",
        "GEOCODE": "06020516006",
        "PROV_KEY": "06",
        "DIST_NO": "02",
        "LLG_NO": "05",
        "WARD_NO": "16",
        "WARD_NAME": "EVASUSU",
        "LATITUDE": -8.935219,
        "LONGITUDE": 147.99702,
        "REGHH": 27,
        "TOTPOP2000": 214,
        "MALE2000": 116,
        "FEMALE2000": 98,
        "POP2008": 265,
        "G_RATE": 1.0269999504089355,
        "Geocode_Num": 6020516006,
        "PROVINCE": 6
      }
    },
    {
      "type": "Feature",
      "id": 13481,
      "geometry": {
        "type": "Point",
        "coordinates": [
          148.01122199969564,
          -8.9364690001442
        ]
      },
      "properties": {
        "OBJECTID": 13481,
        "CU_NAME": "EVASUSU",
        "CU_NO": "009",
        "GEOCODE": "06020516009",
        "PROV_KEY": "06",
        "DIST_NO": "02",
        "LLG_NO": "05",
        "WARD_NO": "16",
        "WARD_NAME": "EVASUSU",
        "LATITUDE": -8.937916,
        "LONGITUDE": 148.010206,
        "REGHH": 38,
        "TOTPOP2000": 246,
        "MALE2000": 132,
        "FEMALE2000": 114,
        "POP2008": 305,
        "G_RATE": 1.0269999504089355,
        "Geocode_Num": 6020516009,
        "PROVINCE": 6
      }
    },
    {
      "type": "Feature",
      "id": 13482,
      "geometry": {
        "type": "Point",
        "coordinates": [
          147.98614499979192,
          -8.917031000380291
        ]
      },
      "properties": {
        "OBJECTID": 13482,
        "CU_NAME": "SORAPE",
        "CU_NO": "034",
        "GEOCODE": "06020516034",
        "PROV_KEY": "06",
        "DIST_NO": "02",
        "LLG_NO": "05",
        "WARD_NO": "16",
        "WARD_NAME": "EVASUSU",
        "LATITUDE": -8.918478,
        "LONGITUDE": 147.985129,
        "REGHH": 13,
        "TOTPOP2000": 85,
        "MALE2000": 46,
        "FEMALE2000": 39,
        "POP2008": 105,
        "G_RATE": 1.0269999504089355,
        "Geocode_Num": 6020516034,
        "PROVINCE": 6
      }
    }
  ]
}