{
  "type": "FeatureCollection",
  "features": [
    {
      "type": "Feature",
      "id": 13527,
      "geometry": {
        "type": "Point",
        "coordinates": [
          148.08775400004708,
          -9.191283999556902
        ]
      },
      "properties": {
        "OBJECTID": 13527,
        "CU_NAME": "KOVIO NO 1",
        "CU_NO": "005",
        "GEOCODE": "06020524005",
        "PROV_KEY": "06",
        "DIST_NO": "02",
        "LLG_NO": "05",
        "WARD_NO": "24",
        "WARD_NAME": "KOVIO",
        "LATITUDE": -9.192734,
        "LONGITUDE": 148.086739,
        "REGHH": 23,
        "TOTPOP2000": 133,
        "MALE2000": 60,
        "FEMALE2000": 73,
        "POP2008": 165,
        "G_RATE": 1.0269999504089355,
        "Geocode_Num": 6020524005,
        "PROVINCE": 6
      }
    },
    {
      "type": "Feature",
      "id": 13528,
      "geometry": {
        "type": "Point",
        "coordinates": [
          148.07805999996913,
          -9.184204999561018
        ]
      },
      "properties": {
        "OBJECTID": 13528,
        "CU_NAME": "KOVIO NO 2",
        "CU_NO": "006",
        "GEOCODE": "06020524006",
        "PROV_KEY": "06",
        "DIST_NO": "02",
        "LLG_NO": "05",
        "WARD_NO": "24",
        "WARD_NAME": "KOVIO",
        "LATITUDE": -9.185655,
        "LONGITUDE": 148.077043,
        "REGHH": 25,
        "TOTPOP2000": 156,
        "MALE2000": 73,
        "FEMALE2000": 83,
        "POP2008": 193,
        "G_RATE": 1.0269999504089355,
        "Geocode_Num": 6020524006,
        "PROVINCE": 6
      }
    }
  ]
}