{
  "type": "FeatureCollection",
  "features": [
    {
      "type": "Feature",
      "id": 9620,
      "geometry": {
        "type": "Point",
        "coordinates": [
          150.10690599971213,
          -10.104803999804687
        ]
      },
      "properties": {
        "OBJECTID": 9620,
        "CU_NAME": "RUMARUMA",
        "CU_NO": "001",
        "GEOCODE": "05010303001",
        "PROV_KEY": "05",
        "DIST_NO": "01",
        "LLG_NO": "03",
        "WARD_NO": "03",
        "WARD_NAME": "RUMARUMA",
        "LATITUDE": -10.104426,
        "LONGITUDE": 150.107596,
        "REGHH": 95,
        "TOTPOP2000": 431,
        "MALE2000": 227,
        "FEMALE2000": 204,
        "POP2008": 526,
        "G_RATE": 1.024999976158142,
        "Geocode_Num": 5010303001,
        "PROVINCE": 5
      }
    },
    {
      "type": "Feature",
      "id": 9621,
      "geometry": {
        "type": "Point",
        "coordinates": [
          150.1087229998666,
          -10.109981000222945
        ]
      },
      "properties": {
        "OBJECTID": 9621,
        "CU_NAME": "WAMIRA COMM. SCHOOL",
        "CU_NO": "401",
        "GEOCODE": "05010303401",
        "PROV_KEY": "05",
        "DIST_NO": "01",
        "LLG_NO": "03",
        "WARD_NO": "03",
        "WARD_NAME": "RUMARUMA",
        "LATITUDE": -10.111446,
        "LONGITUDE": 150.107734,
        "REGHH": 4,
        "TOTPOP2000": 14,
        "MALE2000": 9,
        "FEMALE2000": 5,
        "POP2008": 14,
        "G_RATE": 1.024999976158142,
        "Geocode_Num": 5010303401,
        "PROVINCE": 5
      }
    }
  ]
}