{
  "type": "FeatureCollection",
  "features": [
    {
      "type": "Feature",
      "id": 9677,
      "geometry": {
        "type": "Point",
        "coordinates": [
          150.00758099956352,
          -10.197379999887062
        ]
      },
      "properties": {
        "OBJECTID": 9677,
        "CU_NAME": "DIDIA",
        "CU_NO": "007",
        "GEOCODE": "05010328007",
        "PROV_KEY": "05",
        "DIST_NO": "01",
        "LLG_NO": "03",
        "WARD_NO": "28",
        "WARD_NAME": "DIDIA",
        "LATITUDE": -10.198874,
        "LONGITUDE": 150.009607,
        "REGHH": 32,
        "TOTPOP2000": 210,
        "MALE2000": 98,
        "FEMALE2000": 112,
        "POP2008": 255,
        "G_RATE": 1.024999976158142,
        "Geocode_Num": 5010328007,
        "PROVINCE": 5
      }
    },
    {
      "type": "Feature",
      "id": 9678,
      "geometry": {
        "type": "Point",
        "coordinates": [
          150.01937400021006,
          -10.170345999668086
        ]
      },
      "properties": {
        "OBJECTID": 9678,
        "CU_NAME": "KODOGA",
        "CU_NO": "008",
        "GEOCODE": "05010328008",
        "PROV_KEY": "05",
        "DIST_NO": "01",
        "LLG_NO": "03",
        "WARD_NO": "28",
        "WARD_NAME": "DIDIA",
        "LATITUDE": -10.174613,
        "LONGITUDE": 150.018357,
        "REGHH": 12,
        "TOTPOP2000": 58,
        "MALE2000": 34,
        "FEMALE2000": 24,
        "POP2008": 71,
        "G_RATE": 1.024999976158142,
        "Geocode_Num": 5010328008,
        "PROVINCE": 5
      }
    }
  ]
}