{
  "type": "FeatureCollection",
  "features": [
    {
      "type": "Feature",
      "id": 15624,
      "geometry": {
        "type": "Point",
        "coordinates": [
          141.52415200011478,
          -8.699044999627006
        ]
      },
      "properties": {
        "OBJECTID": 15624,
        "CU_NAME": "IOKWA",
        "CU_NO": "004",
        "GEOCODE": "01031303004",
        "PROV_KEY": "01",
        "DIST_NO": "03",
        "LLG_NO": "13",
        "WARD_NO": "03",
        "WARD_NAME": "WEMNEVERE",
        "LATITUDE": -8.700472,
        "LONGITUDE": 141.523053,
        "REGHH": 43,
        "TOTPOP2000": 229,
        "MALE2000": 117,
        "FEMALE2000": 112,
        "POP2008": 298,
        "G_RATE": 1.0329999923706055,
        "Geocode_Num": 1031303004,
        "PROVINCE": 1
      }
    },
    {
      "type": "Feature",
      "id": 15625,
      "geometry": {
        "type": "Point",
        "coordinates": [
          141.41692699988118,
          -8.739942999769596
        ]
      },
      "properties": {
        "OBJECTID": 15625,
        "CU_NAME": "WEMNEVERE",
        "CU_NO": "012",
        "GEOCODE": "01031303012",
        "PROV_KEY": "01",
        "DIST_NO": "03",
        "LLG_NO": "13",
        "WARD_NO": "03",
        "WARD_NAME": "WEMNEVERE",
        "LATITUDE": -8.74137,
        "LONGITUDE": 141.415826,
        "REGHH": 21,
        "TOTPOP2000": 103,
        "MALE2000": 52,
        "FEMALE2000": 51,
        "POP2008": 133,
        "G_RATE": 1.0329999923706055,
        "Geocode_Num": 1031303012,
        "PROVINCE": 1
      }
    },
    {
      "type": "Feature",
      "id": 15626,
      "geometry": {
        "type": "Point",
        "coordinates": [
          141.4372289999185,
          -8.641864999570032
        ]
      },
      "properties": {
        "OBJECTID": 15626,
        "CU_NAME": "TOKWA",
        "CU_NO": "017",
        "GEOCODE": "01031303017",
        "PROV_KEY": "01",
        "DIST_NO": "03",
        "LLG_NO": "13",
        "WARD_NO": "03",
        "WARD_NAME": "WEMNEVERE",
        "LATITUDE": -8.643291,
        "LONGITUDE": 141.436129,
        "REGHH": 11,
        "TOTPOP2000": 71,
        "MALE2000": 31,
        "FEMALE2000": 40,
        "POP2008": 92,
        "G_RATE": 1.0329999923706055,
        "Geocode_Num": 1031303017,
        "PROVINCE": 1
      }
    }
  ]
}