{
  "type": "FeatureCollection",
  "features": [
    {
      "type": "Feature",
      "id": 10397,
      "geometry": {
        "type": "Point",
        "coordinates": [
          147.05437699979882,
          -7.953507000047978
        ]
      },
      "properties": {
        "OBJECTID": 10397,
        "CU_NAME": "GANO",
        "CU_NO": "003",
        "GEOCODE": "12010201003",
        "PROV_KEY": "12",
        "DIST_NO": "01",
        "LLG_NO": "02",
        "WARD_NO": "01",
        "WARD_NAME": "SAIWARIKA",
        "LATITUDE": -7.954941,
        "LONGITUDE": 147.053351,
        "REGHH": 5,
        "TOTPOP2000": 21,
        "MALE2000": 9,
        "FEMALE2000": 12,
        "POP2008": 29,
        "G_RATE": 1.027999997138977,
        "Geocode_Num": 12010201003,
        "PROVINCE": 12
      }
    },
    {
      "type": "Feature",
      "id": 10398,
      "geometry": {
        "type": "Point",
        "coordinates": [
          147.03132999997956,
          -7.98239500032895
        ]
      },
      "properties": {
        "OBJECTID": 10398,
        "CU_NAME": "MOIMO (MORMOR)",
        "CU_NO": "004",
        "GEOCODE": "12010201004",
        "PROV_KEY": "12",
        "DIST_NO": "01",
        "LLG_NO": "02",
        "WARD_NO": "01",
        "WARD_NAME": "SAIWARIKA",
        "LATITUDE": -7.98383,
        "LONGITUDE": 147.030303,
        "REGHH": 18,
        "TOTPOP2000": 126,
        "MALE2000": 67,
        "FEMALE2000": 59,
        "POP2008": 158,
        "G_RATE": 1.027999997138977,
        "Geocode_Num": 12010201004,
        "PROVINCE": 12
      }
    },
    {
      "type": "Feature",
      "id": 10399,
      "geometry": {
        "type": "Point",
        "coordinates": [
          147.06811600025333,
          -7.9461420003530066
        ]
      },
      "properties": {
        "OBJECTID": 10399,
        "CU_NAME": "SAIKO",
        "CU_NO": "005",
        "GEOCODE": "12010201005",
        "PROV_KEY": "12",
        "DIST_NO": "01",
        "LLG_NO": "02",
        "WARD_NO": "01",
        "WARD_NAME": "SAIWARIKA",
        "LATITUDE": -7.947576,
        "LONGITUDE": 147.06709,
        "REGHH": 37,
        "TOTPOP2000": 162,
        "MALE2000": 73,
        "FEMALE2000": 89,
        "POP2008": 203,
        "G_RATE": 1.027999997138977,
        "Geocode_Num": 12010201005,
        "PROVINCE": 12
      }
    }
  ]
}