{
  "type": "FeatureCollection",
  "features": [
    {
      "type": "Feature",
      "id": 10445,
      "geometry": {
        "type": "Point",
        "coordinates": [
          147.22160099968642,
          -7.991973999600361
        ]
      },
      "properties": {
        "OBJECTID": 10445,
        "CU_NAME": "AU",
        "CU_NO": "003",
        "GEOCODE": "12010215003",
        "PROV_KEY": "12",
        "DIST_NO": "01",
        "LLG_NO": "02",
        "WARD_NO": "15",
        "WARD_NAME": "GARASA",
        "LATITUDE": -7.993409,
        "LONGITUDE": 147.220577,
        "REGHH": 66,
        "TOTPOP2000": 326,
        "MALE2000": 168,
        "FEMALE2000": 158,
        "POP2008": 406,
        "G_RATE": 1.027999997138977,
        "Geocode_Num": 12010215003,
        "PROVINCE": 12
      }
    },
    {
      "type": "Feature",
      "id": 10446,
      "geometry": {
        "type": "Point",
        "coordinates": [
          147.21083300044268,
          -7.9733860003635755
        ]
      },
      "properties": {
        "OBJECTID": 10446,
        "CU_NAME": "WAKAIA 1",
        "CU_NO": "011",
        "GEOCODE": "12010215011",
        "PROV_KEY": "12",
        "DIST_NO": "01",
        "LLG_NO": "02",
        "WARD_NO": "15",
        "WARD_NAME": "GARASA",
        "LATITUDE": -7.977583,
        "LONGITUDE": 147.209811,
        "REGHH": 22,
        "TOTPOP2000": 129,
        "MALE2000": 53,
        "FEMALE2000": 76,
        "POP2008": 161,
        "G_RATE": 1.027999997138977,
        "Geocode_Num": 12010215011,
        "PROVINCE": 12
      }
    },
    {
      "type": "Feature",
      "id": 10447,
      "geometry": {
        "type": "Point",
        "coordinates": [
          147.2025709998518,
          -7.9699569996158175
        ]
      },
      "properties": {
        "OBJECTID": 10447,
        "CU_NAME": "WAKAIA 2",
        "CU_NO": "012",
        "GEOCODE": "12010215012",
        "PROV_KEY": "12",
        "DIST_NO": "01",
        "LLG_NO": "02",
        "WARD_NO": "15",
        "WARD_NAME": "GARASA",
        "LATITUDE": -7.971392,
        "LONGITUDE": 147.201547,
        "REGHH": 47,
        "TOTPOP2000": 248,
        "MALE2000": 115,
        "FEMALE2000": 133,
        "POP2008": 309,
        "G_RATE": 1.027999997138977,
        "Geocode_Num": 12010215012,
        "PROVINCE": 12
      }
    },
    {
      "type": "Feature",
      "id": 10448,
      "geometry": {
        "type": "Point",
        "coordinates": [
          147.217057999727,
          -7.981475000171088
        ]
      },
      "properties": {
        "OBJECTID": 10448,
        "CU_NAME": "GARASA STATION",
        "CU_NO": "401",
        "GEOCODE": "12010215401",
        "PROV_KEY": "12",
        "DIST_NO": "01",
        "LLG_NO": "02",
        "WARD_NO": "15",
        "WARD_NAME": "GARASA",
        "LATITUDE": -7.981256,
        "LONGITUDE": 147.211047,
        "REGHH": 6,
        "TOTPOP2000": 23,
        "MALE2000": 13,
        "FEMALE2000": 10,
        "POP2008": 31,
        "G_RATE": 1.027999997138977,
        "Geocode_Num": 12010215401,
        "PROVINCE": 12
      }
    },
    {
      "type": "Feature",
      "id": 10449,
      "geometry": {
        "type": "Point",
        "coordinates": [
          147.20440499989093,
          -7.96635299979107
        ]
      },
      "properties": {
        "OBJECTID": 10449,
        "CU_NAME": "PEWAURA P/SCH",
        "CU_NO": "402",
        "GEOCODE": "12010215402",
        "PROV_KEY": "12",
        "DIST_NO": "01",
        "LLG_NO": "02",
        "WARD_NO": "15",
        "WARD_NAME": "GARASA",
        "LATITUDE": -7.967788,
        "LONGITUDE": 147.203381,
        "REGHH": 1,
        "TOTPOP2000": 7,
        "MALE2000": 2,
        "FEMALE2000": 5,
        "POP2008": 7,
        "G_RATE": 1.027999997138977,
        "Geocode_Num": 12010215402,
        "PROVINCE": 12
      }
    }
  ]
}