{
  "type": "FeatureCollection",
  "features": [
    {
      "type": "Feature",
      "id": 14111,
      "geometry": {
        "type": "Point",
        "coordinates": [
          144.90666699998212,
          -6.176573999890138
        ]
      },
      "properties": {
        "OBJECTID": 14111,
        "CU_NAME": "SINTAI",
        "CU_NO": "004",
        "GEOCODE": "10020507004",
        "PROV_KEY": "10",
        "DIST_NO": "02",
        "LLG_NO": "05",
        "WARD_NO": "07",
        "WARD_NAME": "KIPAKU",
        "LATITUDE": -6.177985,
        "LONGITUDE": 144.905616,
        "REGHH": 143,
        "TOTPOP2000": 552,
        "MALE2000": 292,
        "FEMALE2000": 260,
        "POP2008": 636,
        "G_RATE": 1.0180000066757202,
        "Geocode_Num": 10020507004,
        "PROVINCE": 10
      }
    },
    {
      "type": "Feature",
      "id": 14112,
      "geometry": {
        "type": "Point",
        "coordinates": [
          144.92061099999773,
          -6.185042000088174
        ]
      },
      "properties": {
        "OBJECTID": 14112,
        "CU_NAME": "TALBAKUL",
        "CU_NO": "005",
        "GEOCODE": "10020507005",
        "PROV_KEY": "10",
        "DIST_NO": "02",
        "LLG_NO": "05",
        "WARD_NO": "07",
        "WARD_NAME": "KIPAKU",
        "LATITUDE": -6.186453,
        "LONGITUDE": 144.91956,
        "REGHH": 62,
        "TOTPOP2000": 260,
        "MALE2000": 137,
        "FEMALE2000": 123,
        "POP2008": 300,
        "G_RATE": 1.0180000066757202,
        "Geocode_Num": 10020507005,
        "PROVINCE": 10
      }
    },
    {
      "type": "Feature",
      "id": 14113,
      "geometry": {
        "type": "Point",
        "coordinates": [
          144.90497500019615,
          -6.178170999791746
        ]
      },
      "properties": {
        "OBJECTID": 14113,
        "CU_NAME": "DIRIMA CATH. MSSN",
        "CU_NO": "401",
        "GEOCODE": "10020507401",
        "PROV_KEY": "10",
        "DIST_NO": "02",
        "LLG_NO": "05",
        "WARD_NO": "07",
        "WARD_NAME": "KIPAKU",
        "LATITUDE": -6.179582,
        "LONGITUDE": 144.903924,
        "REGHH": 11,
        "TOTPOP2000": 29,
        "MALE2000": 10,
        "FEMALE2000": 19,
        "POP2008": 37,
        "G_RATE": 1.0180000066757202,
        "Geocode_Num": 10020507401,
        "PROVINCE": 10
      }
    }
  ]
}