{
  "type": "FeatureCollection",
  "features": [
    {
      "type": "Feature",
      "id": 6005,
      "geometry": {
        "type": "Point",
        "coordinates": [
          142.66062800008217,
          -4.04690600021172
        ]
      },
      "properties": {
        "OBJECTID": 6005,
        "CU_NAME": "AMAKI 1",
        "CU_NO": "002",
        "GEOCODE": "14010107002",
        "PROV_KEY": "14",
        "DIST_NO": "01",
        "LLG_NO": "01",
        "WARD_NO": "07",
        "WARD_NAME": "AMAKI 1",
        "LATITUDE": -4.048488,
        "LONGITUDE": 142.659382,
        "REGHH": 80,
        "TOTPOP2000": 511,
        "MALE2000": 262,
        "FEMALE2000": 249,
        "POP2008": 608,
        "G_RATE": 1.0219999551773071,
        "Geocode_Num": 14010107002,
        "PROVINCE": 14
      }
    },
    {
      "type": "Feature",
      "id": 6006,
      "geometry": {
        "type": "Point",
        "coordinates": [
          142.67764599976317,
          -4.062454999598515
        ]
      },
      "properties": {
        "OBJECTID": 6006,
        "CU_NAME": "AMAKI 2",
        "CU_NO": "003",
        "GEOCODE": "14010107003",
        "PROV_KEY": "14",
        "DIST_NO": "01",
        "LLG_NO": "01",
        "WARD_NO": "07",
        "WARD_NAME": "AMAKI 1",
        "LATITUDE": -4.056527,
        "LONGITUDE": 142.668892,
        "REGHH": 42,
        "TOTPOP2000": 267,
        "MALE2000": 136,
        "FEMALE2000": 131,
        "POP2008": 318,
        "G_RATE": 1.0219999551773071,
        "Geocode_Num": 14010107003,
        "PROVINCE": 14
      }
    },
    {
      "type": "Feature",
      "id": 6007,
      "geometry": {
        "type": "Point",
        "coordinates": [
          142.67019699979176,
          -4.054582999905449
        ]
      },
      "properties": {
        "OBJECTID": 6007,
        "CU_NAME": "MERSEI",
        "CU_NO": "017",
        "GEOCODE": "14010107017",
        "PROV_KEY": "14",
        "DIST_NO": "01",
        "LLG_NO": "01",
        "WARD_NO": "07",
        "WARD_NAME": "AMAKI 1",
        "LATITUDE": -4.060264,
        "LONGITUDE": 142.661841,
        "REGHH": 5,
        "TOTPOP2000": 27,
        "MALE2000": 12,
        "FEMALE2000": 15,
        "POP2008": 35,
        "G_RATE": 1.0219999551773071,
        "Geocode_Num": 14010107017,
        "PROVINCE": 14
      }
    }
  ]
}