{
  "type": "FeatureCollection",
  "features": [
    {
      "type": "Feature",
      "id": 15284,
      "geometry": {
        "type": "Point",
        "coordinates": [
          141.90215300016087,
          -6.291130000049407
        ]
      },
      "properties": {
        "OBJECTID": 15284,
        "CU_NAME": "KUDA",
        "CU_NO": "004",
        "GEOCODE": "01010533004",
        "PROV_KEY": "01",
        "DIST_NO": "01",
        "LLG_NO": "05",
        "WARD_NO": "33",
        "WARD_NAME": "KUDA",
        "LATITUDE": -6.292536,
        "LONGITUDE": 141.901064,
        "REGHH": 46,
        "TOTPOP2000": 251,
        "MALE2000": 104,
        "FEMALE2000": 147,
        "POP2008": 325,
        "G_RATE": 1.0329999923706055,
        "Geocode_Num": 1010533004,
        "PROVINCE": 1
      }
    }
  ]
}