{
  "type": "FeatureCollection",
  "features": [
    {
      "type": "Feature",
      "id": 10118,
      "geometry": {
        "type": "Point",
        "coordinates": [
          151.0718629995779,
          -8.497614999732377
        ]
      },
      "properties": {
        "OBJECTID": 10118,
        "CU_NAME": "BUDUWELAKA",
        "CU_NO": "002",
        "GEOCODE": "05031212002",
        "PROV_KEY": "05",
        "DIST_NO": "03",
        "LLG_NO": "12",
        "WARD_NO": "12",
        "WARD_NAME": "YALAKA",
        "LATITUDE": -8.499065,
        "LONGITUDE": 151.070893,
        "REGHH": 45,
        "TOTPOP2000": 212,
        "MALE2000": 119,
        "FEMALE2000": 93,
        "POP2008": 258,
        "G_RATE": 1.024999976158142,
        "Geocode_Num": 5031212002,
        "PROVINCE": 5
      }
    },
    {
      "type": "Feature",
      "id": 10119,
      "geometry": {
        "type": "Point",
        "coordinates": [
          151.0782039997149,
          -8.486198000237493
        ]
      },
      "properties": {
        "OBJECTID": 10119,
        "CU_NAME": "KULUWA",
        "CU_NO": "009",
        "GEOCODE": "05031212009",
        "PROV_KEY": "05",
        "DIST_NO": "03",
        "LLG_NO": "12",
        "WARD_NO": "12",
        "WARD_NAME": "YALAKA",
        "LATITUDE": -8.487648,
        "LONGITUDE": 151.077234,
        "REGHH": 23,
        "TOTPOP2000": 127,
        "MALE2000": 66,
        "FEMALE2000": 61,
        "POP2008": 154,
        "G_RATE": 1.024999976158142,
        "Geocode_Num": 5031212009,
        "PROVINCE": 5
      }
    },
    {
      "type": "Feature",
      "id": 10120,
      "geometry": {
        "type": "Point",
        "coordinates": [
          151.06343700041725,
          -8.493937000092444
        ]
      },
      "properties": {
        "OBJECTID": 10120,
        "CU_NAME": "YALAKA",
        "CU_NO": "025",
        "GEOCODE": "05031212025",
        "PROV_KEY": "05",
        "DIST_NO": "03",
        "LLG_NO": "12",
        "WARD_NO": "12",
        "WARD_NAME": "YALAKA",
        "LATITUDE": -8.495387,
        "LONGITUDE": 151.062467,
        "REGHH": 130,
        "TOTPOP2000": 674,
        "MALE2000": 352,
        "FEMALE2000": 322,
        "POP2008": 822,
        "G_RATE": 1.024999976158142,
        "Geocode_Num": 5031212025,
        "PROVINCE": 5
      }
    }
  ]
}