{
  "type": "FeatureCollection",
  "features": [
    {
      "type": "Feature",
      "id": 10144,
      "geometry": {
        "type": "Point",
        "coordinates": [
          151.11801600013837,
          -8.552404000144463
        ]
      },
      "properties": {
        "OBJECTID": 10144,
        "CU_NAME": "ILALIMA",
        "CU_NO": "001",
        "GEOCODE": "05031222001",
        "PROV_KEY": "05",
        "DIST_NO": "03",
        "LLG_NO": "12",
        "WARD_NO": "22",
        "WARD_NAME": "ILALIMA",
        "LATITUDE": -8.553855,
        "LONGITUDE": 151.117046,
        "REGHH": 51,
        "TOTPOP2000": 335,
        "MALE2000": 181,
        "FEMALE2000": 154,
        "POP2008": 408,
        "G_RATE": 1.024999976158142,
        "Geocode_Num": 5031222001,
        "PROVINCE": 5
      }
    },
    {
      "type": "Feature",
      "id": 10145,
      "geometry": {
        "type": "Point",
        "coordinates": [
          151.12368199972457,
          -8.558908999750486
        ]
      },
      "properties": {
        "OBJECTID": 10145,
        "CU_NAME": "OSAPOLA",
        "CU_NO": "002",
        "GEOCODE": "05031222002",
        "PROV_KEY": "05",
        "DIST_NO": "03",
        "LLG_NO": "12",
        "WARD_NO": "22",
        "WARD_NAME": "ILALIMA",
        "LATITUDE": -8.56036,
        "LONGITUDE": 151.122712,
        "REGHH": 30,
        "TOTPOP2000": 207,
        "MALE2000": 108,
        "FEMALE2000": 99,
        "POP2008": 252,
        "G_RATE": 1.024999976158142,
        "Geocode_Num": 5031222002,
        "PROVINCE": 5
      }
    },
    {
      "type": "Feature",
      "id": 10146,
      "geometry": {
        "type": "Point",
        "coordinates": [
          151.13377100003174,
          -8.570112000168649
        ]
      },
      "properties": {
        "OBJECTID": 10146,
        "CU_NAME": "KAITUVI",
        "CU_NO": "003",
        "GEOCODE": "05031222003",
        "PROV_KEY": "05",
        "DIST_NO": "03",
        "LLG_NO": "12",
        "WARD_NO": "22",
        "WARD_NAME": "ILALIMA",
        "LATITUDE": -8.573806,
        "LONGITUDE": 151.130145,
        "REGHH": 48,
        "TOTPOP2000": 250,
        "MALE2000": 125,
        "FEMALE2000": 125,
        "POP2008": 304,
        "G_RATE": 1.024999976158142,
        "Geocode_Num": 5031222003,
        "PROVINCE": 5
      }
    }
  ]
}