{
  "type": "FeatureCollection",
  "features": [
    {
      "type": "Feature",
      "id": 10151,
      "geometry": {
        "type": "Point",
        "coordinates": [
          151.09347399972535,
          -8.675831000200446
        ]
      },
      "properties": {
        "OBJECTID": 10151,
        "CU_NAME": "SINAKETA",
        "CU_NO": "001",
        "GEOCODE": "05031224001",
        "PROV_KEY": "05",
        "DIST_NO": "03",
        "LLG_NO": "12",
        "WARD_NO": "24",
        "WARD_NAME": "SINAKETA",
        "LATITUDE": -8.678485,
        "LONGITUDE": 151.087165,
        "REGHH": 39,
        "TOTPOP2000": 216,
        "MALE2000": 104,
        "FEMALE2000": 112,
        "POP2008": 263,
        "G_RATE": 1.024999976158142,
        "Geocode_Num": 5031224001,
        "PROVINCE": 5
      }
    },
    {
      "type": "Feature",
      "id": 10152,
      "geometry": {
        "type": "Point",
        "coordinates": [
          151.1163509997989,
          -8.689018000380372
        ]
      },
      "properties": {
        "OBJECTID": 10152,
        "CU_NAME": "KUMILABWAGA",
        "CU_NO": "002",
        "GEOCODE": "05031224002",
        "PROV_KEY": "05",
        "DIST_NO": "03",
        "LLG_NO": "12",
        "WARD_NO": "24",
        "WARD_NAME": "SINAKETA",
        "LATITUDE": -8.690469,
        "LONGITUDE": 151.115381,
        "REGHH": 52,
        "TOTPOP2000": 300,
        "MALE2000": 158,
        "FEMALE2000": 142,
        "POP2008": 366,
        "G_RATE": 1.024999976158142,
        "Geocode_Num": 5031224002,
        "PROVINCE": 5
      }
    },
    {
      "type": "Feature",
      "id": 10153,
      "geometry": {
        "type": "Point",
        "coordinates": [
          151.11225000043726,
          -8.662889999673723
        ]
      },
      "properties": {
        "OBJECTID": 10153,
        "CU_NAME": "KAULASI",
        "CU_NO": "005",
        "GEOCODE": "05031224005",
        "PROV_KEY": "05",
        "DIST_NO": "03",
        "LLG_NO": "12",
        "WARD_NO": "24",
        "WARD_NAME": "SINAKETA",
        "LATITUDE": -8.664342,
        "LONGITUDE": 151.11128,
        "REGHH": 52,
        "TOTPOP2000": 288,
        "MALE2000": 148,
        "FEMALE2000": 140,
        "POP2008": 351,
        "G_RATE": 1.024999976158142,
        "Geocode_Num": 5031224005,
        "PROVINCE": 5
      }
    }
  ]
}