{
  "type": "FeatureCollection",
  "features": [
    {
      "type": "Feature",
      "id": 10166,
      "geometry": {
        "type": "Point",
        "coordinates": [
          151.3517290003931,
          -8.60445300010582
        ]
      },
      "properties": {
        "OBJECTID": 10166,
        "CU_NAME": "OKABULULA 1,2 & 3",
        "CU_NO": "001",
        "GEOCODE": "05031229001",
        "PROV_KEY": "05",
        "DIST_NO": "03",
        "LLG_NO": "12",
        "WARD_NO": "29",
        "WARD_NAME": "OKABULULA",
        "LATITUDE": -8.60539,
        "LONGITUDE": 151.351958,
        "REGHH": 203,
        "TOTPOP2000": 1063,
        "MALE2000": 542,
        "FEMALE2000": 521,
        "POP2008": 1296,
        "G_RATE": 1.024999976158142,
        "Geocode_Num": 5031229001,
        "PROVINCE": 5
      }
    },
    {
      "type": "Feature",
      "id": 10167,
      "geometry": {
        "type": "Point",
        "coordinates": [
          151.3306349998055,
          -8.61336300000238
        ]
      },
      "properties": {
        "OBJECTID": 10167,
        "CU_NAME": "WAPAYA",
        "CU_NO": "002",
        "GEOCODE": "05031229002",
        "PROV_KEY": "05",
        "DIST_NO": "03",
        "LLG_NO": "12",
        "WARD_NO": "29",
        "WARD_NAME": "OKABULULA",
        "LATITUDE": -8.614815,
        "LONGITUDE": 151.329668,
        "REGHH": 42,
        "TOTPOP2000": 218,
        "MALE2000": 112,
        "FEMALE2000": 106,
        "POP2008": 265,
        "G_RATE": 1.024999976158142,
        "Geocode_Num": 5031229002,
        "PROVINCE": 5
      }
    },
    {
      "type": "Feature",
      "id": 10168,
      "geometry": {
        "type": "Point",
        "coordinates": [
          151.32765900016284,
          -8.620755000043175
        ]
      },
      "properties": {
        "OBJECTID": 10168,
        "CU_NAME": "KUDEULI",
        "CU_NO": "003",
        "GEOCODE": "05031229003",
        "PROV_KEY": "05",
        "DIST_NO": "03",
        "LLG_NO": "12",
        "WARD_NO": "29",
        "WARD_NAME": "OKABULULA",
        "LATITUDE": -8.622207,
        "LONGITUDE": 151.326692,
        "REGHH": 17,
        "TOTPOP2000": 110,
        "MALE2000": 62,
        "FEMALE2000": 48,
        "POP2008": 134,
        "G_RATE": 1.024999976158142,
        "Geocode_Num": 5031229003,
        "PROVINCE": 5
      }
    },
    {
      "type": "Feature",
      "id": 10169,
      "geometry": {
        "type": "Point",
        "coordinates": [
          151.3505930001669,
          -8.606698000212475
        ]
      },
      "properties": {
        "OBJECTID": 10169,
        "CU_NAME": "OKABULULA COMM SCHOOL",
        "CU_NO": "401",
        "GEOCODE": "05031229401",
        "PROV_KEY": "05",
        "DIST_NO": "03",
        "LLG_NO": "12",
        "WARD_NO": "29",
        "WARD_NAME": "OKABULULA",
        "LATITUDE": -8.60539,
        "LONGITUDE": 151.351958,
        "REGHH": 3,
        "TOTPOP2000": 20,
        "MALE2000": 11,
        "FEMALE2000": 9,
        "POP2008": 28,
        "G_RATE": 1.024999976158142,
        "Geocode_Num": 5031229401,
        "PROVINCE": 5
      }
    }
  ]
}