{
  "type": "FeatureCollection",
  "features": [
    {
      "type": "Feature",
      "id": 4943,
      "geometry": {
        "type": "Point",
        "coordinates": [
          151.00235700037535,
          -5.9828300001044
        ]
      },
      "properties": {
        "OBJECTID": 4943,
        "CU_NAME": "HAUMAKIA",
        "CU_NO": "023",
        "GEOCODE": "18031214023",
        "PROV_KEY": "18",
        "DIST_NO": "03",
        "LLG_NO": "12",
        "WARD_NO": "14",
        "WARD_NAME": "HAUMAKIA",
        "LATITUDE": -5.98425,
        "LONGITUDE": 151.001391,
        "REGHH": 41,
        "TOTPOP2000": 225,
        "MALE2000": 114,
        "FEMALE2000": 111,
        "POP2008": 275,
        "G_RATE": 1.024999976158142,
        "Geocode_Num": 18031214023,
        "PROVINCE": 18
      }
    },
    {
      "type": "Feature",
      "id": 4944,
      "geometry": {
        "type": "Point",
        "coordinates": [
          151.0141849999378,
          -5.9830559997345745
        ]
      },
      "properties": {
        "OBJECTID": 4944,
        "CU_NAME": "HULHUL",
        "CU_NO": "030",
        "GEOCODE": "18031214030",
        "PROV_KEY": "18",
        "DIST_NO": "03",
        "LLG_NO": "12",
        "WARD_NO": "14",
        "WARD_NAME": "HAUMAKIA",
        "LATITUDE": -5.984476,
        "LONGITUDE": 151.013219,
        "REGHH": 42,
        "TOTPOP2000": 208,
        "MALE2000": 95,
        "FEMALE2000": 113,
        "POP2008": 253,
        "G_RATE": 1.024999976158142,
        "Geocode_Num": 18031214030,
        "PROVINCE": 18
      }
    }
  ]
}