{
  "type": "FeatureCollection",
  "features": [
    {
      "type": "Feature",
      "id": 7808,
      "geometry": {
        "type": "Point",
        "coordinates": [
          143.885861000285,
          -7.6951619997264515
        ]
      },
      "properties": {
        "OBJECTID": 7808,
        "CU_NAME": "DADEBI",
        "CU_NO": "001",
        "GEOCODE": "02021006001",
        "PROV_KEY": "02",
        "DIST_NO": "02",
        "LLG_NO": "10",
        "WARD_NO": "06",
        "WARD_NAME": "EKEIRAU",
        "LATITUDE": -7.696586,
        "LONGITUDE": 143.884794,
        "REGHH": 15,
        "TOTPOP2000": 92,
        "MALE2000": 46,
        "FEMALE2000": 46,
        "POP2008": 113,
        "G_RATE": 1.0260000228881836,
        "Geocode_Num": 2021006001,
        "PROVINCE": 2
      }
    },
    {
      "type": "Feature",
      "id": 7809,
      "geometry": {
        "type": "Point",
        "coordinates": [
          143.93421399977638,
          -7.755754999793339
        ]
      },
      "properties": {
        "OBJECTID": 7809,
        "CU_NAME": "EREHEHE",
        "CU_NO": "003",
        "GEOCODE": "02021006003",
        "PROV_KEY": "02",
        "DIST_NO": "02",
        "LLG_NO": "10",
        "WARD_NO": "06",
        "WARD_NAME": "EKEIRAU",
        "LATITUDE": -7.753554,
        "LONGITUDE": 143.933173,
        "REGHH": 9,
        "TOTPOP2000": 37,
        "MALE2000": 20,
        "FEMALE2000": 17,
        "POP2008": 45,
        "G_RATE": 1.0260000228881836,
        "Geocode_Num": 2021006003,
        "PROVINCE": 2
      }
    }
  ]
}