{
  "type": "FeatureCollection",
  "features": [
    {
      "type": "Feature",
      "id": 7816,
      "geometry": {
        "type": "Point",
        "coordinates": [
          143.69270799987441,
          -6.879271999702951
        ]
      },
      "properties": {
        "OBJECTID": 7816,
        "CU_NAME": "BAINA",
        "CU_NO": "001",
        "GEOCODE": "02021010001",
        "PROV_KEY": "02",
        "DIST_NO": "02",
        "LLG_NO": "10",
        "WARD_NO": "10",
        "WARD_NAME": "BAINA",
        "LATITUDE": -6.890779,
        "LONGITUDE": 143.682863,
        "REGHH": 42,
        "TOTPOP2000": 211,
        "MALE2000": 109,
        "FEMALE2000": 102,
        "POP2008": 259,
        "G_RATE": 1.0260000228881836,
        "Geocode_Num": 2021010001,
        "PROVINCE": 2
      }
    },
    {
      "type": "Feature",
      "id": 7817,
      "geometry": {
        "type": "Point",
        "coordinates": [
          143.72599099958506,
          -6.880730000389178
        ]
      },
      "properties": {
        "OBJECTID": 7817,
        "CU_NAME": "GOBE",
        "CU_NO": "002",
        "GEOCODE": "02021010002",
        "PROV_KEY": "02",
        "DIST_NO": "02",
        "LLG_NO": "10",
        "WARD_NO": "10",
        "WARD_NAME": "BAINA",
        "LATITUDE": -6.882146,
        "LONGITUDE": 143.724923,
        "REGHH": 18,
        "TOTPOP2000": 188,
        "MALE2000": 185,
        "FEMALE2000": 3,
        "POP2008": 231,
        "G_RATE": 1.0260000228881836,
        "Geocode_Num": 2021010002,
        "PROVINCE": 2
      }
    }
  ]
}