{
  "type": "FeatureCollection",
  "features": [
    {
      "type": "Feature",
      "id": 7772,
      "geometry": {
        "type": "Point",
        "coordinates": [
          145.4188539998123,
          -7.898408999775484
        ]
      },
      "properties": {
        "OBJECTID": 7772,
        "CU_NAME": "IORI",
        "CU_NO": "009",
        "GEOCODE": "02020917009",
        "PROV_KEY": "02",
        "DIST_NO": "02",
        "LLG_NO": "09",
        "WARD_NO": "17",
        "WARD_NAME": "LEPOKERA",
        "LATITUDE": -7.898124,
        "LONGITUDE": 145.418674,
        "REGHH": 56,
        "TOTPOP2000": 321,
        "MALE2000": 162,
        "FEMALE2000": 159,
        "POP2008": 394,
        "G_RATE": 1.0260000228881836,
        "Geocode_Num": 2020917009,
        "PROVINCE": 2
      }
    },
    {
      "type": "Feature",
      "id": 7773,
      "geometry": {
        "type": "Point",
        "coordinates": [
          145.41856600002097,
          -7.908581000312893
        ]
      },
      "properties": {
        "OBJECTID": 7773,
        "CU_NAME": "LEPOKERA",
        "CU_NO": "014",
        "GEOCODE": "02020917014",
        "PROV_KEY": "02",
        "DIST_NO": "02",
        "LLG_NO": "09",
        "WARD_NO": "17",
        "WARD_NAME": "LEPOKERA",
        "LATITUDE": -7.910011,
        "LONGITUDE": 145.417518,
        "REGHH": 61,
        "TOTPOP2000": 440,
        "MALE2000": 210,
        "FEMALE2000": 230,
        "POP2008": 540,
        "G_RATE": 1.0260000228881836,
        "Geocode_Num": 2020917014,
        "PROVINCE": 2
      }
    }
  ]
}