{
  "type": "FeatureCollection",
  "features": [
    {
      "type": "Feature",
      "id": 7350,
      "geometry": {
        "type": "Point",
        "coordinates": [
          143.26499699981173,
          -3.641688999647556
        ]
      },
      "properties": {
        "OBJECTID": 7350,
        "CU_NAME": "KUMUN",
        "CU_NO": "004",
        "GEOCODE": "14062601004",
        "PROV_KEY": "14",
        "DIST_NO": "06",
        "LLG_NO": "26",
        "WARD_NO": "01",
        "WARD_NAME": "KUMUN",
        "LATITUDE": -3.643267,
        "LONGITUDE": 143.263759,
        "REGHH": 66,
        "TOTPOP2000": 309,
        "MALE2000": 140,
        "FEMALE2000": 169,
        "POP2008": 368,
        "G_RATE": 1.0219999551773071,
        "Geocode_Num": 14062601004,
        "PROVINCE": 14
      }
    },
    {
      "type": "Feature",
      "id": 7351,
      "geometry": {
        "type": "Point",
        "coordinates": [
          143.27263200026664,
          -3.641399999810119
        ]
      },
      "properties": {
        "OBJECTID": 7351,
        "CU_NAME": "WINJUON",
        "CU_NO": "006",
        "GEOCODE": "14062601006",
        "PROV_KEY": "14",
        "DIST_NO": "06",
        "LLG_NO": "26",
        "WARD_NO": "01",
        "WARD_NAME": "KUMUN",
        "LATITUDE": -3.642978,
        "LONGITUDE": 143.271394,
        "REGHH": 46,
        "TOTPOP2000": 225,
        "MALE2000": 98,
        "FEMALE2000": 127,
        "POP2008": 268,
        "G_RATE": 1.0219999551773071,
        "Geocode_Num": 14062601006,
        "PROVINCE": 14
      }
    }
  ]
}