{
  "type": "FeatureCollection",
  "features": [
    {
      "type": "Feature",
      "id": 7359,
      "geometry": {
        "type": "Point",
        "coordinates": [
          143.23399400002313,
          -3.651567000116927
        ]
      },
      "properties": {
        "OBJECTID": 7359,
        "CU_NAME": "ALISU",
        "CU_NO": "002",
        "GEOCODE": "14062605002",
        "PROV_KEY": "14",
        "DIST_NO": "06",
        "LLG_NO": "26",
        "WARD_NO": "05",
        "WARD_NAME": "ALISU",
        "LATITUDE": -3.653145,
        "LONGITUDE": 143.232757,
        "REGHH": 39,
        "TOTPOP2000": 193,
        "MALE2000": 102,
        "FEMALE2000": 91,
        "POP2008": 230,
        "G_RATE": 1.0219999551773071,
        "Geocode_Num": 14062605002,
        "PROVINCE": 14
      }
    },
    {
      "type": "Feature",
      "id": 7360,
      "geometry": {
        "type": "Point",
        "coordinates": [
          143.22502099991925,
          -3.6352719996030487
        ]
      },
      "properties": {
        "OBJECTID": 7360,
        "CU_NAME": "BUBUAMU",
        "CU_NO": "005",
        "GEOCODE": "14062605005",
        "PROV_KEY": "14",
        "DIST_NO": "06",
        "LLG_NO": "26",
        "WARD_NO": "05",
        "WARD_NAME": "ALISU",
        "LATITUDE": -3.63685,
        "LONGITUDE": 143.223784,
        "REGHH": 53,
        "TOTPOP2000": 302,
        "MALE2000": 150,
        "FEMALE2000": 152,
        "POP2008": 360,
        "G_RATE": 1.0219999551773071,
        "Geocode_Num": 14062605005,
        "PROVINCE": 14
      }
    }
  ]
}