{
  "type": "FeatureCollection",
  "features": [
    {
      "type": "Feature",
      "id": 7361,
      "geometry": {
        "type": "Point",
        "coordinates": [
          143.21733199967207,
          -3.62465099994364
        ]
      },
      "properties": {
        "OBJECTID": 7361,
        "CU_NAME": "BELEGEL",
        "CU_NO": "003",
        "GEOCODE": "14062606003",
        "PROV_KEY": "14",
        "DIST_NO": "06",
        "LLG_NO": "26",
        "WARD_NO": "06",
        "WARD_NAME": "BONAHITAM",
        "LATITUDE": -3.622517,
        "LONGITUDE": 143.22181,
        "REGHH": 27,
        "TOTPOP2000": 140,
        "MALE2000": 64,
        "FEMALE2000": 76,
        "POP2008": 165,
        "G_RATE": 1.0219999551773071,
        "Geocode_Num": 14062606003,
        "PROVINCE": 14
      }
    },
    {
      "type": "Feature",
      "id": 7362,
      "geometry": {
        "type": "Point",
        "coordinates": [
          143.20966799967846,
          -3.6178930003616188
        ]
      },
      "properties": {
        "OBJECTID": 7362,
        "CU_NAME": "BONAHITAM",
        "CU_NO": "004",
        "GEOCODE": "14062606004",
        "PROV_KEY": "14",
        "DIST_NO": "06",
        "LLG_NO": "26",
        "WARD_NO": "06",
        "WARD_NAME": "BONAHITAM",
        "LATITUDE": -3.619471,
        "LONGITUDE": 143.208431,
        "REGHH": 42,
        "TOTPOP2000": 224,
        "MALE2000": 124,
        "FEMALE2000": 100,
        "POP2008": 266,
        "G_RATE": 1.0219999551773071,
        "Geocode_Num": 14062606004,
        "PROVINCE": 14
      }
    }
  ]
}