{
  "type": "FeatureCollection",
  "features": [
    {
      "type": "Feature",
      "id": 7373,
      "geometry": {
        "type": "Point",
        "coordinates": [
          143.2426150000822,
          -3.6931159997035934
        ]
      },
      "properties": {
        "OBJECTID": 7373,
        "CU_NAME": "YEKINGEN",
        "CU_NO": "001",
        "GEOCODE": "14062614001",
        "PROV_KEY": "14",
        "DIST_NO": "06",
        "LLG_NO": "26",
        "WARD_NO": "14",
        "WARD_NAME": "YEKINGEN",
        "LATITUDE": -3.694695,
        "LONGITUDE": 143.241378,
        "REGHH": 59,
        "TOTPOP2000": 309,
        "MALE2000": 160,
        "FEMALE2000": 149,
        "POP2008": 368,
        "G_RATE": 1.0219999551773071,
        "Geocode_Num": 14062614001,
        "PROVINCE": 14
      }
    },
    {
      "type": "Feature",
      "id": 7374,
      "geometry": {
        "type": "Point",
        "coordinates": [
          143.22500099989634,
          -3.6992209997492864
        ]
      },
      "properties": {
        "OBJECTID": 7374,
        "CU_NAME": "BELMO",
        "CU_NO": "002",
        "GEOCODE": "14062614002",
        "PROV_KEY": "14",
        "DIST_NO": "06",
        "LLG_NO": "26",
        "WARD_NO": "14",
        "WARD_NAME": "YEKINGEN",
        "LATITUDE": -3.7008,
        "LONGITUDE": 143.223764,
        "REGHH": 66,
        "TOTPOP2000": 340,
        "MALE2000": 168,
        "FEMALE2000": 172,
        "POP2008": 405,
        "G_RATE": 1.0219999551773071,
        "Geocode_Num": 14062614002,
        "PROVINCE": 14
      }
    }
  ]
}