{
  "type": "FeatureCollection",
  "features": [
    {
      "type": "Feature",
      "id": 21833,
      "geometry": {
        "type": "Point",
        "coordinates": [
          143.00294799955066,
          -5.825400000409672
        ]
      },
      "properties": {
        "OBJECTID": 21833,
        "CU_NAME": "ITAPU",
        "CU_NO": "004",
        "GEOCODE": "07083002004",
        "PROV_KEY": "21",
        "DIST_NO": "3",
        "LLG_NO": "30",
        "WARD_NO": "02",
        "WARD_NAME": "ITAPU",
        "LATITUDE": -5.826008,
        "LONGITUDE": 142.998647,
        "REGHH": 108,
        "TOTPOP2000": 989,
        "MALE2000": 522,
        "FEMALE2000": 467,
        "POP2008": 1374,
        "G_RATE": 1.0420000553131104,
        "Geocode_Num": 7083002004,
        "PROVINCE": 21
      }
    }
  ]
}