{
  "type": "FeatureCollection",
  "features": [
    {
      "type": "Feature",
      "id": 21726,
      "geometry": {
        "type": "Point",
        "coordinates": [
          143.63300699957347,
          -6.3123510001984755
        ]
      },
      "properties": {
        "OBJECTID": 21726,
        "CU_NAME": "HEALTH CENTRE",
        "CU_NO": "402",
        "GEOCODE": "07072618402",
        "PROV_KEY": "07",
        "DIST_NO": "07",
        "LLG_NO": "26",
        "WARD_NO": "18",
        "WARD_NAME": "POROMA STATION",
        "LATITUDE": -6.316597,
        "LONGITUDE": 143.633284,
        "REGHH": 1,
        "TOTPOP2000": 6,
        "MALE2000": 2,
        "FEMALE2000": 4,
        "POP2008": 6,
        "G_RATE": 1.0420000553131104,
        "Geocode_Num": 7072618402,
        "PROVINCE": 7
      }
    },
    {
      "type": "Feature",
      "id": 21727,
      "geometry": {
        "type": "Point",
        "coordinates": [
          143.63288800038094,
          -6.311404999740887
        ]
      },
      "properties": {
        "OBJECTID": 21727,
        "CU_NAME": "SUARA",
        "CU_NO": "403",
        "GEOCODE": "07072618403",
        "PROV_KEY": "07",
        "DIST_NO": "07",
        "LLG_NO": "26",
        "WARD_NO": "18",
        "WARD_NAME": "POROMA STATION",
        "LATITUDE": -6.315651,
        "LONGITUDE": 143.633165,
        "REGHH": 6,
        "TOTPOP2000": 51,
        "MALE2000": 25,
        "FEMALE2000": 26,
        "POP2008": 70,
        "G_RATE": 1.0420000553131104,
        "Geocode_Num": 7072618403,
        "PROVINCE": 7
      }
    },
    {
      "type": "Feature",
      "id": 21728,
      "geometry": {
        "type": "Point",
        "coordinates": [
          143.63292100010415,
          -6.307901000031052
        ]
      },
      "properties": {
        "OBJECTID": 21728,
        "CU_NAME": "POROMA STATION",
        "CU_NO": "501",
        "GEOCODE": "07072618501",
        "PROV_KEY": "07",
        "DIST_NO": "07",
        "LLG_NO": "26",
        "WARD_NO": "18",
        "WARD_NAME": "POROMA STATION",
        "LATITUDE": -6.312147,
        "LONGITUDE": 143.633198,
        "REGHH": 15,
        "TOTPOP2000": 105,
        "MALE2000": 49,
        "FEMALE2000": 56,
        "POP2008": 146,
        "G_RATE": 1.0420000553131104,
        "Geocode_Num": 7072618501,
        "PROVINCE": 7
      }
    }
  ]
}