{
  "type": "FeatureCollection",
  "features": [
    {
      "type": "Feature",
      "id": 15571,
      "geometry": {
        "type": "Point",
        "coordinates": [
          143.00207599980763,
          -9.10253999992102
        ]
      },
      "properties": {
        "OBJECTID": 15571,
        "CU_NAME": "TURETURE",
        "CU_NO": "014",
        "GEOCODE": "01031203014",
        "PROV_KEY": "01",
        "DIST_NO": "03",
        "LLG_NO": "12",
        "WARD_NO": "03",
        "WARD_NAME": "TURETURE",
        "LATITUDE": -9.103974,
        "LONGITUDE": 143.000994,
        "REGHH": 48,
        "TOTPOP2000": 326,
        "MALE2000": 158,
        "FEMALE2000": 168,
        "POP2008": 422,
        "G_RATE": 1.0329999923706055,
        "Geocode_Num": 1031203014,
        "PROVINCE": 1
      }
    },
    {
      "type": "Feature",
      "id": 15572,
      "geometry": {
        "type": "Point",
        "coordinates": [
          143.06142199992541,
          -9.08422399973773
        ]
      },
      "properties": {
        "OBJECTID": 15572,
        "CU_NAME": "WAEGARA COMM. SCHOOL",
        "CU_NO": "015",
        "GEOCODE": "01031203015",
        "PROV_KEY": "01",
        "DIST_NO": "03",
        "LLG_NO": "12",
        "WARD_NO": "03",
        "WARD_NAME": "TURETURE",
        "LATITUDE": -9.085658,
        "LONGITUDE": 143.06034,
        "REGHH": 1,
        "TOTPOP2000": 3,
        "MALE2000": 1,
        "FEMALE2000": 2,
        "POP2008": 3,
        "G_RATE": 1.0329999923706055,
        "Geocode_Num": 1031203015,
        "PROVINCE": 1
      }
    },
    {
      "type": "Feature",
      "id": 15573,
      "geometry": {
        "type": "Point",
        "coordinates": [
          143.1805010000212,
          -9.03179000000847
        ]
      },
      "properties": {
        "OBJECTID": 15573,
        "CU_NAME": "DUDUPATU",
        "CU_NO": "016",
        "GEOCODE": "01031203016",
        "PROV_KEY": "01",
        "DIST_NO": "03",
        "LLG_NO": "12",
        "WARD_NO": "03",
        "WARD_NAME": "TURETURE",
        "LATITUDE": -9.033224,
        "LONGITUDE": 143.179421,
        "REGHH": 4,
        "TOTPOP2000": 29,
        "MALE2000": 21,
        "FEMALE2000": 8,
        "POP2008": 37,
        "G_RATE": 1.0329999923706055,
        "Geocode_Num": 1031203016,
        "PROVINCE": 1
      }
    },
    {
      "type": "Feature",
      "id": 15574,
      "geometry": {
        "type": "Point",
        "coordinates": [
          143.0982529995763,
          -9.069422999771575
        ]
      },
      "properties": {
        "OBJECTID": 15574,
        "CU_NAME": "MUWOGIDO",
        "CU_NO": "017",
        "GEOCODE": "01031203017",
        "PROV_KEY": "01",
        "DIST_NO": "03",
        "LLG_NO": "12",
        "WARD_NO": "03",
        "WARD_NAME": "TURETURE",
        "LATITUDE": -9.070857,
        "LONGITUDE": 143.097172,
        "REGHH": 16,
        "TOTPOP2000": 86,
        "MALE2000": 49,
        "FEMALE2000": 37,
        "POP2008": 111,
        "G_RATE": 1.0329999923706055,
        "Geocode_Num": 1031203017,
        "PROVINCE": 1
      }
    }
  ]
}