{
  "type": "FeatureCollection",
  "features": [
    {
      "type": "Feature",
      "id": 7236,
      "geometry": {
        "type": "Point",
        "coordinates": [
          143.2601120002687,
          -3.9019409997772527
        ]
      },
      "properties": {
        "OBJECTID": 7236,
        "CU_NAME": "MAKAMBU",
        "CU_NO": "006",
        "GEOCODE": "14062313006",
        "PROV_KEY": "14",
        "DIST_NO": "06",
        "LLG_NO": "23",
        "WARD_NO": "13",
        "WARD_NAME": "MAKAMBU",
        "LATITUDE": -3.908038,
        "LONGITUDE": 143.269398,
        "REGHH": 59,
        "TOTPOP2000": 345,
        "MALE2000": 177,
        "FEMALE2000": 168,
        "POP2008": 411,
        "G_RATE": 1.0219999551773071,
        "Geocode_Num": 14062313006,
        "PROVINCE": 14
      }
    },
    {
      "type": "Feature",
      "id": 7237,
      "geometry": {
        "type": "Point",
        "coordinates": [
          143.26010099976145,
          -3.962525000328469
        ]
      },
      "properties": {
        "OBJECTID": 7237,
        "CU_NAME": "PANGEIMBIT",
        "CU_NO": "007",
        "GEOCODE": "14062313007",
        "PROV_KEY": "14",
        "DIST_NO": "06",
        "LLG_NO": "23",
        "WARD_NO": "13",
        "WARD_NAME": "MAKAMBU",
        "LATITUDE": -3.964107,
        "LONGITUDE": 143.258864,
        "REGHH": 38,
        "TOTPOP2000": 200,
        "MALE2000": 101,
        "FEMALE2000": 99,
        "POP2008": 238,
        "G_RATE": 1.0219999551773071,
        "Geocode_Num": 14062313007,
        "PROVINCE": 14
      }
    }
  ]
}