{
  "type": "FeatureCollection",
  "features": [
    {
      "type": "Feature",
      "id": 13104,
      "geometry": {
        "type": "Point",
        "coordinates": [
          149.20033499976046,
          -9.447749999562802
        ]
      },
      "properties": {
        "OBJECTID": 13104,
        "CU_NAME": "GANJIGA",
        "CU_NO": "002",
        "GEOCODE": "06010204002",
        "PROV_KEY": "06",
        "DIST_NO": "01",
        "LLG_NO": "02",
        "WARD_NO": "04",
        "WARD_NAME": "GANJIGA",
        "LATITUDE": -9.449206,
        "LONGITUDE": 149.199335,
        "REGHH": 44,
        "TOTPOP2000": 314,
        "MALE2000": 161,
        "FEMALE2000": 153,
        "POP2008": 388,
        "G_RATE": 1.0269999504089355,
        "Geocode_Num": 6010204002,
        "PROVINCE": 6
      }
    },
    {
      "type": "Feature",
      "id": 13105,
      "geometry": {
        "type": "Point",
        "coordinates": [
          149.17763399970943,
          -9.391543000309184
        ]
      },
      "properties": {
        "OBJECTID": 13105,
        "CU_NAME": "YUAYU",
        "CU_NO": "003",
        "GEOCODE": "06010204003",
        "PROV_KEY": "06",
        "DIST_NO": "01",
        "LLG_NO": "02",
        "WARD_NO": "04",
        "WARD_NAME": "GANJIGA",
        "LATITUDE": -9.392673,
        "LONGITUDE": 149.180181,
        "REGHH": 22,
        "TOTPOP2000": 172,
        "MALE2000": 82,
        "FEMALE2000": 90,
        "POP2008": 213,
        "G_RATE": 1.0269999504089355,
        "Geocode_Num": 6010204003,
        "PROVINCE": 6
      }
    }
  ]
}