{
  "type": "FeatureCollection",
  "features": [
    {
      "type": "Feature",
      "id": 13222,
      "geometry": {
        "type": "Point",
        "coordinates": [
          149.31804999990766,
          -9.078225000083648
        ]
      },
      "properties": {
        "OBJECTID": 13222,
        "CU_NAME": "TUFI GOVT. STATION",
        "CU_NO": "001",
        "GEOCODE": "06010285001",
        "PROV_KEY": "06",
        "DIST_NO": "01",
        "LLG_NO": "02",
        "WARD_NO": "85",
        "WARD_NAME": "TUFI GOVT. STATION",
        "LATITUDE": -9.079677,
        "LONGITUDE": 149.317052,
        "REGHH": 20,
        "TOTPOP2000": 111,
        "MALE2000": 56,
        "FEMALE2000": 55,
        "POP2008": 136,
        "G_RATE": 1.0269999504089355,
        "Geocode_Num": 6010285001,
        "PROVINCE": 6
      }
    },
    {
      "type": "Feature",
      "id": 13223,
      "geometry": {
        "type": "Point",
        "coordinates": [
          149.31804999990766,
          -9.078225000083648
        ]
      },
      "properties": {
        "OBJECTID": 13223,
        "CU_NAME": "TUFI GOVT. STATION",
        "CU_NO": "002",
        "GEOCODE": "06010285002",
        "PROV_KEY": "06",
        "DIST_NO": "01",
        "LLG_NO": "02",
        "WARD_NO": "85",
        "WARD_NAME": "TUFI GOVT. STATION",
        "LATITUDE": -9.079677,
        "LONGITUDE": 149.317052,
        "REGHH": 25,
        "TOTPOP2000": 180,
        "MALE2000": 91,
        "FEMALE2000": 89,
        "POP2008": 223,
        "G_RATE": 1.0269999504089355,
        "Geocode_Num": 6010285002,
        "PROVINCE": 6
      }
    }
  ]
}