{
  "type": "FeatureCollection",
  "features": [
    {
      "type": "Feature",
      "id": 6194,
      "geometry": {
        "type": "Point",
        "coordinates": [
          142.72492700018097,
          -3.66922699972622
        ]
      },
      "properties": {
        "OBJECTID": 6194,
        "CU_NAME": "TAU 1",
        "CU_NO": "017",
        "GEOCODE": "14010318017",
        "PROV_KEY": "14",
        "DIST_NO": "01",
        "LLG_NO": "03",
        "WARD_NO": "18",
        "WARD_NAME": "TAU 1",
        "LATITUDE": -3.670041,
        "LONGITUDE": 142.722921,
        "REGHH": 128,
        "TOTPOP2000": 513,
        "MALE2000": 257,
        "FEMALE2000": 256,
        "POP2008": 611,
        "G_RATE": 1.0219999551773071,
        "Geocode_Num": 14010318017,
        "PROVINCE": 14
      }
    }
  ]
}