{
  "type": "FeatureCollection",
  "features": [
    {
      "type": "Feature",
      "id": 5044,
      "geometry": {
        "type": "Point",
        "coordinates": [
          151.44261499988238,
          -5.614566000320622
        ]
      },
      "properties": {
        "OBJECTID": 5044,
        "CU_NAME": "IRENA",
        "CU_NO": "001",
        "GEOCODE": "18031410001",
        "PROV_KEY": "18",
        "DIST_NO": "03",
        "LLG_NO": "14",
        "WARD_NO": "10",
        "WARD_NAME": "IRENA",
        "LATITUDE": -5.615982,
        "LONGITUDE": 151.441656,
        "REGHH": 62,
        "TOTPOP2000": 278,
        "MALE2000": 139,
        "FEMALE2000": 139,
        "POP2008": 338,
        "G_RATE": 1.024999976158142,
        "Geocode_Num": 18031410001,
        "PROVINCE": 18
      }
    },
    {
      "type": "Feature",
      "id": 5045,
      "geometry": {
        "type": "Point",
        "coordinates": [
          151.42189500035408,
          -5.61602500015357
        ]
      },
      "properties": {
        "OBJECTID": 5045,
        "CU_NAME": "MARA",
        "CU_NO": "002",
        "GEOCODE": "18031410002",
        "PROV_KEY": "18",
        "DIST_NO": "03",
        "LLG_NO": "14",
        "WARD_NO": "10",
        "WARD_NAME": "IRENA",
        "LATITUDE": -5.62431,
        "LONGITUDE": 151.422,
        "REGHH": 4,
        "TOTPOP2000": 15,
        "MALE2000": 8,
        "FEMALE2000": 7,
        "POP2008": 15,
        "G_RATE": 1.024999976158142,
        "Geocode_Num": 18031410002,
        "PROVINCE": 18
      }
    }
  ]
}