{
  "type": "FeatureCollection",
  "features": [
    {
      "type": "Feature",
      "id": 17506,
      "geometry": {
        "type": "Point",
        "coordinates": [
          143.93976100017005,
          -5.894448000075101
        ]
      },
      "properties": {
        "OBJECTID": 17506,
        "CU_NAME": "PAGAPENA 1",
        "CU_NO": "028",
        "GEOCODE": "09071221028",
        "PROV_KEY": "09",
        "DIST_NO": "07",
        "LLG_NO": "12",
        "WARD_NO": "21",
        "WARD_NAME": "PAGAPENA 1",
        "LATITUDE": -5.895386,
        "LONGITUDE": 143.94009,
        "REGHH": 78,
        "TOTPOP2000": 402,
        "MALE2000": 204,
        "FEMALE2000": 198,
        "POP2008": 490,
        "G_RATE": 1.024999976158142,
        "Geocode_Num": 9071221028,
        "PROVINCE": 9
      }
    }
  ]
}