{
  "type": "FeatureCollection",
  "features": [
    {
      "type": "Feature",
      "id": 17516,
      "geometry": {
        "type": "Point",
        "coordinates": [
          143.94066699968232,
          -5.90540599998684
        ]
      },
      "properties": {
        "OBJECTID": 17516,
        "CU_NAME": "PAMBAKOLA",
        "CU_NO": "021",
        "GEOCODE": "09071227021",
        "PROV_KEY": "09",
        "DIST_NO": "07",
        "LLG_NO": "12",
        "WARD_NO": "27",
        "WARD_NAME": "LAIAGAM  1",
        "LATITUDE": -5.905771,
        "LONGITUDE": 143.941296,
        "REGHH": 89,
        "TOTPOP2000": 440,
        "MALE2000": 223,
        "FEMALE2000": 217,
        "POP2008": 536,
        "G_RATE": 1.024999976158142,
        "Geocode_Num": 9071227021,
        "PROVINCE": 9
      }
    },
    {
      "type": "Feature",
      "id": 17517,
      "geometry": {
        "type": "Point",
        "coordinates": [
          143.93809399973838,
          -5.905023000311189
        ]
      },
      "properties": {
        "OBJECTID": 17517,
        "CU_NAME": "YANO C/SCHOOL",
        "CU_NO": "401",
        "GEOCODE": "09071227401",
        "PROV_KEY": "09",
        "DIST_NO": "07",
        "LLG_NO": "12",
        "WARD_NO": "27",
        "WARD_NAME": "LAIAGAM  1",
        "LATITUDE": -5.905738,
        "LONGITUDE": 143.941288,
        "REGHH": 4,
        "TOTPOP2000": 12,
        "MALE2000": 6,
        "FEMALE2000": 6,
        "POP2008": 12,
        "G_RATE": 1.024999976158142,
        "Geocode_Num": 9071227401,
        "PROVINCE": 9
      }
    }
  ]
}