{
  "type": "FeatureCollection",
  "features": [
    {
      "type": "Feature",
      "id": 21800,
      "geometry": {
        "type": "Point",
        "coordinates": [
          142.931132999988,
          -5.785569000009275
        ]
      },
      "properties": {
        "OBJECTID": 21800,
        "CU_NAME": "HENGANDA 2",
        "CU_NO": "001",
        "GEOCODE": "07082809001",
        "PROV_KEY": "21",
        "DIST_NO": "3",
        "LLG_NO": "28",
        "WARD_NO": "09",
        "WARD_NAME": "HENGANDA 2",
        "LATITUDE": -5.789811,
        "LONGITUDE": 142.931397,
        "REGHH": 89,
        "TOTPOP2000": 314,
        "MALE2000": 153,
        "FEMALE2000": 161,
        "POP2008": 437,
        "G_RATE": 1.0420000553131104,
        "Geocode_Num": 7082809001,
        "PROVINCE": 21
      }
    }
  ]
}