{
  "type": "FeatureCollection",
  "features": [
    {
      "type": "Feature",
      "id": 21801,
      "geometry": {
        "type": "Point",
        "coordinates": [
          142.79589300016187,
          -5.700727999597461
        ]
      },
      "properties": {
        "OBJECTID": 21801,
        "CU_NAME": "MBULI",
        "CU_NO": "001",
        "GEOCODE": "07082810001",
        "PROV_KEY": "21",
        "DIST_NO": "3",
        "LLG_NO": "28",
        "WARD_NO": "10",
        "WARD_NAME": "MBULI",
        "LATITUDE": -5.70497,
        "LONGITUDE": 142.796153,
        "REGHH": 72,
        "TOTPOP2000": 402,
        "MALE2000": 188,
        "FEMALE2000": 214,
        "POP2008": 560,
        "G_RATE": 1.0420000553131104,
        "Geocode_Num": 7082810001,
        "PROVINCE": 21
      }
    }
  ]
}