{
  "type": "FeatureCollection",
  "features": [
    {
      "type": "Feature",
      "id": 21805,
      "geometry": {
        "type": "Point",
        "coordinates": [
          142.94662600038964,
          -5.779170999941641
        ]
      },
      "properties": {
        "OBJECTID": 21805,
        "CU_NAME": "PAIJAKA 1",
        "CU_NO": "005",
        "GEOCODE": "07082814005",
        "PROV_KEY": "21",
        "DIST_NO": "3",
        "LLG_NO": "28",
        "WARD_NO": "14",
        "WARD_NAME": "PAIJAKA 1",
        "LATITUDE": -5.782528,
        "LONGITUDE": 142.938691,
        "REGHH": 54,
        "TOTPOP2000": 413,
        "MALE2000": 220,
        "FEMALE2000": 193,
        "POP2008": 573,
        "G_RATE": 1.0420000553131104,
        "Geocode_Num": 7082814005,
        "PROVINCE": 21
      }
    }
  ]
}