{
  "type": "FeatureCollection",
  "features": [
    {
      "type": "Feature",
      "id": 21814,
      "geometry": {
        "type": "Point",
        "coordinates": [
          142.94363700014753,
          -5.7034269999560365
        ]
      },
      "properties": {
        "OBJECTID": 21814,
        "CU_NAME": "MT. KARE 1",
        "CU_NO": "001",
        "GEOCODE": "07082819001",
        "PROV_KEY": "21",
        "DIST_NO": "3",
        "LLG_NO": "28",
        "WARD_NO": "19",
        "WARD_NAME": "MT. KARE 1",
        "LATITUDE": -5.692847,
        "LONGITUDE": 142.953234,
        "REGHH": 71,
        "TOTPOP2000": 846,
        "MALE2000": 576,
        "FEMALE2000": 270,
        "POP2008": 1177,
        "G_RATE": 1.0420000553131104,
        "Geocode_Num": 7082819001,
        "PROVINCE": 21
      }
    }
  ]
}