{
  "type": "FeatureCollection",
  "features": [
    {
      "type": "Feature",
      "id": 9505,
      "geometry": {
        "type": "Point",
        "coordinates": [
          146.70155099967894,
          -2.15841499965245
        ]
      },
      "properties": {
        "OBJECTID": 9505,
        "CU_NAME": "LIKUM",
        "CU_NO": "005",
        "GEOCODE": "16011003005",
        "PROV_KEY": "16",
        "DIST_NO": "01",
        "LLG_NO": "10",
        "WARD_NO": "03",
        "WARD_NAME": "LIKUM",
        "LATITUDE": -2.161572,
        "LONGITUDE": 146.699235,
        "REGHH": 102,
        "TOTPOP2000": 536,
        "MALE2000": 295,
        "FEMALE2000": 241,
        "POP2008": 658,
        "G_RATE": 1.0260000228881836,
        "Geocode_Num": 16011003005,
        "PROVINCE": 16
      }
    },
    {
      "type": "Feature",
      "id": 9506,
      "geometry": {
        "type": "Point",
        "coordinates": [
          146.82366300024728,
          -2.180682000373963
        ]
      },
      "properties": {
        "OBJECTID": 9506,
        "CU_NAME": "WAMARAI",
        "CU_NO": "013",
        "GEOCODE": "16011003013",
        "PROV_KEY": "16",
        "DIST_NO": "01",
        "LLG_NO": "10",
        "WARD_NO": "03",
        "WARD_NAME": "LIKUM",
        "LATITUDE": -2.187161,
        "LONGITUDE": 146.833131,
        "REGHH": 9,
        "TOTPOP2000": 53,
        "MALE2000": 33,
        "FEMALE2000": 20,
        "POP2008": 64,
        "G_RATE": 1.0260000228881836,
        "Geocode_Num": 16011003013,
        "PROVINCE": 16
      }
    }
  ]
}