{
  "type": "FeatureCollection",
  "features": [
    {
      "type": "Feature",
      "id": 7038,
      "geometry": {
        "type": "Point",
        "coordinates": [
          143.04543300003297,
          -3.985761999916292
        ]
      },
      "properties": {
        "OBJECTID": 7038,
        "CU_NAME": "BURUI",
        "CU_NO": "004",
        "GEOCODE": "14051906004",
        "PROV_KEY": "14",
        "DIST_NO": "05",
        "LLG_NO": "19",
        "WARD_NO": "06",
        "WARD_NAME": "BURUI",
        "LATITUDE": -3.989893,
        "LONGITUDE": 143.035181,
        "REGHH": 72,
        "TOTPOP2000": 428,
        "MALE2000": 206,
        "FEMALE2000": 222,
        "POP2008": 509,
        "G_RATE": 1.0219999551773071,
        "Geocode_Num": 14051906004,
        "PROVINCE": 14
      }
    }
  ]
}