{
  "type": "FeatureCollection",
  "features": [
    {
      "type": "Feature",
      "id": 7058,
      "geometry": {
        "type": "Point",
        "coordinates": [
          143.17162900007838,
          -4.020921999850373
        ]
      },
      "properties": {
        "OBJECTID": 7058,
        "CU_NAME": "SLAI 1",
        "CU_NO": "013",
        "GEOCODE": "14051918013",
        "PROV_KEY": "14",
        "DIST_NO": "05",
        "LLG_NO": "19",
        "WARD_NO": "18",
        "WARD_NAME": "SLAI",
        "LATITUDE": -4.024997,
        "LONGITUDE": 143.175892,
        "REGHH": 40,
        "TOTPOP2000": 210,
        "MALE2000": 109,
        "FEMALE2000": 101,
        "POP2008": 250,
        "G_RATE": 1.0219999551773071,
        "Geocode_Num": 14051918013,
        "PROVINCE": 14
      }
    },
    {
      "type": "Feature",
      "id": 7059,
      "geometry": {
        "type": "Point",
        "coordinates": [
          143.17364200027816,
          -4.000709000320057
        ]
      },
      "properties": {
        "OBJECTID": 7059,
        "CU_NAME": "SLAI 2",
        "CU_NO": "014",
        "GEOCODE": "14051918014",
        "PROV_KEY": "14",
        "DIST_NO": "05",
        "LLG_NO": "19",
        "WARD_NO": "18",
        "WARD_NAME": "SLAI",
        "LATITUDE": -4.014327,
        "LONGITUDE": 143.172936,
        "REGHH": 22,
        "TOTPOP2000": 114,
        "MALE2000": 54,
        "FEMALE2000": 60,
        "POP2008": 138,
        "G_RATE": 1.0219999551773071,
        "Geocode_Num": 14051918014,
        "PROVINCE": 14
      }
    }
  ]
}