{
  "type": "FeatureCollection",
  "features": [
    {
      "type": "Feature",
      "id": 7060,
      "geometry": {
        "type": "Point",
        "coordinates": [
          143.20361000000162,
          -4.035986000253672
        ]
      },
      "properties": {
        "OBJECTID": 7060,
        "CU_NAME": "MIAMBE",
        "CU_NO": "006",
        "GEOCODE": "14051919006",
        "PROV_KEY": "14",
        "DIST_NO": "05",
        "LLG_NO": "19",
        "WARD_NO": "19",
        "WARD_NAME": "MIAMBE",
        "LATITUDE": -4.03757,
        "LONGITUDE": 143.202372,
        "REGHH": 31,
        "TOTPOP2000": 145,
        "MALE2000": 72,
        "FEMALE2000": 73,
        "POP2008": 172,
        "G_RATE": 1.0219999551773071,
        "Geocode_Num": 14051919006,
        "PROVINCE": 14
      }
    },
    {
      "type": "Feature",
      "id": 7061,
      "geometry": {
        "type": "Point",
        "coordinates": [
          143.25028400030646,
          -4.027630999870723
        ]
      },
      "properties": {
        "OBJECTID": 7061,
        "CU_NAME": "SARUM",
        "CU_NO": "010",
        "GEOCODE": "14051919010",
        "PROV_KEY": "14",
        "DIST_NO": "05",
        "LLG_NO": "19",
        "WARD_NO": "19",
        "WARD_NAME": "MIAMBE",
        "LATITUDE": -4.029215,
        "LONGITUDE": 143.249047,
        "REGHH": 41,
        "TOTPOP2000": 195,
        "MALE2000": 99,
        "FEMALE2000": 96,
        "POP2008": 232,
        "G_RATE": 1.0219999551773071,
        "Geocode_Num": 14051919010,
        "PROVINCE": 14
      }
    },
    {
      "type": "Feature",
      "id": 7062,
      "geometry": {
        "type": "Point",
        "coordinates": [
          143.2127630003123,
          -4.016826999866112
        ]
      },
      "properties": {
        "OBJECTID": 7062,
        "CU_NAME": "YAKIAP",
        "CU_NO": "021",
        "GEOCODE": "14051919021",
        "PROV_KEY": "14",
        "DIST_NO": "05",
        "LLG_NO": "19",
        "WARD_NO": "19",
        "WARD_NAME": "MIAMBE",
        "LATITUDE": -4.018409,
        "LONGITUDE": 143.211525,
        "REGHH": 41,
        "TOTPOP2000": 152,
        "MALE2000": 74,
        "FEMALE2000": 78,
        "POP2008": 181,
        "G_RATE": 1.0219999551773071,
        "Geocode_Num": 14051919021,
        "PROVINCE": 14
      }
    }
  ]
}