{
  "type": "FeatureCollection",
  "features": [
    {
      "type": "Feature",
      "id": 9154,
      "geometry": {
        "type": "Point",
        "coordinates": [
          145.17900099969643,
          -5.782749000366039
        ]
      },
      "properties": {
        "OBJECTID": 9154,
        "CU_NAME": "BONONI",
        "CU_NO": "004",
        "GEOCODE": "13061503004",
        "PROV_KEY": "13",
        "DIST_NO": "06",
        "LLG_NO": "15",
        "WARD_NO": "03",
        "WARD_NAME": "WARD 3",
        "LATITUDE": -5.784158,
        "LONGITUDE": 145.177954,
        "REGHH": 62,
        "TOTPOP2000": 401,
        "MALE2000": 198,
        "FEMALE2000": 203,
        "POP2008": 496,
        "G_RATE": 1.0269999504089355,
        "Geocode_Num": 13061503004,
        "PROVINCE": 13
      }
    }
  ]
}