{
  "type": "FeatureCollection",
  "features": [
    {
      "type": "Feature",
      "id": 5556,
      "geometry": {
        "type": "Point",
        "coordinates": [
          143.5593470003638,
          -5.606996000165225
        ]
      },
      "properties": {
        "OBJECTID": 5556,
        "CU_NAME": "YENGIL",
        "CU_NO": "014",
        "GEOCODE": "08030605014",
        "PROV_KEY": "08",
        "DIST_NO": "03",
        "LLG_NO": "06",
        "WARD_NO": "05",
        "WARD_NAME": "YENGIL",
        "LATITUDE": -5.608399,
        "LONGITUDE": 143.55828,
        "REGHH": 65,
        "TOTPOP2000": 337,
        "MALE2000": 177,
        "FEMALE2000": 160,
        "POP2008": 424,
        "G_RATE": 1.0290000438690186,
        "Geocode_Num": 8030605014,
        "PROVINCE": 8
      }
    },
    {
      "type": "Feature",
      "id": 5557,
      "geometry": {
        "type": "Point",
        "coordinates": [
          143.5499650002846,
          -5.648919999957968
        ]
      },
      "properties": {
        "OBJECTID": 5557,
        "CU_NAME": "WAGAM",
        "CU_NO": "015",
        "GEOCODE": "08030605015",
        "PROV_KEY": "08",
        "DIST_NO": "03",
        "LLG_NO": "06",
        "WARD_NO": "05",
        "WARD_NAME": "YENGIL",
        "LATITUDE": -5.652113,
        "LONGITUDE": 143.548906,
        "REGHH": 45,
        "TOTPOP2000": 266,
        "MALE2000": 143,
        "FEMALE2000": 123,
        "POP2008": 334,
        "G_RATE": 1.0290000438690186,
        "Geocode_Num": 8030605015,
        "PROVINCE": 8
      }
    },
    {
      "type": "Feature",
      "id": 5558,
      "geometry": {
        "type": "Point",
        "coordinates": [
          143.53228399970692,
          -5.623817999800792
        ]
      },
      "properties": {
        "OBJECTID": 5558,
        "CU_NAME": "YAKAPELE",
        "CU_NO": "016",
        "GEOCODE": "08030605016",
        "PROV_KEY": "08",
        "DIST_NO": "03",
        "LLG_NO": "06",
        "WARD_NO": "05",
        "WARD_NAME": "YENGIL",
        "LATITUDE": -5.625221,
        "LONGITUDE": 143.531217,
        "REGHH": 45,
        "TOTPOP2000": 271,
        "MALE2000": 156,
        "FEMALE2000": 115,
        "POP2008": 341,
        "G_RATE": 1.0290000438690186,
        "Geocode_Num": 8030605016,
        "PROVINCE": 8
      }
    }
  ]
}