{
  "type": "FeatureCollection",
  "features": [
    {
      "type": "Feature",
      "id": 5574,
      "geometry": {
        "type": "Point",
        "coordinates": [
          143.52828299956082,
          -5.549584000201378
        ]
      },
      "properties": {
        "OBJECTID": 5574,
        "CU_NAME": "MAPOMANDA",
        "CU_NO": "013",
        "GEOCODE": "08030612013",
        "PROV_KEY": "08",
        "DIST_NO": "03",
        "LLG_NO": "06",
        "WARD_NO": "12",
        "WARD_NAME": "MAPOMANDA",
        "LATITUDE": -5.551205,
        "LONGITUDE": 143.5265,
        "REGHH": 22,
        "TOTPOP2000": 110,
        "MALE2000": 59,
        "FEMALE2000": 51,
        "POP2008": 138,
        "G_RATE": 1.0290000438690186,
        "Geocode_Num": 8030612013,
        "PROVINCE": 8
      }
    },
    {
      "type": "Feature",
      "id": 5575,
      "geometry": {
        "type": "Point",
        "coordinates": [
          143.51974999996264,
          -5.522696999566847
        ]
      },
      "properties": {
        "OBJECTID": 5575,
        "CU_NAME": "LADAPUS",
        "CU_NO": "014",
        "GEOCODE": "08030612014",
        "PROV_KEY": "08",
        "DIST_NO": "03",
        "LLG_NO": "06",
        "WARD_NO": "12",
        "WARD_NAME": "MAPOMANDA",
        "LATITUDE": -5.524099,
        "LONGITUDE": 143.518683,
        "REGHH": 59,
        "TOTPOP2000": 308,
        "MALE2000": 164,
        "FEMALE2000": 144,
        "POP2008": 387,
        "G_RATE": 1.0290000438690186,
        "Geocode_Num": 8030612014,
        "PROVINCE": 8
      }
    },
    {
      "type": "Feature",
      "id": 5576,
      "geometry": {
        "type": "Point",
        "coordinates": [
          143.52757600023233,
          -5.551959000007798
        ]
      },
      "properties": {
        "OBJECTID": 5576,
        "CU_NAME": "MAPOMANDA C/SCH & DPI",
        "CU_NO": "401",
        "GEOCODE": "08030612401",
        "PROV_KEY": "08",
        "DIST_NO": "03",
        "LLG_NO": "06",
        "WARD_NO": "12",
        "WARD_NAME": "MAPOMANDA",
        "LATITUDE": -5.551205,
        "LONGITUDE": 143.5265,
        "REGHH": 3,
        "TOTPOP2000": 12,
        "MALE2000": 9,
        "FEMALE2000": 3,
        "POP2008": 12,
        "G_RATE": 1.0290000438690186,
        "Geocode_Num": 8030612401,
        "PROVINCE": 8
      }
    }
  ]
}