{
  "type": "FeatureCollection",
  "features": [
    {
      "type": "Feature",
      "id": 5613,
      "geometry": {
        "type": "Point",
        "coordinates": [
          143.48816999964583,
          -5.49672099957445
        ]
      },
      "properties": {
        "OBJECTID": 5613,
        "CU_NAME": "PAIP",
        "CU_NO": "005",
        "GEOCODE": "08030633005",
        "PROV_KEY": "08",
        "DIST_NO": "03",
        "LLG_NO": "06",
        "WARD_NO": "33",
        "WARD_NAME": "PAIP",
        "LATITUDE": -5.496844,
        "LONGITUDE": 143.483337,
        "REGHH": 172,
        "TOTPOP2000": 830,
        "MALE2000": 426,
        "FEMALE2000": 404,
        "POP2008": 1043,
        "G_RATE": 1.0290000438690186,
        "Geocode_Num": 8030633005,
        "PROVINCE": 8
      }
    }
  ]
}