{
  "type": "FeatureCollection",
  "features": [
    {
      "type": "Feature",
      "id": 6202,
      "geometry": {
        "type": "Point",
        "coordinates": [
          141.64971799988587,
          -4.367244999557045
        ]
      },
      "properties": {
        "OBJECTID": 6202,
        "CU_NAME": "BURMAI",
        "CU_NO": "002",
        "GEOCODE": "14010402002",
        "PROV_KEY": "14",
        "DIST_NO": "01",
        "LLG_NO": "04",
        "WARD_NO": "02",
        "WARD_NAME": "BURMAI",
        "LATITUDE": -4.367768,
        "LONGITUDE": 141.649163,
        "REGHH": 15,
        "TOTPOP2000": 78,
        "MALE2000": 39,
        "FEMALE2000": 39,
        "POP2008": 94,
        "G_RATE": 1.0219999551773071,
        "Geocode_Num": 14010402002,
        "PROVINCE": 14
      }
    },
    {
      "type": "Feature",
      "id": 6203,
      "geometry": {
        "type": "Point",
        "coordinates": [
          141.6506879996515,
          -4.417265000379416
        ]
      },
      "properties": {
        "OBJECTID": 6203,
        "CU_NAME": "YUATRI",
        "CU_NO": "008",
        "GEOCODE": "14010402008",
        "PROV_KEY": "14",
        "DIST_NO": "01",
        "LLG_NO": "04",
        "WARD_NO": "02",
        "WARD_NAME": "BURMAI",
        "LATITUDE": -4.421692,
        "LONGITUDE": 141.632874,
        "REGHH": 18,
        "TOTPOP2000": 103,
        "MALE2000": 59,
        "FEMALE2000": 44,
        "POP2008": 121,
        "G_RATE": 1.0219999551773071,
        "Geocode_Num": 14010402008,
        "PROVINCE": 14
      }
    },
    {
      "type": "Feature",
      "id": 6204,
      "geometry": {
        "type": "Point",
        "coordinates": [
          141.63732200021025,
          -4.383682000324029
        ]
      },
      "properties": {
        "OBJECTID": 6204,
        "CU_NAME": "BURMAI 2/WAYAP",
        "CU_NO": "009",
        "GEOCODE": "14010402009",
        "PROV_KEY": "14",
        "DIST_NO": "01",
        "LLG_NO": "04",
        "WARD_NO": "02",
        "WARD_NAME": "BURMAI",
        "LATITUDE": -4.385266,
        "LONGITUDE": 141.636065,
        "REGHH": 3,
        "TOTPOP2000": 16,
        "MALE2000": 8,
        "FEMALE2000": 8,
        "POP2008": 16,
        "G_RATE": 1.0219999551773071,
        "Geocode_Num": 14010402009,
        "PROVINCE": 14
      }
    }
  ]
}