{
  "type": "FeatureCollection",
  "features": [
    {
      "type": "Feature",
      "id": 6214,
      "geometry": {
        "type": "Point",
        "coordinates": [
          141.7354999996254,
          -4.4702650001295865
        ]
      },
      "properties": {
        "OBJECTID": 6214,
        "CU_NAME": "OROMO",
        "CU_NO": "002",
        "GEOCODE": "14010406002",
        "PROV_KEY": "14",
        "DIST_NO": "01",
        "LLG_NO": "04",
        "WARD_NO": "06",
        "WARD_NAME": "SAMO",
        "LATITUDE": -4.47185,
        "LONGITUDE": 141.734244,
        "REGHH": 3,
        "TOTPOP2000": 14,
        "MALE2000": 5,
        "FEMALE2000": 9,
        "POP2008": 14,
        "G_RATE": 1.0219999551773071,
        "Geocode_Num": 14010406002,
        "PROVINCE": 14
      }
    },
    {
      "type": "Feature",
      "id": 6215,
      "geometry": {
        "type": "Point",
        "coordinates": [
          141.71070199999735,
          -4.477572999893994
        ]
      },
      "properties": {
        "OBJECTID": 6215,
        "CU_NAME": "INAGRI",
        "CU_NO": "007",
        "GEOCODE": "14010406007",
        "PROV_KEY": "14",
        "DIST_NO": "01",
        "LLG_NO": "04",
        "WARD_NO": "06",
        "WARD_NAME": "SAMO",
        "LATITUDE": -4.479158,
        "LONGITUDE": 141.709444,
        "REGHH": 16,
        "TOTPOP2000": 67,
        "MALE2000": 34,
        "FEMALE2000": 33,
        "POP2008": 81,
        "G_RATE": 1.0219999551773071,
        "Geocode_Num": 14010406007,
        "PROVINCE": 14
      }
    },
    {
      "type": "Feature",
      "id": 6216,
      "geometry": {
        "type": "Point",
        "coordinates": [
          141.7230560004341,
          -4.4237829996856135
        ]
      },
      "properties": {
        "OBJECTID": 6216,
        "CU_NAME": "SAMO",
        "CU_NO": "010",
        "GEOCODE": "14010406010",
        "PROV_KEY": "14",
        "DIST_NO": "01",
        "LLG_NO": "04",
        "WARD_NO": "06",
        "WARD_NAME": "SAMO",
        "LATITUDE": -4.425648,
        "LONGITUDE": 141.715772,
        "REGHH": 35,
        "TOTPOP2000": 155,
        "MALE2000": 77,
        "FEMALE2000": 78,
        "POP2008": 185,
        "G_RATE": 1.0219999551773071,
        "Geocode_Num": 14010406010,
        "PROVINCE": 14
      }
    }
  ]
}